{
  "type": "Feature",
  "properties": {
    "gn:admin1_code":"00",
    "gn:asciiname":"Nyamibechire",
    "gn:country_code":"GH",
    "gn:dem":86,
    "gn:feature_class":"P",
    "gn:feature_code":"PPL",
    "gn:name":"Nyamibechire",
    "gn:population":0,
    "gn:timezone":"Africa/Accra",
    "iso:country":"GH",
    "wof:name":"Nyamibechire",
    "wof:placetype":"locality"
},
  "geometry": {"coordinates":[-0.91124,5.54147],"type":"Point"}
}