{
  "type": "Feature",
  "properties": {
    "iso:country":"GH",
    "qs:gn_pop":0,
    "qs:name":"New Tafo",
    "qs:name_adm0":"Ghana",
    "qs:name_adm1":"Ashanti",
    "qs:photos":765,
    "qs:photos_1k":155,
    "qs:photos_9k":3,
    "qs:photos_9r":6,
    "qs:photos_all":765,
    "qs:photos_sr":9,
    "qs:placetype":"Town",
    "qs:pop_sr":"0",
    "qs:woe_adm0":23424824,
    "wof:name":"New Tafo",
    "wof:placetype":"locality"
},
  "geometry": {"coordinates":[-1.568641,6.687624],"type":"Point"}
}