{
  "type": "Feature",
  "properties": {
    "gn:admin1_code":"00",
    "gn:asciiname":"Kwesiansa",
    "gn:country_code":"GH",
    "gn:dem":39,
    "gn:feature_class":"P",
    "gn:feature_code":"PPL",
    "gn:name":"Kwesiansa",
    "gn:population":0,
    "gn:timezone":"Africa/Accra",
    "iso:country":"GH",
    "wof:name":"Kwesiansa",
    "wof:placetype":"locality"
},
  "geometry": {"coordinates":[-1.06456,5.33443],"type":"Point"}
}