{
  "type": "Feature",
  "properties": {
    "gn:admin1_code":"00",
    "gn:asciiname":"Amua",
    "gn:country_code":"GH",
    "gn:dem":201,
    "gn:feature_class":"P",
    "gn:feature_code":"PPL",
    "gn:name":"Amua",
    "gn:population":0,
    "gn:timezone":"Africa/Accra",
    "iso:country":"GH",
    "wof:name":"Amua",
    "wof:placetype":"locality"
},
  "geometry": {"coordinates":[-0.9669,6.52082],"type":"Point"}
}