{
  "type": "Feature",
  "properties": {
    "gn:admin1_code":"00",
    "gn:asciiname":"Abrimso",
    "gn:cc2":"GH",
    "gn:country_code":"GH",
    "gn:dem":196,
    "gn:feature_class":"P",
    "gn:feature_code":"PPL",
    "gn:name":"Abrimso",
    "gn:population":0,
    "gn:timezone":"Africa/Accra",
    "iso:country":"GH",
    "name:und_x_variant":[
        "Abrim",
        "Abrimso"
    ],
    "wof:name":"Abrimso",
    "wof:placetype":"locality"
},
  "geometry": {"coordinates":[-0.31667,5.88333],"type":"Point"}
}