{
  "type": "Feature",
  "properties": {
    "gn:admin1_code":"09",
    "gn:asciiname":"Sa",
    "gn:country_code":"GH",
    "gn:dem":75,
    "gn:feature_class":"P",
    "gn:feature_code":"PPL",
    "gn:name":"Sa",
    "gn:population":0,
    "gn:timezone":"Africa/Accra",
    "iso:country":"GH",
    "name:und_x_variant":[
        "Saa",
        "Sa"
    ],
    "wof:name":"Sa",
    "wof:placetype":"locality"
},
  "geometry": {"coordinates":[-1.82157,5.32237],"type":"Point"}
}