{
  "type": "Feature",
  "properties": {
    "gn:admin1_code":"00",
    "gn:asciiname":"Kwadum",
    "gn:country_code":"GH",
    "gn:dem":116,
    "gn:feature_class":"P",
    "gn:feature_code":"PPL",
    "gn:name":"Kwadum",
    "gn:population":0,
    "gn:timezone":"Africa/Accra",
    "iso:country":"GH",
    "name:und_x_variant":[
        "Nkwadum",
        "Kwadum"
    ],
    "wof:name":"Kwadum",
    "wof:placetype":"locality"
},
  "geometry": {"coordinates":[-0.78576,5.55512],"type":"Point"}
}