{
  "type": "Feature",
  "properties": {
    "gn:admin1_code":"00",
    "gn:asciiname":"Krabo",
    "gn:country_code":"GH",
    "gn:dem":127,
    "gn:feature_class":"P",
    "gn:feature_code":"PPL",
    "gn:name":"Krabo",
    "gn:population":0,
    "gn:timezone":"Africa/Accra",
    "iso:country":"GH",
    "name:und_x_variant":[
        "Kraboakese",
        "Krabo"
    ],
    "wof:name":"Krabo",
    "wof:placetype":"locality"
},
  "geometry": {"coordinates":[-0.43108,5.87823],"type":"Point"}
}