{
  "type": "Feature",
  "properties": {
    "gn:admin1_code":"00",
    "gn:asciiname":"Sibele",
    "gn:country_code":"GH",
    "gn:dem":326,
    "gn:feature_class":"P",
    "gn:feature_code":"PPL",
    "gn:name":"Sibele",
    "gn:population":0,
    "gn:timezone":"Africa/Accra",
    "iso:country":"GH",
    "name:und_x_variant":[
        "Sibela",
        "Sullibalia",
        "Sibele"
    ],
    "wof:name":"Sibele",
    "wof:placetype":"locality"
},
  "geometry": {"coordinates":[-2.0496,10.88822],"type":"Point"}
}