{
  "type": "Feature",
  "properties": {
    "gn:admin1_code":"11",
    "gn:asciiname":"Sombisi",
    "gn:country_code":"GH",
    "gn:dem":199,
    "gn:feature_class":"P",
    "gn:feature_code":"PPL",
    "gn:name":"Sombisi",
    "gn:population":0,
    "gn:timezone":"Africa/Accra",
    "iso:country":"GH",
    "wof:name":"Sombisi",
    "wof:placetype":"locality"
},
  "geometry": {"coordinates":[-1.71733,10.13308],"type":"Point"}
}