{
  "type": "Feature",
  "properties": {
    "gn:admin1_code":"02",
    "gn:asciiname":"Konkori",
    "gn:country_code":"GH",
    "gn:dem":223,
    "gn:feature_class":"P",
    "gn:feature_code":"PPL",
    "gn:name":"Konkori",
    "gn:population":0,
    "gn:timezone":"Africa/Accra",
    "iso:country":"GH",
    "name:eng_x_preferred":[
        "Konkori"
    ],
    "wof:name":"Konkori",
    "wof:placetype":"locality"
},
  "geometry": {"coordinates":[-1.64194,6.54635],"type":"Point"}
}