{
  "type": "Feature",
  "properties": {
    "gn:admin1_code":"02",
    "gn:asciiname":"Konuasi",
    "gn:country_code":"GH",
    "gn:dem":162,
    "gn:feature_class":"P",
    "gn:feature_code":"PPL",
    "gn:name":"Konuasi",
    "gn:population":0,
    "gn:timezone":"Africa/Accra",
    "iso:country":"GH",
    "name:und_x_variant":[
        "Konuase",
        "Konuasi"
    ],
    "wof:name":"Konuasi",
    "wof:placetype":"locality"
},
  "geometry": {"coordinates":[-1.97425,6.34099],"type":"Point"}
}