{
  "type": "Feature",
  "properties": {
    "gn:admin1_code":"00",
    "gn:asciiname":"Abotia",
    "gn:country_code":"GH",
    "gn:dem":17,
    "gn:feature_class":"P",
    "gn:feature_code":"PPL",
    "gn:name":"Abotia",
    "gn:population":0,
    "gn:timezone":"Africa/Accra",
    "iso:country":"GH",
    "name:und_x_variant":[
        "Kwati",
        "Duffor Abotia",
        "Kwatia",
        "Abetia",
        "Abotia"
    ],
    "wof:name":"Abotia",
    "wof:placetype":"locality"
},
  "geometry": {"coordinates":[0.11636,6.23278],"type":"Point"}
}