{
  "type": "Feature",
  "properties": {
    "gn:admin1_code":"00",
    "gn:asciiname":"Kokpelibobgu",
    "gn:country_code":"GH",
    "gn:dem":274,
    "gn:feature_class":"P",
    "gn:feature_code":"PPL",
    "gn:name":"Kokpelibobgu",
    "gn:population":0,
    "gn:timezone":"Africa/Accra",
    "iso:country":"GH",
    "wof:name":"Kokpelibobgu",
    "wof:placetype":"locality"
},
  "geometry": {"coordinates":[-0.31667,10.46667],"type":"Point"}
}