{
  "type": "Feature",
  "properties": {
    "gn:admin1_code":"00",
    "gn:asciiname":"Lagbo",
    "gn:country_code":"GH",
    "gn:dem":56,
    "gn:feature_class":"P",
    "gn:feature_code":"PPL",
    "gn:name":"Lagbo",
    "gn:population":0,
    "gn:timezone":"Africa/Accra",
    "iso:country":"GH",
    "name:und_x_variant":[
        "Lagbokorpe",
        "Lagbo"
    ],
    "wof:name":"Lagbo",
    "wof:placetype":"locality"
},
  "geometry": {"coordinates":[0.82709,6.14693],"type":"Point"}
}