{
  "type": "Feature",
  "properties": {
    "gn:admin1_code":"00",
    "gn:asciiname":"Sorabela",
    "gn:country_code":"GH",
    "gn:dem":329,
    "gn:feature_class":"P",
    "gn:feature_code":"PPL",
    "gn:name":"Sorabela",
    "gn:population":0,
    "gn:timezone":"Africa/Accra",
    "iso:country":"GH",
    "name:und_x_variant":[
        "Sawbellia",
        "Sorabella",
        "Sorabela"
    ],
    "wof:name":"Sorabela",
    "wof:placetype":"locality"
},
  "geometry": {"coordinates":[-2.06288,10.87782],"type":"Point"}
}