{
  "type": "Feature",
  "properties": {
    "gn:admin1_code":"00",
    "gn:asciiname":"Tangbini",
    "gn:country_code":"GH",
    "gn:dem":317,
    "gn:feature_class":"P",
    "gn:feature_code":"PPL",
    "gn:name":"Tangbini",
    "gn:population":0,
    "gn:timezone":"Africa/Accra",
    "iso:country":"GH",
    "wof:name":"Tangbini",
    "wof:placetype":"locality"
},
  "geometry": {"coordinates":[-0.58721,10.46908],"type":"Point"}
}