{
  "type": "Feature",
  "properties": {
    "gn:admin1_code":"01",
    "gn:asciiname":"Ayasu",
    "gn:country_code":"GH",
    "gn:dem":45,
    "gn:feature_class":"P",
    "gn:feature_code":"PPL",
    "gn:name":"Ayasu",
    "gn:population":0,
    "gn:timezone":"Africa/Accra",
    "iso:country":"GH",
    "name:eng_x_preferred":[
        "Ayasu"
    ],
    "name:eng_x_variant":[
        "Ayaso"
    ],
    "wof:name":"Ayasu",
    "wof:placetype":"locality"
},
  "geometry": {"coordinates":[-0.29047,5.67149],"type":"Point"}
}