{
  "type": "Feature",
  "properties": {
    "gn:admin1_code":"00",
    "gn:asciiname":"Toenajile",
    "gn:country_code":"GH",
    "gn:dem":161,
    "gn:feature_class":"P",
    "gn:feature_code":"PPL",
    "gn:name":"Toenajile",
    "gn:population":0,
    "gn:timezone":"Africa/Accra",
    "iso:country":"GH",
    "wof:name":"Toenajile",
    "wof:placetype":"locality"
},
  "geometry": {"coordinates":[-0.08333,8.73333],"type":"Point"}
}