{
  "type": "Feature",
  "properties": {
    "gn:admin1_code":"00",
    "gn:asciiname":"Fishila",
    "gn:cc2":"GH",
    "gn:country_code":"GH",
    "gn:dem":144,
    "gn:feature_class":"P",
    "gn:feature_code":"PPL",
    "gn:name":"Fishila",
    "gn:population":0,
    "gn:timezone":"Africa/Accra",
    "iso:country":"GH",
    "name:und_x_variant":[
        "Fisila",
        "Fishila"
    ],
    "wof:name":"Fishila",
    "wof:placetype":"locality"
},
  "geometry": {"coordinates":[-0.93333,9.28333],"type":"Point"}
}