{
  "type": "Feature",
  "properties": {
    "gn:admin1_code":"02",
    "gn:asciiname":"Domi Beposo",
    "gn:country_code":"GH",
    "gn:dem":279,
    "gn:feature_class":"P",
    "gn:feature_code":"PPL",
    "gn:name":"Domi Beposo",
    "gn:population":0,
    "gn:timezone":"Africa/Accra",
    "iso:country":"GH",
    "name:und_x_variant":[
        "Domi",
        "Domi Beposo"
    ],
    "wof:name":"Domi Beposo",
    "wof:placetype":"locality"
},
  "geometry": {"coordinates":[-1.91549,6.42927],"type":"Point"}
}