{
  "type": "Feature",
  "properties": {
    "gn:admin1_code":"00",
    "gn:asciiname":"Sanduli",
    "gn:cc2":"GH",
    "gn:country_code":"GH",
    "gn:dem":204,
    "gn:feature_class":"P",
    "gn:feature_code":"PPL",
    "gn:name":"Sanduli",
    "gn:population":0,
    "gn:timezone":"Africa/Accra",
    "iso:country":"GH",
    "name:und_x_variant":[
        "Sanguli",
        "Sanduli"
    ],
    "wof:name":"Sanduli",
    "wof:placetype":"locality"
},
  "geometry": {"coordinates":[-0.13333,9.58333],"type":"Point"}
}