{
  "type": "Feature",
  "properties": {
    "gn:admin1_code":"00",
    "gn:asciiname":"Buaben",
    "gn:country_code":"GH",
    "gn:dem":273,
    "gn:feature_class":"P",
    "gn:feature_code":"PPL",
    "gn:name":"Buaben",
    "gn:population":0,
    "gn:timezone":"Africa/Accra",
    "iso:country":"GH",
    "wof:name":"Buaben",
    "wof:placetype":"locality"
},
  "geometry": {"coordinates":[-1.48333,6.43333],"type":"Point"}
}