{
  "type": "Feature",
  "properties": {
    "gn:admin1_code":"00",
    "gn:asciiname":"Halemboi",
    "gn:country_code":"GH",
    "gn:dem":237,
    "gn:feature_class":"P",
    "gn:feature_code":"PPL",
    "gn:name":"Halemboi",
    "gn:population":0,
    "gn:timezone":"Africa/Accra",
    "iso:country":"GH",
    "name:und_x_variant":[
        "Bawiesibal",
        "Hamboi",
        "Halemboi"
    ],
    "wof:name":"Halemboi",
    "wof:placetype":"locality"
},
  "geometry": {"coordinates":[-1.73866,10.2525],"type":"Point"}
}