{
  "type": "Feature",
  "properties": {
    "gn:admin1_code":"00",
    "gn:asciiname":"Awukugua",
    "gn:country_code":"GH",
    "gn:dem":431,
    "gn:feature_class":"P",
    "gn:feature_code":"PPL",
    "gn:name":"Awukugua",
    "gn:population":0,
    "gn:timezone":"Africa/Accra",
    "iso:country":"GH",
    "wof:name":"Awukugua",
    "wof:placetype":"locality"
},
  "geometry": {"coordinates":[-0.08194,5.99575],"type":"Point"}
}