{
  "type": "Feature",
  "properties": {
    "gn:admin1_code":"00",
    "gn:asciiname":"Fiasi",
    "gn:country_code":"GH",
    "gn:dem":244,
    "gn:feature_class":"P",
    "gn:feature_code":"PPL",
    "gn:name":"Fiasi",
    "gn:population":0,
    "gn:timezone":"Africa/Accra",
    "iso:country":"GH",
    "name:und_x_variant":[
        "Tiasi",
        "Tease",
        "Fiasi"
    ],
    "wof:name":"Fiasi",
    "wof:placetype":"locality"
},
  "geometry": {"coordinates":[-0.25704,6.93034],"type":"Point"}
}