{
  "type": "Feature",
  "properties": {
    "gn:admin1_code":"00",
    "gn:asciiname":"Nkrundia",
    "gn:cc2":"GH",
    "gn:country_code":"GH",
    "gn:dem":148,
    "gn:feature_class":"P",
    "gn:feature_code":"PPL",
    "gn:name":"Nkrundia",
    "gn:population":0,
    "gn:timezone":"Africa/Accra",
    "iso:country":"GH",
    "name:und_x_variant":[
        "Nkrondua",
        "Nkrundia"
    ],
    "wof:name":"Nkrundia",
    "wof:placetype":"locality"
},
  "geometry": {"coordinates":[-2.08333,6.23333],"type":"Point"}
}