{
  "type": "Feature",
  "properties": {
    "gn:admin1_code":"00",
    "gn:asciiname":"Zankalla",
    "gn:country_code":"GH",
    "gn:dem":132,
    "gn:feature_class":"P",
    "gn:feature_code":"PPL",
    "gn:name":"Zankalla",
    "gn:population":0,
    "gn:timezone":"Africa/Accra",
    "iso:country":"GH",
    "name:und_x_variant":[
        "Zankali",
        "Zankalla"
    ],
    "wof:name":"Zankalla",
    "wof:placetype":"locality"
},
  "geometry": {"coordinates":[-0.71396,9.84552],"type":"Point"}
}