{
  "type": "Feature",
  "properties": {
    "gn:admin1_code":"00",
    "gn:asciiname":"Sangba",
    "gn:country_code":"GH",
    "gn:dem":134,
    "gn:feature_class":"P",
    "gn:feature_code":"PPL",
    "gn:name":"Sangba",
    "gn:population":0,
    "gn:timezone":"Africa/Accra",
    "iso:country":"GH",
    "name:msa_x_preferred":[
        "Sangba"
    ],
    "wof:name":"Sangba",
    "wof:placetype":"locality"
},
  "geometry": {"coordinates":[-0.55362,9.21573],"type":"Point"}
}