{
  "type": "Feature",
  "properties": {
    "gn:admin1_code":"00",
    "gn:asciiname":"Petuduasi",
    "gn:country_code":"GH",
    "gn:dem":42,
    "gn:feature_class":"P",
    "gn:feature_code":"PPL",
    "gn:name":"Petuduasi",
    "gn:population":0,
    "gn:timezone":"Africa/Accra",
    "iso:country":"GH",
    "name:und_x_variant":[
        "Petuduase",
        "Petuduasi"
    ],
    "wof:name":"Petuduasi",
    "wof:placetype":"locality"
},
  "geometry": {"coordinates":[-0.49363,5.41099],"type":"Point"}
}