{
  "type": "Feature",
  "properties": {
    "gn:admin1_code":"00",
    "gn:asciiname":"Punda",
    "gn:country_code":"GH",
    "gn:dem":107,
    "gn:feature_class":"P",
    "gn:feature_code":"PPL",
    "gn:name":"Punda",
    "gn:population":0,
    "gn:timezone":"Africa/Accra",
    "iso:country":"GH",
    "wof:name":"Punda",
    "wof:placetype":"locality"
},
  "geometry": {"coordinates":[-1.47665,5.46057],"type":"Point"}
}