{
  "type": "Feature",
  "properties": {
    "gn:admin1_code":"00",
    "gn:asciiname":"Oboasiwa",
    "gn:country_code":"GH",
    "gn:dem":199,
    "gn:feature_class":"P",
    "gn:feature_code":"PPL",
    "gn:name":"Oboasiwa",
    "gn:population":0,
    "gn:timezone":"Africa/Accra",
    "iso:country":"GH",
    "wof:name":"Oboasiwa",
    "wof:placetype":"locality"
},
  "geometry": {"coordinates":[-1.33619,6.22383],"type":"Point"}
}