{
  "type": "Feature",
  "properties": {
    "gn:admin1_code":"00",
    "gn:asciiname":"Kwamkrom",
    "gn:country_code":"GH",
    "gn:dem":66,
    "gn:feature_class":"P",
    "gn:feature_code":"PPL",
    "gn:name":"Kwamkrom",
    "gn:population":0,
    "gn:timezone":"Africa/Accra",
    "iso:country":"GH",
    "wof:name":"Kwamkrom",
    "wof:placetype":"locality"
},
  "geometry": {"coordinates":[-2.14209,5.04403],"type":"Point"}
}