{
  "type": "Feature",
  "properties": {
    "gn:admin1_code":"00",
    "gn:asciiname":"Akwaseho",
    "gn:country_code":"GH",
    "gn:dem":246,
    "gn:feature_class":"P",
    "gn:feature_code":"PPL",
    "gn:name":"Akwaseho",
    "gn:population":0,
    "gn:timezone":"Africa/Accra",
    "iso:country":"GH",
    "wof:name":"Akwaseho",
    "wof:placetype":"locality"
},
  "geometry": {"coordinates":[-0.82216,6.61908],"type":"Point"}
}