{
  "type": "Feature",
  "properties": {
    "gn:admin1_code":"01",
    "gn:asciiname":"Okushibiade",
    "gn:country_code":"GH",
    "gn:dem":32,
    "gn:feature_class":"P",
    "gn:feature_code":"PPL",
    "gn:name":"Okushibiade",
    "gn:population":0,
    "gn:timezone":"Africa/Accra",
    "iso:country":"GH",
    "name:und_x_variant":[
        "Okushibiadi"
    ],
    "wof:name":"Okushibiade",
    "wof:placetype":"locality"
},
  "geometry": {"coordinates":[-0.38599,5.69921],"type":"Point"}
}