{
  "type": "Feature",
  "properties": {
    "gn:admin1_code":"00",
    "gn:asciiname":"Bantamfarigu",
    "gn:country_code":"GH",
    "gn:dem":230,
    "gn:feature_class":"P",
    "gn:feature_code":"PPL",
    "gn:name":"Bantamfarigu",
    "gn:population":0,
    "gn:timezone":"Africa/Accra",
    "iso:country":"GH",
    "name:und_x_variant":[
        "Bantavarigu",
        "Bantamfarigu"
    ],
    "wof:name":"Bantamfarigu",
    "wof:placetype":"locality"
},
  "geometry": {"coordinates":[-0.18314,10.75905],"type":"Point"}
}