{
  "type": "Feature",
  "properties": {
    "gn:admin1_code":"00",
    "gn:asciiname":"Lanobe",
    "gn:country_code":"GH",
    "gn:dem":140,
    "gn:feature_class":"P",
    "gn:feature_code":"PPL",
    "gn:name":"Lanobe",
    "gn:population":0,
    "gn:timezone":"Africa/Accra",
    "iso:country":"GH",
    "wof:name":"Lanobe",
    "wof:placetype":"locality"
},
  "geometry": {"coordinates":[-0.23333,10.16667],"type":"Point"}
}