{
  "type": "Feature",
  "properties": {
    "gn:admin1_code":"11",
    "gn:asciiname":"Burutu",
    "gn:country_code":"GH",
    "gn:dem":275,
    "gn:feature_class":"P",
    "gn:feature_code":"PPL",
    "gn:name":"Burutu",
    "gn:population":0,
    "gn:timezone":"Africa/Accra",
    "iso:country":"GH",
    "name:und_x_variant":[
        "Burufu"
    ],
    "wof:name":"Burutu",
    "wof:placetype":"locality"
},
  "geometry": {"coordinates":[-2.74905,10.82892],"type":"Point"}
}