{
  "type": "Feature",
  "properties": {
    "gn:admin1_code":"04",
    "gn:asciiname":"Anomadodom",
    "gn:country_code":"GH",
    "gn:dem":118,
    "gn:feature_class":"P",
    "gn:feature_code":"PPL",
    "gn:name":"Anomadodom",
    "gn:population":0,
    "gn:timezone":"Africa/Accra",
    "iso:country":"GH",
    "name:eng_x_preferred":[
        "Anomadodom"
    ],
    "wof:name":"Anomadodom",
    "wof:placetype":"locality"
},
  "geometry": {"coordinates":[-1.66328,5.89142],"type":"Point"}
}