{
  "type": "Feature",
  "properties": {
    "gn:admin1_code":"00",
    "gn:asciiname":"Agogoso",
    "gn:country_code":"GH",
    "gn:dem":124,
    "gn:feature_class":"P",
    "gn:feature_code":"PPL",
    "gn:name":"Agogoso",
    "gn:population":0,
    "gn:timezone":"Africa/Accra",
    "iso:country":"GH",
    "wof:name":"Agogoso",
    "wof:placetype":"locality"
},
  "geometry": {"coordinates":[-1.49615,6.10627],"type":"Point"}
}