{
  "type": "Feature",
  "properties": {
    "gn:admin1_code":"03",
    "gn:asciiname":"Apesika",
    "gn:country_code":"GH",
    "gn:dem":327,
    "gn:feature_class":"P",
    "gn:feature_code":"PPL",
    "gn:name":"Apesika",
    "gn:population":0,
    "gn:timezone":"Africa/Accra",
    "iso:country":"GH",
    "wof:name":"Apesika",
    "wof:placetype":"locality"
},
  "geometry": {"coordinates":[-1.5453,7.99838],"type":"Point"}
}