{
  "type": "Feature",
  "properties": {
    "gn:admin1_code":"00",
    "gn:asciiname":"Kikaziegu",
    "gn:cc2":"GH",
    "gn:country_code":"GH",
    "gn:dem":182,
    "gn:feature_class":"P",
    "gn:feature_code":"PPL",
    "gn:name":"Kikaziegu",
    "gn:population":0,
    "gn:timezone":"Africa/Accra",
    "iso:country":"GH",
    "name:und_x_variant":[
        "Kakansiga",
        "Kikaziegu"
    ],
    "wof:name":"Kikaziegu",
    "wof:placetype":"locality"
},
  "geometry": {"coordinates":[-0.21667,10.91667],"type":"Point"}
}