{
  "type": "Feature",
  "properties": {
    "gn:admin1_code":"06",
    "gn:asciiname":"Nagbo",
    "gn:country_code":"GH",
    "gn:dem":279,
    "gn:feature_class":"P",
    "gn:feature_code":"PPL",
    "gn:name":"Nagbo",
    "gn:population":0,
    "gn:timezone":"Africa/Accra",
    "iso:country":"GH",
    "name:und_x_variant":[
        "Nagbog",
        "Nagbo"
    ],
    "wof:name":"Nagbo",
    "wof:placetype":"locality"
},
  "geometry": {"coordinates":[-0.3524,10.47015],"type":"Point"}
}