{
  "type": "Feature",
  "properties": {
    "gn:admin1_code":"08",
    "gn:asciiname":"Aginukope",
    "gn:country_code":"GH",
    "gn:dem":27,
    "gn:feature_class":"P",
    "gn:feature_code":"PPL",
    "gn:name":"Aginukope",
    "gn:population":0,
    "gn:timezone":"Africa/Accra",
    "iso:country":"GH",
    "name:und_x_variant":[
        "Aginukofe",
        "Adzinukorpe",
        "Aginukope"
    ],
    "wof:name":"Aginukope",
    "wof:placetype":"locality"
},
  "geometry": {"coordinates":[1.02797,6.13155],"type":"Point"}
}