{
  "type": "Feature",
  "properties": {
    "gn:admin1_code":"00",
    "gn:asciiname":"Balungu",
    "gn:country_code":"GH",
    "gn:dem":175,
    "gn:feature_class":"P",
    "gn:feature_code":"PPL",
    "gn:name":"Balungu",
    "gn:population":0,
    "gn:timezone":"Africa/Accra",
    "iso:country":"GH",
    "name:und_x_variant":[
        "Baluagu",
        "Belungu",
        "Balungu Akpaligabisi",
        "Balung",
        "Balungu"
    ],
    "wof:name":"Balungu",
    "wof:placetype":"locality"
},
  "geometry": {"coordinates":[-0.8696,10.643],"type":"Point"}
}