{
  "type": "Feature",
  "properties": {
    "gn:admin1_code":"00",
    "gn:asciiname":"Palagu",
    "gn:country_code":"GH",
    "gn:dem":241,
    "gn:feature_class":"P",
    "gn:feature_code":"PPL",
    "gn:name":"Palagu",
    "gn:population":0,
    "gn:timezone":"Africa/Accra",
    "iso:country":"GH",
    "name:und_x_variant":[
        "Kpaligu",
        "Paliga",
        "Palagu"
    ],
    "wof:name":"Palagu",
    "wof:placetype":"locality"
},
  "geometry": {"coordinates":[-0.30079,11.03513],"type":"Point"}
}