{
  "type": "Feature",
  "properties": {
    "gn:admin1_code":"00",
    "gn:asciiname":"Fanchirinko",
    "gn:country_code":"GH",
    "gn:dem":50,
    "gn:feature_class":"P",
    "gn:feature_code":"PPL",
    "gn:name":"Fanchirinko",
    "gn:population":0,
    "gn:timezone":"Africa/Accra",
    "iso:country":"GH",
    "name:und_x_variant":[
        "Panchirinko",
        "Fanchirinko"
    ],
    "wof:name":"Fanchirinko",
    "wof:placetype":"locality"
},
  "geometry": {"coordinates":[0.32083,6.32573],"type":"Point"}
}