{
  "type": "Feature",
  "properties": {
    "gn:admin1_code":"00",
    "gn:asciiname":"Konda",
    "gn:country_code":"GH",
    "gn:dem":172,
    "gn:feature_class":"P",
    "gn:feature_code":"PPL",
    "gn:name":"Konda",
    "gn:population":0,
    "gn:timezone":"Africa/Accra",
    "iso:country":"GH",
    "name:ceb_x_preferred":[
        "Konda"
    ],
    "name:deu_x_preferred":[
        "Konda"
    ],
    "name:fra_x_preferred":[
        "Konda"
    ],
    "name:ita_x_preferred":[
        "Konda"
    ],
    "name:swe_x_preferred":[
        "Konda"
    ],
    "name:und_x_variant":[
        "Vakpo Konda",
        "Konda"
    ],
    "wof:name":"Konda",
    "wof:placetype":"locality"
},
  "geometry": {"coordinates":[0.28884,6.93851],"type":"Point"}
}