{
  "type": "Feature",
  "properties": {
    "gn:admin1_code":"00",
    "gn:asciiname":"Kaptun",
    "gn:country_code":"GH",
    "gn:dem":146,
    "gn:feature_class":"P",
    "gn:feature_code":"PPL",
    "gn:name":"Kaptun",
    "gn:population":0,
    "gn:timezone":"Africa/Accra",
    "iso:country":"GH",
    "wof:name":"Kaptun",
    "wof:placetype":"locality"
},
  "geometry": {"coordinates":[-0.31078,10.09867],"type":"Point"}
}