{
  "type": "Feature",
  "properties": {
    "gn:admin1_code":"00",
    "gn:asciiname":"Dukuma",
    "gn:country_code":"GH",
    "gn:dem":262,
    "gn:feature_class":"P",
    "gn:feature_code":"PPL",
    "gn:name":"Dukuma",
    "gn:population":0,
    "gn:timezone":"Africa/Accra",
    "iso:country":"GH",
    "wof:name":"Dukuma",
    "wof:placetype":"locality"
},
  "geometry": {"coordinates":[0.27391,6.79957],"type":"Point"}
}