{
  "type": "Feature",
  "properties": {
    "gn:admin1_code":"00",
    "gn:asciiname":"Namunyokofe",
    "gn:country_code":"GH",
    "gn:dem":81,
    "gn:feature_class":"P",
    "gn:feature_code":"PPL",
    "gn:name":"Namunyokofe",
    "gn:population":0,
    "gn:timezone":"Africa/Accra",
    "iso:country":"GH",
    "wof:name":"Namunyokofe",
    "wof:placetype":"locality"
},
  "geometry": {"coordinates":[0.71667,6.55],"type":"Point"}
}