{
  "type": "Feature",
  "properties": {
    "gn:admin1_code":"00",
    "gn:asciiname":"Gbankuoni",
    "gn:country_code":"GH",
    "gn:dem":323,
    "gn:feature_class":"P",
    "gn:feature_code":"PPL",
    "gn:name":"Gbankuoni",
    "gn:population":0,
    "gn:timezone":"Africa/Accra",
    "iso:country":"GH",
    "name:und_x_variant":[
        "Gbankoni",
        "Gbankuoni"
    ],
    "wof:name":"Gbankuoni",
    "wof:placetype":"locality"
},
  "geometry": {"coordinates":[0.04111,10.59323],"type":"Point"}
}