{
  "type": "Feature",
  "properties": {
    "gn:admin1_code":"00",
    "gn:asciiname":"Senche",
    "gn:country_code":"GH",
    "gn:dem":59,
    "gn:feature_class":"P",
    "gn:feature_code":"PPL",
    "gn:name":"Senche",
    "gn:population":0,
    "gn:timezone":"Africa/Accra",
    "iso:country":"GH",
    "name:und_x_variant":[
        "Senkye Beposo",
        "Senche"
    ],
    "wof:name":"Senche",
    "wof:placetype":"locality"
},
  "geometry": {"coordinates":[-2.07641,5.47899],"type":"Point"}
}