{
  "type": "Feature",
  "properties": {
    "gn:admin1_code":"00",
    "gn:asciiname":"Nabuluga",
    "gn:country_code":"GH",
    "gn:dem":157,
    "gn:feature_class":"P",
    "gn:feature_code":"PPL",
    "gn:name":"Nabuluga",
    "gn:population":0,
    "gn:timezone":"Africa/Accra",
    "iso:country":"GH",
    "name:und_x_variant":[
        "Nabulugu",
        "Nabuluga"
    ],
    "wof:name":"Nabuluga",
    "wof:placetype":"locality"
},
  "geometry": {"coordinates":[-0.65643,10.32553],"type":"Point"}
}