{
  "type": "Feature",
  "properties": {
    "gn:admin1_code":"11",
    "gn:asciiname":"Metaw",
    "gn:country_code":"GH",
    "gn:dem":249,
    "gn:feature_class":"P",
    "gn:feature_code":"PPL",
    "gn:name":"Metaw",
    "gn:population":0,
    "gn:timezone":"Africa/Accra",
    "iso:country":"GH",
    "name:und_x_variant":[
        "Meto",
        "Metaw"
    ],
    "wof:name":"Metaw",
    "wof:placetype":"locality"
},
  "geometry": {"coordinates":[-2.89226,10.5573],"type":"Point"}
}