{
  "type": "Feature",
  "properties": {
    "gn:admin1_code":"00",
    "gn:asciiname":"Asikuma",
    "gn:country_code":"GH",
    "gn:dem":74,
    "gn:feature_class":"P",
    "gn:feature_code":"PPL",
    "gn:name":"Asikuma",
    "gn:population":0,
    "gn:timezone":"Africa/Accra",
    "iso:country":"GH",
    "name:und_x_variant":[
        "Esikuma",
        "Asikuma"
    ],
    "wof:name":"Asikuma",
    "wof:placetype":"locality"
},
  "geometry": {"coordinates":[-0.99433,5.58333],"type":"Point"}
}