{
  "type": "Feature",
  "properties": {
    "gn:admin1_code":"02",
    "gn:asciiname":"Ampabame",
    "gn:country_code":"GH",
    "gn:dem":270,
    "gn:feature_class":"P",
    "gn:feature_code":"PPL",
    "gn:name":"Ampabame",
    "gn:population":0,
    "gn:timezone":"Africa/Accra",
    "iso:country":"GH",
    "name:eng_x_preferred":[
        "Ampabame"
    ],
    "name:eng_x_variant":[
        "Ampabami"
    ],
    "wof:name":"Ampabame",
    "wof:placetype":"locality"
},
  "geometry": {"coordinates":[-1.64475,6.71629],"type":"Point"}
}