{
  "type": "Feature",
  "properties": {
    "gn:admin1_code":"00",
    "gn:asciiname":"Difa",
    "gn:country_code":"GH",
    "gn:dem":155,
    "gn:feature_class":"P",
    "gn:feature_code":"PPL",
    "gn:name":"Difa",
    "gn:population":0,
    "gn:timezone":"Africa/Accra",
    "iso:country":"GH",
    "name:ara_x_preferred":[
        "\u062f\u064a\u0641\u0629"
    ],
    "name:fas_x_preferred":[
        "\u062f\u06cc\u0641\u0647"
    ],
    "name:pol_x_preferred":[
        "Difa"
    ],
    "name:und_x_variant":[
        "Difaa",
        "Defa",
        "Dila"
    ],
    "name:vie_x_preferred":[
        "Difa"
    ],
    "wof:name":"Difa",
    "wof:placetype":"locality"
},
  "geometry": {"coordinates":[-0.75062,9.35474],"type":"Point"}
}