{
  "type": "Feature",
  "properties": {
    "gn:admin1_code":"00",
    "gn:asciiname":"Difa",
    "gn:country_code":"GH",
    "gn:dem":155,
    "gn:feature_class":"P",
    "gn:feature_code":"PPL",
    "gn:name":"Difa",
    "gn:population":0,
    "gn:timezone":"Africa/Accra",
    "iso:country":"GH",
    "name:und_x_variant":[
        "Difaa",
        "Defa",
        "Dila",
        "Difa"
    ],
    "wof:name":"Difa",
    "wof:placetype":"locality"
},
  "geometry": {"coordinates":[-0.75062,9.35474],"type":"Point"}
}