{
  "type": "Feature",
  "properties": {
    "gn:admin1_code":"00",
    "gn:asciiname":"Taga",
    "gn:country_code":"GH",
    "gn:dem":18,
    "gn:feature_class":"P",
    "gn:feature_code":"PPL",
    "gn:name":"Taga",
    "gn:population":0,
    "gn:timezone":"Africa/Accra",
    "iso:country":"GH",
    "name:cat_x_preferred":[
        "Taga"
    ],
    "name:ceb_x_preferred":[
        "Taga"
    ],
    "name:deu_x_preferred":[
        "Taga"
    ],
    "name:fra_x_preferred":[
        "Taga"
    ],
    "name:hun_x_preferred":[
        "Taga"
    ],
    "name:ita_x_preferred":[
        "Taga"
    ],
    "name:nld_x_preferred":[
        "Taga"
    ],
    "name:por_x_preferred":[
        "Taga"
    ],
    "name:vie_x_preferred":[
        "Taga"
    ],
    "wof:name":"Taga",
    "wof:placetype":"locality"
},
  "geometry": {"coordinates":[0.23333,6.18333],"type":"Point"}
}