{
  "type": "Feature",
  "properties": {
    "gn:admin1_code":"00",
    "gn:asciiname":"Babujan",
    "gn:country_code":"GH",
    "gn:dem":251,
    "gn:feature_class":"P",
    "gn:feature_code":"PPL",
    "gn:name":"Babujan",
    "gn:population":0,
    "gn:timezone":"Africa/Accra",
    "iso:country":"GH",
    "wof:name":"Babujan",
    "wof:placetype":"locality"
},
  "geometry": {"coordinates":[-1.68333,10.65],"type":"Point"}
}