{
  "type": "Feature",
  "properties": {
    "gn:admin1_code":"08",
    "gn:asciiname":"Adidotoe",
    "gn:country_code":"GH",
    "gn:dem":19,
    "gn:feature_class":"P",
    "gn:feature_code":"PPL",
    "gn:name":"Adidotoe",
    "gn:population":0,
    "gn:timezone":"Africa/Accra",
    "iso:country":"GH",
    "wof:name":"Adidotoe",
    "wof:placetype":"locality"
},
  "geometry": {"coordinates":[1.1125,6.13194],"type":"Point"}
}