{
  "type": "Feature",
  "properties": {
    "gn:admin1_code":"02",
    "gn:asciiname":"Awaduwankwanta",
    "gn:country_code":"GH",
    "gn:dem":226,
    "gn:feature_class":"P",
    "gn:feature_code":"PPL",
    "gn:name":"Awaduwankwanta",
    "gn:population":0,
    "gn:timezone":"Africa/Accra",
    "iso:country":"GH",
    "name:eng_x_preferred":[
        "Awaduwankwanta"
    ],
    "name:eng_x_variant":[
        "Mposo"
    ],
    "wof:name":"Awaduwankwanta",
    "wof:placetype":"locality"
},
  "geometry": {"coordinates":[-1.97898,6.80461],"type":"Point"}
}