{
  "type": "Feature",
  "properties": {
    "gn:admin1_code":"00",
    "gn:asciiname":"Dahum",
    "gn:country_code":"GH",
    "gn:dem":96,
    "gn:feature_class":"P",
    "gn:feature_code":"PPL",
    "gn:name":"Dahum",
    "gn:population":0,
    "gn:timezone":"Africa/Accra",
    "iso:country":"GH",
    "wof:name":"Dahum",
    "wof:placetype":"locality"
},
  "geometry": {"coordinates":[-0.74758,5.47969],"type":"Point"}
}