{
  "type": "Feature",
  "properties": {
    "gn:admin1_code":"00",
    "gn:asciiname":"Famaye",
    "gn:country_code":"GH",
    "gn:dem":54,
    "gn:feature_class":"P",
    "gn:feature_code":"PPL",
    "gn:name":"Famaye",
    "gn:population":0,
    "gn:timezone":"Africa/Accra",
    "iso:country":"GH",
    "name:und_x_variant":[
        "Fawomanye",
        "Famaye"
    ],
    "wof:name":"Famaye",
    "wof:placetype":"locality"
},
  "geometry": {"coordinates":[-1.04977,5.44014],"type":"Point"}
}