{
  "type": "Feature",
  "properties": {
    "gn:admin1_code":"00",
    "gn:asciiname":"Aboduem",
    "gn:country_code":"GH",
    "gn:dem":280,
    "gn:feature_class":"P",
    "gn:feature_code":"PPL",
    "gn:name":"Aboduem",
    "gn:population":0,
    "gn:timezone":"Africa/Accra",
    "iso:country":"GH",
    "name:und_x_variant":[
        "Abodum",
        "Aboduam",
        "Aboduem"
    ],
    "wof:name":"Aboduem",
    "wof:placetype":"locality"
},
  "geometry": {"coordinates":[-2.46027,6.21202],"type":"Point"}
}