{
  "type": "Feature",
  "properties": {
    "gn:admin1_code":"02",
    "gn:asciiname":"Dominasi",
    "gn:country_code":"GH",
    "gn:dem":221,
    "gn:feature_class":"P",
    "gn:feature_code":"PPL",
    "gn:name":"Dominasi",
    "gn:population":0,
    "gn:timezone":"Africa/Accra",
    "iso:country":"GH",
    "name:eng_x_preferred":[
        "Dominasi"
    ],
    "wof:name":"Dominasi",
    "wof:placetype":"locality"
},
  "geometry": {"coordinates":[-1.70778,6.68201],"type":"Point"}
}