{
  "type": "Feature",
  "properties": {
    "gn:admin1_code":"00",
    "gn:asciiname":"Surukrom",
    "gn:country_code":"GH",
    "gn:dem":144,
    "gn:feature_class":"P",
    "gn:feature_code":"PPL",
    "gn:name":"Surukrom",
    "gn:population":0,
    "gn:timezone":"Africa/Accra",
    "iso:country":"GH",
    "name:und_x_variant":[
        "Surukom",
        "Surukrom"
    ],
    "wof:name":"Surukrom",
    "wof:placetype":"locality"
},
  "geometry": {"coordinates":[-0.4365,7.21822],"type":"Point"}
}