{
  "type": "Feature",
  "properties": {
    "gn:admin1_code":"00",
    "gn:asciiname":"Nwoasi",
    "gn:country_code":"GH",
    "gn:dem":281,
    "gn:feature_class":"P",
    "gn:feature_code":"PPL",
    "gn:name":"Nwoasi",
    "gn:population":0,
    "gn:timezone":"Africa/Accra",
    "iso:country":"GH",
    "name:und_x_variant":[
        "Nwoase",
        "Nwoasi"
    ],
    "wof:name":"Nwoasi",
    "wof:placetype":"locality"
},
  "geometry": {"coordinates":[-2.04098,7.81593],"type":"Point"}
}