{
  "type": "Feature",
  "properties": {
    "gn:admin1_code":"00",
    "gn:asciiname":"Bomli",
    "gn:country_code":"GH",
    "gn:dem":68,
    "gn:feature_class":"P",
    "gn:feature_code":"PPL",
    "gn:name":"Bomli",
    "gn:population":0,
    "gn:timezone":"Africa/Accra",
    "iso:country":"GH",
    "wof:name":"Bomli",
    "wof:placetype":"locality"
},
  "geometry": {"coordinates":[0.20523,6.40239],"type":"Point"}
}