{
  "type": "Feature",
  "properties": {
    "gn:admin1_code":"00",
    "gn:asciiname":"Togbeve",
    "gn:country_code":"GH",
    "gn:dem":19,
    "gn:feature_class":"P",
    "gn:feature_code":"PPL",
    "gn:name":"Togbeve",
    "gn:population":0,
    "gn:timezone":"Africa/Accra",
    "iso:country":"GH",
    "name:und_x_variant":[
        "Torgbeve",
        "Togbeve"
    ],
    "wof:name":"Togbeve",
    "wof:placetype":"locality"
},
  "geometry": {"coordinates":[0.99435,6.17181],"type":"Point"}
}