{
  "type": "Feature",
  "properties": {
    "gn:admin1_code":"09",
    "gn:asciiname":"Kwesiadaikroa",
    "gn:country_code":"GH",
    "gn:dem":213,
    "gn:feature_class":"P",
    "gn:feature_code":"PPL",
    "gn:name":"Kwesiadaikroa",
    "gn:population":0,
    "gn:timezone":"Africa/Accra",
    "iso:country":"GH",
    "name:eng_x_preferred":[
        "Kwesiadaikroa"
    ],
    "wof:name":"Kwesiadaikroa",
    "wof:placetype":"locality"
},
  "geometry": {"coordinates":[-1.94855,5.88091],"type":"Point"}
}