{
  "type": "Feature",
  "properties": {
    "gn:admin1_code":"11",
    "gn:asciiname":"Korro",
    "gn:country_code":"GH",
    "gn:dem":297,
    "gn:feature_class":"P",
    "gn:feature_code":"PPL",
    "gn:name":"Korro",
    "gn:population":0,
    "gn:timezone":"Africa/Accra",
    "iso:country":"GH",
    "name:eng_x_preferred":[
        "Korro"
    ],
    "wof:name":"Korro",
    "wof:placetype":"locality"
},
  "geometry": {"coordinates":[-2.60491,10.91208],"type":"Point"}
}