{
  "type": "Feature",
  "properties": {
    "gn:admin1_code":"00",
    "gn:asciiname":"Agbokofe",
    "gn:country_code":"GH",
    "gn:dem":83,
    "gn:feature_class":"P",
    "gn:feature_code":"PPL",
    "gn:name":"Agbokofe",
    "gn:population":0,
    "gn:timezone":"Africa/Accra",
    "iso:country":"GH",
    "name:und_x_variant":[
        "Agbokorpe",
        "Agbokofe"
    ],
    "wof:name":"Agbokofe",
    "wof:placetype":"locality"
},
  "geometry": {"coordinates":[0.71695,6.49254],"type":"Point"}
}