{
  "type": "Feature",
  "properties": {
    "gn:admin1_code":"00",
    "gn:asciiname":"Lofortoe",
    "gn:country_code":"GH",
    "gn:dem":18,
    "gn:feature_class":"P",
    "gn:feature_code":"PPL",
    "gn:name":"Lofortoe",
    "gn:population":0,
    "gn:timezone":"Africa/Accra",
    "iso:country":"GH",
    "wof:name":"Lofortoe",
    "wof:placetype":"locality"
},
  "geometry": {"coordinates":[0.73333,6.18333],"type":"Point"}
}