{
  "type": "Feature",
  "properties": {
    "gn:admin1_code":"04",
    "gn:asciiname":"Subunukrom",
    "gn:country_code":"GH",
    "gn:dem":91,
    "gn:feature_class":"P",
    "gn:feature_code":"PPL",
    "gn:name":"Subunukrom",
    "gn:population":0,
    "gn:timezone":"Africa/Accra",
    "iso:country":"GH",
    "name:eng_x_preferred":[
        "Subunukrom"
    ],
    "wof:name":"Subunukrom",
    "wof:placetype":"locality"
},
  "geometry": {"coordinates":[-1.52363,5.84861],"type":"Point"}
}