{
  "type": "Feature",
  "properties": {
    "gn:admin1_code":"02",
    "gn:asciiname":"Kubi",
    "gn:country_code":"GH",
    "gn:dem":147,
    "gn:feature_class":"P",
    "gn:feature_code":"PPL",
    "gn:name":"Kubi",
    "gn:population":0,
    "gn:timezone":"Africa/Accra",
    "iso:country":"GH",
    "name:eng_x_preferred":[
        "Kubi"
    ],
    "wof:name":"Kubi",
    "wof:placetype":"locality"
},
  "geometry": {"coordinates":[-1.73391,5.99944],"type":"Point"}
}