{
  "type": "Feature",
  "properties": {
    "gn:admin1_code":"09",
    "gn:asciiname":"Eborabo",
    "gn:country_code":"GH",
    "gn:dem":9,
    "gn:feature_class":"P",
    "gn:feature_code":"PPL",
    "gn:name":"Eborabo",
    "gn:population":0,
    "gn:timezone":"Africa/Abidjan",
    "iso:country":"GH",
    "name:eng_x_preferred":[
        "Eborabo"
    ],
    "wof:name":"Eborabo",
    "wof:placetype":"locality"
},
  "geometry": {"coordinates":[-2.95806,5.0849],"type":"Point"}
}