{
  "type": "Feature",
  "properties": {
    "gn:admin1_code":"02",
    "gn:asciiname":"Aduatu",
    "gn:country_code":"GH",
    "gn:dem":229,
    "gn:feature_class":"P",
    "gn:feature_code":"PPL",
    "gn:name":"Aduatu",
    "gn:population":0,
    "gn:timezone":"Africa/Accra",
    "iso:country":"GH",
    "name:eng_x_preferred":[
        "Aduatu"
    ],
    "wof:name":"Aduatu",
    "wof:placetype":"locality"
},
  "geometry": {"coordinates":[-1.75283,6.50751],"type":"Point"}
}