{
  "type": "Feature",
  "properties": {
    "gn:admin1_code":"00",
    "gn:asciiname":"Salimana",
    "gn:country_code":"GH",
    "gn:dem":255,
    "gn:feature_class":"P",
    "gn:feature_code":"PPL",
    "gn:name":"Salimana",
    "gn:population":0,
    "gn:timezone":"Africa/Accra",
    "iso:country":"GH",
    "wof:name":"Salimana",
    "wof:placetype":"locality"
},
  "geometry": {"coordinates":[-2.64295,9.98541],"type":"Point"}
}