{
  "type": "Feature",
  "properties": {
    "gn:admin1_code":"00",
    "gn:asciiname":"Latinkpa",
    "gn:country_code":"GH",
    "gn:dem":154,
    "gn:feature_class":"P",
    "gn:feature_code":"PPL",
    "gn:name":"Latinkpa",
    "gn:population":0,
    "gn:timezone":"Africa/Accra",
    "iso:country":"GH",
    "wof:name":"Latinkpa",
    "wof:placetype":"locality"
},
  "geometry": {"coordinates":[-0.36744,8.78964],"type":"Point"}
}