{
  "type": "Feature",
  "properties": {
    "gn:admin1_code":"02",
    "gn:asciiname":"Mmensinase",
    "gn:country_code":"GH",
    "gn:dem":217,
    "gn:feature_class":"P",
    "gn:feature_code":"PPL",
    "gn:name":"Mmensinase",
    "gn:population":0,
    "gn:timezone":"Africa/Accra",
    "iso:country":"GH",
    "name:eng_x_preferred":[
        "Mmensinase"
    ],
    "name:eng_x_variant":[
        "Meninasi"
    ],
    "name:und_x_variant":[
        "Mensinase",
        "Mensinasi"
    ],
    "wof:name":"Mmensinase",
    "wof:placetype":"locality"
},
  "geometry": {"coordinates":[-1.54862,6.51382],"type":"Point"}
}