{
  "type": "Feature",
  "properties": {
    "gn:admin1_code":"00",
    "gn:asciiname":"Naturi",
    "gn:country_code":"GH",
    "gn:dem":130,
    "gn:feature_class":"P",
    "gn:feature_code":"PPL",
    "gn:name":"Naturi",
    "gn:population":0,
    "gn:timezone":"Africa/Accra",
    "iso:country":"GH",
    "wof:name":"Naturi",
    "wof:placetype":"locality"
},
  "geometry": {"coordinates":[0.31968,10.09154],"type":"Point"}
}