{
  "type": "Feature",
  "properties": {
    "gn:admin1_code":"00",
    "gn:asciiname":"Ajesa",
    "gn:country_code":"GH",
    "gn:dem":11,
    "gn:feature_class":"P",
    "gn:feature_code":"PPL",
    "gn:name":"Ajesa",
    "gn:population":0,
    "gn:timezone":"Africa/Accra",
    "iso:country":"GH",
    "name:und_x_variant":[
        "Agyeza",
        "Ajesa"
    ],
    "wof:name":"Ajesa",
    "wof:placetype":"locality"
},
  "geometry": {"coordinates":[-2.68983,5.01004],"type":"Point"}
}