{
  "type": "Feature",
  "properties": {
    "gn:admin1_code":"00",
    "gn:asciiname":"Banjanin",
    "gn:country_code":"GH",
    "gn:dem":194,
    "gn:feature_class":"P",
    "gn:feature_code":"PPL",
    "gn:name":"Banjanin",
    "gn:population":0,
    "gn:timezone":"Africa/Accra",
    "iso:country":"GH",
    "name:und_x_variant":[
        "Banjani",
        "Banjanin"
    ],
    "wof:name":"Banjanin",
    "wof:placetype":"locality"
},
  "geometry": {"coordinates":[0.27695,10.11601],"type":"Point"}
}