{
  "type": "Feature",
  "properties": {
    "gn:admin1_code":"00",
    "gn:asciiname":"Bremang",
    "gn:country_code":"GH",
    "gn:dem":47,
    "gn:feature_class":"P",
    "gn:feature_code":"PPL",
    "gn:name":"Bremang",
    "gn:population":0,
    "gn:timezone":"Africa/Accra",
    "iso:country":"GH",
    "name:und_x_variant":[
        "Breman Gold Dredge",
        "Bremang"
    ],
    "wof:name":"Bremang",
    "wof:placetype":"locality"
},
  "geometry": {"coordinates":[-2.17115,5.54028],"type":"Point"}
}