{
  "type": "Feature",
  "properties": {
    "gn:admin1_code":"00",
    "gn:asciiname":"Duakwa",
    "gn:country_code":"GH",
    "gn:dem":124,
    "gn:feature_class":"P",
    "gn:feature_code":"PPL",
    "gn:name":"Duakwa",
    "gn:population":0,
    "gn:timezone":"Africa/Accra",
    "iso:country":"GH",
    "wof:name":"Duakwa",
    "wof:placetype":"locality"
},
  "geometry": {"coordinates":[-0.72563,5.63807],"type":"Point"}
}