{
  "type": "Feature",
  "properties": {
    "gn:admin1_code":"00",
    "gn:asciiname":"Warlung",
    "gn:country_code":"GH",
    "gn:dem":137,
    "gn:feature_class":"P",
    "gn:feature_code":"PPL",
    "gn:name":"Warlung",
    "gn:population":0,
    "gn:timezone":"Africa/Accra",
    "iso:country":"GH",
    "name:und_x_variant":[
        "Wonglon",
        "Warlung"
    ],
    "wof:name":"Warlung",
    "wof:placetype":"locality"
},
  "geometry": {"coordinates":[0.38912,9.1027],"type":"Point"}
}