{
  "type": "Feature",
  "properties": {
    "gn:admin1_code":"00",
    "gn:asciiname":"Bukrom",
    "gn:country_code":"GH",
    "gn:dem":402,
    "gn:feature_class":"P",
    "gn:feature_code":"PPL",
    "gn:name":"Bukrom",
    "gn:population":0,
    "gn:timezone":"Africa/Accra",
    "iso:country":"GH",
    "name:und_x_variant":[
        "Bukrom Otseresuana",
        "Bukrom"
    ],
    "wof:name":"Bukrom",
    "wof:placetype":"locality"
},
  "geometry": {"coordinates":[-0.21949,6.25956],"type":"Point"}
}