{
  "type": "Feature",
  "properties": {
    "gn:admin1_code":"02",
    "gn:asciiname":"Nimsua",
    "gn:country_code":"GH",
    "gn:dem":255,
    "gn:feature_class":"P",
    "gn:feature_code":"PPL",
    "gn:name":"Nimsua",
    "gn:population":0,
    "gn:timezone":"Africa/Accra",
    "iso:country":"GH",
    "name:eng_x_preferred":[
        "Nimsua"
    ],
    "wof:name":"Nimsua",
    "wof:placetype":"locality"
},
  "geometry": {"coordinates":[-1.75537,6.89272],"type":"Point"}
}