{
  "type": "Feature",
  "properties": {
    "gn:admin1_code":"00",
    "gn:asciiname":"Nkrang",
    "gn:country_code":"GH",
    "gn:dem":25,
    "gn:feature_class":"P",
    "gn:feature_code":"PPL",
    "gn:name":"Nkrang",
    "gn:population":0,
    "gn:timezone":"Africa/Accra",
    "iso:country":"GH",
    "wof:name":"Nkrang",
    "wof:placetype":"locality"
},
  "geometry": {"coordinates":[-2.11638,5.40301],"type":"Point"}
}