{
  "type": "Feature",
  "properties": {
    "gn:admin1_code":"00",
    "gn:asciiname":"Adame",
    "gn:country_code":"GH",
    "gn:dem":186,
    "gn:feature_class":"P",
    "gn:feature_code":"PPL",
    "gn:name":"Adame",
    "gn:population":0,
    "gn:timezone":"Africa/Accra",
    "iso:country":"GH",
    "name:spa_x_preferred":[
        "Adame"
    ],
    "wof:name":"Adame",
    "wof:placetype":"locality"
},
  "geometry": {"coordinates":[0.27618,6.89124],"type":"Point"}
}