{
  "type": "Feature",
  "properties": {
    "gn:admin1_code":"09",
    "gn:asciiname":"Ausakrom",
    "gn:country_code":"GH",
    "gn:dem":22,
    "gn:feature_class":"P",
    "gn:feature_code":"PPL",
    "gn:name":"Ausakrom",
    "gn:population":0,
    "gn:timezone":"Africa/Accra",
    "iso:country":"GH",
    "name:eng_x_preferred":[
        "Ausakrom"
    ],
    "wof:name":"Ausakrom",
    "wof:placetype":"locality"
},
  "geometry": {"coordinates":[-2.22589,4.89919],"type":"Point"}
}