{
  "type": "Feature",
  "properties": {
    "gn:admin1_code":"00",
    "gn:asciiname":"Todji",
    "gn:country_code":"GH",
    "gn:dem":151,
    "gn:feature_class":"P",
    "gn:feature_code":"PPL",
    "gn:name":"Todji",
    "gn:population":0,
    "gn:timezone":"Africa/Accra",
    "iso:country":"GH",
    "name:und_x_variant":[
        "Todze",
        "Todzi",
        "Todji"
    ],
    "wof:name":"Todji",
    "wof:placetype":"locality"
},
  "geometry": {"coordinates":[0.29919,6.85248],"type":"Point"}
}