{
  "type": "Feature",
  "properties": {
    "gn:admin1_code":"09",
    "gn:asciiname":"Pampamso",
    "gn:country_code":"GH",
    "gn:dem":23,
    "gn:feature_class":"P",
    "gn:feature_code":"PPL",
    "gn:name":"Pampamso",
    "gn:population":0,
    "gn:timezone":"Africa/Accra",
    "iso:country":"GH",
    "name:eng_x_preferred":[
        "Pampamso"
    ],
    "wof:name":"Pampamso",
    "wof:placetype":"locality"
},
  "geometry": {"coordinates":[-2.09718,4.84208],"type":"Point"}
}