{
  "type": "Feature",
  "properties": {
    "gn:admin1_code":"02",
    "gn:asciiname":"Kodeekuma",
    "gn:country_code":"GH",
    "gn:dem":292,
    "gn:feature_class":"P",
    "gn:feature_code":"PPL",
    "gn:name":"Kodeekuma",
    "gn:population":0,
    "gn:timezone":"Africa/Accra",
    "iso:country":"GH",
    "name:eng_x_preferred":[
        "Kodeekuma"
    ],
    "name:eng_x_variant":[
        "Akurowa"
    ],
    "name:und_x_variant":[
        "Kodie Kuma",
        "Kwadia Kuma"
    ],
    "wof:name":"Kodeekuma",
    "wof:placetype":"locality"
},
  "geometry": {"coordinates":[-1.6491,6.808],"type":"Point"}
}