{
  "type": "Feature",
  "properties": {
    "gn:admin1_code":"00",
    "gn:asciiname":"Afienya",
    "gn:country_code":"GH",
    "gn:dem":24,
    "gn:feature_class":"P",
    "gn:feature_code":"PPL",
    "gn:name":"Afienya",
    "gn:population":0,
    "gn:timezone":"Africa/Accra",
    "iso:country":"GH",
    "wof:name":"Afienya",
    "wof:placetype":"locality"
},
  "geometry": {"coordinates":[0.00555,5.80156],"type":"Point"}
}