{
  "type": "Feature",
  "properties": {
    "gn:admin1_code":"00",
    "gn:asciiname":"Bubu",
    "gn:country_code":"GH",
    "gn:dem":108,
    "gn:feature_class":"P",
    "gn:feature_code":"PPL",
    "gn:name":"Bubu",
    "gn:population":0,
    "gn:timezone":"Africa/Accra",
    "iso:country":"GH",
    "wof:name":"Bubu",
    "wof:placetype":"locality"
},
  "geometry": {"coordinates":[-1.48942,5.48513],"type":"Point"}
}