{
  "type": "Feature",
  "properties": {
    "gn:admin1_code":"00",
    "gn:asciiname":"Mampoma",
    "gn:country_code":"GH",
    "gn:dem":102,
    "gn:feature_class":"P",
    "gn:feature_code":"PPL",
    "gn:name":"Mampoma",
    "gn:population":0,
    "gn:timezone":"Africa/Accra",
    "iso:country":"GH",
    "wof:name":"Mampoma",
    "wof:placetype":"locality"
},
  "geometry": {"coordinates":[-1.62809,5.67101],"type":"Point"}
}