{
  "type": "Feature",
  "properties": {
    "gn:admin1_code":"00",
    "gn:asciiname":"Anyinabasi",
    "gn:country_code":"GH",
    "gn:dem":325,
    "gn:feature_class":"P",
    "gn:feature_code":"PPL",
    "gn:name":"Anyinabasi",
    "gn:population":0,
    "gn:timezone":"Africa/Accra",
    "iso:country":"GH",
    "name:und_x_variant":[
        "Wusuta Anyinabase Gbohome",
        "Anyinabasi"
    ],
    "wof:name":"Anyinabasi",
    "wof:placetype":"locality"
},
  "geometry": {"coordinates":[0.24818,6.80656],"type":"Point"}
}