{
  "type": "Feature",
  "properties": {
    "gn:admin1_code":"09",
    "gn:asciiname":"Pebabitina",
    "gn:country_code":"GH",
    "gn:dem":95,
    "gn:feature_class":"P",
    "gn:feature_code":"PPL",
    "gn:name":"Pebabitina",
    "gn:population":0,
    "gn:timezone":"Africa/Accra",
    "iso:country":"GH",
    "name:eng_x_preferred":[
        "Pebabitina"
    ],
    "wof:name":"Pebabitina",
    "wof:placetype":"locality"
},
  "geometry": {"coordinates":[-2.04229,5.79749],"type":"Point"}
}