{
  "type": "Feature",
  "properties": {
    "gn:admin1_code":"00",
    "gn:asciiname":"Ypala",
    "gn:country_code":"GH",
    "gn:dem":313,
    "gn:feature_class":"P",
    "gn:feature_code":"PPL",
    "gn:name":"Ypala",
    "gn:population":0,
    "gn:timezone":"Africa/Accra",
    "iso:country":"GH",
    "name:und_x_variant":[
        "Yipala",
        "Ypala"
    ],
    "wof:name":"Ypala",
    "wof:placetype":"locality"
},
  "geometry": {"coordinates":[-2.41629,9.57502],"type":"Point"}
}