{
  "type": "Feature",
  "properties": {
    "gn:admin1_code":"00",
    "gn:asciiname":"Ayowahu",
    "gn:cc2":"GH",
    "gn:country_code":"GH",
    "gn:dem":177,
    "gn:feature_class":"P",
    "gn:feature_code":"PPL",
    "gn:name":"Ayowahu",
    "gn:population":0,
    "gn:timezone":"Africa/Accra",
    "iso:country":"GH",
    "name:und_x_variant":[
        "Ayowaho Number 1",
        "Ayowahu"
    ],
    "wof:name":"Ayowahu",
    "wof:placetype":"locality"
},
  "geometry": {"coordinates":[-1.28333,6.21667],"type":"Point"}
}