{
  "type": "Feature",
  "properties": {
    "gn:admin1_code":"04",
    "gn:asciiname":"Wusuaba",
    "gn:country_code":"GH",
    "gn:dem":159,
    "gn:feature_class":"P",
    "gn:feature_code":"PPL",
    "gn:name":"Wusuaba",
    "gn:population":0,
    "gn:timezone":"Africa/Accra",
    "iso:country":"GH",
    "name:eng_x_preferred":[
        "Wusuaba"
    ],
    "wof:name":"Wusuaba",
    "wof:placetype":"locality"
},
  "geometry": {"coordinates":[-1.69984,5.79131],"type":"Point"}
}