{
  "type": "Feature",
  "properties": {
    "gn:admin1_code":"00",
    "gn:asciiname":"Pwandu",
    "gn:cc2":"GH",
    "gn:country_code":"GH",
    "gn:dem":142,
    "gn:feature_class":"P",
    "gn:feature_code":"PPL",
    "gn:name":"Pwandu",
    "gn:population":0,
    "gn:timezone":"Africa/Accra",
    "iso:country":"GH",
    "name:und_x_variant":[
        "Kpandu",
        "Pwandu"
    ],
    "wof:name":"Pwandu",
    "wof:placetype":"locality"
},
  "geometry": {"coordinates":[-0.85,9.25],"type":"Point"}
}