{
  "type": "Feature",
  "properties": {
    "gn:admin1_code":"00",
    "gn:asciiname":"Kamsango",
    "gn:country_code":"GH",
    "gn:dem":276,
    "gn:feature_class":"P",
    "gn:feature_code":"PPL",
    "gn:name":"Kamsango",
    "gn:population":0,
    "gn:timezone":"Africa/Accra",
    "iso:country":"GH",
    "name:und_x_variant":[
        "Kansorgo",
        "Kansango",
        "Kamsaugo",
        "Kamsango"
    ],
    "wof:name":"Kamsango",
    "wof:placetype":"locality"
},
  "geometry": {"coordinates":[-0.51437,10.97585],"type":"Point"}
}