{
  "type": "Feature",
  "properties": {
    "gn:admin1_code":"00",
    "gn:asciiname":"Nsuta",
    "gn:country_code":"GH",
    "gn:dem":131,
    "gn:feature_class":"P",
    "gn:feature_code":"PPL",
    "gn:name":"Nsuta",
    "gn:population":0,
    "gn:timezone":"Africa/Accra",
    "iso:country":"GH",
    "name:swe_x_preferred":[
        "Nsuta"
    ],
    "name:zho_x_preferred":[
        "\u6069\u8607\u5854"
    ],
    "wof:name":"Nsuta",
    "wof:placetype":"locality"
},
  "geometry": {"coordinates":[-1.2313,5.62505],"type":"Point"}
}