{
  "type": "Feature",
  "properties": {
    "gn:admin1_code":"00",
    "gn:asciiname":"Akrofonso",
    "gn:country_code":"GH",
    "gn:dem":126,
    "gn:feature_class":"P",
    "gn:feature_code":"PPL",
    "gn:name":"Akrofonso",
    "gn:population":0,
    "gn:timezone":"Africa/Accra",
    "iso:country":"GH",
    "name:aka_x_preferred":[
        "Akrofonso"
    ],
    "wof:name":"Akrofonso",
    "wof:placetype":"locality"
},
  "geometry": {"coordinates":[-1.56255,8.40544],"type":"Point"}
}