{
  "type": "Feature",
  "properties": {
    "gn:admin1_code":"02",
    "gn:asciiname":"Wamahin",
    "gn:country_code":"GH",
    "gn:dem":180,
    "gn:feature_class":"P",
    "gn:feature_code":"PPL",
    "gn:name":"Wamahin",
    "gn:population":0,
    "gn:timezone":"Africa/Accra",
    "iso:country":"GH",
    "name:eng_x_preferred":[
        "Wamahin"
    ],
    "wof:name":"Wamahin",
    "wof:placetype":"locality"
},
  "geometry": {"coordinates":[-1.62009,6.22131],"type":"Point"}
}