{
  "type": "Feature",
  "properties": {
    "gn:admin1_code":"01",
    "gn:asciiname":"Nsaki",
    "gn:country_code":"GH",
    "gn:dem":106,
    "gn:feature_class":"P",
    "gn:feature_code":"PPL",
    "gn:name":"Nsaki",
    "gn:population":0,
    "gn:timezone":"Africa/Accra",
    "iso:country":"GH",
    "wof:name":"Nsaki",
    "wof:placetype":"locality"
},
  "geometry": {"coordinates":[-0.23205,5.78604],"type":"Point"}
}