{
  "type": "Feature",
  "properties": {
    "gn:admin1_code":"09",
    "gn:asciiname":"Ngalichi",
    "gn:country_code":"GH",
    "gn:dem":7,
    "gn:feature_class":"P",
    "gn:feature_code":"PPL",
    "gn:name":"Ngalichi",
    "gn:population":0,
    "gn:timezone":"Africa/Accra",
    "iso:country":"GH",
    "name:und_x_variant":[
        "Ngalechi",
        "Ngalichi"
    ],
    "wof:name":"Ngalichi",
    "wof:placetype":"locality"
},
  "geometry": {"coordinates":[-2.49507,4.96891],"type":"Point"}
}