{
  "type": "Feature",
  "properties": {
    "gn:admin1_code":"00",
    "gn:asciiname":"Botoku",
    "gn:country_code":"GH",
    "gn:dem":170,
    "gn:feature_class":"P",
    "gn:feature_code":"PPL",
    "gn:name":"Botoku",
    "gn:population":0,
    "gn:timezone":"Africa/Accra",
    "iso:country":"GH",
    "wof:name":"Botoku",
    "wof:placetype":"locality"
},
  "geometry": {"coordinates":[0.26667,6.76667],"type":"Point"}
}