{
  "type": "Feature",
  "properties": {
    "gn:admin1_code":"00",
    "gn:asciiname":"Asechanu",
    "gn:country_code":"GH",
    "gn:dem":15,
    "gn:feature_class":"P",
    "gn:feature_code":"PPL",
    "gn:name":"Asechanu",
    "gn:population":0,
    "gn:timezone":"Africa/Accra",
    "iso:country":"GH",
    "name:und_x_variant":[
        "Esuekyir",
        "Asechana",
        "Asechanu"
    ],
    "wof:name":"Asechanu",
    "wof:placetype":"locality"
},
  "geometry": {"coordinates":[-1.30795,5.14646],"type":"Point"}
}