{
  "type": "Feature",
  "properties": {
    "gn:admin1_code":"00",
    "gn:asciiname":"Nwiso",
    "gn:country_code":"GH",
    "gn:dem":194,
    "gn:feature_class":"P",
    "gn:feature_code":"PPL",
    "gn:name":"Nwiso",
    "gn:population":0,
    "gn:timezone":"Africa/Accra",
    "iso:country":"GH",
    "name:und_x_variant":[
        "Nwinso",
        "Nwiso"
    ],
    "wof:name":"Nwiso",
    "wof:placetype":"locality"
},
  "geometry": {"coordinates":[-0.94143,6.45896],"type":"Point"}
}