{
  "type": "Feature",
  "properties": {
    "gn:admin1_code":"00",
    "gn:asciiname":"Zandua",
    "gn:country_code":"GH",
    "gn:dem":131,
    "gn:feature_class":"P",
    "gn:feature_code":"PPL",
    "gn:name":"Zandua",
    "gn:population":0,
    "gn:timezone":"Africa/Accra",
    "iso:country":"GH",
    "name:und_x_variant":[
        "Saandua",
        "Zandua"
    ],
    "wof:name":"Zandua",
    "wof:placetype":"locality"
},
  "geometry": {"coordinates":[-0.291,10.19759],"type":"Point"}
}