{
  "type": "Feature",
  "properties": {
    "gn:admin1_code":"00",
    "gn:asciiname":"Tarankoro",
    "gn:country_code":"GH",
    "gn:dem":98,
    "gn:feature_class":"P",
    "gn:feature_code":"PPL",
    "gn:name":"Tarankoro",
    "gn:population":0,
    "gn:timezone":"Africa/Accra",
    "iso:country":"GH",
    "name:und_x_variant":[
        "Tadankoro",
        "Tarankoro"
    ],
    "wof:name":"Tarankoro",
    "wof:placetype":"locality"
},
  "geometry": {"coordinates":[-0.30277,5.91749],"type":"Point"}
}