{
  "type": "Feature",
  "properties": {
    "gn:admin1_code":"00",
    "gn:asciiname":"Nandukpolugu",
    "gn:cc2":"GH",
    "gn:country_code":"GH",
    "gn:dem":123,
    "gn:feature_class":"P",
    "gn:feature_code":"PPL",
    "gn:name":"Nandukpolugu",
    "gn:population":0,
    "gn:timezone":"Africa/Accra",
    "iso:country":"GH",
    "name:und_x_variant":[
        "Nandupelliga",
        "Nandukpolugu"
    ],
    "wof:name":"Nandukpolugu",
    "wof:placetype":"locality"
},
  "geometry": {"coordinates":[-0.58333,10.11667],"type":"Point"}
}