{
  "type": "Feature",
  "properties": {
    "gn:admin1_code":"00",
    "gn:asciiname":"Nyatechikrom",
    "gn:country_code":"GH",
    "gn:dem":114,
    "gn:feature_class":"P",
    "gn:feature_code":"PPL",
    "gn:name":"Nyatechikrom",
    "gn:population":0,
    "gn:timezone":"Africa/Accra",
    "iso:country":"GH",
    "wof:name":"Nyatechikrom",
    "wof:placetype":"locality"
},
  "geometry": {"coordinates":[-1.40073,5.88036],"type":"Point"}
}