{
  "type": "Feature",
  "properties": {
    "gn:admin1_code":"09",
    "gn:asciiname":"Nsuasi",
    "gn:country_code":"GH",
    "gn:dem":79,
    "gn:feature_class":"P",
    "gn:feature_code":"PPL",
    "gn:name":"Nsuasi",
    "gn:population":0,
    "gn:timezone":"Africa/Accra",
    "iso:country":"GH",
    "name:eng_x_preferred":[
        "Nsuasi"
    ],
    "wof:name":"Nsuasi",
    "wof:placetype":"locality"
},
  "geometry": {"coordinates":[-2.06892,5.78133],"type":"Point"}
}