{
  "type": "Feature",
  "properties": {
    "gn:admin1_code":"00",
    "gn:asciiname":"Kwapon",
    "gn:country_code":"GH",
    "gn:dem":202,
    "gn:feature_class":"P",
    "gn:feature_code":"PPL",
    "gn:name":"Kwapon",
    "gn:population":0,
    "gn:timezone":"Africa/Accra",
    "iso:country":"GH",
    "name:und_x_variant":[
        "Kwapong",
        "Kwapon"
    ],
    "wof:name":"Kwapon",
    "wof:placetype":"locality"
},
  "geometry": {"coordinates":[-2.48052,6.6169],"type":"Point"}
}