{
  "type": "Feature",
  "properties": {
    "gn:admin1_code":"00",
    "gn:asciiname":"Saraha",
    "gn:country_code":"GH",
    "gn:dem":64,
    "gn:feature_class":"P",
    "gn:feature_code":"PPL",
    "gn:name":"Saraha",
    "gn:population":0,
    "gn:timezone":"Africa/Accra",
    "iso:country":"GH",
    "name:ben_x_preferred":[
        "\u09b8\u09b0\u09b9 \u09aa\u09be"
    ],
    "name:bih_x_preferred":[
        "\u0938\u0930\u0939\u092a\u093e"
    ],
    "name:bul_x_preferred":[
        "\u0421\u0430\u0440\u0430\u0445\u0430"
    ],
    "name:ces_x_preferred":[
        "Saraha"
    ],
    "name:cym_x_preferred":[
        "Saraha"
    ],
    "name:deu_x_preferred":[
        "Saraha"
    ],
    "name:hin_x_preferred":[
        "\u0938\u0930\u0939"
    ],
    "name:jpn_x_preferred":[
        "\u30b5\u30e9\u30cf"
    ],
    "name:ori_x_preferred":[
        "\u0b38\u0b30\u0b39\u0b2a\u0b3e"
    ],
    "name:pol_x_preferred":[
        "Saraha"
    ],
    "name:rus_x_preferred":[
        "\u0421\u0430\u0440\u0430\u0445\u0430"
    ],
    "name:spa_x_preferred":[
        "Saraha"
    ],
    "name:ukr_x_preferred":[
        "\u0421\u0430\u0440\u0430\u0445\u0430"
    ],
    "name:zho_x_preferred":[
        "\u85a9\u54c8\u62c9\u5df4"
    ],
    "wof:name":"Saraha",
    "wof:placetype":"locality"
},
  "geometry": {"coordinates":[-0.75,5.46667],"type":"Point"}
}