{
  "type": "Feature",
  "properties": {
    "gn:admin1_code":"00",
    "gn:asciiname":"Saraha",
    "gn:country_code":"GH",
    "gn:dem":64,
    "gn:feature_class":"P",
    "gn:feature_code":"PPL",
    "gn:name":"Saraha",
    "gn:population":0,
    "gn:timezone":"Africa/Accra",
    "iso:country":"GH",
    "wof:name":"Saraha",
    "wof:placetype":"locality"
},
  "geometry": {"coordinates":[-0.75,5.46667],"type":"Point"}
}