{
  "type": "Feature",
  "properties": {
    "gn:admin1_code":"00",
    "gn:asciiname":"Kojobonipe",
    "gn:cc2":"GH",
    "gn:country_code":"GH",
    "gn:dem":153,
    "gn:feature_class":"P",
    "gn:feature_code":"PPL",
    "gn:name":"Kojobonipe",
    "gn:population":0,
    "gn:timezone":"Africa/Accra",
    "iso:country":"GH",
    "name:und_x_variant":[
        "Kwodjobonae",
        "Kojobonipe"
    ],
    "wof:name":"Kojobonipe",
    "wof:placetype":"locality"
},
  "geometry": {"coordinates":[-0.15,8.46667],"type":"Point"}
}