{
  "type": "Feature",
  "properties": {
    "gn:admin1_code":"11",
    "gn:asciiname":"Gengenkpe",
    "gn:country_code":"GH",
    "gn:dem":268,
    "gn:feature_class":"P",
    "gn:feature_code":"PPL",
    "gn:name":"Gengenkpe",
    "gn:population":0,
    "gn:timezone":"Africa/Accra",
    "iso:country":"GH",
    "name:und_x_variant":[
        "Gegempwe"
    ],
    "wof:name":"Gengenkpe",
    "wof:placetype":"locality"
},
  "geometry": {"coordinates":[-2.84869,10.82263],"type":"Point"}
}