{
  "type": "Feature",
  "properties": {
    "gn:admin1_code":"00",
    "gn:asciiname":"Zongo Dagi",
    "gn:country_code":"GH",
    "gn:dem":303,
    "gn:feature_class":"P",
    "gn:feature_code":"PPL",
    "gn:name":"Zongo Dagi",
    "gn:population":0,
    "gn:timezone":"Africa/Accra",
    "iso:country":"GH",
    "name:und_x_variant":[
        "Zongo Dagyi",
        "Zongo Dagi"
    ],
    "wof:name":"Zongo Dagi",
    "wof:placetype":"locality"
},
  "geometry": {"coordinates":[-1.73701,7.9799],"type":"Point"}
}