{
  "type": "Feature",
  "properties": {
    "gn:admin1_code":"00",
    "gn:asciiname":"Keshago",
    "gn:cc2":"GH",
    "gn:country_code":"GH",
    "gn:dem":165,
    "gn:feature_class":"P",
    "gn:feature_code":"PPL",
    "gn:name":"Keshago",
    "gn:population":0,
    "gn:timezone":"Africa/Accra",
    "iso:country":"GH",
    "name:und_x_variant":[
        "Cheshagu",
        "Kiesheggo",
        "Keshago"
    ],
    "wof:name":"Keshago",
    "wof:placetype":"locality"
},
  "geometry": {"coordinates":[-0.95,9.45],"type":"Point"}
}