{
  "type": "Feature",
  "properties": {
    "gn:admin1_code":"04",
    "gn:asciiname":"Besiasi",
    "gn:country_code":"GH",
    "gn:dem":185,
    "gn:feature_class":"P",
    "gn:feature_code":"PPL",
    "gn:name":"Besiasi",
    "gn:population":0,
    "gn:timezone":"Africa/Accra",
    "iso:country":"GH",
    "name:eng_x_preferred":[
        "Besiasi"
    ],
    "wof:name":"Besiasi",
    "wof:placetype":"locality"
},
  "geometry": {"coordinates":[-1.78714,5.75887],"type":"Point"}
}