{
  "type": "Feature",
  "properties": {
    "gn:admin1_code":"00",
    "gn:asciiname":"Atroni",
    "gn:country_code":"GH",
    "gn:dem":221,
    "gn:feature_class":"P",
    "gn:feature_code":"PPL",
    "gn:name":"Atroni",
    "gn:population":0,
    "gn:timezone":"Africa/Accra",
    "iso:country":"GH",
    "name:und_x_variant":[
        "Antronie",
        "Atroni"
    ],
    "wof:name":"Atroni",
    "wof:placetype":"locality"
},
  "geometry": {"coordinates":[-2.40482,7.15876],"type":"Point"}
}