{
  "type": "Feature",
  "properties": {
    "gn:admin1_code":"00",
    "gn:asciiname":"Bediakukrom",
    "gn:country_code":"GH",
    "gn:dem":252,
    "gn:feature_class":"P",
    "gn:feature_code":"PPL",
    "gn:name":"Bediakukrom",
    "gn:population":0,
    "gn:timezone":"Africa/Accra",
    "iso:country":"GH",
    "name:und_x_variant":[
        "Bediakokurom",
        "Bediakukrom"
    ],
    "wof:name":"Bediakukrom",
    "wof:placetype":"locality"
},
  "geometry": {"coordinates":[-2.61852,6.95805],"type":"Point"}
}