{
  "type": "Feature",
  "properties": {
    "gn:admin1_code":"00",
    "gn:asciiname":"Lofito",
    "gn:country_code":"GH",
    "gn:dem":1,
    "gn:feature_class":"P",
    "gn:feature_code":"PPL",
    "gn:name":"Lofito",
    "gn:population":0,
    "gn:timezone":"Africa/Accra",
    "iso:country":"GH",
    "wof:name":"Lofito",
    "wof:placetype":"locality"
},
  "geometry": {"coordinates":[0.81443,5.82802],"type":"Point"}
}