{
  "type": "Feature",
  "properties": {
    "gn:admin1_code":"00",
    "gn:asciiname":"Inkubeta",
    "gn:country_code":"GH",
    "gn:dem":362,
    "gn:feature_class":"P",
    "gn:feature_code":"PPL",
    "gn:name":"Inkubeta",
    "gn:population":0,
    "gn:timezone":"Africa/Accra",
    "iso:country":"GH",
    "name:und_x_variant":[
        "Nkubeta",
        "Inkubeta"
    ],
    "wof:name":"Inkubeta",
    "wof:placetype":"locality"
},
  "geometry": {"coordinates":[-1.43836,7.0696],"type":"Point"}
}