{
  "type": "Feature",
  "properties": {
    "gn:admin1_code":"00",
    "gn:asciiname":"Nzadiapra",
    "gn:country_code":"GH",
    "gn:dem":76,
    "gn:feature_class":"P",
    "gn:feature_code":"PPL",
    "gn:name":"Nzadiapra",
    "gn:population":0,
    "gn:timezone":"Africa/Accra",
    "iso:country":"GH",
    "wof:name":"Nzadiapra",
    "wof:placetype":"locality"
},
  "geometry": {"coordinates":[-2.56667,5.65],"type":"Point"}
}