{
  "type": "Feature",
  "properties": {
    "gn:admin1_code":"02",
    "gn:asciiname":"Asuofuo",
    "gn:country_code":"GH",
    "gn:dem":269,
    "gn:feature_class":"P",
    "gn:feature_code":"PPL",
    "gn:name":"Asuofuo",
    "gn:population":0,
    "gn:timezone":"Africa/Accra",
    "iso:country":"GH",
    "name:eng_x_preferred":[
        "Asuofuo"
    ],
    "name:und_x_variant":[
        "Asuofa",
        "Asuofia"
    ],
    "wof:name":"Asuofuo",
    "wof:placetype":"locality"
},
  "geometry": {"coordinates":[-1.68441,6.77507],"type":"Point"}
}