{
  "type": "Feature",
  "properties": {
    "gn:admin1_code":"09",
    "gn:asciiname":"Sanko",
    "gn:country_code":"GH",
    "gn:dem":29,
    "gn:feature_class":"P",
    "gn:feature_code":"PPL",
    "gn:name":"Sanko",
    "gn:population":0,
    "gn:timezone":"Africa/Accra",
    "iso:country":"GH",
    "name:eng_x_preferred":[
        "Sanko"
    ],
    "name:und_x_variant":[
        "Sankor",
        "Sankro"
    ],
    "wof:name":"Sanko",
    "wof:placetype":"locality"
},
  "geometry": {"coordinates":[-1.96275,4.8268],"type":"Point"}
}