{
  "type": "Feature",
  "properties": {
    "gn:admin1_code":"00",
    "gn:asciiname":"Santienga",
    "gn:country_code":"GH",
    "gn:dem":165,
    "gn:feature_class":"P",
    "gn:feature_code":"PPL",
    "gn:name":"Santienga",
    "gn:population":0,
    "gn:timezone":"Africa/Accra",
    "iso:country":"GH",
    "name:und_x_variant":[
        "Shaka",
        "Santienga"
    ],
    "wof:name":"Santienga",
    "wof:placetype":"locality"
},
  "geometry": {"coordinates":[-0.80772,10.66592],"type":"Point"}
}