{
  "type": "Feature",
  "properties": {
    "gn:admin1_code":"00",
    "gn:asciiname":"Mfranta",
    "gn:country_code":"GH",
    "gn:dem":182,
    "gn:feature_class":"P",
    "gn:feature_code":"PPL",
    "gn:name":"Mfranta",
    "gn:population":0,
    "gn:timezone":"Africa/Accra",
    "iso:country":"GH",
    "wof:name":"Mfranta",
    "wof:placetype":"locality"
},
  "geometry": {"coordinates":[-0.52541,5.99435],"type":"Point"}
}