{
  "type": "Feature",
  "properties": {
    "gn:admin1_code":"02",
    "gn:asciiname":"Kaniago",
    "gn:country_code":"GH",
    "gn:dem":173,
    "gn:feature_class":"P",
    "gn:feature_code":"PPL",
    "gn:name":"Kaniago",
    "gn:population":0,
    "gn:timezone":"Africa/Accra",
    "iso:country":"GH",
    "name:eng_x_preferred":[
        "Kaniago"
    ],
    "name:eng_x_variant":[
        "Dome Kaniago"
    ],
    "name:und_x_variant":[
        "Dome Keniago",
        "Domi Keniago"
    ],
    "wof:name":"Kaniago",
    "wof:placetype":"locality"
},
  "geometry": {"coordinates":[-2.0194,6.369],"type":"Point"}
}