{
  "type": "Feature",
  "properties": {
    "gn:admin1_code":"00",
    "gn:asciiname":"Dabala",
    "gn:country_code":"GH",
    "gn:dem":4,
    "gn:feature_class":"P",
    "gn:feature_code":"PPL",
    "gn:name":"Dabala",
    "gn:population":0,
    "gn:timezone":"Africa/Accra",
    "iso:country":"GH",
    "wof:name":"Dabala",
    "wof:placetype":"locality"
},
  "geometry": {"coordinates":[0.67877,5.97959],"type":"Point"}
}