{
  "type": "Feature",
  "properties": {
    "gn:admin1_code":"00",
    "gn:asciiname":"Agoveme",
    "gn:country_code":"GH",
    "gn:dem":29,
    "gn:feature_class":"P",
    "gn:feature_code":"PPL",
    "gn:name":"Agoveme",
    "gn:population":0,
    "gn:timezone":"Africa/Accra",
    "iso:country":"GH",
    "name:und_x_variant":[
        "Agorveme",
        "Agoveme"
    ],
    "wof:name":"Agoveme",
    "wof:placetype":"locality"
},
  "geometry": {"coordinates":[0.84925,6.07621],"type":"Point"}
}