{
  "type": "Feature",
  "properties": {
    "gn:admin1_code":"00",
    "gn:asciiname":"Amlakpo",
    "gn:country_code":"GH",
    "gn:dem":8,
    "gn:feature_class":"P",
    "gn:feature_code":"PPL",
    "gn:name":"Amlakpo",
    "gn:population":0,
    "gn:timezone":"Africa/Accra",
    "iso:country":"GH",
    "wof:name":"Amlakpo",
    "wof:placetype":"locality"
},
  "geometry": {"coordinates":[0.5029,5.8833],"type":"Point"}
}