{
  "type": "Feature",
  "properties": {
    "gn:admin1_code":"00",
    "gn:asciiname":"Yabogo",
    "gn:country_code":"GH",
    "gn:dem":222,
    "gn:feature_class":"P",
    "gn:feature_code":"PPL",
    "gn:name":"Yabogo",
    "gn:population":0,
    "gn:timezone":"Africa/Accra",
    "iso:country":"GH",
    "name:und_x_variant":[
        "Afumyinga",
        "Yabogo"
    ],
    "wof:name":"Yabogo",
    "wof:placetype":"locality"
},
  "geometry": {"coordinates":[-0.11565,10.05414],"type":"Point"}
}