{
  "type": "Feature",
  "properties": {
    "gn:admin1_code":"00",
    "gn:asciiname":"Ogokrom",
    "gn:country_code":"GH",
    "gn:dem":47,
    "gn:feature_class":"P",
    "gn:feature_code":"PPL",
    "gn:name":"Ogokrom",
    "gn:population":0,
    "gn:timezone":"Africa/Accra",
    "iso:country":"GH",
    "wof:name":"Ogokrom",
    "wof:placetype":"locality"
},
  "geometry": {"coordinates":[-1.10858,5.24104],"type":"Point"}
}