{
  "type": "Feature",
  "properties": {
    "gn:admin1_code":"00",
    "gn:asciiname":"Tokpo",
    "gn:country_code":"GH",
    "gn:dem":10,
    "gn:feature_class":"P",
    "gn:feature_code":"PPL",
    "gn:name":"Tokpo",
    "gn:population":0,
    "gn:timezone":"Africa/Accra",
    "iso:country":"GH",
    "wof:name":"Tokpo",
    "wof:placetype":"locality"
},
  "geometry": {"coordinates":[0.33218,6.03448],"type":"Point"}
}