{
  "type": "Feature",
  "properties": {
    "gn:admin1_code":"00",
    "gn:asciiname":"Agopuigbo",
    "gn:country_code":"GH",
    "gn:dem":3,
    "gn:feature_class":"P",
    "gn:feature_code":"PPL",
    "gn:name":"Agopuigbo",
    "gn:population":0,
    "gn:timezone":"Africa/Accra",
    "iso:country":"GH",
    "wof:name":"Agopuigbo",
    "wof:placetype":"locality"
},
  "geometry": {"coordinates":[0.91748,5.78583],"type":"Point"}
}