{
  "type": "Feature",
  "properties": {
    "gn:admin1_code":"04",
    "gn:asciiname":"Apeagyeikurom",
    "gn:country_code":"GH",
    "gn:dem":141,
    "gn:feature_class":"P",
    "gn:feature_code":"PPL",
    "gn:name":"Apeagyeikurom",
    "gn:population":0,
    "gn:timezone":"Africa/Accra",
    "iso:country":"GH",
    "name:eng_x_preferred":[
        "Apeagyeikurom"
    ],
    "name:eng_x_variant":[
        "Apiajeikrom"
    ],
    "wof:name":"Apeagyeikurom",
    "wof:placetype":"locality"
},
  "geometry": {"coordinates":[-1.6745,5.81264],"type":"Point"}
}