{
  "type": "Feature",
  "properties": {
    "gn:admin1_code":"09",
    "gn:asciiname":"Daboasi",
    "gn:country_code":"GH",
    "gn:dem":10,
    "gn:feature_class":"P",
    "gn:feature_code":"PPL",
    "gn:name":"Daboasi",
    "gn:population":0,
    "gn:timezone":"Africa/Accra",
    "iso:country":"GH",
    "name:swe_x_preferred":[
        "Daboase"
    ],
    "name:und_x_variant":[
        "Daboase",
        "Daboasi"
    ],
    "wof:name":"Daboasi",
    "wof:placetype":"locality"
},
  "geometry": {"coordinates":[-1.6601,5.13823],"type":"Point"}
}