{
  "type": "Feature",
  "properties": {
    "gn:admin1_code":"00",
    "gn:asciiname":"Vargung",
    "gn:country_code":"GH",
    "gn:dem":119,
    "gn:feature_class":"P",
    "gn:feature_code":"PPL",
    "gn:name":"Vargung",
    "gn:population":0,
    "gn:timezone":"Africa/Accra",
    "iso:country":"GH",
    "wof:name":"Vargung",
    "wof:placetype":"locality"
},
  "geometry": {"coordinates":[-1.15302,9.66356],"type":"Point"}
}