{
  "type": "Feature",
  "properties": {
    "gn:admin1_code":"00",
    "gn:asciiname":"Kwajowusu",
    "gn:country_code":"GH",
    "gn:dem":113,
    "gn:feature_class":"P",
    "gn:feature_code":"PPL",
    "gn:name":"Kwajowusu",
    "gn:population":0,
    "gn:timezone":"Africa/Accra",
    "iso:country":"GH",
    "name:und_x_variant":[
        "Kwadwowusu",
        "Kwajowusu"
    ],
    "wof:name":"Kwajowusu",
    "wof:placetype":"locality"
},
  "geometry": {"coordinates":[0.12288,6.29518],"type":"Point"}
}