{
  "type": "Feature",
  "properties": {
    "gn:admin1_code":"00",
    "gn:asciiname":"Kojimakrom",
    "gn:country_code":"GH",
    "gn:dem":92,
    "gn:feature_class":"P",
    "gn:feature_code":"PPL",
    "gn:name":"Kojimakrom",
    "gn:population":0,
    "gn:timezone":"Africa/Accra",
    "iso:country":"GH",
    "wof:name":"Kojimakrom",
    "wof:placetype":"locality"
},
  "geometry": {"coordinates":[-2.20269,5.46188],"type":"Point"}
}