{
  "type": "Feature",
  "properties": {
    "gn:admin1_code":"00",
    "gn:asciiname":"Nyamineye",
    "gn:country_code":"GH",
    "gn:dem":139,
    "gn:feature_class":"P",
    "gn:feature_code":"PPL",
    "gn:name":"Nyamineye",
    "gn:population":0,
    "gn:timezone":"Africa/Accra",
    "iso:country":"GH",
    "wof:name":"Nyamineye",
    "wof:placetype":"locality"
},
  "geometry": {"coordinates":[-1.26476,5.46069],"type":"Point"}
}