{
  "type": "Feature",
  "properties": {
    "gn:admin1_code":"00",
    "gn:asciiname":"Ntenanta",
    "gn:country_code":"GH",
    "gn:dem":78,
    "gn:feature_class":"P",
    "gn:feature_code":"PPL",
    "gn:name":"Ntenanta",
    "gn:population":0,
    "gn:timezone":"Africa/Accra",
    "iso:country":"GH",
    "wof:name":"Ntenanta",
    "wof:placetype":"locality"
},
  "geometry": {"coordinates":[-0.92533,5.44812],"type":"Point"}
}