{
  "type": "Feature",
  "properties": {
    "gn:admin1_code":"00",
    "gn:asciiname":"Adotim",
    "gn:country_code":"GH",
    "gn:dem":105,
    "gn:feature_class":"P",
    "gn:feature_code":"PPL",
    "gn:name":"Adotim",
    "gn:population":0,
    "gn:timezone":"Africa/Accra",
    "iso:country":"GH",
    "wof:name":"Adotim",
    "wof:placetype":"locality"
},
  "geometry": {"coordinates":[-0.64118,5.72389],"type":"Point"}
}