{
  "type": "Feature",
  "properties": {
    "gn:admin1_code":"00",
    "gn:asciiname":"Adija",
    "gn:country_code":"GH",
    "gn:dem":81,
    "gn:feature_class":"P",
    "gn:feature_code":"PPL",
    "gn:name":"Adija",
    "gn:population":0,
    "gn:timezone":"Africa/Accra",
    "iso:country":"GH",
    "name:und_x_variant":[
        "Adugyaa",
        "Adija"
    ],
    "wof:name":"Adija",
    "wof:placetype":"locality"
},
  "geometry": {"coordinates":[-1.61707,5.57739],"type":"Point"}
}