{
  "type": "Feature",
  "properties": {
    "gn:admin1_code":"00",
    "gn:asciiname":"Dayinu",
    "gn:country_code":"GH",
    "gn:dem":100,
    "gn:feature_class":"P",
    "gn:feature_code":"PPL",
    "gn:name":"Dayinu",
    "gn:population":0,
    "gn:timezone":"Africa/Accra",
    "iso:country":"GH",
    "wof:name":"Dayinu",
    "wof:placetype":"locality"
},
  "geometry": {"coordinates":[0.327,6.90074],"type":"Point"}
}