{
  "type": "Feature",
  "properties": {
    "gn:admin1_code":"02",
    "gn:asciiname":"Fwidiem",
    "gn:country_code":"GH",
    "gn:dem":230,
    "gn:feature_class":"P",
    "gn:feature_code":"PPL",
    "gn:name":"Fwidiem",
    "gn:population":0,
    "gn:timezone":"Africa/Accra",
    "iso:country":"GH",
    "name:und_x_variant":[
        "Hwidiem",
        "Fwidiem"
    ],
    "wof:name":"Fwidiem",
    "wof:placetype":"locality"
},
  "geometry": {"coordinates":[-1.78912,6.62521],"type":"Point"}
}