{
  "type": "Feature",
  "properties": {
    "gn:admin1_code":"00",
    "gn:asciiname":"Ntunkumso",
    "gn:country_code":"GH",
    "gn:dem":302,
    "gn:feature_class":"P",
    "gn:feature_code":"PPL",
    "gn:name":"Ntunkumso",
    "gn:population":0,
    "gn:timezone":"Africa/Accra",
    "iso:country":"GH",
    "name:und_x_variant":[
        "Ntumkumso",
        "Ntunkumso"
    ],
    "wof:name":"Ntunkumso",
    "wof:placetype":"locality"
},
  "geometry": {"coordinates":[-1.36199,6.81051],"type":"Point"}
}