{
  "type": "Feature",
  "properties": {
    "gn:admin1_code":"00",
    "gn:asciiname":"Namgbamba",
    "gn:country_code":"GH",
    "gn:dem":176,
    "gn:feature_class":"P",
    "gn:feature_code":"PPL",
    "gn:name":"Namgbamba",
    "gn:population":0,
    "gn:timezone":"Africa/Accra",
    "iso:country":"GH",
    "wof:name":"Namgbamba",
    "wof:placetype":"locality"
},
  "geometry": {"coordinates":[-0.00033,10.26317],"type":"Point"}
}