{
  "type": "Feature",
  "properties": {
    "gn:admin1_code":"00",
    "gn:asciiname":"Gonu",
    "gn:country_code":"GH",
    "gn:dem":2,
    "gn:feature_class":"P",
    "gn:feature_code":"PPL",
    "gn:name":"Gonu",
    "gn:population":0,
    "gn:timezone":"Africa/Accra",
    "iso:country":"GH",
    "name:por_x_preferred":[
        "Kono"
    ],
    "wof:name":"Gonu",
    "wof:placetype":"locality"
},
  "geometry": {"coordinates":[0.74257,5.89582],"type":"Point"}
}