{
  "type": "Feature",
  "properties": {
    "gn:admin1_code":"02",
    "gn:asciiname":"Denyamiso",
    "gn:country_code":"GH",
    "gn:dem":262,
    "gn:feature_class":"P",
    "gn:feature_code":"PPL",
    "gn:name":"Denyamiso",
    "gn:population":0,
    "gn:timezone":"Africa/Accra",
    "iso:country":"GH",
    "name:eng_x_preferred":[
        "Denyamiso"
    ],
    "wof:name":"Denyamiso",
    "wof:placetype":"locality"
},
  "geometry": {"coordinates":[-1.7565,6.87079],"type":"Point"}
}