{
  "type": "Feature",
  "properties": {
    "gn:admin1_code":"00",
    "gn:asciiname":"Banjora",
    "gn:country_code":"GH",
    "gn:dem":118,
    "gn:feature_class":"P",
    "gn:feature_code":"PPL",
    "gn:name":"Banjora",
    "gn:population":0,
    "gn:timezone":"Africa/Accra",
    "iso:country":"GH",
    "wof:name":"Banjora",
    "wof:placetype":"locality"
},
  "geometry": {"coordinates":[-1.28285,9.64121],"type":"Point"}
}