{
  "type": "Feature",
  "properties": {
    "gn:admin1_code":"00",
    "gn:asciiname":"Jumwa",
    "gn:country_code":"GH",
    "gn:dem":336,
    "gn:feature_class":"P",
    "gn:feature_code":"PPL",
    "gn:name":"Jumwa",
    "gn:population":0,
    "gn:timezone":"Africa/Accra",
    "iso:country":"GH",
    "name:und_x_variant":[
        "Dzumwa Adome",
        "Jumwa"
    ],
    "wof:name":"Jumwa",
    "wof:placetype":"locality"
},
  "geometry": {"coordinates":[-0.15222,6.35157],"type":"Point"}
}