{
  "type": "Feature",
  "properties": {
    "gn:admin1_code":"00",
    "gn:asciiname":"Amantin",
    "gn:country_code":"GH",
    "gn:dem":171,
    "gn:feature_class":"P",
    "gn:feature_code":"PPL",
    "gn:name":"Amantin",
    "gn:population":0,
    "gn:timezone":"Africa/Accra",
    "iso:country":"GH",
    "name:und_x_variant":[
        "Amanten",
        "Amantin"
    ],
    "wof:name":"Amantin",
    "wof:placetype":"locality"
},
  "geometry": {"coordinates":[-1.20312,7.54401],"type":"Point"}
}