{
  "type": "Feature",
  "properties": {
    "gn:admin1_code":"11",
    "gn:asciiname":"Kokoligu",
    "gn:country_code":"GH",
    "gn:dem":265,
    "gn:feature_class":"P",
    "gn:feature_code":"PPL",
    "gn:name":"Kokoligu",
    "gn:population":0,
    "gn:timezone":"Africa/Accra",
    "iso:country":"GH",
    "name:und_x_variant":[
        "Kokolubu"
    ],
    "wof:name":"Kokoligu",
    "wof:placetype":"locality"
},
  "geometry": {"coordinates":[-2.78565,10.96316],"type":"Point"}
}