{
  "type": "Feature",
  "properties": {
    "gn:admin1_code":"01",
    "gn:asciiname":"Ofaso",
    "gn:country_code":"GH",
    "gn:dem":126,
    "gn:feature_class":"P",
    "gn:feature_code":"PPL",
    "gn:name":"Ofaso",
    "gn:population":0,
    "gn:timezone":"Africa/Accra",
    "iso:country":"GH",
    "wof:name":"Ofaso",
    "wof:placetype":"locality"
},
  "geometry": {"coordinates":[-0.5579,5.71462],"type":"Point"}
}