{
  "type": "Feature",
  "properties": {
    "gn:admin1_code":"00",
    "gn:asciiname":"Kududaw",
    "gn:country_code":"GH",
    "gn:dem":7,
    "gn:feature_class":"P",
    "gn:feature_code":"PPL",
    "gn:name":"Kududaw",
    "gn:population":0,
    "gn:timezone":"Africa/Accra",
    "iso:country":"GH",
    "wof:name":"Kududaw",
    "wof:placetype":"locality"
},
  "geometry": {"coordinates":[0.4447,6.00579],"type":"Point"}
}