{
  "type": "Feature",
  "properties": {
    "gn:admin1_code":"00",
    "gn:asciiname":"Nankasi",
    "gn:country_code":"GH",
    "gn:dem":187,
    "gn:feature_class":"P",
    "gn:feature_code":"PPL",
    "gn:name":"Nankasi",
    "gn:population":0,
    "gn:timezone":"Africa/Accra",
    "iso:country":"GH",
    "name:und_x_variant":[
        "Nankese Abesem",
        "Nankasi"
    ],
    "wof:name":"Nankasi",
    "wof:placetype":"locality"
},
  "geometry": {"coordinates":[-0.37877,6.09149],"type":"Point"}
}