{
  "type": "Feature",
  "properties": {
    "gn:admin1_code":"04",
    "gn:asciiname":"Chirenkumso",
    "gn:country_code":"GH",
    "gn:dem":113,
    "gn:feature_class":"P",
    "gn:feature_code":"PPL",
    "gn:name":"Chirenkumso",
    "gn:population":0,
    "gn:timezone":"Africa/Accra",
    "iso:country":"GH",
    "name:eng_x_preferred":[
        "Chirenkumso"
    ],
    "wof:name":"Chirenkumso",
    "wof:placetype":"locality"
},
  "geometry": {"coordinates":[-1.60014,5.82893],"type":"Point"}
}