{
  "type": "Feature",
  "properties": {
    "gn:admin1_code":"00",
    "gn:asciiname":"Sumadure",
    "gn:country_code":"GH",
    "gn:dem":233,
    "gn:feature_class":"P",
    "gn:feature_code":"PPL",
    "gn:name":"Sumadure",
    "gn:population":0,
    "gn:timezone":"Africa/Accra",
    "iso:country":"GH",
    "name:und_x_variant":[
        "Simaduri",
        "Sumadure"
    ],
    "wof:name":"Sumadure",
    "wof:placetype":"locality"
},
  "geometry": {"coordinates":[-0.17957,10.8397],"type":"Point"}
}