{
  "type": "Feature",
  "properties": {
    "gn:admin1_code":"00",
    "gn:asciiname":"Chiranam",
    "gn:country_code":"GH",
    "gn:dem":126,
    "gn:feature_class":"P",
    "gn:feature_code":"PPL",
    "gn:name":"Chiranam",
    "gn:population":0,
    "gn:timezone":"Africa/Accra",
    "iso:country":"GH",
    "wof:name":"Chiranam",
    "wof:placetype":"locality"
},
  "geometry": {"coordinates":[-2.43333,5.93333],"type":"Point"}
}