{
  "type": "Feature",
  "properties": {
    "gn:admin1_code":"00",
    "gn:asciiname":"Ntoaboma",
    "gn:country_code":"GH",
    "gn:dem":127,
    "gn:feature_class":"P",
    "gn:feature_code":"PPL",
    "gn:name":"Ntoaboma",
    "gn:population":0,
    "gn:timezone":"Africa/Accra",
    "iso:country":"GH",
    "wof:name":"Ntoaboma",
    "wof:placetype":"locality"
},
  "geometry": {"coordinates":[0.13333,7.28333],"type":"Point"}
}