{
  "type": "Feature",
  "properties": {
    "gn:admin1_code":"00",
    "gn:asciiname":"Sakulo",
    "gn:country_code":"GH",
    "gn:dem":280,
    "gn:feature_class":"P",
    "gn:feature_code":"PPL",
    "gn:name":"Sakulo",
    "gn:population":0,
    "gn:timezone":"Africa/Accra",
    "iso:country":"GH",
    "name:und_x_variant":[
        "Sakallu",
        "Sakulo"
    ],
    "wof:name":"Sakulo",
    "wof:placetype":"locality"
},
  "geometry": {"coordinates":[-2.03279,10.67668],"type":"Point"}
}