{
  "type": "Feature",
  "properties": {
    "gn:admin1_code":"09",
    "gn:asciiname":"Anyinam",
    "gn:country_code":"GH",
    "gn:dem":203,
    "gn:feature_class":"P",
    "gn:feature_code":"PPL",
    "gn:name":"Anyinam",
    "gn:population":0,
    "gn:timezone":"Africa/Accra",
    "iso:country":"GH",
    "name:eng_x_preferred":[
        "Anyinam"
    ],
    "wof:name":"Anyinam",
    "wof:placetype":"locality"
},
  "geometry": {"coordinates":[-1.99092,5.82641],"type":"Point"}
}