{
  "type": "Feature",
  "properties": {
    "gn:admin1_code":"00",
    "gn:asciiname":"Longsa",
    "gn:country_code":"GH",
    "gn:dem":218,
    "gn:feature_class":"P",
    "gn:feature_code":"PPL",
    "gn:name":"Longsa",
    "gn:population":0,
    "gn:timezone":"Africa/Accra",
    "iso:country":"GH",
    "wof:name":"Longsa",
    "wof:placetype":"locality"
},
  "geometry": {"coordinates":[-1.27778,10.64398],"type":"Point"}
}