{
  "type": "Feature",
  "properties": {
    "gn:admin1_code":"00",
    "gn:asciiname":"Jetokwe",
    "gn:country_code":"GH",
    "gn:dem":7,
    "gn:feature_class":"P",
    "gn:feature_code":"PPL",
    "gn:name":"Jetokwe",
    "gn:population":0,
    "gn:timezone":"Africa/Accra",
    "iso:country":"GH",
    "name:und_x_variant":[
        "Dzetokwe",
        "Jetokwe"
    ],
    "wof:name":"Jetokwe",
    "wof:placetype":"locality"
},
  "geometry": {"coordinates":[0.6139,5.89267],"type":"Point"}
}