{
  "type": "Feature",
  "properties": {
    "gn:admin1_code":"00",
    "gn:asciiname":"Kpalsako",
    "gn:country_code":"GH",
    "gn:dem":144,
    "gn:feature_class":"P",
    "gn:feature_code":"PPL",
    "gn:name":"Kpalsako",
    "gn:population":0,
    "gn:timezone":"Africa/Accra",
    "iso:country":"GH",
    "name:und_x_variant":[
        "Jinwol",
        "Kpalsako"
    ],
    "wof:name":"Kpalsako",
    "wof:placetype":"locality"
},
  "geometry": {"coordinates":[-0.26042,10.24075],"type":"Point"}
}