{
  "type": "Feature",
  "properties": {
    "gn:admin1_code":"02",
    "gn:asciiname":"Saaman",
    "gn:country_code":"GH",
    "gn:dem":304,
    "gn:feature_class":"P",
    "gn:feature_code":"PPL",
    "gn:name":"Saaman",
    "gn:population":0,
    "gn:timezone":"Africa/Accra",
    "iso:country":"GH",
    "name:eng_x_preferred":[
        "Saaman"
    ],
    "name:und_x_variant":[
        "Saman",
        "Samang"
    ],
    "wof:name":"Saaman",
    "wof:placetype":"locality"
},
  "geometry": {"coordinates":[-1.54489,6.76858],"type":"Point"}
}