{
  "type": "Feature",
  "properties": {
    "gn:admin1_code":"00",
    "gn:asciiname":"Sinisaw",
    "gn:country_code":"GH",
    "gn:dem":285,
    "gn:feature_class":"P",
    "gn:feature_code":"PPL",
    "gn:name":"Sinisaw",
    "gn:population":0,
    "gn:timezone":"Africa/Accra",
    "iso:country":"GH",
    "name:und_x_variant":[
        "Sisinaw",
        "Sinisaw"
    ],
    "wof:name":"Sinisaw",
    "wof:placetype":"locality"
},
  "geometry": {"coordinates":[-1.39153,10.89954],"type":"Point"}
}