{
  "type": "Feature",
  "properties": {
    "gn:admin1_code":"00",
    "gn:asciiname":"Akrofu",
    "gn:country_code":"GH",
    "gn:dem":123,
    "gn:feature_class":"P",
    "gn:feature_code":"PPL",
    "gn:name":"Akrofu",
    "gn:population":0,
    "gn:timezone":"Africa/Accra",
    "iso:country":"GH",
    "wof:name":"Akrofu",
    "wof:placetype":"locality"
},
  "geometry": {"coordinates":[0.37934,6.63161],"type":"Point"}
}