{
  "type": "Feature",
  "properties": {
    "gn:admin1_code":"09",
    "gn:asciiname":"Nyamichire",
    "gn:country_code":"GH",
    "gn:dem":105,
    "gn:feature_class":"P",
    "gn:feature_code":"PPL",
    "gn:name":"Nyamichire",
    "gn:population":0,
    "gn:timezone":"Africa/Accra",
    "iso:country":"GH",
    "name:eng_x_preferred":[
        "Nyamichire"
    ],
    "wof:name":"Nyamichire",
    "wof:placetype":"locality"
},
  "geometry": {"coordinates":[-1.78844,5.53931],"type":"Point"}
}