{
  "type": "Feature",
  "properties": {
    "gn:admin1_code":"02",
    "gn:asciiname":"Adubia",
    "gn:country_code":"GH",
    "gn:dem":216,
    "gn:feature_class":"P",
    "gn:feature_code":"PPL",
    "gn:name":"Adubia",
    "gn:population":0,
    "gn:timezone":"Africa/Accra",
    "iso:country":"GH",
    "name:und_x_variant":[
        "Edubia"
    ],
    "wof:name":"Adubia",
    "wof:placetype":"locality"
},
  "geometry": {"coordinates":[-1.93555,6.40187],"type":"Point"}
}