{
  "type": "Feature",
  "properties": {
    "gn:admin1_code":"00",
    "gn:asciiname":"Boasi",
    "gn:country_code":"GH",
    "gn:dem":102,
    "gn:feature_class":"P",
    "gn:feature_code":"PPL",
    "gn:name":"Boasi",
    "gn:population":0,
    "gn:timezone":"Africa/Accra",
    "iso:country":"GH",
    "wof:name":"Boasi",
    "wof:placetype":"locality"
},
  "geometry": {"coordinates":[-0.96144,5.64383],"type":"Point"}
}