{
  "type": "Feature",
  "properties": {
    "gn:admin1_code":"00",
    "gn:asciiname":"Yaopaw",
    "gn:country_code":"GH",
    "gn:dem":-1,
    "gn:feature_class":"P",
    "gn:feature_code":"PPL",
    "gn:name":"Yaopaw",
    "gn:population":0,
    "gn:timezone":"Africa/Accra",
    "iso:country":"GH",
    "wof:name":"Yaopaw",
    "wof:placetype":"locality"
},
  "geometry": {"coordinates":[0.59098,5.89371],"type":"Point"}
}