{
  "type": "Feature",
  "properties": {
    "gn:admin1_code":"00",
    "gn:asciiname":"Mokwa",
    "gn:country_code":"GH",
    "gn:dem":85,
    "gn:feature_class":"P",
    "gn:feature_code":"PPL",
    "gn:name":"Mokwa",
    "gn:population":0,
    "gn:timezone":"Africa/Accra",
    "iso:country":"GH",
    "name:ceb_x_preferred":[
        "Mokwa"
    ],
    "name:fra_x_preferred":[
        "Mokwa"
    ],
    "name:hau_x_preferred":[
        "Mokwa"
    ],
    "name:ita_x_preferred":[
        "Mokwa"
    ],
    "name:spa_x_preferred":[
        "Mokwa"
    ],
    "name:und_x_variant":[
        "Mokwaa",
        "Mokwa"
    ],
    "wof:name":"Mokwa",
    "wof:placetype":"locality"
},
  "geometry": {"coordinates":[-1.59812,5.71551],"type":"Point"}
}