{
  "type": "Feature",
  "properties": {
    "gn:admin1_code":"00",
    "gn:asciiname":"Komayili",
    "gn:country_code":"GH",
    "gn:dem":196,
    "gn:feature_class":"P",
    "gn:feature_code":"PPL",
    "gn:name":"Komayili",
    "gn:population":0,
    "gn:timezone":"Africa/Accra",
    "iso:country":"GH",
    "name:und_x_variant":[
        "Komoayili",
        "Komayili"
    ],
    "wof:name":"Komayili",
    "wof:placetype":"locality"
},
  "geometry": {"coordinates":[-0.39518,9.85789],"type":"Point"}
}