{
  "type": "Feature",
  "properties": {
    "gn:admin1_code":"00",
    "gn:asciiname":"Aveta",
    "gn:country_code":"GH",
    "gn:dem":73,
    "gn:feature_class":"P",
    "gn:feature_code":"PPL",
    "gn:name":"Aveta",
    "gn:population":0,
    "gn:timezone":"Africa/Accra",
    "iso:country":"GH",
    "name:cat_x_preferred":[
        "Aveta"
    ],
    "name:fra_x_preferred":[
        "Aveta"
    ],
    "name:glg_x_preferred":[
        "Aveta"
    ],
    "name:heb_x_preferred":[
        "\u05d0\u05d5\u05d5\u05d8\u05d4"
    ],
    "name:nld_x_preferred":[
        "Aveta"
    ],
    "name:por_x_preferred":[
        "Aveta"
    ],
    "name:srp_x_preferred":[
        "\u0410\u0432\u0435\u0442\u0430"
    ],
    "name:tur_x_preferred":[
        "Aveta"
    ],
    "name:zho_x_preferred":[
        "\u963f\u7ef4\u5854"
    ],
    "wof:name":"Aveta",
    "wof:placetype":"locality"
},
  "geometry": {"coordinates":[0.59779,6.32645],"type":"Point"}
}