{
  "type": "Feature",
  "properties": {
    "gn:admin1_code":"00",
    "gn:asciiname":"Aveta",
    "gn:country_code":"GH",
    "gn:dem":73,
    "gn:feature_class":"P",
    "gn:feature_code":"PPL",
    "gn:name":"Aveta",
    "gn:population":0,
    "gn:timezone":"Africa/Accra",
    "iso:country":"GH",
    "wof:name":"Aveta",
    "wof:placetype":"locality"
},
  "geometry": {"coordinates":[0.59779,6.32645],"type":"Point"}
}