{
  "type": "Feature",
  "properties": {
    "gn:admin1_code":"00",
    "gn:asciiname":"Nanyiri",
    "gn:country_code":"GH",
    "gn:dem":189,
    "gn:feature_class":"P",
    "gn:feature_code":"PPL",
    "gn:name":"Nanyiri",
    "gn:population":0,
    "gn:timezone":"Africa/Accra",
    "iso:country":"GH",
    "wof:name":"Nanyiri",
    "wof:placetype":"locality"
},
  "geometry": {"coordinates":[-0.05735,10.17708],"type":"Point"}
}