{
  "type": "Feature",
  "properties": {
    "gn:admin1_code":"00",
    "gn:asciiname":"Kpodzi",
    "gn:country_code":"GH",
    "gn:dem":68,
    "gn:feature_class":"P",
    "gn:feature_code":"PPL",
    "gn:name":"Kpodzi",
    "gn:population":0,
    "gn:timezone":"Africa/Accra",
    "iso:country":"GH",
    "name:und_x_variant":[
        "Kpodji",
        "Kpodzi"
    ],
    "wof:name":"Kpodzi",
    "wof:placetype":"locality"
},
  "geometry": {"coordinates":[0.6568,6.41973],"type":"Point"}
}