{
  "type": "Feature",
  "properties": {
    "gn:admin1_code":"00",
    "gn:asciiname":"Wawasi",
    "gn:country_code":"GH",
    "gn:dem":112,
    "gn:feature_class":"P",
    "gn:feature_code":"PPL",
    "gn:name":"Wawasi",
    "gn:population":0,
    "gn:timezone":"Africa/Accra",
    "iso:country":"GH",
    "name:und_x_variant":[
        "Wawase",
        "Wawasi"
    ],
    "wof:name":"Wawasi",
    "wof:placetype":"locality"
},
  "geometry": {"coordinates":[-1.46719,5.8131],"type":"Point"}
}