{
  "type": "Feature",
  "properties": {
    "gn:admin1_code":"00",
    "gn:asciiname":"Adawsena",
    "gn:country_code":"GH",
    "gn:dem":192,
    "gn:feature_class":"P",
    "gn:feature_code":"PPL",
    "gn:name":"Adawsena",
    "gn:population":0,
    "gn:timezone":"Africa/Accra",
    "iso:country":"GH",
    "name:und_x_variant":[
        "Adansina",
        "Adausina",
        "Adausena",
        "Adawsena"
    ],
    "wof:name":"Adawsena",
    "wof:placetype":"locality"
},
  "geometry": {"coordinates":[-1.05423,6.34737],"type":"Point"}
}