{
  "type": "Feature",
  "properties": {
    "gn:admin1_code":"06",
    "gn:asciiname":"Kugnani",
    "gn:country_code":"GH",
    "gn:dem":110,
    "gn:feature_class":"P",
    "gn:feature_code":"PPL",
    "gn:name":"Kugnani",
    "gn:population":0,
    "gn:timezone":"Africa/Accra",
    "iso:country":"GH",
    "name:und_x_variant":[
        "Kengau",
        "Kughan",
        "Kengua",
        "Kugnani"
    ],
    "wof:name":"Kugnani",
    "wof:placetype":"locality"
},
  "geometry": {"coordinates":[0.35668,9.59064],"type":"Point"}
}