{
  "type": "Feature",
  "properties": {
    "gn:admin1_code":"00",
    "gn:asciiname":"Kwadajin",
    "gn:country_code":"GH",
    "gn:dem":71,
    "gn:feature_class":"P",
    "gn:feature_code":"PPL",
    "gn:name":"Kwadajin",
    "gn:population":0,
    "gn:timezone":"Africa/Accra",
    "iso:country":"GH",
    "name:und_x_variant":[
        "Kedadwin",
        "Kwadajin"
    ],
    "wof:name":"Kwadajin",
    "wof:placetype":"locality"
},
  "geometry": {"coordinates":[-2.08563,5.02901],"type":"Point"}
}