{
  "type": "Feature",
  "properties": {
    "gn:admin1_code":"00",
    "gn:asciiname":"Nabal",
    "gn:country_code":"GH",
    "gn:dem":163,
    "gn:feature_class":"P",
    "gn:feature_code":"PPL",
    "gn:name":"Nabal",
    "gn:population":0,
    "gn:timezone":"Africa/Accra",
    "iso:country":"GH",
    "name:deu_x_preferred":[
        "Nabal"
    ],
    "name:ell_x_preferred":[
        "\u039d\u03ac\u03b2\u03b1\u03bb"
    ],
    "name:heb_x_preferred":[
        "\u05e0\u05d1\u05dc \u05d4\u05db\u05e8\u05de\u05dc\u05d9"
    ],
    "name:nor_x_preferred":[
        "Nabal"
    ],
    "name:pol_x_preferred":[
        "Nabal"
    ],
    "name:rus_x_preferred":[
        "\u041d\u0430\u0432\u0430\u043b"
    ],
    "name:spa_x_preferred":[
        "Nabal"
    ],
    "wof:name":"Nabal",
    "wof:placetype":"locality"
},
  "geometry": {"coordinates":[-0.07791,10.36339],"type":"Point"}
}