{
  "type": "Feature",
  "properties": {
    "gn:admin1_code":"00",
    "gn:asciiname":"Nabal",
    "gn:country_code":"GH",
    "gn:dem":163,
    "gn:feature_class":"P",
    "gn:feature_code":"PPL",
    "gn:name":"Nabal",
    "gn:population":0,
    "gn:timezone":"Africa/Accra",
    "iso:country":"GH",
    "wof:name":"Nabal",
    "wof:placetype":"locality"
},
  "geometry": {"coordinates":[-0.07791,10.36339],"type":"Point"}
}