{
  "type": "Feature",
  "properties": {
    "gn:admin1_code":"00",
    "gn:asciiname":"Atito",
    "gn:country_code":"GH",
    "gn:dem":6,
    "gn:feature_class":"P",
    "gn:feature_code":"PPL",
    "gn:name":"Atito",
    "gn:population":0,
    "gn:timezone":"Africa/Accra",
    "iso:country":"GH",
    "name:und_x_variant":[
        "Achito",
        "Atito"
    ],
    "wof:name":"Atito",
    "wof:placetype":"locality"
},
  "geometry": {"coordinates":[0.86227,5.84631],"type":"Point"}
}