{
  "type": "Feature",
  "properties": {
    "gn:admin1_code":"02",
    "gn:asciiname":"Sakoban",
    "gn:country_code":"GH",
    "gn:dem":234,
    "gn:feature_class":"P",
    "gn:feature_code":"PPL",
    "gn:name":"Sakoban",
    "gn:population":0,
    "gn:timezone":"Africa/Accra",
    "iso:country":"GH",
    "name:eng_x_preferred":[
        "Sakoban"
    ],
    "name:und_x_variant":[
        "Sokoban",
        "Sokobang",
        "Sokoben"
    ],
    "wof:name":"Sakoban",
    "wof:placetype":"locality"
},
  "geometry": {"coordinates":[-1.61716,6.62694],"type":"Point"}
}