{
  "type": "Feature",
  "properties": {
    "gn:admin1_code":"00",
    "gn:asciiname":"Somboro",
    "gn:country_code":"GH",
    "gn:dem":302,
    "gn:feature_class":"P",
    "gn:feature_code":"PPL",
    "gn:name":"Somboro",
    "gn:population":0,
    "gn:timezone":"Africa/Accra",
    "iso:country":"GH",
    "name:und_x_variant":[
        "Sumboru",
        "Somburo",
        "Somboro"
    ],
    "wof:name":"Somboro",
    "wof:placetype":"locality"
},
  "geometry": {"coordinates":[-1.72987,10.72303],"type":"Point"}
}