{
  "type": "Feature",
  "properties": {
    "gn:admin1_code":"00",
    "gn:asciiname":"Mambuen",
    "gn:country_code":"GH",
    "gn:dem":14,
    "gn:feature_class":"P",
    "gn:feature_code":"PPL",
    "gn:name":"Mambuen",
    "gn:population":0,
    "gn:timezone":"Africa/Accra",
    "iso:country":"GH",
    "wof:name":"Mambuen",
    "wof:placetype":"locality"
},
  "geometry": {"coordinates":[-2.50706,5.01052],"type":"Point"}
}