{
  "type": "Feature",
  "properties": {
    "gn:admin1_code":"09",
    "gn:asciiname":"Domama Wasa",
    "gn:country_code":"GH",
    "gn:dem":77,
    "gn:feature_class":"P",
    "gn:feature_code":"PPL",
    "gn:name":"Domama Wasa",
    "gn:population":0,
    "gn:timezone":"Africa/Accra",
    "iso:country":"GH",
    "name:eng_x_preferred":[
        "Domama Wasa"
    ],
    "name:eng_x_variant":[
        "Dumama"
    ],
    "wof:name":"Domama Wasa",
    "wof:placetype":"locality"
},
  "geometry": {"coordinates":[-1.57184,5.37513],"type":"Point"}
}