{
  "type": "Feature",
  "properties": {
    "gn:admin1_code":"01",
    "gn:asciiname":"Chokome",
    "gn:country_code":"GH",
    "gn:dem":-9999,
    "gn:feature_class":"P",
    "gn:feature_code":"PPL",
    "gn:name":"Chokome",
    "gn:population":0,
    "gn:timezone":"Africa/Accra",
    "iso:country":"GH",
    "name:und_x_variant":[
        "Tsokome",
        "Chokome"
    ],
    "wof:name":"Chokome",
    "wof:placetype":"locality"
},
  "geometry": {"coordinates":[-0.3276,5.50759],"type":"Point"}
}