{
  "type": "Feature",
  "properties": {
    "gn:admin1_code":"11",
    "gn:asciiname":"Naapali",
    "gn:country_code":"GH",
    "gn:dem":267,
    "gn:feature_class":"P",
    "gn:feature_code":"PPL",
    "gn:name":"Naapali",
    "gn:population":0,
    "gn:timezone":"Africa/Accra",
    "iso:country":"GH",
    "name:eng_x_preferred":[
        "Naapali"
    ],
    "name:und_x_variant":[
        "Wapali",
        "Naapal",
        "Napali"
    ],
    "wof:name":"Naapali",
    "wof:placetype":"locality"
},
  "geometry": {"coordinates":[-2.81523,10.87065],"type":"Point"}
}