{
  "type": "Feature",
  "properties": {
    "gn:admin1_code":"02",
    "gn:asciiname":"Esasi",
    "gn:country_code":"GH",
    "gn:dem":95,
    "gn:feature_class":"P",
    "gn:feature_code":"PPL",
    "gn:name":"Esasi",
    "gn:population":0,
    "gn:timezone":"Africa/Accra",
    "iso:country":"GH",
    "name:eng_x_preferred":[
        "Esasi"
    ],
    "wof:name":"Esasi",
    "wof:placetype":"locality"
},
  "geometry": {"coordinates":[-1.58558,5.95239],"type":"Point"}
}