{
  "type": "Feature",
  "properties": {
    "gn:admin1_code":"00",
    "gn:asciiname":"Adzato",
    "gn:country_code":"GH",
    "gn:dem":0,
    "gn:feature_class":"P",
    "gn:feature_code":"PPL",
    "gn:name":"Adzato",
    "gn:population":0,
    "gn:timezone":"Africa/Accra",
    "iso:country":"GH",
    "wof:name":"Adzato",
    "wof:placetype":"locality"
},
  "geometry": {"coordinates":[0.80402,5.86868],"type":"Point"}
}