{
  "type": "Feature",
  "properties": {
    "gn:admin1_code":"09",
    "gn:asciiname":"Nyamibechire",
    "gn:country_code":"GH",
    "gn:dem":63,
    "gn:feature_class":"P",
    "gn:feature_code":"PPL",
    "gn:name":"Nyamibechire",
    "gn:population":0,
    "gn:timezone":"Africa/Accra",
    "iso:country":"GH",
    "name:und_x_variant":[
        "Anwiasu",
        "Nyamebekyere Number 1",
        "Nyamibechire"
    ],
    "wof:name":"Nyamibechire",
    "wof:placetype":"locality"
},
  "geometry": {"coordinates":[-2.10183,4.95124],"type":"Point"}
}