{
  "type": "Feature",
  "properties": {
    "gn:admin1_code":"00",
    "gn:asciiname":"Akuse",
    "gn:country_code":"GH",
    "gn:dem":14,
    "gn:feature_class":"P",
    "gn:feature_code":"PPL",
    "gn:name":"Akuse",
    "gn:population":0,
    "gn:timezone":"Africa/Accra",
    "iso:country":"GH",
    "name:azb_x_preferred":[
        "\u0627\u06a9\u0648\u0633"
    ],
    "name:fas_x_preferred":[
        "\u0627\u06a9\u0648\u0633"
    ],
    "name:und_x_variant":[
        "Amedika Akuse",
        "Akuse"
    ],
    "wof:name":"Akuse",
    "wof:placetype":"locality"
},
  "geometry": {"coordinates":[0.12588,6.0984],"type":"Point"}
}