{
  "type": "Feature",
  "properties": {
    "gn:admin1_code":"00",
    "gn:asciiname":"Ejeman",
    "gn:country_code":"GH",
    "gn:dem":359,
    "gn:feature_class":"P",
    "gn:feature_code":"PPL",
    "gn:name":"Ejeman",
    "gn:population":0,
    "gn:timezone":"Africa/Accra",
    "iso:country":"GH",
    "wof:name":"Ejeman",
    "wof:placetype":"locality"
},
  "geometry": {"coordinates":[-1.36667,6.48333],"type":"Point"}
}