{
  "type": "Feature",
  "properties": {
    "gn:admin1_code":"09",
    "gn:asciiname":"Kwesimintsim",
    "gn:country_code":"GH",
    "gn:dem":11,
    "gn:feature_class":"P",
    "gn:feature_code":"PPL",
    "gn:name":"Kwesimintsim",
    "gn:population":0,
    "gn:timezone":"Africa/Accra",
    "iso:country":"GH",
    "name:und_x_variant":[
        "Kwasimintim",
        "Kwesimintim"
    ],
    "wof:name":"Kwesimintsim",
    "wof:placetype":"locality"
},
  "geometry": {"coordinates":[-1.78808,4.91508],"type":"Point"}
}