{
  "type": "Feature",
  "properties": {
    "gn:admin1_code":"00",
    "gn:asciiname":"Adrakpo",
    "gn:country_code":"GH",
    "gn:dem":32,
    "gn:feature_class":"P",
    "gn:feature_code":"PPL",
    "gn:name":"Adrakpo",
    "gn:population":0,
    "gn:timezone":"Africa/Accra",
    "iso:country":"GH",
    "wof:name":"Adrakpo",
    "wof:placetype":"locality"
},
  "geometry": {"coordinates":[0.83951,6.0847],"type":"Point"}
}