{
  "type": "Feature",
  "properties": {
    "gn:admin1_code":"00",
    "gn:asciiname":"Yokpoe",
    "gn:country_code":"GH",
    "gn:dem":42,
    "gn:feature_class":"P",
    "gn:feature_code":"PPL",
    "gn:name":"Yokpoe",
    "gn:population":0,
    "gn:timezone":"Africa/Accra",
    "iso:country":"GH",
    "wof:name":"Yokpoe",
    "wof:placetype":"locality"
},
  "geometry": {"coordinates":[0.42396,6.32941],"type":"Point"}
}