{
  "type": "Feature",
  "properties": {
    "gn:admin1_code":"00",
    "gn:asciiname":"Boifi",
    "gn:country_code":"GH",
    "gn:dem":92,
    "gn:feature_class":"P",
    "gn:feature_code":"PPL",
    "gn:name":"Boifi",
    "gn:population":0,
    "gn:timezone":"Africa/Accra",
    "iso:country":"GH",
    "wof:name":"Boifi",
    "wof:placetype":"locality"
},
  "geometry": {"coordinates":[-0.76662,5.5343],"type":"Point"}
}