{
  "type": "Feature",
  "properties": {
    "gn:admin1_code":"00",
    "gn:asciiname":"Biko",
    "gn:country_code":"GH",
    "gn:dem":7,
    "gn:feature_class":"P",
    "gn:feature_code":"PPL",
    "gn:name":"Biko",
    "gn:population":0,
    "gn:timezone":"Africa/Accra",
    "iso:country":"GH",
    "name:ceb_x_preferred":[
        "Biko"
    ],
    "name:deu_x_preferred":[
        "Biko"
    ],
    "name:ell_x_preferred":[
        "\u039c\u03c0\u03af\u03ba\u03bf"
    ],
    "name:ita_x_preferred":[
        "Biko"
    ],
    "name:pol_x_preferred":[
        "Biko"
    ],
    "name:swe_x_preferred":[
        "Biko"
    ],
    "name:und_x_variant":[
        "Bikor",
        "Biko"
    ],
    "wof:name":"Biko",
    "wof:placetype":"locality"
},
  "geometry": {"coordinates":[1.03445,6.03243],"type":"Point"}
}