{
  "type": "Feature",
  "properties": {
    "gn:admin1_code":"02",
    "gn:asciiname":"Dekyewa",
    "gn:country_code":"GH",
    "gn:dem":175,
    "gn:feature_class":"P",
    "gn:feature_code":"PPL",
    "gn:name":"Dekyewa",
    "gn:population":0,
    "gn:timezone":"Africa/Accra",
    "iso:country":"GH",
    "name:eng_x_preferred":[
        "Dekyewa"
    ],
    "name:und_x_variant":[
        "Dekyiwa",
        "Dechiwa"
    ],
    "wof:name":"Dekyewa",
    "wof:placetype":"locality"
},
  "geometry": {"coordinates":[-1.71683,6.2041],"type":"Point"}
}