{
  "type": "Feature",
  "properties": {
    "gn:admin1_code":"00",
    "gn:asciiname":"Kuyine",
    "gn:country_code":"GH",
    "gn:dem":112,
    "gn:feature_class":"P",
    "gn:feature_code":"PPL",
    "gn:name":"Kuyine",
    "gn:population":0,
    "gn:timezone":"Africa/Accra",
    "iso:country":"GH",
    "wof:name":"Kuyine",
    "wof:placetype":"locality"
},
  "geometry": {"coordinates":[0.35,9.13333],"type":"Point"}
}