{
  "type": "Feature",
  "properties": {
    "gn:admin1_code":"00",
    "gn:asciiname":"Nchata",
    "gn:cc2":"GH",
    "gn:country_code":"GH",
    "gn:dem":105,
    "gn:feature_class":"P",
    "gn:feature_code":"PPL",
    "gn:name":"Nchata",
    "gn:population":0,
    "gn:timezone":"Africa/Accra",
    "iso:country":"GH",
    "name:und_x_variant":[
        "Nohata",
        "Nehata",
        "Nchata"
    ],
    "wof:name":"Nchata",
    "wof:placetype":"locality"
},
  "geometry": {"coordinates":[-1.23333,6.03333],"type":"Point"}
}