{
  "type": "Feature",
  "properties": {
    "gn:admin1_code":"01",
    "gn:asciiname":"Amuanda",
    "gn:country_code":"GH",
    "gn:dem":91,
    "gn:feature_class":"P",
    "gn:feature_code":"PPL",
    "gn:name":"Amuanda",
    "gn:population":0,
    "gn:timezone":"Africa/Accra",
    "iso:country":"GH",
    "wof:name":"Amuanda",
    "wof:placetype":"locality"
},
  "geometry": {"coordinates":[-0.57637,5.52247],"type":"Point"}
}