{
  "type": "Feature",
  "properties": {
    "gn:admin1_code":"02",
    "gn:asciiname":"Nyamiadom",
    "gn:country_code":"GH",
    "gn:dem":229,
    "gn:feature_class":"P",
    "gn:feature_code":"PPL",
    "gn:name":"Nyamiadom",
    "gn:population":0,
    "gn:timezone":"Africa/Accra",
    "iso:country":"GH",
    "name:und_x_variant":[
        "Betinko",
        "Nyamiadom"
    ],
    "wof:name":"Nyamiadom",
    "wof:placetype":"locality"
},
  "geometry": {"coordinates":[-1.96406,6.62638],"type":"Point"}
}