{
  "type": "Feature",
  "properties": {
    "gn:admin1_code":"00",
    "gn:asciiname":"Agudekope",
    "gn:cc2":"GH",
    "gn:country_code":"GH",
    "gn:dem":3,
    "gn:feature_class":"P",
    "gn:feature_code":"PPL",
    "gn:name":"Agudekope",
    "gn:population":0,
    "gn:timezone":"Africa/Accra",
    "iso:country":"GH",
    "name:und_x_variant":[
        "Agude Korpe",
        "Agudekope"
    ],
    "wof:name":"Agudekope",
    "wof:placetype":"locality"
},
  "geometry": {"coordinates":[0.55,5.93333],"type":"Point"}
}