{
  "type": "Feature",
  "properties": {
    "gn:admin1_code":"00",
    "gn:asciiname":"Asayensu",
    "gn:country_code":"GH",
    "gn:dem":143,
    "gn:feature_class":"P",
    "gn:feature_code":"PPL",
    "gn:name":"Asayensu",
    "gn:population":0,
    "gn:timezone":"Africa/Accra",
    "iso:country":"GH",
    "wof:name":"Asayensu",
    "wof:placetype":"locality"
},
  "geometry": {"coordinates":[-0.51105,7.04749],"type":"Point"}
}