{
  "type": "Feature",
  "properties": {
    "gn:admin1_code":"00",
    "gn:asciiname":"Sasi",
    "gn:country_code":"GH",
    "gn:dem":137,
    "gn:feature_class":"P",
    "gn:feature_code":"PPL",
    "gn:name":"Sasi",
    "gn:population":0,
    "gn:timezone":"Africa/Accra",
    "iso:country":"GH",
    "name:bos_x_preferred":[
        "Sasi"
    ],
    "name:ceb_x_preferred":[
        "Sasi"
    ],
    "name:mal_x_preferred":[
        "\u0d36\u0d36\u0d3f"
    ],
    "name:slk_x_preferred":[
        "Sasi"
    ],
    "name:swe_x_preferred":[
        "Sasi"
    ],
    "wof:name":"Sasi",
    "wof:placetype":"locality"
},
  "geometry": {"coordinates":[-0.63333,5.91667],"type":"Point"}
}