{
  "type": "Feature",
  "properties": {
    "gn:admin1_code":"00",
    "gn:asciiname":"Tonu",
    "gn:country_code":"GH",
    "gn:dem":121,
    "gn:feature_class":"P",
    "gn:feature_code":"PPL",
    "gn:name":"Tonu",
    "gn:population":0,
    "gn:timezone":"Africa/Accra",
    "iso:country":"GH",
    "name:und_x_variant":[
        "Gbefi Tonu",
        "Tonu"
    ],
    "wof:name":"Tonu",
    "wof:placetype":"locality"
},
  "geometry": {"coordinates":[0.37658,6.99293],"type":"Point"}
}