{
  "type": "Feature",
  "properties": {
    "gn:admin1_code":"00",
    "gn:asciiname":"Agbelechime",
    "gn:country_code":"GH",
    "gn:dem":52,
    "gn:feature_class":"P",
    "gn:feature_code":"PPL",
    "gn:name":"Agbelechime",
    "gn:population":0,
    "gn:timezone":"Africa/Accra",
    "iso:country":"GH",
    "wof:name":"Agbelechime",
    "wof:placetype":"locality"
},
  "geometry": {"coordinates":[0.66513,6.35104],"type":"Point"}
}