{
  "type": "Feature",
  "properties": {
    "gn:admin1_code":"01",
    "gn:asciiname":"Ashongman",
    "gn:country_code":"GH",
    "gn:dem":141,
    "gn:feature_class":"P",
    "gn:feature_code":"PPL",
    "gn:name":"Ashongman",
    "gn:population":0,
    "gn:timezone":"Africa/Accra",
    "iso:country":"GH",
    "wof:name":"Ashongman",
    "wof:placetype":"locality"
},
  "geometry": {"coordinates":[-0.23359,5.7105],"type":"Point"}
}