{
  "type": "Feature",
  "properties": {
    "gn:admin1_code":"09",
    "gn:asciiname":"Prusi Akatakyi",
    "gn:country_code":"GH",
    "gn:dem":5,
    "gn:feature_class":"P",
    "gn:feature_code":"PPL",
    "gn:name":"Prusi Akatakyi",
    "gn:population":0,
    "gn:timezone":"Africa/Accra",
    "iso:country":"GH",
    "name:eng_x_preferred":[
        "Prusi Akatakyi"
    ],
    "name:und_x_variant":[
        "Akitekyi",
        "Aketechi"
    ],
    "wof:name":"Prusi Akatakyi",
    "wof:placetype":"locality"
},
  "geometry": {"coordinates":[-2.10769,4.78165],"type":"Point"}
}