{
  "type": "Feature",
  "properties": {
    "gn:admin1_code":"00",
    "gn:asciiname":"Balo",
    "gn:country_code":"GH",
    "gn:dem":188,
    "gn:feature_class":"P",
    "gn:feature_code":"PPL",
    "gn:name":"Balo",
    "gn:population":0,
    "gn:timezone":"Africa/Accra",
    "iso:country":"GH",
    "name:ceb_x_preferred":[
        "Balo"
    ],
    "name:fra_x_preferred":[
        "Balo"
    ],
    "name:swe_x_preferred":[
        "Balo"
    ],
    "name:und_x_variant":[
        "B\u00f3lo",
        "Balo"
    ],
    "wof:name":"Balo",
    "wof:placetype":"locality"
},
  "geometry": {"coordinates":[-0.08873,9.47998],"type":"Point"}
}