{
  "type": "Feature",
  "properties": {
    "gn:admin1_code":"00",
    "gn:asciiname":"Bensuaso",
    "gn:country_code":"GH",
    "gn:dem":191,
    "gn:feature_class":"P",
    "gn:feature_code":"PPL",
    "gn:name":"Bensuaso",
    "gn:population":0,
    "gn:timezone":"Africa/Accra",
    "iso:country":"GH",
    "wof:name":"Bensuaso",
    "wof:placetype":"locality"
},
  "geometry": {"coordinates":[-1.77874,6.47124],"type":"Point"}
}