{
  "type": "Feature",
  "properties": {
    "gn:admin1_code":"09",
    "gn:asciiname":"Hianue",
    "gn:country_code":"GH",
    "gn:dem":75,
    "gn:feature_class":"P",
    "gn:feature_code":"PPL",
    "gn:name":"Hianue",
    "gn:population":0,
    "gn:timezone":"Africa/Accra",
    "iso:country":"GH",
    "name:eng_x_preferred":[
        "Hianue"
    ],
    "name:und_x_variant":[
        "Hianye"
    ],
    "wof:name":"Hianue",
    "wof:placetype":"locality"
},
  "geometry": {"coordinates":[-1.99821,5.25452],"type":"Point"}
}