{
  "type": "Feature",
  "properties": {
    "gn:admin1_code":"06",
    "gn:asciiname":"Nambiri",
    "gn:country_code":"GH",
    "gn:dem":138,
    "gn:feature_class":"P",
    "gn:feature_code":"PPL",
    "gn:name":"Nambiri",
    "gn:population":0,
    "gn:timezone":"Africa/Accra",
    "iso:country":"GH",
    "wof:name":"Nambiri",
    "wof:placetype":"locality"
},
  "geometry": {"coordinates":[0.32227,9.89359],"type":"Point"}
}