{
  "type": "Feature",
  "properties": {
    "gn:admin1_code":"00",
    "gn:asciiname":"Kuli",
    "gn:country_code":"GH",
    "gn:dem":125,
    "gn:feature_class":"P",
    "gn:feature_code":"PPL",
    "gn:name":"Kuli",
    "gn:population":0,
    "gn:timezone":"Africa/Accra",
    "iso:country":"GH",
    "name:ceb_x_preferred":[
        "Kuli"
    ],
    "name:deu_x_preferred":[
        "Kuli"
    ],
    "name:nds_x_preferred":[
        "Kuli"
    ],
    "name:nor_x_preferred":[
        "Kuli"
    ],
    "name:swe_x_preferred":[
        "Kuli"
    ],
    "wof:name":"Kuli",
    "wof:placetype":"locality"
},
  "geometry": {"coordinates":[-1.1886,9.66579],"type":"Point"}
}