{
  "type": "Feature",
  "properties": {
    "gn:admin1_code":"00",
    "gn:asciiname":"Pampetia",
    "gn:country_code":"GH",
    "gn:dem":234,
    "gn:feature_class":"P",
    "gn:feature_code":"PPL",
    "gn:name":"Pampetia",
    "gn:population":0,
    "gn:timezone":"Africa/Accra",
    "iso:country":"GH",
    "name:und_x_variant":[
        "Apampetia",
        "Pampetia"
    ],
    "wof:name":"Pampetia",
    "wof:placetype":"locality"
},
  "geometry": {"coordinates":[-0.61318,6.24391],"type":"Point"}
}