{
  "type": "Feature",
  "properties": {
    "gn:admin1_code":"00",
    "gn:asciiname":"Pipepe",
    "gn:country_code":"GH",
    "gn:dem":110,
    "gn:feature_class":"P",
    "gn:feature_code":"PPL",
    "gn:name":"Pipepe",
    "gn:population":0,
    "gn:timezone":"Africa/Accra",
    "iso:country":"GH",
    "wof:name":"Pipepe",
    "wof:placetype":"locality"
},
  "geometry": {"coordinates":[-2.06996,5.40826],"type":"Point"}
}