{
  "type": "Feature",
  "properties": {
    "gn:admin1_code":"00",
    "gn:asciiname":"Nobochu",
    "gn:country_code":"GH",
    "gn:dem":12,
    "gn:feature_class":"P",
    "gn:feature_code":"PPL",
    "gn:name":"Nobochu",
    "gn:population":0,
    "gn:timezone":"Africa/Accra",
    "iso:country":"GH",
    "name:und_x_variant":[
        "Nobochi",
        "Nobochu"
    ],
    "wof:name":"Nobochu",
    "wof:placetype":"locality"
},
  "geometry": {"coordinates":[0.07388,6.14717],"type":"Point"}
}