{
  "type": "Feature",
  "properties": {
    "gn:admin1_code":"00",
    "gn:asciiname":"Dewu",
    "gn:country_code":"GH",
    "gn:dem":323,
    "gn:feature_class":"P",
    "gn:feature_code":"PPL",
    "gn:name":"Dewu",
    "gn:population":0,
    "gn:timezone":"Africa/Accra",
    "iso:country":"GH",
    "wof:name":"Dewu",
    "wof:placetype":"locality"
},
  "geometry": {"coordinates":[-1.47346,6.99098],"type":"Point"}
}