{
  "type": "Feature",
  "properties": {
    "gn:admin1_code":"00",
    "gn:asciiname":"Bwania",
    "gn:country_code":"GH",
    "gn:dem":179,
    "gn:feature_class":"P",
    "gn:feature_code":"PPL",
    "gn:name":"Bwania",
    "gn:population":0,
    "gn:timezone":"Africa/Accra",
    "iso:country":"GH",
    "wof:name":"Bwania",
    "wof:placetype":"locality"
},
  "geometry": {"coordinates":[-1.12374,10.86917],"type":"Point"}
}