{
  "type": "Feature",
  "properties": {
    "gn:admin1_code":"00",
    "gn:asciiname":"Deboko",
    "gn:country_code":"GH",
    "gn:dem":122,
    "gn:feature_class":"P",
    "gn:feature_code":"PPL",
    "gn:name":"Deboko",
    "gn:population":0,
    "gn:timezone":"Africa/Accra",
    "iso:country":"GH",
    "wof:name":"Deboko",
    "wof:placetype":"locality"
},
  "geometry": {"coordinates":[-0.67224,9.21107],"type":"Point"}
}