{
  "type": "Feature",
  "properties": {
    "gn:admin1_code":"00",
    "gn:asciiname":"Kuntulo",
    "gn:country_code":"GH",
    "gn:dem":276,
    "gn:feature_class":"P",
    "gn:feature_code":"PPL",
    "gn:name":"Kuntulo",
    "gn:population":0,
    "gn:timezone":"Africa/Accra",
    "iso:country":"GH",
    "name:und_x_variant":[
        "Kuntule",
        "Kuntulo"
    ],
    "wof:name":"Kuntulo",
    "wof:placetype":"locality"
},
  "geometry": {"coordinates":[-2.29589,10.74005],"type":"Point"}
}