{
  "type": "Feature",
  "properties": {
    "gn:admin1_code":"00",
    "gn:asciiname":"Ahantamwa",
    "gn:country_code":"GH",
    "gn:dem":234,
    "gn:feature_class":"P",
    "gn:feature_code":"PPL",
    "gn:name":"Ahantamwa",
    "gn:population":0,
    "gn:timezone":"Africa/Accra",
    "iso:country":"GH",
    "name:und_x_variant":[
        "Ahantamuo",
        "Ahantamwa"
    ],
    "wof:name":"Ahantamwa",
    "wof:placetype":"locality"
},
  "geometry": {"coordinates":[-2.61674,6.70017],"type":"Point"}
}