{
  "type": "Feature",
  "properties": {
    "gn:admin1_code":"06",
    "gn:asciiname":"Sakogu",
    "gn:country_code":"GH",
    "gn:dem":364,
    "gn:feature_class":"P",
    "gn:feature_code":"PPL",
    "gn:name":"Sakogu",
    "gn:population":0,
    "gn:timezone":"Africa/Accra",
    "iso:country":"GH",
    "name:und_x_variant":[
        "Sakku",
        "Sakogu"
    ],
    "wof:name":"Sakogu",
    "wof:placetype":"locality"
},
  "geometry": {"coordinates":[-0.27333,10.57951],"type":"Point"}
}