{
  "type": "Feature",
  "properties": {
    "gn:admin1_code":"09",
    "gn:asciiname":"Bukruso",
    "gn:country_code":"GH",
    "gn:dem":101,
    "gn:feature_class":"P",
    "gn:feature_code":"PPL",
    "gn:name":"Bukruso",
    "gn:population":0,
    "gn:timezone":"Africa/Accra",
    "iso:country":"GH",
    "name:eng_x_preferred":[
        "Bukruso"
    ],
    "wof:name":"Bukruso",
    "wof:placetype":"locality"
},
  "geometry": {"coordinates":[-1.68315,5.26552],"type":"Point"}
}