{
  "type": "Feature",
  "properties": {
    "gn:admin1_code":"00",
    "gn:asciiname":"Gindabo",
    "gn:cc2":"GH",
    "gn:country_code":"GH",
    "gn:dem":368,
    "gn:feature_class":"P",
    "gn:feature_code":"PPL",
    "gn:name":"Gindabo",
    "gn:population":0,
    "gn:timezone":"Africa/Accra",
    "iso:country":"GH",
    "name:und_x_variant":[
        "Gmdabo",
        "Jindabo",
        "Gindabo"
    ],
    "wof:name":"Gindabo",
    "wof:placetype":"locality"
},
  "geometry": {"coordinates":[-2.48333,9.66667],"type":"Point"}
}