{
  "type": "Feature",
  "properties": {
    "gn:admin1_code":"00",
    "gn:asciiname":"Fetenta",
    "gn:country_code":"GH",
    "gn:dem":348,
    "gn:feature_class":"P",
    "gn:feature_code":"PPL",
    "gn:name":"Fetenta",
    "gn:population":0,
    "gn:timezone":"Africa/Accra",
    "iso:country":"GH",
    "name:und_x_variant":[
        "Fetanta",
        "Fetenta"
    ],
    "wof:name":"Fetenta",
    "wof:placetype":"locality"
},
  "geometry": {"coordinates":[-2.66982,7.46736],"type":"Point"}
}