{
  "type": "Feature",
  "properties": {
    "gn:admin1_code":"00",
    "gn:asciiname":"Otaw",
    "gn:country_code":"GH",
    "gn:dem":28,
    "gn:feature_class":"P",
    "gn:feature_code":"PPL",
    "gn:name":"Otaw",
    "gn:population":0,
    "gn:timezone":"Africa/Accra",
    "iso:country":"GH",
    "name:und_x_variant":[
        "Otsew Dwokwaa",
        "Otaw"
    ],
    "wof:name":"Otaw",
    "wof:placetype":"locality"
},
  "geometry": {"coordinates":[-0.71001,5.35906],"type":"Point"}
}