{
  "type": "Feature",
  "properties": {
    "gn:admin1_code":"00",
    "gn:asciiname":"Zangum",
    "gn:country_code":"GH",
    "gn:dem":174,
    "gn:feature_class":"P",
    "gn:feature_code":"PPL",
    "gn:name":"Zangum",
    "gn:population":0,
    "gn:timezone":"Africa/Accra",
    "iso:country":"GH",
    "wof:name":"Zangum",
    "wof:placetype":"locality"
},
  "geometry": {"coordinates":[-0.82789,10.39741],"type":"Point"}
}