{
  "type": "Feature",
  "properties": {
    "gn:admin1_code":"00",
    "gn:asciiname":"Ngnani",
    "gn:country_code":"GH",
    "gn:dem":158,
    "gn:feature_class":"P",
    "gn:feature_code":"PPL",
    "gn:name":"Ngnani",
    "gn:population":0,
    "gn:timezone":"Africa/Accra",
    "iso:country":"GH",
    "wof:name":"Ngnani",
    "wof:placetype":"locality"
},
  "geometry": {"coordinates":[-0.22619,10.32537],"type":"Point"}
}