{
  "type": "Feature",
  "properties": {
    "gn:admin1_code":"00",
    "gn:asciiname":"Salwelsi",
    "gn:cc2":"GH",
    "gn:country_code":"GH",
    "gn:dem":188,
    "gn:feature_class":"P",
    "gn:feature_code":"PPL",
    "gn:name":"Salwelsi",
    "gn:population":0,
    "gn:timezone":"Africa/Accra",
    "iso:country":"GH",
    "name:und_x_variant":[
        "Zakpalsi",
        "Sakwelsi",
        "Salwelsi"
    ],
    "wof:name":"Salwelsi",
    "wof:placetype":"locality"
},
  "geometry": {"coordinates":[-0.31667,9.46667],"type":"Point"}
}