{
  "type": "Feature",
  "properties": {
    "gn:admin1_code":"02",
    "gn:asciiname":"Wioso",
    "gn:country_code":"GH",
    "gn:dem":307,
    "gn:feature_class":"P",
    "gn:feature_code":"PPL",
    "gn:name":"Wioso",
    "gn:population":0,
    "gn:timezone":"Africa/Accra",
    "iso:country":"GH",
    "name:eng_x_preferred":[
        "Wioso"
    ],
    "name:eng_x_variant":[
        "Wiawso"
    ],
    "wof:name":"Wioso",
    "wof:placetype":"locality"
},
  "geometry": {"coordinates":[-2.02998,6.90715],"type":"Point"}
}