{
  "type": "Feature",
  "properties": {
    "gn:admin1_code":"00",
    "gn:asciiname":"Bisiasi",
    "gn:country_code":"GH",
    "gn:dem":135,
    "gn:feature_class":"P",
    "gn:feature_code":"PPL",
    "gn:name":"Bisiasi",
    "gn:population":0,
    "gn:timezone":"Africa/Accra",
    "iso:country":"GH",
    "name:und_x_variant":[
        "Besiasi",
        "Bisiasi"
    ],
    "wof:name":"Bisiasi",
    "wof:placetype":"locality"
},
  "geometry": {"coordinates":[-2.01738,6.03717],"type":"Point"}
}