{
  "type": "Feature",
  "properties": {
    "gn:admin1_code":"09",
    "gn:asciiname":"Amukrom",
    "gn:country_code":"GH",
    "gn:dem":74,
    "gn:feature_class":"P",
    "gn:feature_code":"PPL",
    "gn:name":"Amukrom",
    "gn:population":0,
    "gn:timezone":"Africa/Accra",
    "iso:country":"GH",
    "name:eng_x_preferred":[
        "Amukrom"
    ],
    "wof:name":"Amukrom",
    "wof:placetype":"locality"
},
  "geometry": {"coordinates":[-1.80743,5.0223],"type":"Point"}
}