{
  "type": "Feature",
  "properties": {
    "gn:admin1_code":"00",
    "gn:asciiname":"Pojive",
    "gn:country_code":"GH",
    "gn:dem":129,
    "gn:feature_class":"P",
    "gn:feature_code":"PPL",
    "gn:name":"Pojive",
    "gn:population":0,
    "gn:timezone":"Africa/Accra",
    "iso:country":"GH",
    "wof:name":"Pojive",
    "wof:placetype":"locality"
},
  "geometry": {"coordinates":[0.31856,6.45428],"type":"Point"}
}