{
  "type": "Feature",
  "properties": {
    "gn:admin1_code":"06",
    "gn:asciiname":"Nanguri",
    "gn:country_code":"GH",
    "gn:dem":181,
    "gn:feature_class":"P",
    "gn:feature_code":"PPL",
    "gn:name":"Nanguri",
    "gn:population":0,
    "gn:timezone":"Africa/Accra",
    "iso:country":"GH",
    "name:und_x_variant":[
        "Yikpabango",
        "Nanguri"
    ],
    "wof:name":"Nanguri",
    "wof:placetype":"locality"
},
  "geometry": {"coordinates":[-1.56711,10.24111],"type":"Point"}
}