{
  "type": "Feature",
  "properties": {
    "gn:admin1_code":"00",
    "gn:asciiname":"Kunyebin",
    "gn:country_code":"GH",
    "gn:dem":248,
    "gn:feature_class":"P",
    "gn:feature_code":"PPL",
    "gn:name":"Kunyebin",
    "gn:population":0,
    "gn:timezone":"Africa/Accra",
    "iso:country":"GH",
    "wof:name":"Kunyebin",
    "wof:placetype":"locality"
},
  "geometry": {"coordinates":[-1.79602,10.19594],"type":"Point"}
}