{
  "type": "Feature",
  "properties": {
    "gn:admin1_code":"00",
    "gn:asciiname":"Bomini",
    "gn:country_code":"GH",
    "gn:dem":337,
    "gn:feature_class":"P",
    "gn:feature_code":"PPL",
    "gn:name":"Bomini",
    "gn:population":0,
    "gn:timezone":"Africa/Accra",
    "iso:country":"GH",
    "wof:name":"Bomini",
    "wof:placetype":"locality"
},
  "geometry": {"coordinates":[-1.65446,7.72813],"type":"Point"}
}