{
  "type": "Feature",
  "properties": {
    "gn:admin1_code":"02",
    "gn:asciiname":"Asokore Mampon",
    "gn:country_code":"GH",
    "gn:dem":280,
    "gn:feature_class":"P",
    "gn:feature_code":"PPL",
    "gn:name":"Asokore Mampon",
    "gn:population":0,
    "gn:timezone":"Africa/Accra",
    "iso:country":"GH",
    "name:und_x_variant":[
        "Asokori Mampon",
        "Asokori Mampong"
    ],
    "wof:name":"Asokore Mampon",
    "wof:placetype":"locality"
},
  "geometry": {"coordinates":[-1.56673,6.70953],"type":"Point"}
}