{
  "type": "Feature",
  "properties": {
    "gn:admin1_code":"00",
    "gn:asciiname":"Sumangho",
    "gn:country_code":"GH",
    "gn:dem":47,
    "gn:feature_class":"P",
    "gn:feature_code":"PPL",
    "gn:name":"Sumangho",
    "gn:population":0,
    "gn:timezone":"Africa/Accra",
    "iso:country":"GH",
    "wof:name":"Sumangho",
    "wof:placetype":"locality"
},
  "geometry": {"coordinates":[-2.18627,5.5008],"type":"Point"}
}