{
  "type": "Feature",
  "properties": {
    "gn:admin1_code":"00",
    "gn:asciiname":"Asapong",
    "gn:country_code":"GH",
    "gn:dem":254,
    "gn:feature_class":"P",
    "gn:feature_code":"PPL",
    "gn:name":"Asapong",
    "gn:population":0,
    "gn:timezone":"Africa/Accra",
    "iso:country":"GH",
    "name:und_x_variant":[
        "Asupong",
        "Asapon",
        "Asapong"
    ],
    "wof:name":"Asapong",
    "wof:placetype":"locality"
},
  "geometry": {"coordinates":[-1.43946,6.68789],"type":"Point"}
}