{
  "type": "Feature",
  "properties": {
    "gn:admin1_code":"00",
    "gn:asciiname":"Devenu",
    "gn:country_code":"GH",
    "gn:dem":-1,
    "gn:feature_class":"P",
    "gn:feature_code":"PPL",
    "gn:name":"Devenu",
    "gn:population":0,
    "gn:timezone":"Africa/Accra",
    "iso:country":"GH",
    "name:und_x_variant":[
        "Dewenu",
        "Devenu"
    ],
    "wof:name":"Devenu",
    "wof:placetype":"locality"
},
  "geometry": {"coordinates":[0.8013,5.90825],"type":"Point"}
}