{
  "type": "Feature",
  "properties": {
    "gn:admin1_code":"00",
    "gn:asciiname":"Ebu",
    "gn:country_code":"GH",
    "gn:dem":69,
    "gn:feature_class":"P",
    "gn:feature_code":"PPL",
    "gn:name":"Ebu",
    "gn:population":0,
    "gn:timezone":"Africa/Accra",
    "iso:country":"GH",
    "name:und_x_variant":[
        "Old Ebu",
        "Ebu"
    ],
    "wof:name":"Ebu",
    "wof:placetype":"locality"
},
  "geometry": {"coordinates":[-1.23346,5.21245],"type":"Point"}
}