{
  "type": "Feature",
  "properties": {
    "gn:admin1_code":"02",
    "gn:asciiname":"Finaso",
    "gn:country_code":"GH",
    "gn:dem":167,
    "gn:feature_class":"P",
    "gn:feature_code":"PPL",
    "gn:name":"Finaso",
    "gn:population":0,
    "gn:timezone":"Africa/Accra",
    "iso:country":"GH",
    "name:und_x_variant":[
        "Finaso Number 1",
        "Finaso"
    ],
    "wof:name":"Finaso",
    "wof:placetype":"locality"
},
  "geometry": {"coordinates":[-1.74058,6.21711],"type":"Point"}
}