{
  "type": "Feature",
  "properties": {
    "gn:admin1_code":"00",
    "gn:asciiname":"Obonwu",
    "gn:country_code":"GH",
    "gn:dem":126,
    "gn:feature_class":"P",
    "gn:feature_code":"PPL",
    "gn:name":"Obonwu",
    "gn:population":0,
    "gn:timezone":"Africa/Accra",
    "iso:country":"GH",
    "wof:name":"Obonwu",
    "wof:placetype":"locality"
},
  "geometry": {"coordinates":[-0.46667,5.95],"type":"Point"}
}