{
  "type": "Feature",
  "properties": {
    "gn:admin1_code":"00",
    "gn:asciiname":"Krobo",
    "gn:country_code":"GH",
    "gn:dem":91,
    "gn:feature_class":"P",
    "gn:feature_code":"PPL",
    "gn:name":"Krobo",
    "gn:population":0,
    "gn:timezone":"Africa/Accra",
    "iso:country":"GH",
    "wof:name":"Krobo",
    "wof:placetype":"locality"
},
  "geometry": {"coordinates":[-1.39986,5.24462],"type":"Point"}
}