{
  "type": "Feature",
  "properties": {
    "gn:admin1_code":"00",
    "gn:asciiname":"Nyarigbini",
    "gn:country_code":"GH",
    "gn:dem":214,
    "gn:feature_class":"P",
    "gn:feature_code":"PPL",
    "gn:name":"Nyarigbini",
    "gn:population":0,
    "gn:timezone":"Africa/Accra",
    "iso:country":"GH",
    "wof:name":"Nyarigbini",
    "wof:placetype":"locality"
},
  "geometry": {"coordinates":[-0.18333,10.43333],"type":"Point"}
}