{
  "type": "Feature",
  "properties": {
    "gn:admin1_code":"00",
    "gn:asciiname":"Anwianwia",
    "gn:country_code":"GH",
    "gn:dem":66,
    "gn:feature_class":"P",
    "gn:feature_code":"PPL",
    "gn:name":"Anwianwia",
    "gn:population":0,
    "gn:timezone":"Africa/Accra",
    "iso:country":"GH",
    "wof:name":"Anwianwia",
    "wof:placetype":"locality"
},
  "geometry": {"coordinates":[-2.66667,5.36667],"type":"Point"}
}