{
  "type": "Feature",
  "properties": {
    "gn:admin1_code":"00",
    "gn:asciiname":"Dedemede",
    "gn:country_code":"GH",
    "gn:dem":93,
    "gn:feature_class":"P",
    "gn:feature_code":"PPL",
    "gn:name":"Dedemede",
    "gn:population":0,
    "gn:timezone":"Africa/Accra",
    "iso:country":"GH",
    "wof:name":"Dedemede",
    "wof:placetype":"locality"
},
  "geometry": {"coordinates":[-1.61667,5.66667],"type":"Point"}
}