{
  "type": "Feature",
  "properties": {
    "gn:admin1_code":"09",
    "gn:asciiname":"Ndatiem",
    "gn:country_code":"GH",
    "gn:dem":15,
    "gn:feature_class":"P",
    "gn:feature_code":"PPL",
    "gn:name":"Ndatiem",
    "gn:population":0,
    "gn:timezone":"Africa/Accra",
    "iso:country":"GH",
    "name:und_x_variant":[
        "Natiem"
    ],
    "wof:name":"Ndatiem",
    "wof:placetype":"locality"
},
  "geometry": {"coordinates":[-2.20647,4.89492],"type":"Point"}
}