{
  "type": "Feature",
  "properties": {
    "gn:admin1_code":"00",
    "gn:asciiname":"Nkroakan",
    "gn:country_code":"GH",
    "gn:dem":175,
    "gn:feature_class":"P",
    "gn:feature_code":"PPL",
    "gn:name":"Nkroakan",
    "gn:population":0,
    "gn:timezone":"Africa/Accra",
    "iso:country":"GH",
    "name:und_x_variant":[
        "Nkurakan",
        "Nkroakan"
    ],
    "wof:name":"Nkroakan",
    "wof:placetype":"locality"
},
  "geometry": {"coordinates":[-0.81322,6.71253],"type":"Point"}
}