{
  "type": "Feature",
  "properties": {
    "gn:admin1_code":"00",
    "gn:asciiname":"Achiekrom",
    "gn:country_code":"GH",
    "gn:dem":63,
    "gn:feature_class":"P",
    "gn:feature_code":"PPL",
    "gn:name":"Achiekrom",
    "gn:population":0,
    "gn:timezone":"Africa/Accra",
    "iso:country":"GH",
    "wof:name":"Achiekrom",
    "wof:placetype":"locality"
},
  "geometry": {"coordinates":[-2.58333,5.61667],"type":"Point"}
}