{
  "type": "Feature",
  "properties": {
    "gn:admin1_code":"00",
    "gn:asciiname":"Wojiengo",
    "gn:country_code":"GH",
    "gn:dem":208,
    "gn:feature_class":"P",
    "gn:feature_code":"PPL",
    "gn:name":"Wojiengo",
    "gn:population":0,
    "gn:timezone":"Africa/Accra",
    "iso:country":"GH",
    "name:und_x_variant":[
        "Sirigu Wugingo",
        "Wojiengo"
    ],
    "wof:name":"Wojiengo",
    "wof:placetype":"locality"
},
  "geometry": {"coordinates":[-0.92093,10.96077],"type":"Point"}
}