{
  "type": "Feature",
  "properties": {
    "gn:admin1_code":"11",
    "gn:asciiname":"Kalsara",
    "gn:country_code":"GH",
    "gn:dem":296,
    "gn:feature_class":"P",
    "gn:feature_code":"PPL",
    "gn:name":"Kalsara",
    "gn:population":0,
    "gn:timezone":"Africa/Accra",
    "iso:country":"GH",
    "name:und_x_variant":[
        "Kalsagra",
        "Kalsara"
    ],
    "wof:name":"Kalsara",
    "wof:placetype":"locality"
},
  "geometry": {"coordinates":[-2.66315,10.41005],"type":"Point"}
}