{
  "type": "Feature",
  "properties": {
    "gn:admin1_code":"00",
    "gn:asciiname":"Nayawko",
    "gn:country_code":"GH",
    "gn:dem":158,
    "gn:feature_class":"P",
    "gn:feature_code":"PPL",
    "gn:name":"Nayawko",
    "gn:population":0,
    "gn:timezone":"Africa/Accra",
    "iso:country":"GH",
    "name:und_x_variant":[
        "Naiyoko",
        "Nayoku",
        "Nayuwko",
        "Nayawko"
    ],
    "wof:name":"Nayawko",
    "wof:placetype":"locality"
},
  "geometry": {"coordinates":[-0.76584,10.37723],"type":"Point"}
}