{
  "type": "Feature",
  "properties": {
    "gn:admin1_code":"00",
    "gn:asciiname":"Bofe",
    "gn:country_code":"GH",
    "gn:dem":240,
    "gn:feature_class":"P",
    "gn:feature_code":"PPL",
    "gn:name":"Bofe",
    "gn:population":0,
    "gn:timezone":"Africa/Accra",
    "iso:country":"GH",
    "wof:name":"Bofe",
    "wof:placetype":"locality"
},
  "geometry": {"coordinates":[-2.37457,8.02212],"type":"Point"}
}