{
  "type": "Feature",
  "properties": {
    "gn:admin1_code":"00",
    "gn:asciiname":"Kugusabliga",
    "gn:country_code":"GH",
    "gn:dem":213,
    "gn:feature_class":"P",
    "gn:feature_code":"PPL",
    "gn:name":"Kugusabliga",
    "gn:population":0,
    "gn:timezone":"Africa/Accra",
    "iso:country":"GH",
    "name:und_x_variant":[
        "Kulusabelega",
        "Kugsabla",
        "Kugusabliga"
    ],
    "wof:name":"Kugusabliga",
    "wof:placetype":"locality"
},
  "geometry": {"coordinates":[-0.11512,10.8986],"type":"Point"}
}