{
  "type": "Feature",
  "properties": {
    "gn:admin1_code":"00",
    "gn:asciiname":"Agbolikpota",
    "gn:country_code":"GH",
    "gn:dem":1,
    "gn:feature_class":"P",
    "gn:feature_code":"PPL",
    "gn:name":"Agbolikpota",
    "gn:population":0,
    "gn:timezone":"Africa/Accra",
    "iso:country":"GH",
    "name:und_x_variant":[
        "Agbolinkpota",
        "Agbolikpota"
    ],
    "wof:name":"Agbolikpota",
    "wof:placetype":"locality"
},
  "geometry": {"coordinates":[0.65668,5.94515],"type":"Point"}
}