{
  "type": "Feature",
  "properties": {
    "gn:admin1_code":"00",
    "gn:asciiname":"Abasi",
    "gn:country_code":"GH",
    "gn:dem":367,
    "gn:feature_class":"P",
    "gn:feature_code":"PPL",
    "gn:name":"Abasi",
    "gn:population":0,
    "gn:timezone":"Africa/Accra",
    "iso:country":"GH",
    "name:und_x_variant":[
        "Abase",
        "Abasi"
    ],
    "wof:name":"Abasi",
    "wof:placetype":"locality"
},
  "geometry": {"coordinates":[-1.23572,6.89386],"type":"Point"}
}