{
  "type": "Feature",
  "properties": {
    "gn:admin1_code":"00",
    "gn:asciiname":"Abasi",
    "gn:country_code":"GH",
    "gn:dem":367,
    "gn:feature_class":"P",
    "gn:feature_code":"PPL",
    "gn:name":"Abasi",
    "gn:population":0,
    "gn:timezone":"Africa/Accra",
    "iso:country":"GH",
    "name:bul_x_preferred":[
        "\u0410\u0431\u0430\u0441\u0438"
    ],
    "name:ces_x_preferred":[
        "Abasi"
    ],
    "name:fas_x_preferred":[
        "\u0639\u0628\u0627\u0633\u06cc"
    ],
    "name:fra_x_preferred":[
        "Abasi"
    ],
    "name:rus_x_preferred":[
        "\u0410\u0431\u0430\u0441\u0438"
    ],
    "name:slk_x_preferred":[
        "Abasi"
    ],
    "name:snd_x_preferred":[
        "\u0639\u0628\u0627\u0633\u064a"
    ],
    "name:ukr_x_preferred":[
        "\u0410\u0431\u0430\u0441\u0456"
    ],
    "name:und_x_variant":[
        "Abase"
    ],
    "name:urd_x_preferred":[
        "\u0639\u0628\u0627\u0633\u06cc"
    ],
    "wof:name":"Abasi",
    "wof:placetype":"locality"
},
  "geometry": {"coordinates":[-1.23572,6.89386],"type":"Point"}
}