{
  "type": "Feature",
  "properties": {
    "gn:admin1_code":"00",
    "gn:asciiname":"Afopa",
    "gn:cc2":"GH",
    "gn:country_code":"GH",
    "gn:dem":12,
    "gn:feature_class":"P",
    "gn:feature_code":"PPL",
    "gn:name":"Afopa",
    "gn:population":0,
    "gn:timezone":"Africa/Accra",
    "iso:country":"GH",
    "name:und_x_variant":[
        "Afopakorpe",
        "Afopa"
    ],
    "wof:name":"Afopa",
    "wof:placetype":"locality"
},
  "geometry": {"coordinates":[0.11667,6.15],"type":"Point"}
}