{
  "type": "Feature",
  "properties": {
    "gn:admin1_code":"00",
    "gn:asciiname":"Apirede",
    "gn:country_code":"GH",
    "gn:dem":427,
    "gn:feature_class":"P",
    "gn:feature_code":"PPL",
    "gn:name":"Apirede",
    "gn:population":0,
    "gn:timezone":"Africa/Accra",
    "iso:country":"GH",
    "wof:name":"Apirede",
    "wof:placetype":"locality"
},
  "geometry": {"coordinates":[-0.07873,6.03621],"type":"Point"}
}