{
  "type": "Feature",
  "properties": {
    "gn:admin1_code":"00",
    "gn:asciiname":"Keri",
    "gn:country_code":"GH",
    "gn:dem":212,
    "gn:feature_class":"P",
    "gn:feature_code":"PPL",
    "gn:name":"Keri",
    "gn:population":0,
    "gn:timezone":"Africa/Accra",
    "iso:country":"GH",
    "name:heb_x_preferred":[
        "\u05d1\u05e2\u05dc \u05e7\u05e8\u05d9"
    ],
    "wof:name":"Keri",
    "wof:placetype":"locality"
},
  "geometry": {"coordinates":[0.53255,8.38998],"type":"Point"}
}