{
  "type": "Feature",
  "properties": {
    "gn:admin1_code":"00",
    "gn:asciiname":"Keri",
    "gn:country_code":"GH",
    "gn:dem":212,
    "gn:feature_class":"P",
    "gn:feature_code":"PPL",
    "gn:name":"Keri",
    "gn:population":0,
    "gn:timezone":"Africa/Accra",
    "iso:country":"GH",
    "wof:name":"Keri",
    "wof:placetype":"locality"
},
  "geometry": {"coordinates":[0.53255,8.38998],"type":"Point"}
}