{
  "type": "Feature",
  "properties": {
    "gn:admin1_code":"00",
    "gn:asciiname":"Sutapong",
    "gn:cc2":"GH",
    "gn:country_code":"GH",
    "gn:dem":432,
    "gn:feature_class":"P",
    "gn:feature_code":"PPL",
    "gn:name":"Sutapong",
    "gn:population":0,
    "gn:timezone":"Africa/Accra",
    "iso:country":"GH",
    "name:und_x_variant":[
        "Sutapong South",
        "Sutapong"
    ],
    "wof:name":"Sutapong",
    "wof:placetype":"locality"
},
  "geometry": {"coordinates":[-0.26667,6.26667],"type":"Point"}
}