{
  "type": "Feature",
  "properties": {
    "gn:admin1_code":"09",
    "gn:asciiname":"Owurakese",
    "gn:country_code":"GH",
    "gn:dem":133,
    "gn:feature_class":"P",
    "gn:feature_code":"PPL",
    "gn:name":"Owurakese",
    "gn:population":0,
    "gn:timezone":"Africa/Accra",
    "iso:country":"GH",
    "name:eng_x_preferred":[
        "Owurakese"
    ],
    "wof:name":"Owurakese",
    "wof:placetype":"locality"
},
  "geometry": {"coordinates":[-1.85705,5.66774],"type":"Point"}
}