{
  "type": "Feature",
  "properties": {
    "gn:admin1_code":"02",
    "gn:asciiname":"Amrada",
    "gn:country_code":"GH",
    "gn:dem":192,
    "gn:feature_class":"P",
    "gn:feature_code":"PPL",
    "gn:name":"Amrada",
    "gn:population":0,
    "gn:timezone":"Africa/Accra",
    "iso:country":"GH",
    "name:und_x_variant":[
        "Omrada",
        "Amrada"
    ],
    "wof:name":"Amrada",
    "wof:placetype":"locality"
},
  "geometry": {"coordinates":[-1.99134,6.64458],"type":"Point"}
}