{
  "type": "Feature",
  "properties": {
    "gn:admin1_code":"00",
    "gn:asciiname":"Djagbemba",
    "gn:country_code":"GH",
    "gn:dem":145,
    "gn:feature_class":"P",
    "gn:feature_code":"PPL",
    "gn:name":"Djagbemba",
    "gn:population":0,
    "gn:timezone":"Africa/Accra",
    "iso:country":"GH",
    "name:und_x_variant":[
        "Djagblema",
        "Djagbema",
        "Djagbemba"
    ],
    "wof:name":"Djagbemba",
    "wof:placetype":"locality"
},
  "geometry": {"coordinates":[-0.049,9.12489],"type":"Point"}
}