{
  "type": "Feature",
  "properties": {
    "gn:admin1_code":"00",
    "gn:asciiname":"Anyimaducho",
    "gn:country_code":"GH",
    "gn:dem":110,
    "gn:feature_class":"P",
    "gn:feature_code":"PPL",
    "gn:name":"Anyimaducho",
    "gn:population":0,
    "gn:timezone":"Africa/Accra",
    "iso:country":"GH",
    "wof:name":"Anyimaducho",
    "wof:placetype":"locality"
},
  "geometry": {"coordinates":[-1.68333,5.63333],"type":"Point"}
}