{
  "type": "Feature",
  "properties": {
    "gn:admin1_code":"00",
    "gn:asciiname":"Asakwam",
    "gn:country_code":"GH",
    "gn:dem":80,
    "gn:feature_class":"P",
    "gn:feature_code":"PPL",
    "gn:name":"Asakwam",
    "gn:population":0,
    "gn:timezone":"Africa/Accra",
    "iso:country":"GH",
    "wof:name":"Asakwam",
    "wof:placetype":"locality"
},
  "geometry": {"coordinates":[-2.13333,5.05],"type":"Point"}
}