{
  "type": "Feature",
  "properties": {
    "gn:admin1_code":"00",
    "gn:asciiname":"Fumso",
    "gn:country_code":"GH",
    "gn:dem":132,
    "gn:feature_class":"P",
    "gn:feature_code":"PPL",
    "gn:name":"Fumso",
    "gn:population":0,
    "gn:timezone":"Africa/Accra",
    "iso:country":"GH",
    "wof:name":"Fumso",
    "wof:placetype":"locality"
},
  "geometry": {"coordinates":[-1.45141,6.11333],"type":"Point"}
}