{
  "type": "Feature",
  "properties": {
    "gn:admin1_code":"00",
    "gn:asciiname":"Buni",
    "gn:country_code":"GH",
    "gn:dem":305,
    "gn:feature_class":"P",
    "gn:feature_code":"PPL",
    "gn:name":"Buni",
    "gn:population":0,
    "gn:timezone":"Africa/Accra",
    "iso:country":"GH",
    "wof:name":"Buni",
    "wof:placetype":"locality"
},
  "geometry": {"coordinates":[-2.64236,7.80433],"type":"Point"}
}