{
  "type": "Feature",
  "properties": {
    "gn:admin1_code":"00",
    "gn:asciiname":"Jentidua",
    "gn:country_code":"GH",
    "gn:dem":101,
    "gn:feature_class":"P",
    "gn:feature_code":"PPL",
    "gn:name":"Jentidua",
    "gn:population":0,
    "gn:timezone":"Africa/Accra",
    "iso:country":"GH",
    "name:und_x_variant":[
        "Ajantudua",
        "Gyentidua",
        "Jentidua"
    ],
    "wof:name":"Jentidua",
    "wof:placetype":"locality"
},
  "geometry": {"coordinates":[-0.79675,8.23836],"type":"Point"}
}