{
  "type": "Feature",
  "properties": {
    "gn:admin1_code":"00",
    "gn:asciiname":"Kwasibuokrom",
    "gn:country_code":"GH",
    "gn:dem":260,
    "gn:feature_class":"P",
    "gn:feature_code":"PPL",
    "gn:name":"Kwasibuokrom",
    "gn:population":0,
    "gn:timezone":"Africa/Accra",
    "iso:country":"GH",
    "name:und_x_variant":[
        "Kwasibookurom",
        "Kwasibuokrom"
    ],
    "wof:name":"Kwasibuokrom",
    "wof:placetype":"locality"
},
  "geometry": {"coordinates":[-2.79307,7.57787],"type":"Point"}
}