{
  "type": "Feature",
  "properties": {
    "gn:admin1_code":"00",
    "gn:asciiname":"Pekura",
    "gn:country_code":"GH",
    "gn:dem":143,
    "gn:feature_class":"P",
    "gn:feature_code":"PPL",
    "gn:name":"Pekura",
    "gn:population":0,
    "gn:timezone":"Africa/Accra",
    "iso:country":"GH",
    "name:und_x_variant":[
        "Pokura",
        "Pokurra",
        "Pekura"
    ],
    "wof:name":"Pekura",
    "wof:placetype":"locality"
},
  "geometry": {"coordinates":[-0.33378,10.23629],"type":"Point"}
}