{
  "type": "Feature",
  "properties": {
    "gn:admin1_code":"02",
    "gn:asciiname":"Opunikrom",
    "gn:country_code":"GH",
    "gn:dem":133,
    "gn:feature_class":"P",
    "gn:feature_code":"PPL",
    "gn:name":"Opunikrom",
    "gn:population":0,
    "gn:timezone":"Africa/Accra",
    "iso:country":"GH",
    "name:und_x_variant":[
        "Aduposo",
        "Opunikrom"
    ],
    "wof:name":"Opunikrom",
    "wof:placetype":"locality"
},
  "geometry": {"coordinates":[-1.51537,6.00492],"type":"Point"}
}