{
  "type": "Feature",
  "properties": {
    "gn:admin1_code":"02",
    "gn:asciiname":"Bechikrom",
    "gn:country_code":"GH",
    "gn:dem":240,
    "gn:feature_class":"P",
    "gn:feature_code":"PPL",
    "gn:name":"Bechikrom",
    "gn:population":0,
    "gn:timezone":"Africa/Accra",
    "iso:country":"GH",
    "name:eng_x_preferred":[
        "Bechikrom"
    ],
    "wof:name":"Bechikrom",
    "wof:placetype":"locality"
},
  "geometry": {"coordinates":[-1.83871,6.90093],"type":"Point"}
}