{
  "type": "Feature",
  "properties": {
    "gn:admin1_code":"00",
    "gn:asciiname":"Amanfro",
    "gn:country_code":"GH",
    "gn:dem":50,
    "gn:feature_class":"P",
    "gn:feature_code":"PPL",
    "gn:name":"Amanfro",
    "gn:population":0,
    "gn:timezone":"Africa/Accra",
    "iso:country":"GH",
    "wof:name":"Amanfro",
    "wof:placetype":"locality"
},
  "geometry": {"coordinates":[-0.03559,5.93456],"type":"Point"}
}