{
  "type": "Feature",
  "properties": {
    "gn:admin1_code":"00",
    "gn:asciiname":"Kosa",
    "gn:country_code":"GH",
    "gn:dem":281,
    "gn:feature_class":"P",
    "gn:feature_code":"PPL",
    "gn:name":"Kosa",
    "gn:population":0,
    "gn:timezone":"Africa/Accra",
    "iso:country":"GH",
    "wof:name":"Kosa",
    "wof:placetype":"locality"
},
  "geometry": {"coordinates":[-0.31667,10.48333],"type":"Point"}
}