{
  "type": "Feature",
  "properties": {
    "gn:admin1_code":"02",
    "gn:asciiname":"Esase",
    "gn:country_code":"GH",
    "gn:dem":306,
    "gn:feature_class":"P",
    "gn:feature_code":"PPL",
    "gn:name":"Esase",
    "gn:population":0,
    "gn:timezone":"Africa/Accra",
    "iso:country":"GH",
    "name:und_x_variant":[
        "Esasi",
        "Essase",
        "Esase"
    ],
    "wof:name":"Esase",
    "wof:placetype":"locality"
},
  "geometry": {"coordinates":[-1.88991,6.56082],"type":"Point"}
}