{
  "type": "Feature",
  "properties": {
    "gn:admin1_code":"00",
    "gn:asciiname":"Tsikoe",
    "gn:country_code":"GH",
    "gn:dem":278,
    "gn:feature_class":"P",
    "gn:feature_code":"PPL",
    "gn:name":"Tsikoe",
    "gn:population":0,
    "gn:timezone":"Africa/Accra",
    "iso:country":"GH",
    "name:und_x_variant":[
        "Wusutatsikoe Bohome",
        "Tsikoe"
    ],
    "wof:name":"Tsikoe",
    "wof:placetype":"locality"
},
  "geometry": {"coordinates":[0.25405,6.80915],"type":"Point"}
}