{
  "type": "Feature",
  "properties": {
    "gn:admin1_code":"00",
    "gn:asciiname":"Aholukofe",
    "gn:country_code":"GH",
    "gn:dem":40,
    "gn:feature_class":"P",
    "gn:feature_code":"PPL",
    "gn:name":"Aholukofe",
    "gn:population":0,
    "gn:timezone":"Africa/Accra",
    "iso:country":"GH",
    "wof:name":"Aholukofe",
    "wof:placetype":"locality"
},
  "geometry": {"coordinates":[0.53333,6.16667],"type":"Point"}
}