{
  "type": "Feature",
  "properties": {
    "gn:admin1_code":"01",
    "gn:asciiname":"Gbegbeyise",
    "gn:country_code":"GH",
    "gn:dem":12,
    "gn:feature_class":"P",
    "gn:feature_code":"PPL",
    "gn:name":"Gbegbeyise",
    "gn:population":0,
    "gn:timezone":"Africa/Accra",
    "iso:country":"GH",
    "name:und_x_variant":[
        "Gbegbe"
    ],
    "wof:name":"Gbegbeyise",
    "wof:placetype":"locality"
},
  "geometry": {"coordinates":[-0.26486,5.52468],"type":"Point"}
}