{
  "type": "Feature",
  "properties": {
    "gn:admin1_code":"00",
    "gn:asciiname":"Ashanti Kpoeta",
    "gn:country_code":"GH",
    "gn:dem":559,
    "gn:feature_class":"P",
    "gn:feature_code":"PPL",
    "gn:name":"Ashanti Kpoeta",
    "gn:population":0,
    "gn:timezone":"Africa/Accra",
    "iso:country":"GH",
    "name:und_x_variant":[
        "Ashanti",
        "Ashanti Kpoeta"
    ],
    "wof:name":"Ashanti Kpoeta",
    "wof:placetype":"locality"
},
  "geometry": {"coordinates":[0.53667,6.91428],"type":"Point"}
}