{
  "type": "Feature",
  "properties": {
    "gn:admin1_code":"09",
    "gn:asciiname":"Agona",
    "gn:country_code":"GH",
    "gn:dem":40,
    "gn:feature_class":"P",
    "gn:feature_code":"PPL",
    "gn:name":"Agona",
    "gn:population":0,
    "gn:timezone":"Africa/Accra",
    "iso:country":"GH",
    "name:azb_x_preferred":[
        "\u0627\u0642\u0648\u0646\u0627"
    ],
    "name:deu_x_preferred":[
        "Agona"
    ],
    "name:eng_x_preferred":[
        "Agona"
    ],
    "name:fas_x_preferred":[
        "\u0627\u06af\u0648\u0646\u0627"
    ],
    "name:pol_x_preferred":[
        "Agona"
    ],
    "name:swe_x_preferred":[
        "Agona"
    ],
    "name:urd_x_preferred":[
        "\u0627\u06af\u0648\u0646\u0627"
    ],
    "wof:name":"Agona",
    "wof:placetype":"locality"
},
  "geometry": {"coordinates":[-1.9671,4.89715],"type":"Point"}
}