{
  "type": "Feature",
  "properties": {
    "gn:admin1_code":"01",
    "gn:asciiname":"Obuasi",
    "gn:country_code":"GH",
    "gn:dem":89,
    "gn:feature_class":"P",
    "gn:feature_code":"PPL",
    "gn:name":"Obuasi",
    "gn:population":0,
    "gn:timezone":"Africa/Accra",
    "iso:country":"GH",
    "wof:name":"Obuasi",
    "wof:placetype":"locality"
},
  "geometry": {"coordinates":[-0.25081,5.7337],"type":"Point"}
}