{
  "type": "Feature",
  "properties": {
    "gn:admin1_code":"11",
    "gn:asciiname":"Kugia",
    "gn:country_code":"GH",
    "gn:dem":249,
    "gn:feature_class":"P",
    "gn:feature_code":"PPL",
    "gn:name":"Kugia",
    "gn:population":0,
    "gn:timezone":"Africa/Accra",
    "iso:country":"GH",
    "name:und_x_variant":[
        "Kuzia",
        "Kugia"
    ],
    "wof:name":"Kugia",
    "wof:placetype":"locality"
},
  "geometry": {"coordinates":[-2.72117,10.11427],"type":"Point"}
}