{
  "type": "Feature",
  "properties": {
    "gn:admin1_code":"00",
    "gn:asciiname":"Babianiha",
    "gn:country_code":"GH",
    "gn:dem":59,
    "gn:feature_class":"P",
    "gn:feature_code":"PPL",
    "gn:name":"Babianiha",
    "gn:population":0,
    "gn:timezone":"Africa/Accra",
    "iso:country":"GH",
    "wof:name":"Babianiha",
    "wof:placetype":"locality"
},
  "geometry": {"coordinates":[-2.18333,5.41667],"type":"Point"}
}