{
  "type": "Feature",
  "properties": {
    "gn:admin1_code":"00",
    "gn:asciiname":"Paranatic",
    "gn:country_code":"GH",
    "gn:dem":250,
    "gn:feature_class":"P",
    "gn:feature_code":"PPL",
    "gn:name":"Paranatic",
    "gn:population":0,
    "gn:timezone":"Africa/Accra",
    "iso:country":"GH",
    "name:und_x_variant":[
        "Pagnatig",
        "Paranatic"
    ],
    "wof:name":"Paranatic",
    "wof:placetype":"locality"
},
  "geometry": {"coordinates":[0.11617,10.53434],"type":"Point"}
}