{
  "type": "Feature",
  "properties": {
    "gn:admin1_code":"00",
    "gn:asciiname":"Puti Gongo",
    "gn:country_code":"GH",
    "gn:dem":255,
    "gn:feature_class":"P",
    "gn:feature_code":"PPL",
    "gn:name":"Puti Gongo",
    "gn:population":0,
    "gn:timezone":"Africa/Accra",
    "iso:country":"GH",
    "name:und_x_variant":[
        "Pusgongo",
        "Puti Gongo"
    ],
    "wof:name":"Puti Gongo",
    "wof:placetype":"locality"
},
  "geometry": {"coordinates":[-0.05548,10.83658],"type":"Point"}
}