{
  "type": "Feature",
  "properties": {
    "gn:admin1_code":"02",
    "gn:asciiname":"Katachiwa",
    "gn:country_code":"GH",
    "gn:dem":195,
    "gn:feature_class":"P",
    "gn:feature_code":"PPL",
    "gn:name":"Katachiwa",
    "gn:population":0,
    "gn:timezone":"Africa/Accra",
    "iso:country":"GH",
    "name:eng_x_preferred":[
        "Katachiwa"
    ],
    "wof:name":"Katachiwa",
    "wof:placetype":"locality"
},
  "geometry": {"coordinates":[-1.9952,6.6967],"type":"Point"}
}