{
  "type": "Feature",
  "properties": {
    "gn:admin1_code":"02",
    "gn:asciiname":"Nyamekeyere",
    "gn:country_code":"GH",
    "gn:dem":183,
    "gn:feature_class":"P",
    "gn:feature_code":"PPL",
    "gn:name":"Nyamekeyere",
    "gn:population":0,
    "gn:timezone":"Africa/Accra",
    "iso:country":"GH",
    "name:eng_x_preferred":[
        "Nyamekeyere"
    ],
    "name:und_x_variant":[
        "Nyamebekyere",
        "Nyamibechire"
    ],
    "wof:name":"Nyamekeyere",
    "wof:placetype":"locality"
},
  "geometry": {"coordinates":[-1.72006,6.1452],"type":"Point"}
}