{
  "type": "Feature",
  "properties": {
    "gn:admin1_code":"04",
    "gn:asciiname":"Abuakwankwanta",
    "gn:country_code":"GH",
    "gn:dem":132,
    "gn:feature_class":"P",
    "gn:feature_code":"PPL",
    "gn:name":"Abuakwankwanta",
    "gn:population":0,
    "gn:timezone":"Africa/Accra",
    "iso:country":"GH",
    "name:eng_x_preferred":[
        "Abuakwankwanta"
    ],
    "wof:name":"Abuakwankwanta",
    "wof:placetype":"locality"
},
  "geometry": {"coordinates":[-1.76362,5.94078],"type":"Point"}
}