{
  "type": "Feature",
  "properties": {
    "gn:admin1_code":"00",
    "gn:asciiname":"Ntuaso",
    "gn:country_code":"GH",
    "gn:dem":55,
    "gn:feature_class":"P",
    "gn:feature_code":"PPL",
    "gn:name":"Ntuaso",
    "gn:population":0,
    "gn:timezone":"Africa/Accra",
    "iso:country":"GH",
    "wof:name":"Ntuaso",
    "wof:placetype":"locality"
},
  "geometry": {"coordinates":[-0.35363,5.83873],"type":"Point"}
}