{
  "type": "Feature",
  "properties": {
    "gn:admin1_code":"09",
    "gn:asciiname":"Esienkrom",
    "gn:country_code":"GH",
    "gn:dem":76,
    "gn:feature_class":"P",
    "gn:feature_code":"PPL",
    "gn:name":"Esienkrom",
    "gn:population":0,
    "gn:timezone":"Africa/Accra",
    "iso:country":"GH",
    "name:eng_x_preferred":[
        "Esienkrom"
    ],
    "wof:name":"Esienkrom",
    "wof:placetype":"locality"
},
  "geometry": {"coordinates":[-1.99077,4.80204],"type":"Point"}
}