{
  "type": "Feature",
  "properties": {
    "gn:admin1_code":"00",
    "gn:asciiname":"Eguafo",
    "gn:country_code":"GH",
    "gn:dem":61,
    "gn:feature_class":"P",
    "gn:feature_code":"PPL",
    "gn:name":"Eguafo",
    "gn:population":0,
    "gn:timezone":"Africa/Accra",
    "iso:country":"GH",
    "name:und_x_variant":[
        "Aguafo",
        "Eguafo"
    ],
    "wof:name":"Eguafo",
    "wof:placetype":"locality"
},
  "geometry": {"coordinates":[-1.41117,5.16103],"type":"Point"}
}