{
  "type": "Feature",
  "properties": {
    "gn:admin1_code":"00",
    "gn:asciiname":"Tabosum",
    "gn:country_code":"GH",
    "gn:dem":90,
    "gn:feature_class":"P",
    "gn:feature_code":"PPL",
    "gn:name":"Tabosum",
    "gn:population":0,
    "gn:timezone":"Africa/Accra",
    "iso:country":"GH",
    "wof:name":"Tabosum",
    "wof:placetype":"locality"
},
  "geometry": {"coordinates":[-1.11706,5.32008],"type":"Point"}
}