{
  "type": "Feature",
  "properties": {
    "gn:admin1_code":"00",
    "gn:asciiname":"Aluaso",
    "gn:country_code":"GH",
    "gn:dem":16,
    "gn:feature_class":"P",
    "gn:feature_code":"PPL",
    "gn:name":"Aluaso",
    "gn:population":0,
    "gn:timezone":"Africa/Accra",
    "iso:country":"GH",
    "name:und_x_variant":[
        "Eluado"
    ],
    "wof:name":"Aluaso",
    "wof:placetype":"locality"
},
  "geometry": {"coordinates":[-2.00659,4.81282],"type":"Point"}
}