{
  "type": "Feature",
  "properties": {
    "gn:admin1_code":"00",
    "gn:asciiname":"Adahomasi",
    "gn:country_code":"GH",
    "gn:dem":84,
    "gn:feature_class":"P",
    "gn:feature_code":"PPL",
    "gn:name":"Adahomasi",
    "gn:population":0,
    "gn:timezone":"Africa/Accra",
    "iso:country":"GH",
    "wof:name":"Adahomasi",
    "wof:placetype":"locality"
},
  "geometry": {"coordinates":[-2.01343,5.46312],"type":"Point"}
}