{
  "type": "Feature",
  "properties": {
    "gn:admin1_code":"00",
    "gn:asciiname":"Badu",
    "gn:country_code":"GH",
    "gn:dem":189,
    "gn:feature_class":"P",
    "gn:feature_code":"PPL",
    "gn:name":"Badu",
    "gn:population":0,
    "gn:timezone":"Africa/Accra",
    "iso:country":"GH",
    "name:ceb_x_preferred":[
        "Badu"
    ],
    "name:deu_x_preferred":[
        "Badu"
    ],
    "name:fra_x_preferred":[
        "Badu"
    ],
    "name:rus_x_preferred":[
        "\u0411\u0430\u0434\u0443"
    ],
    "name:swe_x_preferred":[
        "Badu"
    ],
    "wof:name":"Badu",
    "wof:placetype":"locality"
},
  "geometry": {"coordinates":[-2.23034,7.69288],"type":"Point"}
}