{
  "type": "Feature",
  "properties": {
    "gn:admin1_code":"01",
    "gn:asciiname":"Tokusemitsigani",
    "gn:country_code":"GH",
    "gn:dem":42,
    "gn:feature_class":"P",
    "gn:feature_code":"PPL",
    "gn:name":"Tokusemitsigani",
    "gn:population":0,
    "gn:timezone":"Africa/Accra",
    "iso:country":"GH",
    "name:eng_x_preferred":[
        "Tokusemitsigani"
    ],
    "name:und_x_variant":[
        "Tokusee",
        "Tokuse"
    ],
    "wof:name":"Tokusemitsigani",
    "wof:placetype":"locality"
},
  "geometry": {"coordinates":[-0.37836,5.54697],"type":"Point"}
}