{
  "type": "Feature",
  "properties": {
    "gn:admin1_code":"00",
    "gn:asciiname":"Bonkro",
    "gn:country_code":"GH",
    "gn:dem":248,
    "gn:feature_class":"P",
    "gn:feature_code":"PPL",
    "gn:name":"Bonkro",
    "gn:population":0,
    "gn:timezone":"Africa/Accra",
    "iso:country":"GH",
    "wof:name":"Bonkro",
    "wof:placetype":"locality"
},
  "geometry": {"coordinates":[-2.11667,6.95],"type":"Point"}
}