{
  "type": "Feature",
  "properties": {
    "gn:admin1_code":"00",
    "gn:asciiname":"Ahireku",
    "gn:country_code":"GH",
    "gn:dem":115,
    "gn:feature_class":"P",
    "gn:feature_code":"PPL",
    "gn:name":"Ahireku",
    "gn:population":0,
    "gn:timezone":"Africa/Accra",
    "iso:country":"GH",
    "name:und_x_variant":[
        "Adukwaokrom",
        "Ahireku"
    ],
    "wof:name":"Ahireku",
    "wof:placetype":"locality"
},
  "geometry": {"coordinates":[-2.17031,5.48714],"type":"Point"}
}