{
  "type": "Feature",
  "properties": {
    "gn:admin1_code":"09",
    "gn:asciiname":"Owuochi",
    "gn:country_code":"GH",
    "gn:dem":77,
    "gn:feature_class":"P",
    "gn:feature_code":"PPL",
    "gn:name":"Owuochi",
    "gn:population":0,
    "gn:timezone":"Africa/Accra",
    "iso:country":"GH",
    "name:eng_x_preferred":[
        "Owuochi"
    ],
    "wof:name":"Owuochi",
    "wof:placetype":"locality"
},
  "geometry": {"coordinates":[-1.56363,5.37543],"type":"Point"}
}