{
  "type": "Feature",
  "properties": {
    "gn:admin1_code":"08",
    "gn:asciiname":"Avome",
    "gn:cc2":"GH",
    "gn:country_code":"GH",
    "gn:dem":8,
    "gn:feature_class":"P",
    "gn:feature_code":"PPL",
    "gn:name":"Avome",
    "gn:population":0,
    "gn:timezone":"Africa/Accra",
    "iso:country":"GH",
    "name:und_x_variant":[
        "Avoeme",
        "Avome"
    ],
    "wof:name":"Avome",
    "wof:placetype":"locality"
},
  "geometry": {"coordinates":[1.17139,6.11222],"type":"Point"}
}