{
  "type": "Feature",
  "properties": {
    "gn:admin1_code":"00",
    "gn:asciiname":"Ntafrewaso",
    "gn:country_code":"GH",
    "gn:dem":69,
    "gn:feature_class":"P",
    "gn:feature_code":"PPL",
    "gn:name":"Ntafrewaso",
    "gn:population":0,
    "gn:timezone":"Africa/Accra",
    "iso:country":"GH",
    "name:und_x_variant":[
        "Tafroaso",
        "Ntafrewaso"
    ],
    "wof:name":"Ntafrewaso",
    "wof:placetype":"locality"
},
  "geometry": {"coordinates":[-1.54493,5.55915],"type":"Point"}
}