{
  "type": "Feature",
  "properties": {
    "gn:admin1_code":"00",
    "gn:asciiname":"Samina Kuu",
    "gn:country_code":"GH",
    "gn:dem":272,
    "gn:feature_class":"P",
    "gn:feature_code":"PPL",
    "gn:name":"Samina Kuu",
    "gn:population":0,
    "gn:timezone":"Africa/Accra",
    "iso:country":"GH",
    "name:und_x_variant":[
        "Banna",
        "Banda",
        "Samina Kuu",
        "Bandafie"
    ],
    "wof:name":"Samina Kuu",
    "wof:placetype":"locality"
},
  "geometry": {"coordinates":[-2.35625,8.16572],"type":"Point"}
}