{
  "type": "Feature",
  "properties": {
    "gn:admin1_code":"00",
    "gn:asciiname":"Praso",
    "gn:cc2":"GH",
    "gn:country_code":"GH",
    "gn:dem":145,
    "gn:feature_class":"P",
    "gn:feature_code":"PPL",
    "gn:name":"Praso",
    "gn:population":0,
    "gn:timezone":"Africa/Accra",
    "iso:country":"GH",
    "name:und_x_variant":[
        "Peraso",
        "Praso"
    ],
    "wof:name":"Praso",
    "wof:placetype":"locality"
},
  "geometry": {"coordinates":[-2.26667,6.33333],"type":"Point"}
}