{
  "type": "Feature",
  "properties": {
    "gn:admin1_code":"00",
    "gn:asciiname":"Praso",
    "gn:cc2":"GH",
    "gn:country_code":"GH",
    "gn:dem":145,
    "gn:feature_class":"P",
    "gn:feature_code":"PPL",
    "gn:name":"Praso",
    "gn:population":0,
    "gn:timezone":"Africa/Accra",
    "iso:country":"GH",
    "name:azb_x_preferred":[
        "\u067e\u0631\u0627\u0633\u0648"
    ],
    "name:bel_x_preferred":[
        "\u041f\u0440\u0430\u0437\u0430"
    ],
    "name:cat_x_preferred":[
        "Praso"
    ],
    "name:ceb_x_preferred":[
        "Praso"
    ],
    "name:deu_x_preferred":[
        "Praso"
    ],
    "name:epo_x_preferred":[
        "Praso"
    ],
    "name:eus_x_preferred":[
        "Praso"
    ],
    "name:fas_x_preferred":[
        "\u067e\u0631\u0627\u0633\u0648"
    ],
    "name:fra_x_preferred":[
        "Praso"
    ],
    "name:hun_x_preferred":[
        "Praso"
    ],
    "name:hye_x_preferred":[
        "\u054a\u0580\u0561\u0566\u0578"
    ],
    "name:ind_x_preferred":[
        "Praso"
    ],
    "name:ita_x_preferred":[
        "Praso"
    ],
    "name:jpn_x_preferred":[
        "\u30d7\u30e9\u30fc\u30be"
    ],
    "name:kaz_x_preferred":[
        "\u041f\u0440\u0430\u0437\u043e"
    ],
    "name:lat_x_preferred":[
        "Prasium"
    ],
    "name:lmo_x_preferred":[
        "Pras"
    ],
    "name:msa_x_preferred":[
        "Praso"
    ],
    "name:nap_x_preferred":[
        "Praso"
    ],
    "name:nld_x_preferred":[
        "Praso"
    ],
    "name:pms_x_preferred":[
        "Praso"
    ],
    "name:pol_x_preferred":[
        "Praso"
    ],
    "name:por_x_preferred":[
        "Praso"
    ],
    "name:ron_x_preferred":[
        "Praso"
    ],
    "name:rus_x_preferred":[
        "\u041f\u0440\u0430\u0437\u043e"
    ],
    "name:scn_x_preferred":[
        "Praso"
    ],
    "name:spa_x_preferred":[
        "Praso"
    ],
    "name:srp_x_preferred":[
        "\u041f\u0440\u0430\u0437\u043e"
    ],
    "name:tgl_x_preferred":[
        "Praso"
    ],
    "name:ukr_x_preferred":[
        "\u041f\u0440\u0430\u0437\u043e"
    ],
    "name:und_x_variant":[
        "Peraso"
    ],
    "name:uzb_x_preferred":[
        "Praso"
    ],
    "name:vie_x_preferred":[
        "Praso"
    ],
    "name:vol_x_preferred":[
        "Praso"
    ],
    "name:war_x_preferred":[
        "Praso"
    ],
    "name:zho_x_preferred":[
        "\u666e\u62c9\u7d22"
    ],
    "wof:name":"Praso",
    "wof:placetype":"locality"
},
  "geometry": {"coordinates":[-2.26667,6.33333],"type":"Point"}
}