{
  "type": "Feature",
  "properties": {
    "gn:admin1_code":"00",
    "gn:asciiname":"Akawkawakawkaw",
    "gn:country_code":"GH",
    "gn:dem":146,
    "gn:feature_class":"P",
    "gn:feature_code":"PPL",
    "gn:name":"Akawkawakawkaw",
    "gn:population":0,
    "gn:timezone":"Africa/Accra",
    "iso:country":"GH",
    "name:und_x_variant":[
        "Akoakoko",
        "Akawkawakawkaw"
    ],
    "wof:name":"Akawkawakawkaw",
    "wof:placetype":"locality"
},
  "geometry": {"coordinates":[-0.69727,5.66407],"type":"Point"}
}