{
  "type": "Feature",
  "properties": {
    "gn:admin1_code":"00",
    "gn:asciiname":"Bende",
    "gn:country_code":"GH",
    "gn:dem":296,
    "gn:feature_class":"P",
    "gn:feature_code":"PPL",
    "gn:name":"Bende",
    "gn:population":0,
    "gn:timezone":"Africa/Accra",
    "iso:country":"GH",
    "name:ceb_x_preferred":[
        "Bende"
    ],
    "name:deu_x_preferred":[
        "Bende"
    ],
    "name:fra_x_preferred":[
        "Bende"
    ],
    "name:ita_x_preferred":[
        "Bende"
    ],
    "name:nld_x_preferred":[
        "Bende"
    ],
    "name:swe_x_preferred":[
        "Bende"
    ],
    "name:und_x_variant":[
        "Bandei",
        "Bende"
    ],
    "wof:name":"Bende",
    "wof:placetype":"locality"
},
  "geometry": {"coordinates":[-2.01124,10.64132],"type":"Point"}
}