{
  "type": "Feature",
  "properties": {
    "gn:admin1_code":"00",
    "gn:asciiname":"Jegori",
    "gn:country_code":"GH",
    "gn:dem":290,
    "gn:feature_class":"P",
    "gn:feature_code":"PPL",
    "gn:name":"Jegori",
    "gn:population":0,
    "gn:timezone":"Africa/Accra",
    "iso:country":"GH",
    "name:und_x_variant":[
        "Tema",
        "Jegori"
    ],
    "wof:name":"Jegori",
    "wof:placetype":"locality"
},
  "geometry": {"coordinates":[-0.13799,10.47667],"type":"Point"}
}