{
  "type": "Feature",
  "properties": {
    "gn:admin1_code":"00",
    "gn:asciiname":"Vesekpo",
    "gn:country_code":"GH",
    "gn:dem":12,
    "gn:feature_class":"P",
    "gn:feature_code":"PPL",
    "gn:name":"Vesekpo",
    "gn:population":0,
    "gn:timezone":"Africa/Accra",
    "iso:country":"GH",
    "wof:name":"Vesekpo",
    "wof:placetype":"locality"
},
  "geometry": {"coordinates":[0.23455,6.11375],"type":"Point"}
}