{
  "type": "Feature",
  "properties": {
    "gn:admin1_code":"00",
    "gn:asciiname":"Krobuasi",
    "gn:country_code":"GH",
    "gn:dem":101,
    "gn:feature_class":"P",
    "gn:feature_code":"PPL",
    "gn:name":"Krobuasi",
    "gn:population":0,
    "gn:timezone":"Africa/Accra",
    "iso:country":"GH",
    "name:und_x_variant":[
        "Kroboase",
        "Krobuasi"
    ],
    "wof:name":"Krobuasi",
    "wof:placetype":"locality"
},
  "geometry": {"coordinates":[-1.03281,5.59005],"type":"Point"}
}