{
  "type": "Feature",
  "properties": {
    "gn:admin1_code":"02",
    "gn:asciiname":"Odumasi",
    "gn:country_code":"GH",
    "gn:dem":215,
    "gn:feature_class":"P",
    "gn:feature_code":"PPL",
    "gn:name":"Odumasi",
    "gn:population":0,
    "gn:timezone":"Africa/Accra",
    "iso:country":"GH",
    "name:und_x_variant":[
        "Odumase",
        "Odumasi"
    ],
    "wof:name":"Odumasi",
    "wof:placetype":"locality"
},
  "geometry": {"coordinates":[-1.91585,6.37252],"type":"Point"}
}