{
  "type": "Feature",
  "properties": {
    "gn:admin1_code":"00",
    "gn:asciiname":"Atimpoko",
    "gn:country_code":"GH",
    "gn:dem":45,
    "gn:feature_class":"P",
    "gn:feature_code":"PPL",
    "gn:name":"Atimpoko",
    "gn:population":0,
    "gn:timezone":"Africa/Accra",
    "iso:country":"GH",
    "name:und_x_variant":[
        "Atempoku",
        "Atimpoko"
    ],
    "wof:name":"Atimpoko",
    "wof:placetype":"locality"
},
  "geometry": {"coordinates":[0.09018,6.23383],"type":"Point"}
}