{
  "type": "Feature",
  "properties": {
    "gn:admin1_code":"00",
    "gn:asciiname":"Sodadiem",
    "gn:country_code":"GH",
    "gn:dem":173,
    "gn:feature_class":"P",
    "gn:feature_code":"PPL",
    "gn:name":"Sodadiem",
    "gn:population":0,
    "gn:timezone":"Africa/Accra",
    "iso:country":"GH",
    "wof:name":"Sodadiem",
    "wof:placetype":"locality"
},
  "geometry": {"coordinates":[-1.48333,6.21667],"type":"Point"}
}