{
  "type": "Feature",
  "properties": {
    "gn:admin1_code":"00",
    "gn:asciiname":"Safo",
    "gn:country_code":"GH",
    "gn:dem":325,
    "gn:feature_class":"P",
    "gn:feature_code":"PPL",
    "gn:name":"Safo",
    "gn:population":0,
    "gn:timezone":"Africa/Accra",
    "iso:country":"GH",
    "name:ceb_x_preferred":[
        "Safo"
    ],
    "name:deu_x_preferred":[
        "Safo"
    ],
    "name:ita_x_preferred":[
        "Safo"
    ],
    "name:por_x_preferred":[
        "Safo"
    ],
    "name:swe_x_preferred":[
        "Safo"
    ],
    "wof:name":"Safo",
    "wof:placetype":"locality"
},
  "geometry": {"coordinates":[-1.48257,6.84354],"type":"Point"}
}