{
  "type": "Feature",
  "properties": {
    "gn:admin1_code":"00",
    "gn:asciiname":"Adina",
    "gn:country_code":"GH",
    "gn:dem":77,
    "gn:feature_class":"P",
    "gn:feature_code":"PPL",
    "gn:name":"Adina",
    "gn:population":0,
    "gn:timezone":"Africa/Accra",
    "iso:country":"GH",
    "name:deu_x_preferred":[
        "Adina"
    ],
    "name:glg_x_preferred":[
        "Adina"
    ],
    "name:hun_x_preferred":[
        "Adina"
    ],
    "name:ita_x_preferred":[
        "Adina"
    ],
    "name:pol_x_preferred":[
        "Adina"
    ],
    "name:slk_x_preferred":[
        "Adina"
    ],
    "wof:name":"Adina",
    "wof:placetype":"locality"
},
  "geometry": {"coordinates":[-2.08333,5.65],"type":"Point"}
}