{
  "type": "Feature",
  "properties": {
    "gn:admin1_code":"00",
    "gn:asciiname":"Nabukpeni",
    "gn:country_code":"GH",
    "gn:dem":133,
    "gn:feature_class":"P",
    "gn:feature_code":"PPL",
    "gn:name":"Nabukpeni",
    "gn:population":0,
    "gn:timezone":"Africa/Accra",
    "iso:country":"GH",
    "name:und_x_variant":[
        "Naburinu",
        "Nabukpeni"
    ],
    "wof:name":"Nabukpeni",
    "wof:placetype":"locality"
},
  "geometry": {"coordinates":[0.31888,9.92427],"type":"Point"}
}