{
  "type": "Feature",
  "properties": {
    "gn:admin1_code":"00",
    "gn:asciiname":"Gefia",
    "gn:country_code":"GH",
    "gn:dem":49,
    "gn:feature_class":"P",
    "gn:feature_code":"PPL",
    "gn:name":"Gefia",
    "gn:population":0,
    "gn:timezone":"Africa/Accra",
    "iso:country":"GH",
    "wof:name":"Gefia",
    "wof:placetype":"locality"
},
  "geometry": {"coordinates":[0.85593,6.15458],"type":"Point"}
}