{
  "type": "Feature",
  "properties": {
    "gn:admin1_code":"00",
    "gn:asciiname":"Mpantuasi",
    "gn:country_code":"GH",
    "gn:dem":466,
    "gn:feature_class":"P",
    "gn:feature_code":"PPL",
    "gn:name":"Mpantuasi",
    "gn:population":0,
    "gn:timezone":"Africa/Accra",
    "iso:country":"GH",
    "name:und_x_variant":[
        "Mpantasua",
        "Mpantuasi"
    ],
    "wof:name":"Mpantuasi",
    "wof:placetype":"locality"
},
  "geometry": {"coordinates":[-1.34227,7.04074],"type":"Point"}
}