{
  "type": "Feature",
  "properties": {
    "gn:admin1_code":"04",
    "gn:asciiname":"Nipanka",
    "gn:country_code":"GH",
    "gn:dem":73,
    "gn:feature_class":"P",
    "gn:feature_code":"PPL",
    "gn:name":"Nipanka",
    "gn:population":0,
    "gn:timezone":"Africa/Accra",
    "iso:country":"GH",
    "name:eng_x_preferred":[
        "Nipanka"
    ],
    "wof:name":"Nipanka",
    "wof:placetype":"locality"
},
  "geometry": {"coordinates":[-1.5394,5.42305],"type":"Point"}
}