{
  "type": "Feature",
  "properties": {
    "gn:admin1_code":"02",
    "gn:asciiname":"Kronko Number Two",
    "gn:country_code":"GH",
    "gn:dem":152,
    "gn:feature_class":"P",
    "gn:feature_code":"PPL",
    "gn:name":"Kronko Number Two",
    "gn:population":0,
    "gn:timezone":"Africa/Accra",
    "iso:country":"GH",
    "name:eng_x_preferred":[
        "Kronko Number Two"
    ],
    "name:eng_x_variant":[
        "Kurawnkaw",
        "Kronko Number 2"
    ],
    "wof:name":"Kronko Number Two",
    "wof:placetype":"locality"
},
  "geometry": {"coordinates":[-1.84315,6.09393],"type":"Point"}
}