{
  "type": "Feature",
  "properties": {
    "gn:admin1_code":"00",
    "gn:asciiname":"Atoabasa",
    "gn:country_code":"GH",
    "gn:dem":104,
    "gn:feature_class":"P",
    "gn:feature_code":"PPL",
    "gn:name":"Atoabasa",
    "gn:population":0,
    "gn:timezone":"Africa/Accra",
    "iso:country":"GH",
    "wof:name":"Atoabasa",
    "wof:placetype":"locality"
},
  "geometry": {"coordinates":[-1.47253,5.76716],"type":"Point"}
}