{
  "type": "Feature",
  "properties": {
    "gn:admin1_code":"09",
    "gn:asciiname":"Yaofiankukrom",
    "gn:country_code":"GH",
    "gn:dem":63,
    "gn:feature_class":"P",
    "gn:feature_code":"PPL",
    "gn:name":"Yaofiankukrom",
    "gn:population":0,
    "gn:timezone":"Africa/Accra",
    "iso:country":"GH",
    "name:eng_x_preferred":[
        "Yaofiankukrom"
    ],
    "wof:name":"Yaofiankukrom",
    "wof:placetype":"locality"
},
  "geometry": {"coordinates":[-1.58969,5.36006],"type":"Point"}
}