{
  "type": "Feature",
  "properties": {
    "gn:admin1_code":"00",
    "gn:asciiname":"Adahem",
    "gn:country_code":"GH",
    "gn:dem":180,
    "gn:feature_class":"P",
    "gn:feature_code":"PPL",
    "gn:name":"Adahem",
    "gn:population":0,
    "gn:timezone":"Africa/Accra",
    "iso:country":"GH",
    "wof:name":"Adahem",
    "wof:placetype":"locality"
},
  "geometry": {"coordinates":[-1.24358,5.73495],"type":"Point"}
}