{
  "type": "Feature",
  "properties": {
    "gn:admin1_code":"00",
    "gn:asciiname":"Kpong",
    "gn:country_code":"GH",
    "gn:dem":17,
    "gn:feature_class":"P",
    "gn:feature_code":"PPL",
    "gn:name":"Kpong",
    "gn:population":0,
    "gn:timezone":"Africa/Accra",
    "iso:country":"GH",
    "wof:name":"Kpong",
    "wof:placetype":"locality"
},
  "geometry": {"coordinates":[0.06261,6.15861],"type":"Point"}
}