{
  "type": "Feature",
  "properties": {
    "gn:admin1_code":"00",
    "gn:asciiname":"Nsawam",
    "gn:country_code":"GH",
    "gn:dem":70,
    "gn:feature_class":"P",
    "gn:feature_code":"PPL",
    "gn:name":"Nsawam",
    "gn:population":0,
    "gn:timezone":"Africa/Accra",
    "iso:country":"GH",
    "name:ceb_x_preferred":[
        "Nsawam"
    ],
    "name:glg_x_preferred":[
        "Nsawam"
    ],
    "name:nld_x_preferred":[
        "Nsawam"
    ],
    "name:pol_x_preferred":[
        "Nsawam"
    ],
    "name:spa_x_preferred":[
        "Nsawam"
    ],
    "name:swe_x_preferred":[
        "Nsawam"
    ],
    "name:twi_x_preferred":[
        "Nsawam"
    ],
    "name:urd_x_preferred":[
        "\u0646\u0633\u0627\u0648\u0627\u0645"
    ],
    "name:zho_x_preferred":[
        "\u6069\u85a9\u74e6\u59c6"
    ],
    "wof:name":"Nsawam",
    "wof:placetype":"locality"
},
  "geometry": {"coordinates":[-0.92485,5.59828],"type":"Point"}
}