{
  "type": "Feature",
  "properties": {
    "gn:admin1_code":"00",
    "gn:asciiname":"Atibie",
    "gn:country_code":"GH",
    "gn:dem":473,
    "gn:feature_class":"P",
    "gn:feature_code":"PPL",
    "gn:name":"Atibie",
    "gn:population":0,
    "gn:timezone":"Africa/Accra",
    "iso:country":"GH",
    "wof:name":"Atibie",
    "wof:placetype":"locality"
},
  "geometry": {"coordinates":[-0.73565,6.58795],"type":"Point"}
}