{
  "type": "Feature",
  "properties": {
    "gn:admin1_code":"09",
    "gn:asciiname":"Dompoase",
    "gn:country_code":"GH",
    "gn:dem":157,
    "gn:feature_class":"P",
    "gn:feature_code":"PPL",
    "gn:name":"Dompoase",
    "gn:population":0,
    "gn:timezone":"Africa/Accra",
    "iso:country":"GH",
    "name:eng_x_preferred":[
        "Dompoasi"
    ],
    "name:und_x_variant":[
        "Dompasi"
    ],
    "wof:name":"Dompoase",
    "wof:placetype":"locality"
},
  "geometry": {"coordinates":[-2.0162,5.99624],"type":"Point"}
}