{
  "type": "Feature",
  "properties": {
    "gn:admin1_code":"00",
    "gn:asciiname":"Bango",
    "gn:country_code":"GH",
    "gn:dem":209,
    "gn:feature_class":"P",
    "gn:feature_code":"PPL",
    "gn:name":"Bango",
    "gn:population":0,
    "gn:timezone":"Africa/Accra",
    "iso:country":"GH",
    "name:ceb_x_preferred":[
        "Bango"
    ],
    "name:deu_x_preferred":[
        "Bango"
    ],
    "name:swe_x_preferred":[
        "Bango"
    ],
    "name:und_x_variant":[
        "Gbong Beda",
        "Bongo"
    ],
    "wof:name":"Bango",
    "wof:placetype":"locality"
},
  "geometry": {"coordinates":[-0.43386,10.72729],"type":"Point"}
}