{
  "type": "Feature",
  "properties": {
    "gn:admin1_code":"01",
    "gn:asciiname":"Kolokowhe",
    "gn:country_code":"GH",
    "gn:dem":36,
    "gn:feature_class":"P",
    "gn:feature_code":"PPL",
    "gn:name":"Kolokowhe",
    "gn:population":0,
    "gn:timezone":"Africa/Accra",
    "iso:country":"GH",
    "name:eng_x_preferred":[
        "Kolokowhe"
    ],
    "name:eng_x_variant":[
        "Krokohwe"
    ],
    "wof:name":"Kolokowhe",
    "wof:placetype":"locality"
},
  "geometry": {"coordinates":[-0.39075,5.67793],"type":"Point"}
}