{
  "type": "Feature",
  "properties": {
    "gn:admin1_code":"00",
    "gn:asciiname":"Jahadzi",
    "gn:country_code":"GH",
    "gn:dem":19,
    "gn:feature_class":"P",
    "gn:feature_code":"PPL",
    "gn:name":"Jahadzi",
    "gn:population":0,
    "gn:timezone":"Africa/Accra",
    "iso:country":"GH",
    "name:und_x_variant":[
        "Gyahadzi",
        "Jahadzi"
    ],
    "wof:name":"Jahadzi",
    "wof:placetype":"locality"
},
  "geometry": {"coordinates":[-0.58786,5.38476],"type":"Point"}
}