{
  "type": "Feature",
  "properties": {
    "gn:admin1_code":"00",
    "gn:asciiname":"Asantikrom",
    "gn:country_code":"GH",
    "gn:dem":39,
    "gn:feature_class":"P",
    "gn:feature_code":"PPL",
    "gn:name":"Asantikrom",
    "gn:population":0,
    "gn:timezone":"Africa/Accra",
    "iso:country":"GH",
    "wof:name":"Asantikrom",
    "wof:placetype":"locality"
},
  "geometry": {"coordinates":[-2.21568,5.34362],"type":"Point"}
}