{
  "type": "Feature",
  "properties": {
    "gn:admin1_code":"00",
    "gn:asciiname":"Chandayili",
    "gn:country_code":"GH",
    "gn:dem":194,
    "gn:feature_class":"P",
    "gn:feature_code":"PPL",
    "gn:name":"Chandayili",
    "gn:population":0,
    "gn:timezone":"Africa/Accra",
    "iso:country":"GH",
    "name:und_x_variant":[
        "Chandayib",
        "Chantin-da-yib",
        "Chandayili"
    ],
    "wof:name":"Chandayili",
    "wof:placetype":"locality"
},
  "geometry": {"coordinates":[-0.42313,9.22085],"type":"Point"}
}