{
  "type": "Feature",
  "properties": {
    "gn:admin1_code":"09",
    "gn:asciiname":"Diamos",
    "gn:country_code":"GH",
    "gn:dem":6,
    "gn:feature_class":"P",
    "gn:feature_code":"PPL",
    "gn:name":"Diamos",
    "gn:population":0,
    "gn:timezone":"Africa/Accra",
    "iso:country":"GH",
    "name:eng_x_preferred":[
        "Diamos"
    ],
    "wof:name":"Diamos",
    "wof:placetype":"locality"
},
  "geometry": {"coordinates":[-2.98803,5.07885],"type":"Point"}
}