{
  "type": "Feature",
  "properties": {
    "gn:admin1_code":"00",
    "gn:asciiname":"Omen Bobikuma",
    "gn:country_code":"GH",
    "gn:dem":96,
    "gn:feature_class":"P",
    "gn:feature_code":"PPL",
    "gn:name":"Omen Bobikuma",
    "gn:population":0,
    "gn:timezone":"Africa/Accra",
    "iso:country":"GH",
    "wof:name":"Omen Bobikuma",
    "wof:placetype":"locality"
},
  "geometry": {"coordinates":[-0.8485,5.55057],"type":"Point"}
}