{
  "type": "Feature",
  "properties": {
    "gn:admin1_code":"00",
    "gn:asciiname":"Katanga",
    "gn:country_code":"GH",
    "gn:dem":97,
    "gn:feature_class":"P",
    "gn:feature_code":"PPL",
    "gn:name":"Katanga",
    "gn:population":0,
    "gn:timezone":"Africa/Accra",
    "iso:country":"GH",
    "name:und_x_variant":[
        "Katange",
        "Katangal"
    ],
    "wof:name":"Katanga",
    "wof:placetype":"locality"
},
  "geometry": {"coordinates":[-1.22839,9.26749],"type":"Point"}
}