{
  "type": "Feature",
  "properties": {
    "gn:admin1_code":"00",
    "gn:asciiname":"Katanga",
    "gn:country_code":"GH",
    "gn:dem":97,
    "gn:feature_class":"P",
    "gn:feature_code":"PPL",
    "gn:name":"Katanga",
    "gn:population":0,
    "gn:timezone":"Africa/Accra",
    "iso:country":"GH",
    "name:ceb_x_preferred":[
        "Katanga"
    ],
    "name:ces_x_preferred":[
        "Katanga"
    ],
    "name:deu_x_preferred":[
        "Katanga"
    ],
    "name:est_x_preferred":[
        "Katanga"
    ],
    "name:fra_x_preferred":[
        "Katanga"
    ],
    "name:heb_x_preferred":[
        "\u05e7\u05d8\u05e0\u05d2\u05d4"
    ],
    "name:ina_x_preferred":[
        "Katanga"
    ],
    "name:ind_x_preferred":[
        "Katanga"
    ],
    "name:ita_x_preferred":[
        "Katanga"
    ],
    "name:nld_x_preferred":[
        "Katanga"
    ],
    "name:nor_x_preferred":[
        "Katanga"
    ],
    "name:pol_x_preferred":[
        "Katanga"
    ],
    "name:por_x_preferred":[
        "Katanga"
    ],
    "name:rus_x_preferred":[
        "\u041a\u0430\u0442\u0430\u043d\u0433\u0430"
    ],
    "name:slk_x_preferred":[
        "Katanga"
    ],
    "name:spa_x_preferred":[
        "Katanga"
    ],
    "name:swe_x_preferred":[
        "Katanga"
    ],
    "name:und_x_variant":[
        "Katange",
        "Katangal"
    ],
    "wof:name":"Katanga",
    "wof:placetype":"locality"
},
  "geometry": {"coordinates":[-1.22839,9.26749],"type":"Point"}
}