{
  "type": "Feature",
  "properties": {
    "gn:admin1_code":"00",
    "gn:asciiname":"Dejanso",
    "gn:cc2":"GH",
    "gn:country_code":"GH",
    "gn:dem":306,
    "gn:feature_class":"P",
    "gn:feature_code":"PPL",
    "gn:name":"Dejanso",
    "gn:population":0,
    "gn:timezone":"Africa/Accra",
    "iso:country":"GH",
    "name:und_x_variant":[
        "Dagyanso",
        "Dejanso"
    ],
    "wof:name":"Dejanso",
    "wof:placetype":"locality"
},
  "geometry": {"coordinates":[-1.46667,6.46667],"type":"Point"}
}