{
  "type": "Feature",
  "properties": {
    "gn:admin1_code":"00",
    "gn:asciiname":"Dodi Papase",
    "gn:country_code":"GH",
    "gn:dem":158,
    "gn:feature_class":"P",
    "gn:feature_code":"PPL",
    "gn:name":"Dodi Papase",
    "gn:population":0,
    "gn:timezone":"Africa/Accra",
    "iso:country":"GH",
    "name:und_x_variant":[
        "Papase",
        "Dodi Papase"
    ],
    "wof:name":"Dodi Papase",
    "wof:placetype":"locality"
},
  "geometry": {"coordinates":[0.50809,7.72545],"type":"Point"}
}