{
  "type": "Feature",
  "properties": {
    "gn:admin1_code":"00",
    "gn:asciiname":"Soandi",
    "gn:country_code":"GH",
    "gn:dem":183,
    "gn:feature_class":"P",
    "gn:feature_code":"PPL",
    "gn:name":"Soandi",
    "gn:population":0,
    "gn:timezone":"Africa/Accra",
    "iso:country":"GH",
    "name:und_x_variant":[
        "Saundi",
        "Soandi"
    ],
    "wof:name":"Soandi",
    "wof:placetype":"locality"
},
  "geometry": {"coordinates":[-0.34479,10.70149],"type":"Point"}
}