{
  "type": "Feature",
  "properties": {
    "gn:admin1_code":"00",
    "gn:asciiname":"Agawtaw",
    "gn:country_code":"GH",
    "gn:dem":23,
    "gn:feature_class":"P",
    "gn:feature_code":"PPL",
    "gn:name":"Agawtaw",
    "gn:population":0,
    "gn:timezone":"Africa/Accra",
    "iso:country":"GH",
    "name:und_x_variant":[
        "Agorto",
        "Agawtaw"
    ],
    "wof:name":"Agawtaw",
    "wof:placetype":"locality"
},
  "geometry": {"coordinates":[0.23168,5.95011],"type":"Point"}
}