{
  "type": "Feature",
  "properties": {
    "gn:admin1_code":"11",
    "gn:asciiname":"Kapachuhu",
    "gn:country_code":"GH",
    "gn:dem":304,
    "gn:feature_class":"P",
    "gn:feature_code":"PPL",
    "gn:name":"Kapachuhu",
    "gn:population":0,
    "gn:timezone":"Africa/Accra",
    "iso:country":"GH",
    "name:eng_x_preferred":[
        "Moiri"
    ],
    "name:und_x_variant":[
        "Kpachuhu",
        "Kapachuhu"
    ],
    "wof:name":"Kapachuhu",
    "wof:placetype":"locality"
},
  "geometry": {"coordinates":[-2.6905,10.4989],"type":"Point"}
}