{
  "type": "Feature",
  "properties": {
    "gn:admin1_code":"04",
    "gn:asciiname":"Ayamfor",
    "gn:country_code":"GH",
    "gn:dem":164,
    "gn:feature_class":"P",
    "gn:feature_code":"PPL",
    "gn:name":"Ayamfor",
    "gn:population":0,
    "gn:timezone":"Africa/Accra",
    "iso:country":"GH",
    "name:eng_x_preferred":[
        "Ayamfor"
    ],
    "name:und_x_variant":[
        "Ayenfuri",
        "Ayanfure",
        "Ayanfuri"
    ],
    "wof:name":"Ayamfor",
    "wof:placetype":"locality"
},
  "geometry": {"coordinates":[-1.89498,5.96275],"type":"Point"}
}