{
  "type": "Feature",
  "properties": {
    "gn:admin1_code":"02",
    "gn:asciiname":"Kwame Kyemkurom",
    "gn:country_code":"GH",
    "gn:dem":339,
    "gn:feature_class":"P",
    "gn:feature_code":"PPL",
    "gn:name":"Kwame Kyemkurom",
    "gn:population":0,
    "gn:timezone":"Africa/Accra",
    "iso:country":"GH",
    "name:eng_x_preferred":[
        "Kwame Kyemkurom"
    ],
    "name:und_x_variant":[
        "Kwamekyekurom",
        "Kwamechekrom"
    ],
    "wof:name":"Kwame Kyemkurom",
    "wof:placetype":"locality"
},
  "geometry": {"coordinates":[-1.94108,6.98664],"type":"Point"}
}