{
  "type": "Feature",
  "properties": {
    "gn:admin1_code":"02",
    "gn:asciiname":"Adukuro",
    "gn:country_code":"GH",
    "gn:dem":287,
    "gn:feature_class":"P",
    "gn:feature_code":"PPL",
    "gn:name":"Adukuro",
    "gn:population":0,
    "gn:timezone":"Africa/Accra",
    "iso:country":"GH",
    "name:und_x_variant":[
        "Adukra",
        "Odukro"
    ],
    "wof:name":"Adukuro",
    "wof:placetype":"locality"
},
  "geometry": {"coordinates":[-1.67134,6.95051],"type":"Point"}
}