{
  "type": "Feature",
  "properties": {
    "gn:admin1_code":"00",
    "gn:asciiname":"Agbogbla",
    "gn:country_code":"GH",
    "gn:dem":3,
    "gn:feature_class":"P",
    "gn:feature_code":"PPL",
    "gn:name":"Agbogbla",
    "gn:population":0,
    "gn:timezone":"Africa/Accra",
    "iso:country":"GH",
    "name:und_x_variant":[
        "Agoblan",
        "Agbogbla"
    ],
    "wof:name":"Agbogbla",
    "wof:placetype":"locality"
},
  "geometry": {"coordinates":[0.69745,5.98306],"type":"Point"}
}