{
  "type": "Feature",
  "properties": {
    "gn:admin1_code":"03",
    "gn:asciiname":"Asoee",
    "gn:country_code":"GH",
    "gn:dem":380,
    "gn:feature_class":"P",
    "gn:feature_code":"PPL",
    "gn:name":"Asoee",
    "gn:population":0,
    "gn:timezone":"Africa/Accra",
    "iso:country":"GH",
    "name:eng_x_preferred":[
        "Asoee"
    ],
    "name:und_x_variant":[
        "Asueyi",
        "Asuaye"
    ],
    "wof:name":"Asoee",
    "wof:placetype":"locality"
},
  "geometry": {"coordinates":[-1.98028,7.63556],"type":"Point"}
}