{
  "type": "Feature",
  "properties": {
    "gn:admin1_code":"00",
    "gn:asciiname":"Piri",
    "gn:country_code":"GH",
    "gn:dem":309,
    "gn:feature_class":"P",
    "gn:feature_code":"PPL",
    "gn:name":"Piri",
    "gn:population":0,
    "gn:timezone":"Africa/Accra",
    "iso:country":"GH",
    "name:deu_x_preferred":[
        "Piri"
    ],
    "name:fin_x_preferred":[
        "Piri"
    ],
    "name:fra_x_preferred":[
        "Piri"
    ],
    "name:ind_x_preferred":[
        "Piri"
    ],
    "name:nld_x_preferred":[
        "Piri"
    ],
    "name:spa_x_preferred":[
        "Piri"
    ],
    "name:und_x_variant":[
        "Ping",
        "Piri"
    ],
    "wof:name":"Piri",
    "wof:placetype":"locality"
},
  "geometry": {"coordinates":[-2.49382,10.62921],"type":"Point"}
}