{
  "type": "Feature",
  "properties": {
    "gn:admin1_code":"00",
    "gn:asciiname":"Adonokofe",
    "gn:country_code":"GH",
    "gn:dem":43,
    "gn:feature_class":"P",
    "gn:feature_code":"PPL",
    "gn:name":"Adonokofe",
    "gn:population":0,
    "gn:timezone":"Africa/Accra",
    "iso:country":"GH",
    "wof:name":"Adonokofe",
    "wof:placetype":"locality"
},
  "geometry": {"coordinates":[0.66692,6.28746],"type":"Point"}
}