{
  "type": "Feature",
  "properties": {
    "gn:admin1_code":"00",
    "gn:asciiname":"Akamukope",
    "gn:country_code":"GH",
    "gn:dem":10,
    "gn:feature_class":"P",
    "gn:feature_code":"PPL",
    "gn:name":"Akamukope",
    "gn:population":0,
    "gn:timezone":"Africa/Accra",
    "iso:country":"GH",
    "name:und_x_variant":[
        "Akamkorpe",
        "Akamukope"
    ],
    "wof:name":"Akamukope",
    "wof:placetype":"locality"
},
  "geometry": {"coordinates":[0.5455,5.94559],"type":"Point"}
}