{
  "type": "Feature",
  "properties": {
    "gn:admin1_code":"09",
    "gn:asciiname":"Achim",
    "gn:country_code":"GH",
    "gn:dem":65,
    "gn:feature_class":"P",
    "gn:feature_code":"PPL",
    "gn:name":"Achim",
    "gn:population":0,
    "gn:timezone":"Africa/Accra",
    "iso:country":"GH",
    "name:und_x_variant":[
        "Achimoto",
        "Akyem",
        "Achim"
    ],
    "wof:name":"Achim",
    "wof:placetype":"locality"
},
  "geometry": {"coordinates":[-1.97966,5.25141],"type":"Point"}
}