{
  "type": "Feature",
  "properties": {
    "gn:admin1_code":"04",
    "gn:asciiname":"Amosua",
    "gn:country_code":"GH",
    "gn:dem":62,
    "gn:feature_class":"P",
    "gn:feature_code":"PPL",
    "gn:name":"Amosua",
    "gn:population":0,
    "gn:timezone":"Africa/Accra",
    "iso:country":"GH",
    "name:eng_x_preferred":[
        "Amosua"
    ],
    "wof:name":"Amosua",
    "wof:placetype":"locality"
},
  "geometry": {"coordinates":[-1.59067,5.44956],"type":"Point"}
}