{
  "type": "Feature",
  "properties": {
    "gn:admin1_code":"02",
    "gn:asciiname":"Kwanchiabo",
    "gn:country_code":"GH",
    "gn:dem":219,
    "gn:feature_class":"P",
    "gn:feature_code":"PPL",
    "gn:name":"Kwanchiabo",
    "gn:population":0,
    "gn:timezone":"Africa/Accra",
    "iso:country":"GH",
    "name:und_x_variant":[
        "Kwonchiabo",
        "Kwankyeabo",
        "Kwanchiabo"
    ],
    "wof:name":"Kwanchiabo",
    "wof:placetype":"locality"
},
  "geometry": {"coordinates":[-1.94013,6.66687],"type":"Point"}
}