{
  "type": "Feature",
  "properties": {
    "gn:admin1_code":"00",
    "gn:asciiname":"Anka",
    "gn:country_code":"GH",
    "gn:dem":104,
    "gn:feature_class":"P",
    "gn:feature_code":"PPL",
    "gn:name":"Anka",
    "gn:population":0,
    "gn:timezone":"Africa/Accra",
    "iso:country":"GH",
    "name:ben_x_preferred":[
        "\u0985\u0999\u09cd\u0995"
    ],
    "name:ceb_x_preferred":[
        "Anka"
    ],
    "name:deu_x_preferred":[
        "Anka"
    ],
    "name:fra_x_preferred":[
        "Anka"
    ],
    "name:jpn_x_preferred":[
        "\u30a2\u30f3\u30ab"
    ],
    "name:nld_x_preferred":[
        "Anka"
    ],
    "name:swe_x_preferred":[
        "Anka"
    ],
    "name:tur_x_preferred":[
        "Simurg"
    ],
    "wof:name":"Anka",
    "wof:placetype":"locality"
},
  "geometry": {"coordinates":[-1.43572,5.7298],"type":"Point"}
}