{
  "type": "Feature",
  "properties": {
    "gn:admin1_code":"10",
    "gn:asciiname":"Sambruno",
    "gn:country_code":"GH",
    "gn:dem":188,
    "gn:feature_class":"P",
    "gn:feature_code":"PPL",
    "gn:name":"Sambruno",
    "gn:population":0,
    "gn:timezone":"Africa/Accra",
    "iso:country":"GH",
    "name:und_x_variant":[
        "Zorebisi",
        "Sambrungo",
        "Sumbrungo Azorebisi",
        "Sambruno"
    ],
    "wof:name":"Sambruno",
    "wof:placetype":"locality"
},
  "geometry": {"coordinates":[-0.91237,10.83296],"type":"Point"}
}