{
  "type": "Feature",
  "properties": {
    "gn:admin1_code":"00",
    "gn:asciiname":"Takyiman",
    "gn:country_code":"GH",
    "gn:dem":219,
    "gn:feature_class":"P",
    "gn:feature_code":"PPL",
    "gn:name":"Takyiman",
    "gn:population":0,
    "gn:timezone":"Africa/Accra",
    "iso:country":"GH",
    "name:und_x_variant":[
        "Techimang",
        "Takyiman"
    ],
    "wof:name":"Takyiman",
    "wof:placetype":"locality"
},
  "geometry": {"coordinates":[-0.66592,6.16316],"type":"Point"}
}