{
  "type": "Feature",
  "properties": {
    "gn:admin1_code":"09",
    "gn:asciiname":"Kojina",
    "gn:country_code":"GH",
    "gn:dem":150,
    "gn:feature_class":"P",
    "gn:feature_code":"PPL",
    "gn:name":"Kojina",
    "gn:population":0,
    "gn:timezone":"Africa/Accra",
    "iso:country":"GH",
    "name:und_x_variant":[
        "Subrinkwanta",
        "Subrinkwata",
        "Kojina"
    ],
    "wof:name":"Kojina",
    "wof:placetype":"locality"
},
  "geometry": {"coordinates":[-2.24016,6.30562],"type":"Point"}
}