{
  "type": "Feature",
  "properties": {
    "gn:admin1_code":"00",
    "gn:asciiname":"Asamang-Krofuso",
    "gn:country_code":"GH",
    "gn:dem":290,
    "gn:feature_class":"P",
    "gn:feature_code":"PPL",
    "gn:name":"Asamang-Krofuso",
    "gn:population":0,
    "gn:timezone":"Africa/Accra",
    "iso:country":"GH",
    "name:und_x_variant":[
        "Asaman Krofuso",
        "Asamang-Krotuso",
        "Asamang-Krofuso"
    ],
    "wof:name":"Asamang-Krofuso",
    "wof:placetype":"locality"
},
  "geometry": {"coordinates":[-1.49676,6.73772],"type":"Point"}
}