{
  "type": "Feature",
  "properties": {
    "gn:admin1_code":"00",
    "gn:asciiname":"Anyinibuni",
    "gn:cc2":"GH",
    "gn:country_code":"GH",
    "gn:dem":17,
    "gn:feature_class":"P",
    "gn:feature_code":"PPL",
    "gn:name":"Anyinibuni",
    "gn:population":0,
    "gn:timezone":"Africa/Accra",
    "iso:country":"GH",
    "name:und_x_variant":[
        "Anyinibani",
        "Anyinibuni"
    ],
    "wof:name":"Anyinibuni",
    "wof:placetype":"locality"
},
  "geometry": {"coordinates":[-2.21667,5.03333],"type":"Point"}
}