{
  "type": "Feature",
  "properties": {
    "gn:admin1_code":"06",
    "gn:asciiname":"Nabori",
    "gn:country_code":"GH",
    "gn:dem":235,
    "gn:feature_class":"P",
    "gn:feature_code":"PPL",
    "gn:name":"Nabori",
    "gn:population":0,
    "gn:timezone":"Africa/Accra",
    "iso:country":"GH",
    "name:eng_x_preferred":[
        "Nabori"
    ],
    "wof:name":"Nabori",
    "wof:placetype":"locality"
},
  "geometry": {"coordinates":[-1.8521,9.15306],"type":"Point"}
}