{
  "type": "Feature",
  "properties": {
    "gn:admin1_code":"01",
    "gn:asciiname":"Bebianiha",
    "gn:country_code":"GH",
    "gn:dem":97,
    "gn:feature_class":"P",
    "gn:feature_code":"PPL",
    "gn:name":"Bebianiha",
    "gn:population":0,
    "gn:timezone":"Africa/Accra",
    "iso:country":"GH",
    "name:und_x_variant":[
        "Bebianeha",
        "Bebianiha"
    ],
    "wof:name":"Bebianiha",
    "wof:placetype":"locality"
},
  "geometry": {"coordinates":[-0.46278,5.72696],"type":"Point"}
}