{
  "type": "Feature",
  "properties": {
    "gn:admin1_code":"00",
    "gn:asciiname":"Enyanmem",
    "gn:country_code":"GH",
    "gn:dem":23,
    "gn:feature_class":"P",
    "gn:feature_code":"PPL",
    "gn:name":"Enyanmem",
    "gn:population":0,
    "gn:timezone":"Africa/Accra",
    "iso:country":"GH",
    "name:und_x_variant":[
        "Enyanmanmu",
        "Enyanmem"
    ],
    "wof:name":"Enyanmem",
    "wof:placetype":"locality"
},
  "geometry": {"coordinates":[-1.01868,5.31639],"type":"Point"}
}