{
  "type": "Feature",
  "properties": {
    "gn:admin1_code":"00",
    "gn:asciiname":"Gonre",
    "gn:country_code":"GH",
    "gn:dem":214,
    "gn:feature_class":"P",
    "gn:feature_code":"PPL",
    "gn:name":"Gonre",
    "gn:population":0,
    "gn:timezone":"Africa/Accra",
    "iso:country":"GH",
    "wof:name":"Gonre",
    "wof:placetype":"locality"
},
  "geometry": {"coordinates":[-0.23297,11.00017],"type":"Point"}
}