{
  "type": "Feature",
  "properties": {
    "gn:admin1_code":"00",
    "gn:asciiname":"Konko",
    "gn:country_code":"GH",
    "gn:dem":179,
    "gn:feature_class":"P",
    "gn:feature_code":"PPL",
    "gn:name":"Konko",
    "gn:population":0,
    "gn:timezone":"Africa/Accra",
    "iso:country":"GH",
    "name:und_x_variant":[
        "Konka",
        "Konko"
    ],
    "wof:name":"Konko",
    "wof:placetype":"locality"
},
  "geometry": {"coordinates":[-0.19907,6.02552],"type":"Point"}
}