{
  "type": "Feature",
  "properties": {
    "gn:admin1_code":"02",
    "gn:asciiname":"Samanhia",
    "gn:country_code":"GH",
    "gn:dem":237,
    "gn:feature_class":"P",
    "gn:feature_code":"PPL",
    "gn:name":"Samanhia",
    "gn:population":0,
    "gn:timezone":"Africa/Accra",
    "iso:country":"GH",
    "name:und_x_variant":[
        "Samahia",
        "Samanyiakurom",
        "Samanhia"
    ],
    "wof:name":"Samanhia",
    "wof:placetype":"locality"
},
  "geometry": {"coordinates":[-1.70415,6.53793],"type":"Point"}
}