{
  "type": "Feature",
  "properties": {
    "gn:admin1_code":"00",
    "gn:asciiname":"Chwerebuana",
    "gn:cc2":"GH",
    "gn:country_code":"GH",
    "gn:dem":75,
    "gn:feature_class":"P",
    "gn:feature_code":"PPL",
    "gn:name":"Chwerebuana",
    "gn:population":0,
    "gn:timezone":"Africa/Accra",
    "iso:country":"GH",
    "name:und_x_variant":[
        "Twenebianyo",
        "Chwerebuana"
    ],
    "wof:name":"Chwerebuana",
    "wof:placetype":"locality"
},
  "geometry": {"coordinates":[-0.11667,6.51667],"type":"Point"}
}