{
  "type": "Feature",
  "properties": {
    "gn:admin1_code":"02",
    "gn:asciiname":"Ofinso Ahenkro",
    "gn:country_code":"GH",
    "gn:dem":268,
    "gn:feature_class":"P",
    "gn:feature_code":"PPL",
    "gn:name":"Ofinso Ahenkro",
    "gn:population":0,
    "gn:timezone":"Africa/Accra",
    "iso:country":"GH",
    "name:eng_x_preferred":[
        "Ofinso Ahenkro"
    ],
    "name:und_x_variant":[
        "Ofinso Ahinkro",
        "Ahenkro",
        "Ahinkro"
    ],
    "wof:name":"Ofinso Ahenkro",
    "wof:placetype":"locality"
},
  "geometry": {"coordinates":[-1.62665,6.8755],"type":"Point"}
}