{
  "type": "Feature",
  "properties": {
    "gn:admin1_code":"00",
    "gn:asciiname":"Mopti",
    "gn:country_code":"GH",
    "gn:dem":123,
    "gn:feature_class":"P",
    "gn:feature_code":"PPL",
    "gn:name":"Mopti",
    "gn:population":0,
    "gn:timezone":"Africa/Accra",
    "iso:country":"GH",
    "name:ara_x_preferred":[
        "\u0645\u0648\u0628\u062a\u064a"
    ],
    "name:azb_x_preferred":[
        "\u0645\u0648\u067e\u062a\u06cc"
    ],
    "name:bam_x_preferred":[
        "Mopti"
    ],
    "name:cat_x_preferred":[
        "Mopti"
    ],
    "name:ceb_x_preferred":[
        "Mopti"
    ],
    "name:dan_x_preferred":[
        "Mopti"
    ],
    "name:deu_x_preferred":[
        "Mopti"
    ],
    "name:ell_x_preferred":[
        "\u039c\u03bf\u03c0\u03c4\u03af"
    ],
    "name:epo_x_preferred":[
        "Mopti"
    ],
    "name:est_x_preferred":[
        "Mopti"
    ],
    "name:eus_x_preferred":[
        "Mopti"
    ],
    "name:fas_x_preferred":[
        "\u0645\u0648\u067e\u062a\u06cc"
    ],
    "name:fin_x_preferred":[
        "Mopti"
    ],
    "name:fra_x_preferred":[
        "Mopti"
    ],
    "name:frr_x_preferred":[
        "Mopti"
    ],
    "name:heb_x_preferred":[
        "\u05de\u05d5\u05e4\u05d8\u05d9"
    ],
    "name:hrv_x_preferred":[
        "Mopti"
    ],
    "name:hun_x_preferred":[
        "Mopti"
    ],
    "name:ind_x_preferred":[
        "Mopti"
    ],
    "name:ita_x_preferred":[
        "Mopti"
    ],
    "name:jpn_x_preferred":[
        "\u30e2\u30d7\u30c6\u30a3"
    ],
    "name:kat_x_preferred":[
        "\u10db\u10dd\u10de\u10e2\u10d8"
    ],
    "name:lat_x_preferred":[
        "Mopti"
    ],
    "name:lit_x_preferred":[
        "Moptis"
    ],
    "name:nld_x_preferred":[
        "Mopti"
    ],
    "name:nno_x_preferred":[
        "Mopti"
    ],
    "name:nor_x_preferred":[
        "Mopti"
    ],
    "name:pol_x_preferred":[
        "Mopti"
    ],
    "name:por_x_preferred":[
        "Mopti"
    ],
    "name:ron_x_preferred":[
        "Mopti"
    ],
    "name:rus_x_preferred":[
        "\u041c\u043e\u043f\u0442\u0438"
    ],
    "name:spa_x_preferred":[
        "Mopti"
    ],
    "name:swe_x_preferred":[
        "Mopti"
    ],
    "name:tur_x_preferred":[
        "Mopti"
    ],
    "name:ukr_x_preferred":[
        "\u041c\u043e\u043f\u0442\u0456"
    ],
    "name:und_x_variant":[
        "Mpoti",
        "Mopti"
    ],
    "name:urd_x_preferred":[
        "\u0645\u0648\u067e\u0679\u06cc"
    ],
    "name:zho_x_preferred":[
        "\u83ab\u666e\u63d0"
    ],
    "wof:name":"Mopti",
    "wof:placetype":"locality"
},
  "geometry": {"coordinates":[-0.13751,6.82283],"type":"Point"}
}