{
  "type": "Feature",
  "properties": {
    "gn:admin1_code":"02",
    "gn:asciiname":"Patakro",
    "gn:country_code":"GH",
    "gn:dem":230,
    "gn:feature_class":"P",
    "gn:feature_code":"PPL",
    "gn:name":"Patakro",
    "gn:population":0,
    "gn:timezone":"Africa/Accra",
    "iso:country":"GH",
    "name:eng_x_preferred":[
        "Patakro"
    ],
    "wof:name":"Patakro",
    "wof:placetype":"locality"
},
  "geometry": {"coordinates":[-1.64478,6.27949],"type":"Point"}
}