{
  "type": "Feature",
  "properties": {
    "gn:admin1_code":"00",
    "gn:asciiname":"Mayara",
    "gn:country_code":"GH",
    "gn:dem":326,
    "gn:feature_class":"P",
    "gn:feature_code":"PPL",
    "gn:name":"Mayara",
    "gn:population":0,
    "gn:timezone":"Africa/Accra",
    "iso:country":"GH",
    "name:und_x_variant":[
        "Mayera",
        "Mayara"
    ],
    "wof:name":"Mayara",
    "wof:placetype":"locality"
},
  "geometry": {"coordinates":[-2.68033,7.8606],"type":"Point"}
}