{
  "type": "Feature",
  "properties": {
    "gn:admin1_code":"06",
    "gn:asciiname":"Bongo-Da",
    "gn:country_code":"GH",
    "gn:dem":172,
    "gn:feature_class":"P",
    "gn:feature_code":"PPL",
    "gn:name":"Bongo-Da",
    "gn:population":0,
    "gn:timezone":"Africa/Accra",
    "iso:country":"GH",
    "name:und_x_variant":[
        "Gbandaa",
        "Bongo",
        "Gbangdaa",
        "Gbongo",
        "Bongo-Da"
    ],
    "wof:name":"Bongo-Da",
    "wof:placetype":"locality"
},
  "geometry": {"coordinates":[-0.27253,10.34246],"type":"Point"}
}