{
  "type": "Feature",
  "properties": {
    "gn:admin1_code":"00",
    "gn:asciiname":"Abontsa",
    "gn:country_code":"GH",
    "gn:dem":42,
    "gn:feature_class":"P",
    "gn:feature_code":"PPL",
    "gn:name":"Abontsa",
    "gn:population":0,
    "gn:timezone":"Africa/Accra",
    "iso:country":"GH",
    "name:und_x_variant":[
        "Obontser",
        "Abontsa"
    ],
    "wof:name":"Abontsa",
    "wof:placetype":"locality"
},
  "geometry": {"coordinates":[-0.9491,5.31806],"type":"Point"}
}