{
  "type": "Feature",
  "properties": {
    "gn:admin1_code":"04",
    "gn:asciiname":"Kwanyako",
    "gn:country_code":"GH",
    "gn:dem":129,
    "gn:feature_class":"P",
    "gn:feature_code":"PPL",
    "gn:name":"Kwanyako",
    "gn:population":0,
    "gn:timezone":"Africa/Accra",
    "iso:country":"GH",
    "name:und_x_variant":[
        "Nkotumso Nkasawura",
        "Okotumso",
        "Kwanyako"
    ],
    "wof:name":"Kwanyako",
    "wof:placetype":"locality"
},
  "geometry": {"coordinates":[-1.91963,5.99993],"type":"Point"}
}