{
  "type": "Feature",
  "properties": {
    "gn:admin1_code":"00",
    "gn:asciiname":"Agoreke",
    "gn:country_code":"GH",
    "gn:dem":75,
    "gn:feature_class":"P",
    "gn:feature_code":"PPL",
    "gn:name":"Agoreke",
    "gn:population":0,
    "gn:timezone":"Africa/Accra",
    "iso:country":"GH",
    "wof:name":"Agoreke",
    "wof:placetype":"locality"
},
  "geometry": {"coordinates":[0.15,6.66667],"type":"Point"}
}