{
  "type": "Feature",
  "properties": {
    "gn:admin1_code":"03",
    "gn:asciiname":"Antwirifo",
    "gn:country_code":"GH",
    "gn:dem":280,
    "gn:feature_class":"P",
    "gn:feature_code":"PPL",
    "gn:name":"Antwirifo",
    "gn:population":0,
    "gn:timezone":"Africa/Accra",
    "iso:country":"GH",
    "name:eng_x_preferred":[
        "Antwirifo"
    ],
    "name:und_x_variant":[
        "Antwerefo",
        "Anchwirifu"
    ],
    "wof:name":"Antwirifo",
    "wof:placetype":"locality"
},
  "geometry": {"coordinates":[-2.9494,7.2939],"type":"Point"}
}