{
  "type": "Feature",
  "properties": {
    "gn:admin1_code":"00",
    "gn:asciiname":"Atobiasi",
    "gn:country_code":"GH",
    "gn:dem":102,
    "gn:feature_class":"P",
    "gn:feature_code":"PPL",
    "gn:name":"Atobiasi",
    "gn:population":0,
    "gn:timezone":"Africa/Accra",
    "iso:country":"GH",
    "name:und_x_variant":[
        "Atobiase",
        "Atobiasi"
    ],
    "wof:name":"Atobiasi",
    "wof:placetype":"locality"
},
  "geometry": {"coordinates":[-1.37638,6.00659],"type":"Point"}
}