{
  "type": "Feature",
  "properties": {
    "gn:admin1_code":"00",
    "gn:asciiname":"Nyamibechere",
    "gn:country_code":"GH",
    "gn:dem":101,
    "gn:feature_class":"P",
    "gn:feature_code":"PPL",
    "gn:name":"Nyamibechere",
    "gn:population":0,
    "gn:timezone":"Africa/Accra",
    "iso:country":"GH",
    "wof:name":"Nyamibechere",
    "wof:placetype":"locality"
},
  "geometry": {"coordinates":[-1.18333,5.41667],"type":"Point"}
}