{
  "type": "Feature",
  "properties": {
    "gn:admin1_code":"00",
    "gn:asciiname":"Nabon",
    "gn:country_code":"GH",
    "gn:dem":200,
    "gn:feature_class":"P",
    "gn:feature_code":"PPL",
    "gn:name":"Nabon",
    "gn:population":0,
    "gn:timezone":"Africa/Accra",
    "iso:country":"GH",
    "wof:name":"Nabon",
    "wof:placetype":"locality"
},
  "geometry": {"coordinates":[0.51831,9.19806],"type":"Point"}
}