{
  "type": "Feature",
  "properties": {
    "gn:admin1_code":"02",
    "gn:asciiname":"Abotendua",
    "gn:country_code":"GH",
    "gn:dem":197,
    "gn:feature_class":"P",
    "gn:feature_code":"PPL",
    "gn:name":"Abotendua",
    "gn:population":0,
    "gn:timezone":"Africa/Accra",
    "iso:country":"GH",
    "name:eng_x_preferred":[
        "Abotendua"
    ],
    "wof:name":"Abotendua",
    "wof:placetype":"locality"
},
  "geometry": {"coordinates":[-1.75634,6.30463],"type":"Point"}
}