{
  "type": "Feature",
  "properties": {
    "gn:admin1_code":"00",
    "gn:asciiname":"Mpeim",
    "gn:country_code":"GH",
    "gn:dem":296,
    "gn:feature_class":"P",
    "gn:feature_code":"PPL",
    "gn:name":"Mpeim",
    "gn:population":0,
    "gn:timezone":"Africa/Accra",
    "iso:country":"GH",
    "name:und_x_variant":[
        "Mpem",
        "Mpeim"
    ],
    "wof:name":"Mpeim",
    "wof:placetype":"locality"
},
  "geometry": {"coordinates":[-1.67091,7.57956],"type":"Point"}
}