{
  "type": "Feature",
  "properties": {
    "gn:admin1_code":"00",
    "gn:asciiname":"Potsin",
    "gn:country_code":"GH",
    "gn:dem":54,
    "gn:feature_class":"P",
    "gn:feature_code":"PPL",
    "gn:name":"Potsin",
    "gn:population":0,
    "gn:timezone":"Africa/Accra",
    "iso:country":"GH",
    "name:und_x_variant":[
        "Potsen",
        "Potsin"
    ],
    "wof:name":"Potsin",
    "wof:placetype":"locality"
},
  "geometry": {"coordinates":[-0.58232,5.44958],"type":"Point"}
}