{
  "type": "Feature",
  "properties": {
    "gn:admin1_code":"00",
    "gn:asciiname":"Gbeni",
    "gn:country_code":"GH",
    "gn:dem":179,
    "gn:feature_class":"P",
    "gn:feature_code":"PPL",
    "gn:name":"Gbeni",
    "gn:population":0,
    "gn:timezone":"Africa/Accra",
    "iso:country":"GH",
    "wof:name":"Gbeni",
    "wof:placetype":"locality"
},
  "geometry": {"coordinates":[-0.15241,9.0314],"type":"Point"}
}