{
  "type": "Feature",
  "properties": {
    "gn:admin1_code":"00",
    "gn:asciiname":"Nakpabone",
    "gn:country_code":"GH",
    "gn:dem":150,
    "gn:feature_class":"P",
    "gn:feature_code":"PPL",
    "gn:name":"Nakpabone",
    "gn:population":0,
    "gn:timezone":"Africa/Accra",
    "iso:country":"GH",
    "name:und_x_variant":[
        "Nakp\u0101mbon\u00e9",
        "Nakpabone"
    ],
    "wof:name":"Nakpabone",
    "wof:placetype":"locality"
},
  "geometry": {"coordinates":[0.08578,9.70142],"type":"Point"}
}