{
  "type": "Feature",
  "properties": {
    "gn:admin1_code":"11",
    "gn:asciiname":"Funsi",
    "gn:country_code":"GH",
    "gn:dem":258,
    "gn:feature_class":"P",
    "gn:feature_code":"PPL",
    "gn:name":"Funsi",
    "gn:population":0,
    "gn:timezone":"Africa/Accra",
    "iso:country":"GH",
    "wof:name":"Funsi",
    "wof:placetype":"locality"
},
  "geometry": {"coordinates":[-1.96679,10.29627],"type":"Point"}
}