{
  "type": "Feature",
  "properties": {
    "gn:admin1_code":"06",
    "gn:asciiname":"Bale",
    "gn:country_code":"GH",
    "gn:dem":242,
    "gn:feature_class":"P",
    "gn:feature_code":"PPL",
    "gn:name":"Bale",
    "gn:population":0,
    "gn:timezone":"Africa/Accra",
    "iso:country":"GH",
    "name:eng_x_preferred":[
        "Bale"
    ],
    "wof:name":"Bale",
    "wof:placetype":"locality"
},
  "geometry": {"coordinates":[-2.59645,9.08042],"type":"Point"}
}