{
  "type": "Feature",
  "properties": {
    "gn:admin1_code":"06",
    "gn:asciiname":"Bale",
    "gn:country_code":"GH",
    "gn:dem":242,
    "gn:feature_class":"P",
    "gn:feature_code":"PPL",
    "gn:name":"Bale",
    "gn:population":0,
    "gn:timezone":"Africa/Accra",
    "iso:country":"GH",
    "name:bos_x_preferred":[
        "Bale"
    ],
    "name:cat_x_preferred":[
        "Bale"
    ],
    "name:ceb_x_preferred":[
        "Bale"
    ],
    "name:ces_x_preferred":[
        "Bale"
    ],
    "name:deu_x_preferred":[
        "Bale"
    ],
    "name:eng_x_preferred":[
        "Bale"
    ],
    "name:eus_x_preferred":[
        "Bale"
    ],
    "name:fra_x_preferred":[
        "Bale"
    ],
    "name:heb_x_preferred":[
        "\u05d1\u05d9\u05d9\u05dc"
    ],
    "name:hrv_x_preferred":[
        "Bale"
    ],
    "name:hun_x_preferred":[
        "Bale"
    ],
    "name:ita_x_preferred":[
        "Bale"
    ],
    "name:kor_x_preferred":[
        "\ubca0\uc77c"
    ],
    "name:nld_x_preferred":[
        "Bale"
    ],
    "name:pol_x_preferred":[
        "Bale"
    ],
    "name:rus_x_preferred":[
        "\u0411\u0430\u043b\u0435"
    ],
    "name:slv_x_preferred":[
        "Bale"
    ],
    "name:spa_x_preferred":[
        "Bale"
    ],
    "name:srp_x_preferred":[
        "\u0411\u0430\u043b\u0435"
    ],
    "name:swe_x_preferred":[
        "Bale"
    ],
    "name:ukr_x_preferred":[
        "\u0411\u0435\u0439\u043b"
    ],
    "wof:name":"Bale",
    "wof:placetype":"locality"
},
  "geometry": {"coordinates":[-2.59645,9.08042],"type":"Point"}
}