{
  "type": "Feature",
  "properties": {
    "gn:admin1_code":"06",
    "gn:asciiname":"Niengah",
    "gn:country_code":"GH",
    "gn:dem":184,
    "gn:feature_class":"P",
    "gn:feature_code":"PPL",
    "gn:name":"Niengah",
    "gn:population":0,
    "gn:timezone":"Africa/Accra",
    "iso:country":"GH",
    "name:und_x_variant":[
        "Nyingali",
        "Niengah"
    ],
    "wof:name":"Niengah",
    "wof:placetype":"locality"
},
  "geometry": {"coordinates":[-0.31692,9.93742],"type":"Point"}
}