{
  "type": "Feature",
  "properties": {
    "gn:admin1_code":"00",
    "gn:asciiname":"Kovedji",
    "gn:cc2":"GH",
    "gn:country_code":"GH",
    "gn:dem":50,
    "gn:feature_class":"P",
    "gn:feature_code":"PPL",
    "gn:name":"Kovedji",
    "gn:population":0,
    "gn:timezone":"Africa/Accra",
    "iso:country":"GH",
    "name:und_x_variant":[
        "Kovedje",
        "Kovedji"
    ],
    "wof:name":"Kovedji",
    "wof:placetype":"locality"
},
  "geometry": {"coordinates":[0.96667,6.31667],"type":"Point"}
}