{
  "type": "Feature",
  "properties": {
    "gn:admin1_code":"01",
    "gn:asciiname":"Aidan",
    "gn:country_code":"GH",
    "gn:dem":63,
    "gn:feature_class":"P",
    "gn:feature_code":"PPL",
    "gn:name":"Aidan",
    "gn:population":0,
    "gn:timezone":"Africa/Accra",
    "iso:country":"GH",
    "name:deu_x_preferred":[
        "Aidan"
    ],
    "name:eus_x_preferred":[
        "Aidan"
    ],
    "name:fra_x_preferred":[
        "Aidan"
    ],
    "name:ita_x_preferred":[
        "Aidano"
    ],
    "name:jpn_x_preferred":[
        "\u30a8\u30a4\u30c0\u30f3"
    ],
    "name:pol_x_preferred":[
        "Aidan"
    ],
    "name:rus_x_preferred":[
        "\u0410\u0439\u0434\u0430\u043d"
    ],
    "wof:name":"Aidan",
    "wof:placetype":"locality"
},
  "geometry": {"coordinates":[-0.41667,5.75],"type":"Point"}
}