{
  "type": "Feature",
  "properties": {
    "gn:admin1_code":"00",
    "gn:asciiname":"Awuaya",
    "gn:country_code":"GH",
    "gn:dem":31,
    "gn:feature_class":"P",
    "gn:feature_code":"PPL",
    "gn:name":"Awuaya",
    "gn:population":0,
    "gn:timezone":"Africa/Accra",
    "iso:country":"GH",
    "wof:name":"Awuaya",
    "wof:placetype":"locality"
},
  "geometry": {"coordinates":[-1.06235,5.23967],"type":"Point"}
}