{
  "type": "Feature",
  "properties": {
    "gn:admin1_code":"00",
    "gn:asciiname":"Baguli",
    "gn:country_code":"GH",
    "gn:dem":172,
    "gn:feature_class":"P",
    "gn:feature_code":"PPL",
    "gn:name":"Baguli",
    "gn:population":0,
    "gn:timezone":"Africa/Accra",
    "iso:country":"GH",
    "name:und_x_variant":[
        "Baguri",
        "Baguli"
    ],
    "wof:name":"Baguli",
    "wof:placetype":"locality"
},
  "geometry": {"coordinates":[0.2154,10.06599],"type":"Point"}
}