{
  "type": "Feature",
  "properties": {
    "gn:admin1_code":"00",
    "gn:asciiname":"Dove",
    "gn:country_code":"GH",
    "gn:dem":5,
    "gn:feature_class":"P",
    "gn:feature_code":"PPL",
    "gn:name":"Dove",
    "gn:population":0,
    "gn:timezone":"Africa/Accra",
    "iso:country":"GH",
    "wof:name":"Dove",
    "wof:placetype":"locality"
},
  "geometry": {"coordinates":[0.4771,6.02696],"type":"Point"}
}