{
  "type": "Feature",
  "properties": {
    "gn:admin1_code":"01",
    "gn:asciiname":"Pantampo",
    "gn:country_code":"GH",
    "gn:dem":36,
    "gn:feature_class":"P",
    "gn:feature_code":"PPL",
    "gn:name":"Pantampo",
    "gn:population":0,
    "gn:timezone":"Africa/Accra",
    "iso:country":"GH",
    "name:und_x_variant":[
        "Pantampa",
        "Pantampo"
    ],
    "wof:name":"Pantampo",
    "wof:placetype":"locality"
},
  "geometry": {"coordinates":[-0.42142,5.56975],"type":"Point"}
}