{
  "type": "Feature",
  "properties": {
    "gn:admin1_code":"00",
    "gn:asciiname":"Ajireso",
    "gn:cc2":"GH",
    "gn:country_code":"GH",
    "gn:dem":88,
    "gn:feature_class":"P",
    "gn:feature_code":"PPL",
    "gn:name":"Ajireso",
    "gn:population":0,
    "gn:timezone":"Africa/Accra",
    "iso:country":"GH",
    "name:und_x_variant":[
        "Agyireso",
        "Ajireso"
    ],
    "wof:name":"Ajireso",
    "wof:placetype":"locality"
},
  "geometry": {"coordinates":[-2.48333,5.61667],"type":"Point"}
}