{
  "type": "Feature",
  "properties": {
    "gn:admin1_code":"00",
    "gn:asciiname":"Angu",
    "gn:country_code":"GH",
    "gn:dem":45,
    "gn:feature_class":"P",
    "gn:feature_code":"PPL",
    "gn:name":"Angu",
    "gn:population":0,
    "gn:timezone":"Africa/Accra",
    "iso:country":"GH",
    "name:und_x_variant":[
        "Engow",
        "Angu"
    ],
    "wof:name":"Angu",
    "wof:placetype":"locality"
},
  "geometry": {"coordinates":[-0.92926,5.30417],"type":"Point"}
}