{
  "type": "Feature",
  "properties": {
    "gn:admin1_code":"00",
    "gn:asciiname":"Angu",
    "gn:country_code":"GH",
    "gn:dem":45,
    "gn:feature_class":"P",
    "gn:feature_code":"PPL",
    "gn:name":"Angu",
    "gn:population":0,
    "gn:timezone":"Africa/Accra",
    "iso:country":"GH",
    "name:fra_x_preferred":[
        "Kukukukus"
    ],
    "name:hrv_x_preferred":[
        "Kukukuku"
    ],
    "name:hun_x_preferred":[
        "Kukukukuk"
    ],
    "name:jpn_x_preferred":[
        "\u30af\u30ab\u30af\u30ab\u65cf"
    ],
    "name:kat_x_preferred":[
        "\u10d0\u10dc\u10d2\u10e3"
    ],
    "name:rus_x_preferred":[
        "\u0410\u043d\u0433\u0443"
    ],
    "name:und_x_variant":[
        "Engow",
        "Angu"
    ],
    "name:zho_x_preferred":[
        "\u5eab\u5361\u5eab\u5361\u4eba"
    ],
    "wof:name":"Angu",
    "wof:placetype":"locality"
},
  "geometry": {"coordinates":[-0.92926,5.30417],"type":"Point"}
}