{
  "type": "Feature",
  "properties": {
    "gn:admin1_code":"00",
    "gn:asciiname":"Sikaman",
    "gn:country_code":"GH",
    "gn:dem":113,
    "gn:feature_class":"P",
    "gn:feature_code":"PPL",
    "gn:name":"Sikaman",
    "gn:population":0,
    "gn:timezone":"Africa/Accra",
    "iso:country":"GH",
    "wof:name":"Sikaman",
    "wof:placetype":"locality"
},
  "geometry": {"coordinates":[-1.33985,5.3291],"type":"Point"}
}