{
  "type": "Feature",
  "properties": {
    "gn:admin1_code":"00",
    "gn:asciiname":"Takwa",
    "gn:country_code":"GH",
    "gn:dem":111,
    "gn:feature_class":"P",
    "gn:feature_code":"PPL",
    "gn:name":"Takwa",
    "gn:population":0,
    "gn:timezone":"Africa/Accra",
    "iso:country":"GH",
    "name:cat_x_preferred":[
        "Takwa"
    ],
    "name:deu_x_preferred":[
        "Takwa"
    ],
    "name:fra_x_preferred":[
        "Takwa"
    ],
    "name:rus_x_preferred":[
        "\u0422\u0430\u043a\u0432\u0430"
    ],
    "name:swa_x_preferred":[
        "Takwa"
    ],
    "wof:name":"Takwa",
    "wof:placetype":"locality"
},
  "geometry": {"coordinates":[-1.18333,6.16667],"type":"Point"}
}