{
  "type": "Feature",
  "properties": {
    "gn:admin1_code":"00",
    "gn:asciiname":"Yorugu",
    "gn:country_code":"GH",
    "gn:dem":181,
    "gn:feature_class":"P",
    "gn:feature_code":"PPL",
    "gn:name":"Yorugu",
    "gn:population":0,
    "gn:timezone":"Africa/Accra",
    "iso:country":"GH",
    "name:und_x_variant":[
        "Yarugu",
        "Yarigo",
        "Yorugu"
    ],
    "wof:name":"Yorugu",
    "wof:placetype":"locality"
},
  "geometry": {"coordinates":[-0.39121,10.95649],"type":"Point"}
}