{
  "type": "Feature",
  "properties": {
    "gn:admin1_code":"00",
    "gn:asciiname":"Kubonga",
    "gn:country_code":"GH",
    "gn:dem":251,
    "gn:feature_class":"P",
    "gn:feature_code":"PPL",
    "gn:name":"Kubonga",
    "gn:population":0,
    "gn:timezone":"Africa/Accra",
    "iso:country":"GH",
    "wof:name":"Kubonga",
    "wof:placetype":"locality"
},
  "geometry": {"coordinates":[-0.01667,11.01667],"type":"Point"}
}