{
  "type": "Feature",
  "properties": {
    "gn:admin1_code":"00",
    "gn:asciiname":"Soyegu",
    "gn:country_code":"GH",
    "gn:dem":430,
    "gn:feature_class":"P",
    "gn:feature_code":"PPL",
    "gn:name":"Soyegu",
    "gn:population":0,
    "gn:timezone":"Africa/Accra",
    "iso:country":"GH",
    "name:und_x_variant":[
        "Sejeho",
        "Sowjegu",
        "Sayogu",
        "Soyegu"
    ],
    "wof:name":"Soyegu",
    "wof:placetype":"locality"
},
  "geometry": {"coordinates":[-0.12951,10.62806],"type":"Point"}
}