{
  "type": "Feature",
  "properties": {
    "gn:admin1_code":"00",
    "gn:asciiname":"Bimbini",
    "gn:cc2":"GH",
    "gn:country_code":"GH",
    "gn:dem":133,
    "gn:feature_class":"P",
    "gn:feature_code":"PPL",
    "gn:name":"Bimbini",
    "gn:population":0,
    "gn:timezone":"Africa/Accra",
    "iso:country":"GH",
    "name:azb_x_preferred":[
        "\u0628\u06cc\u0645\u0628\u06cc\u0646\u06cc"
    ],
    "name:ceb_x_preferred":[
        "Bimbini"
    ],
    "name:deu_x_preferred":[
        "Bimbini"
    ],
    "name:fas_x_preferred":[
        "\u0628\u06cc\u0645\u0628\u06cc\u0646\u06cc"
    ],
    "name:fra_x_preferred":[
        "Bimbini"
    ],
    "name:swe_x_preferred":[
        "Bimbini"
    ],
    "name:und_x_variant":[
        "Binbini"
    ],
    "wof:name":"Bimbini",
    "wof:placetype":"locality"
},
  "geometry": {"coordinates":[-1.06667,10.33333],"type":"Point"}
}