{
  "type": "Feature",
  "properties": {
    "gn:admin1_code":"00",
    "gn:asciiname":"Wawasi",
    "gn:country_code":"GH",
    "gn:dem":142,
    "gn:feature_class":"P",
    "gn:feature_code":"PPL",
    "gn:name":"Wawasi",
    "gn:population":0,
    "gn:timezone":"Africa/Accra",
    "iso:country":"GH",
    "wof:name":"Wawasi",
    "wof:placetype":"locality"
},
  "geometry": {"coordinates":[-1.25,5.85],"type":"Point"}
}