{
  "type": "Feature",
  "properties": {
    "gn:admin1_code":"00",
    "gn:asciiname":"Dadiasi",
    "gn:cc2":"GH",
    "gn:country_code":"GH",
    "gn:dem":419,
    "gn:feature_class":"P",
    "gn:feature_code":"PPL",
    "gn:name":"Dadiasi",
    "gn:population":0,
    "gn:timezone":"Africa/Accra",
    "iso:country":"GH",
    "name:und_x_variant":[
        "Dadiase",
        "Dadiasi"
    ],
    "wof:name":"Dadiasi",
    "wof:placetype":"locality"
},
  "geometry": {"coordinates":[-1.36667,7.01667],"type":"Point"}
}