{
  "type": "Feature",
  "properties": {
    "gn:admin1_code":"00",
    "gn:asciiname":"Asimpa",
    "gn:cc2":"GH",
    "gn:country_code":"GH",
    "gn:dem":64,
    "gn:feature_class":"P",
    "gn:feature_code":"PPL",
    "gn:name":"Asimpa",
    "gn:population":0,
    "gn:timezone":"Africa/Accra",
    "iso:country":"GH",
    "name:und_x_variant":[
        "Simpa",
        "Asimpa"
    ],
    "wof:name":"Asimpa",
    "wof:placetype":"locality"
},
  "geometry": {"coordinates":[-2.56667,5.55],"type":"Point"}
}