{
  "type": "Feature",
  "properties": {
    "gn:admin1_code":"00",
    "gn:asciiname":"Adakpo",
    "gn:country_code":"GH",
    "gn:dem":39,
    "gn:feature_class":"P",
    "gn:feature_code":"PPL",
    "gn:name":"Adakpo",
    "gn:population":0,
    "gn:timezone":"Africa/Accra",
    "iso:country":"GH",
    "wof:name":"Adakpo",
    "wof:placetype":"locality"
},
  "geometry": {"coordinates":[0.67034,6.17464],"type":"Point"}
}