{
  "type": "Feature",
  "properties": {
    "gn:admin1_code":"00",
    "gn:asciiname":"Adeitu",
    "gn:cc2":"GH",
    "gn:country_code":"GH",
    "gn:dem":356,
    "gn:feature_class":"P",
    "gn:feature_code":"PPL",
    "gn:name":"Adeitu",
    "gn:population":0,
    "gn:timezone":"Africa/Accra",
    "iso:country":"GH",
    "name:und_x_variant":[
        "Adeito",
        "Adeitu"
    ],
    "wof:name":"Adeitu",
    "wof:placetype":"locality"
},
  "geometry": {"coordinates":[-1.38333,6.45],"type":"Point"}
}