{
  "type": "Feature",
  "properties": {
    "gn:admin1_code":"00",
    "gn:asciiname":"Nokaben",
    "gn:country_code":"GH",
    "gn:dem":9,
    "gn:feature_class":"P",
    "gn:feature_code":"PPL",
    "gn:name":"Nokaben",
    "gn:population":0,
    "gn:timezone":"Africa/Abidjan",
    "iso:country":"GH",
    "name:und_x_variant":[
        "Nokobanu Number 2",
        "Nokaben"
    ],
    "wof:name":"Nokaben",
    "wof:placetype":"locality"
},
  "geometry": {"coordinates":[-3.00208,5.10766],"type":"Point"}
}