{
  "type": "Feature",
  "properties": {
    "gn:admin1_code":"00",
    "gn:asciiname":"Zomai",
    "gn:country_code":"GH",
    "gn:dem":97,
    "gn:feature_class":"P",
    "gn:feature_code":"PPL",
    "gn:name":"Zomai",
    "gn:population":0,
    "gn:timezone":"Africa/Accra",
    "iso:country":"GH",
    "wof:name":"Zomai",
    "wof:placetype":"locality"
},
  "geometry": {"coordinates":[0.73308,6.46977],"type":"Point"}
}