{
  "type": "Feature",
  "properties": {
    "gn:admin1_code":"00",
    "gn:asciiname":"Akusuno",
    "gn:country_code":"GH",
    "gn:dem":26,
    "gn:feature_class":"P",
    "gn:feature_code":"PPL",
    "gn:name":"Akusuno",
    "gn:population":0,
    "gn:timezone":"Africa/Accra",
    "iso:country":"GH",
    "wof:name":"Akusuno",
    "wof:placetype":"locality"
},
  "geometry": {"coordinates":[-2.41225,5.07524],"type":"Point"}
}