{
  "type": "Feature",
  "properties": {
    "gn:admin1_code":"04",
    "gn:asciiname":"Kyerenkum",
    "gn:country_code":"GH",
    "gn:dem":154,
    "gn:feature_class":"P",
    "gn:feature_code":"PPL",
    "gn:name":"Kyerenkum",
    "gn:population":0,
    "gn:timezone":"Africa/Accra",
    "iso:country":"GH",
    "name:eng_x_preferred":[
        "Kyerenkum"
    ],
    "name:eng_x_variant":[
        "Banahenekrom"
    ],
    "wof:name":"Kyerenkum",
    "wof:placetype":"locality"
},
  "geometry": {"coordinates":[-1.62602,5.86192],"type":"Point"}
}