{
  "type": "Feature",
  "properties": {
    "gn:admin1_code":"00",
    "gn:asciiname":"Lakpa",
    "gn:country_code":"GH",
    "gn:dem":170,
    "gn:feature_class":"P",
    "gn:feature_code":"PPL",
    "gn:name":"Lakpa",
    "gn:population":0,
    "gn:timezone":"Africa/Accra",
    "iso:country":"GH",
    "wof:name":"Lakpa",
    "wof:placetype":"locality"
},
  "geometry": {"coordinates":[-0.17503,6.09167],"type":"Point"}
}