{
  "type": "Feature",
  "properties": {
    "gn:admin1_code":"00",
    "gn:asciiname":"Nabiago",
    "gn:country_code":"GH",
    "gn:dem":186,
    "gn:feature_class":"P",
    "gn:feature_code":"PPL",
    "gn:name":"Nabiago",
    "gn:population":0,
    "gn:timezone":"Africa/Accra",
    "iso:country":"GH",
    "name:und_x_variant":[
        "Nabiegu",
        "Nabiago"
    ],
    "wof:name":"Nabiago",
    "wof:placetype":"locality"
},
  "geometry": {"coordinates":[-0.03338,10.23629],"type":"Point"}
}