{
  "type": "Feature",
  "properties": {
    "gn:admin1_code":"00",
    "gn:asciiname":"Sitane",
    "gn:country_code":"GH",
    "gn:dem":193,
    "gn:feature_class":"P",
    "gn:feature_code":"PPL",
    "gn:name":"Sitane",
    "gn:population":0,
    "gn:timezone":"Africa/Accra",
    "iso:country":"GH",
    "name:und_x_variant":[
        "Setani",
        "Sitane"
    ],
    "wof:name":"Sitane",
    "wof:placetype":"locality"
},
  "geometry": {"coordinates":[-0.43911,10.87116],"type":"Point"}
}