{
  "type": "Feature",
  "properties": {
    "gn:admin1_code":"04",
    "gn:asciiname":"Techikrom",
    "gn:country_code":"GH",
    "gn:dem":108,
    "gn:feature_class":"P",
    "gn:feature_code":"PPL",
    "gn:name":"Techikrom",
    "gn:population":0,
    "gn:timezone":"Africa/Accra",
    "iso:country":"GH",
    "name:und_x_variant":[
        "Kwekuponkrom",
        "Techikrom"
    ],
    "wof:name":"Techikrom",
    "wof:placetype":"locality"
},
  "geometry": {"coordinates":[-1.6767,5.7557],"type":"Point"}
}