{
  "type": "Feature",
  "properties": {
    "gn:admin1_code":"00",
    "gn:asciiname":"Avenopedu",
    "gn:country_code":"GH",
    "gn:dem":22,
    "gn:feature_class":"P",
    "gn:feature_code":"PPL",
    "gn:name":"Avenopedu",
    "gn:population":0,
    "gn:timezone":"Africa/Accra",
    "iso:country":"GH",
    "name:und_x_variant":[
        "Avenopedo",
        "Avenopedu"
    ],
    "wof:name":"Avenopedu",
    "wof:placetype":"locality"
},
  "geometry": {"coordinates":[0.84513,6.05788],"type":"Point"}
}