{
  "type": "Feature",
  "properties": {
    "gn:admin1_code":"11",
    "gn:asciiname":"Sihiduori",
    "gn:country_code":"GH",
    "gn:dem":269,
    "gn:feature_class":"P",
    "gn:feature_code":"PPL",
    "gn:name":"Sihiduori",
    "gn:population":0,
    "gn:timezone":"Africa/Accra",
    "iso:country":"GH",
    "name:eng_x_preferred":[
        "Sihiduori"
    ],
    "name:eng_x_variant":[
        "Sombo"
    ],
    "wof:name":"Sihiduori",
    "wof:placetype":"locality"
},
  "geometry": {"coordinates":[-2.68959,10.31141],"type":"Point"}
}