{
  "type": "Feature",
  "properties": {
    "gn:admin1_code":"00",
    "gn:asciiname":"Tambalugu",
    "gn:cc2":"GH",
    "gn:country_code":"GH",
    "gn:dem":198,
    "gn:feature_class":"P",
    "gn:feature_code":"PPL",
    "gn:name":"Tambalugu",
    "gn:population":0,
    "gn:timezone":"Africa/Accra",
    "iso:country":"GH",
    "name:und_x_variant":[
        "Tambaliga",
        "Tambalugu"
    ],
    "wof:name":"Tambalugu",
    "wof:placetype":"locality"
},
  "geometry": {"coordinates":[-0.23333,10.86667],"type":"Point"}
}