{
  "type": "Feature",
  "properties": {
    "gn:admin1_code":"00",
    "gn:asciiname":"Abominya",
    "gn:country_code":"GH",
    "gn:dem":58,
    "gn:feature_class":"P",
    "gn:feature_code":"PPL",
    "gn:name":"Abominya",
    "gn:population":0,
    "gn:timezone":"Africa/Accra",
    "iso:country":"GH",
    "wof:name":"Abominya",
    "wof:placetype":"locality"
},
  "geometry": {"coordinates":[-0.01014,5.95784],"type":"Point"}
}