{
  "type": "Feature",
  "properties": {
    "gn:admin1_code":"00",
    "gn:asciiname":"Nandaw",
    "gn:country_code":"GH",
    "gn:dem":275,
    "gn:feature_class":"P",
    "gn:feature_code":"PPL",
    "gn:name":"Nandaw",
    "gn:population":0,
    "gn:timezone":"Africa/Accra",
    "iso:country":"GH",
    "name:und_x_variant":[
        "Nindow",
        "Nandaw"
    ],
    "wof:name":"Nandaw",
    "wof:placetype":"locality"
},
  "geometry": {"coordinates":[-2.38309,10.69453],"type":"Point"}
}