{
  "type": "Feature",
  "properties": {
    "gn:admin1_code":"01",
    "gn:asciiname":"Dzamai",
    "gn:country_code":"GH",
    "gn:dem":22,
    "gn:feature_class":"P",
    "gn:feature_code":"PPL",
    "gn:name":"Dzamai",
    "gn:population":0,
    "gn:timezone":"Africa/Accra",
    "iso:country":"GH",
    "name:eng_x_preferred":[
        "Dzamai"
    ],
    "name:eng_x_variant":[
        "Joma",
        "Dzoma"
    ],
    "wof:name":"Dzamai",
    "wof:placetype":"locality"
},
  "geometry": {"coordinates":[-0.35047,5.60331],"type":"Point"}
}