{
  "type": "Feature",
  "properties": {
    "gn:admin1_code":"09",
    "gn:asciiname":"Banso",
    "gn:country_code":"GH",
    "gn:dem":54,
    "gn:feature_class":"P",
    "gn:feature_code":"PPL",
    "gn:name":"Banso",
    "gn:population":0,
    "gn:timezone":"Africa/Accra",
    "iso:country":"GH",
    "name:eng_x_preferred":[
        "Banso"
    ],
    "wof:name":"Banso",
    "wof:placetype":"locality"
},
  "geometry": {"coordinates":[-2.21977,4.87528],"type":"Point"}
}