{
  "type": "Feature",
  "properties": {
    "gn:admin1_code":"09",
    "gn:asciiname":"Mensakrom",
    "gn:country_code":"GH",
    "gn:dem":135,
    "gn:feature_class":"P",
    "gn:feature_code":"PPL",
    "gn:name":"Mensakrom",
    "gn:population":0,
    "gn:timezone":"Africa/Accra",
    "iso:country":"GH",
    "name:und_x_variant":[
        "Mensakurom",
        "Mensakrom"
    ],
    "wof:name":"Mensakrom",
    "wof:placetype":"locality"
},
  "geometry": {"coordinates":[-1.93486,5.58732],"type":"Point"}
}