{
  "type": "Feature",
  "properties": {
    "gn:admin1_code":"00",
    "gn:asciiname":"Kulenpiyo",
    "gn:country_code":"GH",
    "gn:dem":208,
    "gn:feature_class":"P",
    "gn:feature_code":"PPL",
    "gn:name":"Kulenpiyo",
    "gn:population":0,
    "gn:timezone":"Africa/Accra",
    "iso:country":"GH",
    "name:und_x_variant":[
        "Kulkpegu",
        "Kulenpiyo"
    ],
    "wof:name":"Kulenpiyo",
    "wof:placetype":"locality"
},
  "geometry": {"coordinates":[-0.25853,9.35811],"type":"Point"}
}