{
  "type": "Feature",
  "properties": {
    "gn:admin1_code":"01",
    "gn:asciiname":"Mensakwa",
    "gn:country_code":"GH",
    "gn:dem":89,
    "gn:feature_class":"P",
    "gn:feature_code":"PPL",
    "gn:name":"Mensakwa",
    "gn:population":0,
    "gn:timezone":"Africa/Accra",
    "iso:country":"GH",
    "name:und_x_variant":[
        "Mensakwaa",
        "Mensakwa"
    ],
    "wof:name":"Mensakwa",
    "wof:placetype":"locality"
},
  "geometry": {"coordinates":[-0.56667,5.55],"type":"Point"}
}