{
  "type": "Feature",
  "properties": {
    "gn:admin1_code":"09",
    "gn:asciiname":"Asabie",
    "gn:country_code":"GH",
    "gn:dem":51,
    "gn:feature_class":"P",
    "gn:feature_code":"PPL",
    "gn:name":"Asabie",
    "gn:population":0,
    "gn:timezone":"Africa/Accra",
    "iso:country":"GH",
    "wof:name":"Asabie",
    "wof:placetype":"locality"
},
  "geometry": {"coordinates":[-2.13989,4.99247],"type":"Point"}
}