{
  "type": "Feature",
  "properties": {
    "gn:admin1_code":"00",
    "gn:asciiname":"Wusuta Dzigbe",
    "gn:country_code":"GH",
    "gn:dem":142,
    "gn:feature_class":"P",
    "gn:feature_code":"PPL",
    "gn:name":"Wusuta Dzigbe",
    "gn:population":0,
    "gn:timezone":"Africa/Accra",
    "iso:country":"GH",
    "name:und_x_variant":[
        "Gadje",
        "Wusuta Number 1",
        "Wusuta Dzigbe"
    ],
    "wof:name":"Wusuta Dzigbe",
    "wof:placetype":"locality"
},
  "geometry": {"coordinates":[0.23991,6.8368],"type":"Point"}
}