{
  "type": "Feature",
  "properties": {
    "gn:admin1_code":"00",
    "gn:asciiname":"Terrepa",
    "gn:country_code":"GH",
    "gn:dem":158,
    "gn:feature_class":"P",
    "gn:feature_code":"PPL",
    "gn:name":"Terrepa",
    "gn:population":0,
    "gn:timezone":"Africa/Accra",
    "iso:country":"GH",
    "name:und_x_variant":[
        "Tarikpaa",
        "Terrepa"
    ],
    "wof:name":"Terrepa",
    "wof:placetype":"locality"
},
  "geometry": {"coordinates":[-0.90191,9.58593],"type":"Point"}
}