{
  "type": "Feature",
  "properties": {
    "gn:admin1_code":"00",
    "gn:asciiname":"Asuboni",
    "gn:country_code":"GH",
    "gn:dem":87,
    "gn:feature_class":"P",
    "gn:feature_code":"PPL",
    "gn:name":"Asuboni",
    "gn:population":0,
    "gn:timezone":"Africa/Accra",
    "iso:country":"GH",
    "name:und_x_variant":[
        "Asubone",
        "Asubon",
        "Asuboni"
    ],
    "wof:name":"Asuboni",
    "wof:placetype":"locality"
},
  "geometry": {"coordinates":[-0.45509,6.6955],"type":"Point"}
}