{
  "type": "Feature",
  "properties": {
    "gn:admin1_code":"09",
    "gn:asciiname":"Deabenekrom",
    "gn:country_code":"GH",
    "gn:dem":36,
    "gn:feature_class":"P",
    "gn:feature_code":"PPL",
    "gn:name":"Deabenekrom",
    "gn:population":0,
    "gn:timezone":"Africa/Accra",
    "iso:country":"GH",
    "name:und_x_variant":[
        "Deabinakrom",
        "Deabenekrom"
    ],
    "wof:name":"Deabenekrom",
    "wof:placetype":"locality"
},
  "geometry": {"coordinates":[-1.75134,4.9614],"type":"Point"}
}