{
  "type": "Feature",
  "properties": {
    "gn:admin1_code":"00",
    "gn:asciiname":"Dzogbove",
    "gn:country_code":"GH",
    "gn:dem":1,
    "gn:feature_class":"P",
    "gn:feature_code":"PPL",
    "gn:name":"Dzogbove",
    "gn:population":0,
    "gn:timezone":"Africa/Accra",
    "iso:country":"GH",
    "name:und_x_variant":[
        "Jogbove",
        "Dzogborve",
        "Dzogbove"
    ],
    "wof:name":"Dzogbove",
    "wof:placetype":"locality"
},
  "geometry": {"coordinates":[0.69718,5.84849],"type":"Point"}
}