{
  "type": "Feature",
  "properties": {
    "gn:admin1_code":"00",
    "gn:asciiname":"Gidikpe Chegakofe",
    "gn:cc2":"GH",
    "gn:country_code":"GH",
    "gn:dem":48,
    "gn:feature_class":"P",
    "gn:feature_code":"PPL",
    "gn:name":"Gidikpe Chegakofe",
    "gn:population":0,
    "gn:timezone":"Africa/Accra",
    "iso:country":"GH",
    "name:und_x_variant":[
        "Gidikpe Tsegakorpe",
        "Gidikpe Chegakofe"
    ],
    "wof:name":"Gidikpe Chegakofe",
    "wof:placetype":"locality"
},
  "geometry": {"coordinates":[0.65,6.31667],"type":"Point"}
}