{
  "type": "Feature",
  "properties": {
    "gn:admin1_code":"09",
    "gn:asciiname":"Mamanhu",
    "gn:country_code":"GH",
    "gn:dem":111,
    "gn:feature_class":"P",
    "gn:feature_code":"PPL",
    "gn:name":"Mamanhu",
    "gn:population":0,
    "gn:timezone":"Africa/Accra",
    "iso:country":"GH",
    "name:eng_x_preferred":[
        "Mamanhu"
    ],
    "wof:name":"Mamanhu",
    "wof:placetype":"locality"
},
  "geometry": {"coordinates":[-1.84274,5.71978],"type":"Point"}
}