{
  "type": "Feature",
  "properties": {
    "gn:admin1_code":"00",
    "gn:asciiname":"Kwaboanta",
    "gn:country_code":"GH",
    "gn:dem":138,
    "gn:feature_class":"P",
    "gn:feature_code":"PPL",
    "gn:name":"Kwaboanta",
    "gn:population":0,
    "gn:timezone":"Africa/Accra",
    "iso:country":"GH",
    "wof:name":"Kwaboanta",
    "wof:placetype":"locality"
},
  "geometry": {"coordinates":[-0.56177,5.91815],"type":"Point"}
}