{
  "type": "Feature",
  "properties": {
    "gn:admin1_code":"09",
    "gn:asciiname":"Kwesikra",
    "gn:country_code":"GH",
    "gn:dem":207,
    "gn:feature_class":"P",
    "gn:feature_code":"PPL",
    "gn:name":"Kwesikra",
    "gn:population":0,
    "gn:timezone":"Africa/Accra",
    "iso:country":"GH",
    "name:eng_x_preferred":[
        "Kwesikra"
    ],
    "wof:name":"Kwesikra",
    "wof:placetype":"locality"
},
  "geometry": {"coordinates":[-1.97249,5.41783],"type":"Point"}
}