{
  "type": "Feature",
  "properties": {
    "gn:admin1_code":"00",
    "gn:asciiname":"Lawgawre",
    "gn:country_code":"GH",
    "gn:dem":263,
    "gn:feature_class":"P",
    "gn:feature_code":"PPL",
    "gn:name":"Lawgawre",
    "gn:population":0,
    "gn:timezone":"Africa/Accra",
    "iso:country":"GH",
    "wof:name":"Lawgawre",
    "wof:placetype":"locality"
},
  "geometry": {"coordinates":[-0.71667,10.81667],"type":"Point"}
}