{
  "type": "Feature",
  "properties": {
    "gn:admin1_code":"00",
    "gn:asciiname":"Aduasa",
    "gn:country_code":"GH",
    "gn:dem":129,
    "gn:feature_class":"P",
    "gn:feature_code":"PPL",
    "gn:name":"Aduasa",
    "gn:population":0,
    "gn:timezone":"Africa/Accra",
    "iso:country":"GH",
    "wof:name":"Aduasa",
    "wof:placetype":"locality"
},
  "geometry": {"coordinates":[-1.04622,5.90706],"type":"Point"}
}