{
  "type": "Feature",
  "properties": {
    "gn:admin1_code":"11",
    "gn:asciiname":"Nakori",
    "gn:country_code":"GH",
    "gn:dem":304,
    "gn:feature_class":"P",
    "gn:feature_code":"PPL",
    "gn:name":"Nakori",
    "gn:population":0,
    "gn:timezone":"Africa/Accra",
    "iso:country":"GH",
    "name:und_x_variant":[
        "Nakora"
    ],
    "wof:name":"Nakori",
    "wof:placetype":"locality"
},
  "geometry": {"coordinates":[-2.54679,10.01943],"type":"Point"}
}