{
  "type": "Feature",
  "properties": {
    "gn:admin1_code":"00",
    "gn:asciiname":"Takpe",
    "gn:country_code":"GH",
    "gn:dem":11,
    "gn:feature_class":"P",
    "gn:feature_code":"PPL",
    "gn:name":"Takpe",
    "gn:population":0,
    "gn:timezone":"Africa/Accra",
    "iso:country":"GH",
    "wof:name":"Takpe",
    "wof:placetype":"locality"
},
  "geometry": {"coordinates":[0.22203,6.09385],"type":"Point"}
}