{
  "type": "Feature",
  "properties": {
    "gn:admin1_code":"08",
    "gn:asciiname":"Domanko",
    "gn:country_code":"GH",
    "gn:dem":105,
    "gn:feature_class":"P",
    "gn:feature_code":"PPL",
    "gn:name":"Domanko",
    "gn:population":0,
    "gn:timezone":"Africa/Accra",
    "iso:country":"GH",
    "wof:name":"Domanko",
    "wof:placetype":"locality"
},
  "geometry": {"coordinates":[0.18228,8.68752],"type":"Point"}
}