{
  "type": "Feature",
  "properties": {
    "gn:admin1_code":"00",
    "gn:asciiname":"Gwal",
    "gn:country_code":"GH",
    "gn:dem":303,
    "gn:feature_class":"P",
    "gn:feature_code":"PPL",
    "gn:name":"Gwal",
    "gn:population":0,
    "gn:timezone":"Africa/Accra",
    "iso:country":"GH",
    "name:und_x_variant":[
        "Gbal",
        "Gwal"
    ],
    "wof:name":"Gwal",
    "wof:placetype":"locality"
},
  "geometry": {"coordinates":[-2.32932,10.93548],"type":"Point"}
}