{
  "type": "Feature",
  "properties": {
    "gn:admin1_code":"00",
    "gn:asciiname":"Praso",
    "gn:country_code":"GH",
    "gn:dem":206,
    "gn:feature_class":"P",
    "gn:feature_code":"PPL",
    "gn:name":"Praso",
    "gn:population":0,
    "gn:timezone":"Africa/Accra",
    "iso:country":"GH",
    "name:und_x_variant":[
        "Praaso Konongo",
        "Praso"
    ],
    "wof:name":"Praso",
    "wof:placetype":"locality"
},
  "geometry": {"coordinates":[-1.26813,6.51431],"type":"Point"}
}