{
  "type": "Feature",
  "properties": {
    "gn:admin1_code":"09",
    "gn:asciiname":"Adamanso",
    "gn:country_code":"GH",
    "gn:dem":95,
    "gn:feature_class":"P",
    "gn:feature_code":"PPL",
    "gn:name":"Adamanso",
    "gn:population":0,
    "gn:timezone":"Africa/Accra",
    "iso:country":"GH",
    "name:eng_x_preferred":[
        "Adamanso"
    ],
    "wof:name":"Adamanso",
    "wof:placetype":"locality"
},
  "geometry": {"coordinates":[-2.04632,5.88282],"type":"Point"}
}