{
  "type": "Feature",
  "properties": {
    "gn:admin1_code":"00",
    "gn:asciiname":"Bakundiba",
    "gn:country_code":"GH",
    "gn:dem":138,
    "gn:feature_class":"P",
    "gn:feature_code":"PPL",
    "gn:name":"Bakundiba",
    "gn:population":0,
    "gn:timezone":"Africa/Accra",
    "iso:country":"GH",
    "wof:name":"Bakundiba",
    "wof:placetype":"locality"
},
  "geometry": {"coordinates":[0.1143,9.77105],"type":"Point"}
}