{
  "type": "Feature",
  "properties": {
    "gn:admin1_code":"03",
    "gn:asciiname":"Amkromkwanta",
    "gn:country_code":"GH",
    "gn:dem":228,
    "gn:feature_class":"P",
    "gn:feature_code":"PPL",
    "gn:name":"Amkromkwanta",
    "gn:population":0,
    "gn:timezone":"Africa/Accra",
    "iso:country":"GH",
    "name:eng_x_preferred":[
        "Amkromkwanta"
    ],
    "name:und_x_variant":[
        "Nkrankwanta",
        "Ankrakwanto",
        "Ankrankwanta"
    ],
    "wof:name":"Amkromkwanta",
    "wof:placetype":"locality"
},
  "geometry": {"coordinates":[-3.04536,7.0222],"type":"Point"}
}