{
  "type": "Feature",
  "properties": {
    "gn:admin1_code":"00",
    "gn:asciiname":"Hanya",
    "gn:cc2":"GH",
    "gn:country_code":"GH",
    "gn:dem":19,
    "gn:feature_class":"P",
    "gn:feature_code":"PPL",
    "gn:name":"Hanya",
    "gn:population":0,
    "gn:timezone":"Africa/Accra",
    "iso:country":"GH",
    "name:und_x_variant":[
        "Ahanya",
        "Hanya"
    ],
    "wof:name":"Hanya",
    "wof:placetype":"locality"
},
  "geometry": {"coordinates":[0.06667,5.73333],"type":"Point"}
}