{
  "type": "Feature",
  "properties": {
    "gn:admin1_code":"00",
    "gn:asciiname":"Yiripani",
    "gn:country_code":"GH",
    "gn:dem":142,
    "gn:feature_class":"P",
    "gn:feature_code":"PPL",
    "gn:name":"Yiripani",
    "gn:population":0,
    "gn:timezone":"Africa/Accra",
    "iso:country":"GH",
    "name:und_x_variant":[
        "Yiripali",
        "Yiripani"
    ],
    "wof:name":"Yiripani",
    "wof:placetype":"locality"
},
  "geometry": {"coordinates":[-1.09834,9.26837],"type":"Point"}
}