{
  "type": "Feature",
  "properties": {
    "gn:admin1_code":"01",
    "gn:asciiname":"Ahireso",
    "gn:country_code":"GH",
    "gn:dem":103,
    "gn:feature_class":"P",
    "gn:feature_code":"PPL",
    "gn:name":"Ahireso",
    "gn:population":0,
    "gn:timezone":"Africa/Accra",
    "iso:country":"GH",
    "wof:name":"Ahireso",
    "wof:placetype":"locality"
},
  "geometry": {"coordinates":[-0.51806,5.62336],"type":"Point"}
}