{
  "type": "Feature",
  "properties": {
    "gn:admin1_code":"09",
    "gn:asciiname":"Ebunaso",
    "gn:country_code":"GH",
    "gn:dem":75,
    "gn:feature_class":"P",
    "gn:feature_code":"PPL",
    "gn:name":"Ebunaso",
    "gn:population":0,
    "gn:timezone":"Africa/Accra",
    "iso:country":"GH",
    "name:eng_x_preferred":[
        "Ebunaso"
    ],
    "wof:name":"Ebunaso",
    "wof:placetype":"locality"
},
  "geometry": {"coordinates":[-1.89728,5.0816],"type":"Point"}
}