{
  "type": "Feature",
  "properties": {
    "gn:admin1_code":"02",
    "gn:asciiname":"Mosikrom",
    "gn:country_code":"GH",
    "gn:dem":143,
    "gn:feature_class":"P",
    "gn:feature_code":"PPL",
    "gn:name":"Mosikrom",
    "gn:population":0,
    "gn:timezone":"Africa/Accra",
    "iso:country":"GH",
    "name:und_x_variant":[
        "Mosikurom",
        "Mosikrom"
    ],
    "wof:name":"Mosikrom",
    "wof:placetype":"locality"
},
  "geometry": {"coordinates":[-1.89513,6.31954],"type":"Point"}
}