{
  "type": "Feature",
  "properties": {
    "gn:admin1_code":"00",
    "gn:asciiname":"Breponsu",
    "gn:country_code":"GH",
    "gn:dem":520,
    "gn:feature_class":"P",
    "gn:feature_code":"PPL",
    "gn:name":"Breponsu",
    "gn:population":0,
    "gn:timezone":"Africa/Accra",
    "iso:country":"GH",
    "wof:name":"Breponsu",
    "wof:placetype":"locality"
},
  "geometry": {"coordinates":[-0.24469,6.31955],"type":"Point"}
}