{
  "type": "Feature",
  "properties": {
    "gn:admin1_code":"10",
    "gn:asciiname":"Datoko",
    "gn:cc2":"GH",
    "gn:country_code":"GH",
    "gn:dem":190,
    "gn:feature_class":"P",
    "gn:feature_code":"PPL",
    "gn:name":"Datoko",
    "gn:population":0,
    "gn:timezone":"Africa/Accra",
    "iso:country":"GH",
    "name:und_x_variant":[
        "Datuku",
        "Datoko"
    ],
    "wof:name":"Datoko",
    "wof:placetype":"locality"
},
  "geometry": {"coordinates":[-0.64972,10.70583],"type":"Point"}
}