{
  "type": "Feature",
  "properties": {
    "gn:admin1_code":"09",
    "gn:asciiname":"Essem",
    "gn:country_code":"GH",
    "gn:dem":192,
    "gn:feature_class":"P",
    "gn:feature_code":"PPL",
    "gn:name":"Essem",
    "gn:population":0,
    "gn:timezone":"Africa/Accra",
    "iso:country":"GH",
    "name:eng_x_preferred":[
        "Essem"
    ],
    "name:eng_x_variant":[
        "Esem"
    ],
    "wof:name":"Essem",
    "wof:placetype":"locality"
},
  "geometry": {"coordinates":[-3.11005,6.66645],"type":"Point"}
}