{
  "type": "Feature",
  "properties": {
    "gn:admin1_code":"00",
    "gn:asciiname":"Oforamasi",
    "gn:country_code":"GH",
    "gn:dem":115,
    "gn:feature_class":"P",
    "gn:feature_code":"PPL",
    "gn:name":"Oforamasi",
    "gn:population":0,
    "gn:timezone":"Africa/Accra",
    "iso:country":"GH",
    "name:und_x_variant":[
        "Oforomase",
        "Oforamasi"
    ],
    "wof:name":"Oforamasi",
    "wof:placetype":"locality"
},
  "geometry": {"coordinates":[-0.79622,5.59073],"type":"Point"}
}