{
  "type": "Feature",
  "properties": {
    "gn:admin1_code":"00",
    "gn:asciiname":"Tibogona",
    "gn:country_code":"GH",
    "gn:dem":148,
    "gn:feature_class":"P",
    "gn:feature_code":"PPL",
    "gn:name":"Tibogona",
    "gn:population":0,
    "gn:timezone":"Africa/Accra",
    "iso:country":"GH",
    "name:und_x_variant":[
        "Tali Tibogu",
        "Tibogo",
        "Tibogona"
    ],
    "wof:name":"Tibogona",
    "wof:placetype":"locality"
},
  "geometry": {"coordinates":[-1.24337,9.4992],"type":"Point"}
}