{
  "type": "Feature",
  "properties": {
    "gn:admin1_code":"00",
    "gn:asciiname":"Badasi",
    "gn:country_code":"GH",
    "gn:dem":41,
    "gn:feature_class":"P",
    "gn:feature_code":"PPL",
    "gn:name":"Badasi",
    "gn:population":0,
    "gn:timezone":"Africa/Accra",
    "iso:country":"GH",
    "wof:name":"Badasi",
    "wof:placetype":"locality"
},
  "geometry": {"coordinates":[0.38578,6.29919],"type":"Point"}
}