{
  "type": "Feature",
  "properties": {
    "gn:admin1_code":"02",
    "gn:asciiname":"Poano",
    "gn:country_code":"GH",
    "gn:dem":203,
    "gn:feature_class":"P",
    "gn:feature_code":"PPL",
    "gn:name":"Poano",
    "gn:population":0,
    "gn:timezone":"Africa/Accra",
    "iso:country":"GH",
    "name:und_x_variant":[
        "Pano",
        "Poano",
        "Poanu"
    ],
    "wof:name":"Poano",
    "wof:placetype":"locality"
},
  "geometry": {"coordinates":[-1.68032,6.43644],"type":"Point"}
}