{
  "type": "Feature",
  "properties": {
    "gn:admin1_code":"11",
    "gn:asciiname":"Takpo",
    "gn:country_code":"GH",
    "gn:dem":286,
    "gn:feature_class":"P",
    "gn:feature_code":"PPL",
    "gn:name":"Takpo",
    "gn:population":0,
    "gn:timezone":"Africa/Accra",
    "iso:country":"GH",
    "name:und_x_variant":[
        "Tappo"
    ],
    "wof:name":"Takpo",
    "wof:placetype":"locality"
},
  "geometry": {"coordinates":[-2.65014,10.21399],"type":"Point"}
}