{
  "type": "Feature",
  "properties": {
    "gn:admin1_code":"00",
    "gn:asciiname":"Agokpo",
    "gn:country_code":"GH",
    "gn:dem":290,
    "gn:feature_class":"P",
    "gn:feature_code":"PPL",
    "gn:name":"Agokpo",
    "gn:population":0,
    "gn:timezone":"Africa/Accra",
    "iso:country":"GH",
    "name:und_x_variant":[
        "Agokpo Saviepe",
        "Agokpo"
    ],
    "wof:name":"Agokpo",
    "wof:placetype":"locality"
},
  "geometry": {"coordinates":[0.41058,6.78077],"type":"Point"}
}