{
  "type": "Feature",
  "properties": {
    "gn:admin1_code":"09",
    "gn:asciiname":"Echei",
    "gn:country_code":"GH",
    "gn:dem":77,
    "gn:feature_class":"P",
    "gn:feature_code":"PPL",
    "gn:name":"Echei",
    "gn:population":0,
    "gn:timezone":"Africa/Accra",
    "iso:country":"GH",
    "name:eng_x_preferred":[
        "Echei"
    ],
    "wof:name":"Echei",
    "wof:placetype":"locality"
},
  "geometry": {"coordinates":[-1.68238,5.17956],"type":"Point"}
}