{
  "type": "Feature",
  "properties": {
    "gn:admin1_code":"01",
    "gn:asciiname":"Odumasi",
    "gn:country_code":"GH",
    "gn:dem":105,
    "gn:feature_class":"P",
    "gn:feature_code":"PPL",
    "gn:name":"Odumasi",
    "gn:population":0,
    "gn:timezone":"Africa/Accra",
    "iso:country":"GH",
    "name:und_x_variant":[
        "Odumase Number 1",
        "Odumasi"
    ],
    "wof:name":"Odumasi",
    "wof:placetype":"locality"
},
  "geometry": {"coordinates":[-0.57568,5.75648],"type":"Point"}
}