{
  "type": "Feature",
  "properties": {
    "gn:admin1_code":"00",
    "gn:asciiname":"Aserima",
    "gn:cc2":"GH",
    "gn:country_code":"GH",
    "gn:dem":365,
    "gn:feature_class":"P",
    "gn:feature_code":"PPL",
    "gn:name":"Aserima",
    "gn:population":0,
    "gn:timezone":"Africa/Accra",
    "iso:country":"GH",
    "name:und_x_variant":[
        "Aserema",
        "Aserima"
    ],
    "wof:name":"Aserima",
    "wof:placetype":"locality"
},
  "geometry": {"coordinates":[-0.08333,6.06667],"type":"Point"}
}