{
  "type": "Feature",
  "properties": {
    "gn:admin1_code":"00",
    "gn:asciiname":"Adiembra",
    "gn:country_code":"GH",
    "gn:dem":139,
    "gn:feature_class":"P",
    "gn:feature_code":"PPL",
    "gn:name":"Adiembra",
    "gn:population":0,
    "gn:timezone":"Africa/Accra",
    "iso:country":"GH",
    "wof:name":"Adiembra",
    "wof:placetype":"locality"
},
  "geometry": {"coordinates":[-1.29496,5.67964],"type":"Point"}
}