{
  "type": "Feature",
  "properties": {
    "gn:admin1_code":"02",
    "gn:asciiname":"Sampruso",
    "gn:country_code":"GH",
    "gn:dem":216,
    "gn:feature_class":"P",
    "gn:feature_code":"PPL",
    "gn:name":"Sampruso",
    "gn:population":0,
    "gn:timezone":"Africa/Accra",
    "iso:country":"GH",
    "name:eng_x_preferred":[
        "Sampruso"
    ],
    "wof:name":"Sampruso",
    "wof:placetype":"locality"
},
  "geometry": {"coordinates":[-1.82137,6.71358],"type":"Point"}
}