{
  "type": "Feature",
  "properties": {
    "gn:admin1_code":"00",
    "gn:asciiname":"Biyemba",
    "gn:country_code":"GH",
    "gn:dem":210,
    "gn:feature_class":"P",
    "gn:feature_code":"PPL",
    "gn:name":"Biyemba",
    "gn:population":0,
    "gn:timezone":"Africa/Accra",
    "iso:country":"GH",
    "name:und_x_variant":[
        "Briyemba",
        "Biyimba",
        "Bligemba",
        "Biyemba"
    ],
    "wof:name":"Biyemba",
    "wof:placetype":"locality"
},
  "geometry": {"coordinates":[0.04233,10.07369],"type":"Point"}
}