{
  "type": "Feature",
  "properties": {
    "gn:admin1_code":"03",
    "gn:asciiname":"Aboabo Number Two",
    "gn:country_code":"GH",
    "gn:dem":296,
    "gn:feature_class":"P",
    "gn:feature_code":"PPL",
    "gn:name":"Aboabo Number Two",
    "gn:population":0,
    "gn:timezone":"Africa/Accra",
    "iso:country":"GH",
    "name:eng_x_preferred":[
        "Aboabo Number Two"
    ],
    "name:eng_x_variant":[
        "Kuasi"
    ],
    "name:und_x_variant":[
        "Aboabo Number 2",
        "Adukwatukrom",
        "Asutifi",
        "Aboabo Number 3",
        "Aboabo"
    ],
    "wof:name":"Aboabo Number Two",
    "wof:placetype":"locality"
},
  "geometry": {"coordinates":[-2.80825,7.20974],"type":"Point"}
}