{
  "type": "Feature",
  "properties": {
    "gn:admin1_code":"02",
    "gn:asciiname":"Apuayem",
    "gn:country_code":"GH",
    "gn:dem":209,
    "gn:feature_class":"P",
    "gn:feature_code":"PPL",
    "gn:name":"Apuayem",
    "gn:population":0,
    "gn:timezone":"Africa/Accra",
    "iso:country":"GH",
    "name:eng_x_preferred":[
        "Apuayem"
    ],
    "wof:name":"Apuayem",
    "wof:placetype":"locality"
},
  "geometry": {"coordinates":[-1.86149,6.7222],"type":"Point"}
}