{
  "type": "Feature",
  "properties": {
    "gn:admin1_code":"00",
    "gn:asciiname":"Datano",
    "gn:country_code":"GH",
    "gn:dem":94,
    "gn:feature_class":"P",
    "gn:feature_code":"PPL",
    "gn:name":"Datano",
    "gn:population":0,
    "gn:timezone":"Africa/Accra",
    "iso:country":"GH",
    "wof:name":"Datano",
    "wof:placetype":"locality"
},
  "geometry": {"coordinates":[-2.56667,5.46667],"type":"Point"}
}