{
  "type": "Feature",
  "properties": {
    "gn:admin1_code":"00",
    "gn:asciiname":"Achwa",
    "gn:country_code":"GH",
    "gn:dem":17,
    "gn:feature_class":"P",
    "gn:feature_code":"PPL",
    "gn:name":"Achwa",
    "gn:population":0,
    "gn:timezone":"Africa/Accra",
    "iso:country":"GH",
    "wof:name":"Achwa",
    "wof:placetype":"locality"
},
  "geometry": {"coordinates":[-0.91667,5.23333],"type":"Point"}
}