{
  "type": "Feature",
  "properties": {
    "gn:admin1_code":"00",
    "gn:asciiname":"Manchekope",
    "gn:country_code":"GH",
    "gn:dem":9,
    "gn:feature_class":"P",
    "gn:feature_code":"PPL",
    "gn:name":"Manchekope",
    "gn:population":0,
    "gn:timezone":"Africa/Accra",
    "iso:country":"GH",
    "name:und_x_variant":[
        "Maatsekorpe",
        "Manchekope"
    ],
    "wof:name":"Manchekope",
    "wof:placetype":"locality"
},
  "geometry": {"coordinates":[0.44694,5.86751],"type":"Point"}
}