{
  "type": "Feature",
  "properties": {
    "iso:country":"GH",
    "name:ceb_x_preferred":[
        "Ejura"
    ],
    "name:deu_x_preferred":[
        "Ejura"
    ],
    "name:eng_x_preferred":[
        "Ejura"
    ],
    "name:fra_x_preferred":[
        "Ejura"
    ],
    "name:ita_x_preferred":[
        "Ejura"
    ],
    "name:jpn_x_preferred":[
        "\u30a8\u30b8\u30e5\u30e9"
    ],
    "name:nld_x_preferred":[
        "Ejura"
    ],
    "name:pol_x_preferred":[
        "Ejura"
    ],
    "name:spa_x_preferred":[
        "Ejura"
    ],
    "name:swa_x_preferred":[
        "Ejura"
    ],
    "name:swe_x_preferred":[
        "Ejura"
    ],
    "name:twi_x_preferred":[
        "Ejura"
    ],
    "name:urd_x_preferred":[
        "\u0639\u062c\u0648\u0631\u0627"
    ],
    "qs:gn_country":"GH",
    "qs:gn_fcode":"PPL",
    "qs:gn_pop":43403,
    "qs:name":"Ejura",
    "qs:name_adm0":"Ghana",
    "qs:name_adm1":"Ashanti",
    "qs:photos":0,
    "qs:photos_1k":0,
    "qs:photos_9k":0,
    "qs:photos_9r":0,
    "qs:photos_all":0,
    "qs:photos_sr":0,
    "qs:placetype":"Town",
    "qs:pop_sr":"7",
    "qs:woe_adm0":23424824,
    "wd:wordcount":100,
    "wof:name":"Ejura",
    "wof:placetype":"locality",
    "wof:population":43403
},
  "geometry": {"coordinates":[-1.35617,7.38558],"type":"Point"}
}