{
  "type": "Feature",
  "properties": {
    "gn:admin1_code":"02",
    "gn:asciiname":"Odumkesie",
    "gn:country_code":"GH",
    "gn:dem":228,
    "gn:feature_class":"P",
    "gn:feature_code":"PPL",
    "gn:name":"Odumkesie",
    "gn:population":0,
    "gn:timezone":"Africa/Accra",
    "iso:country":"GH",
    "name:eng_x_preferred":[
        "Odumkesie"
    ],
    "wof:name":"Odumkesie",
    "wof:placetype":"locality"
},
  "geometry": {"coordinates":[-1.75468,6.54974],"type":"Point"}
}