{
  "type": "Feature",
  "properties": {
    "gn:admin1_code":"06",
    "gn:asciiname":"Sekpe",
    "gn:country_code":"GH",
    "gn:dem":222,
    "gn:feature_class":"P",
    "gn:feature_code":"PPL",
    "gn:name":"Sekpe",
    "gn:population":0,
    "gn:timezone":"Africa/Accra",
    "iso:country":"GH",
    "name:und_x_variant":[
        "Sekwi",
        "Sakpe",
        "Sekwe",
        "Sekpe"
    ],
    "wof:name":"Sekpe",
    "wof:placetype":"locality"
},
  "geometry": {"coordinates":[-0.26687,9.58165],"type":"Point"}
}