{
  "type": "Feature",
  "properties": {
    "gn:admin1_code":"01",
    "gn:asciiname":"Ofrajato",
    "gn:country_code":"GH",
    "gn:dem":95,
    "gn:feature_class":"P",
    "gn:feature_code":"PPL",
    "gn:name":"Ofrajato",
    "gn:population":0,
    "gn:timezone":"Africa/Accra",
    "iso:country":"GH",
    "name:und_x_variant":[
        "Ofrajato Number 1",
        "Ofagyato Nyamebedzi",
        "Ofrajato"
    ],
    "wof:name":"Ofrajato",
    "wof:placetype":"locality"
},
  "geometry": {"coordinates":[-0.51667,5.65],"type":"Point"}
}