{
  "type": "Feature",
  "properties": {
    "gn:admin1_code":"11",
    "gn:asciiname":"Yala",
    "gn:country_code":"GH",
    "gn:dem":222,
    "gn:feature_class":"P",
    "gn:feature_code":"PPL",
    "gn:name":"Yala",
    "gn:population":0,
    "gn:timezone":"Africa/Accra",
    "iso:country":"GH",
    "name:ceb_x_preferred":[
        "Yala"
    ],
    "name:deu_x_preferred":[
        "Yala"
    ],
    "name:fra_x_preferred":[
        "Yala"
    ],
    "name:ita_x_preferred":[
        "Yala"
    ],
    "name:nld_x_preferred":[
        "Yala"
    ],
    "name:pnb_x_preferred":[
        "\u06cc\u0627\u0644\u0627"
    ],
    "name:pol_x_preferred":[
        "Yala"
    ],
    "name:rus_x_preferred":[
        "\u042f\u043b\u0430"
    ],
    "name:sco_x_preferred":[
        "Yala"
    ],
    "name:swe_x_preferred":[
        "Yala"
    ],
    "name:tha_x_preferred":[
        "\u0e22\u0e30\u0e25\u0e32"
    ],
    "wof:name":"Yala",
    "wof:placetype":"locality"
},
  "geometry": {"coordinates":[-1.83912,10.12702],"type":"Point"}
}