{
  "type": "Feature",
  "properties": {
    "gn:admin1_code":"11",
    "gn:asciiname":"Yala",
    "gn:country_code":"GH",
    "gn:dem":222,
    "gn:feature_class":"P",
    "gn:feature_code":"PPL",
    "gn:name":"Yala",
    "gn:population":0,
    "gn:timezone":"Africa/Accra",
    "iso:country":"GH",
    "wof:name":"Yala",
    "wof:placetype":"locality"
},
  "geometry": {"coordinates":[-1.83912,10.12702],"type":"Point"}
}