{
  "type": "Feature",
  "properties": {
    "gn:admin1_code":"00",
    "gn:asciiname":"Wuratinkong",
    "gn:country_code":"GH",
    "gn:dem":128,
    "gn:feature_class":"P",
    "gn:feature_code":"PPL",
    "gn:name":"Wuratinkong",
    "gn:population":0,
    "gn:timezone":"Africa/Accra",
    "iso:country":"GH",
    "wof:name":"Wuratinkong",
    "wof:placetype":"locality"
},
  "geometry": {"coordinates":[-1.40543,5.84288],"type":"Point"}
}