{
  "type": "Feature",
  "properties": {
    "gn:admin1_code":"00",
    "gn:asciiname":"Debisa",
    "gn:country_code":"GH",
    "gn:dem":67,
    "gn:feature_class":"P",
    "gn:feature_code":"PPL",
    "gn:name":"Debisa",
    "gn:population":0,
    "gn:timezone":"Africa/Accra",
    "iso:country":"GH",
    "name:und_x_variant":[
        "Apiah Kwa Debiso",
        "Debiso",
        "Debisa"
    ],
    "wof:name":"Debisa",
    "wof:placetype":"locality"
},
  "geometry": {"coordinates":[-0.86433,5.46259],"type":"Point"}
}