{
  "type": "Feature",
  "properties": {
    "gn:admin1_code":"00",
    "gn:asciiname":"Biseasi",
    "gn:country_code":"GH",
    "gn:dem":90,
    "gn:feature_class":"P",
    "gn:feature_code":"PPL",
    "gn:name":"Biseasi",
    "gn:population":0,
    "gn:timezone":"Africa/Accra",
    "iso:country":"GH",
    "name:und_x_variant":[
        "Besease",
        "Biseasi"
    ],
    "wof:name":"Biseasi",
    "wof:placetype":"locality"
},
  "geometry": {"coordinates":[-0.97725,5.4596],"type":"Point"}
}