{
  "type": "Feature",
  "properties": {
    "gn:admin1_code":"00",
    "gn:asciiname":"Domefe",
    "gn:country_code":"GH",
    "gn:dem":137,
    "gn:feature_class":"P",
    "gn:feature_code":"PPL",
    "gn:name":"Domefe",
    "gn:population":0,
    "gn:timezone":"Africa/Accra",
    "iso:country":"GH",
    "wof:name":"Domefe",
    "wof:placetype":"locality"
},
  "geometry": {"coordinates":[0.35505,6.76617],"type":"Point"}
}