{
  "type": "Feature",
  "properties": {
    "gn:admin1_code":"11",
    "gn:asciiname":"Erimon",
    "gn:country_code":"GH",
    "gn:dem":289,
    "gn:feature_class":"P",
    "gn:feature_code":"PPL",
    "gn:name":"Erimon",
    "gn:population":0,
    "gn:timezone":"Africa/Accra",
    "iso:country":"GH",
    "name:eng_x_preferred":[
        "Erimon"
    ],
    "name:und_x_variant":[
        "Arumon"
    ],
    "wof:name":"Erimon",
    "wof:placetype":"locality"
},
  "geometry": {"coordinates":[-2.7907,10.66526],"type":"Point"}
}