{
  "type": "Feature",
  "properties": {
    "gn:admin1_code":"00",
    "gn:asciiname":"Adaprasi",
    "gn:country_code":"GH",
    "gn:dem":152,
    "gn:feature_class":"P",
    "gn:feature_code":"PPL",
    "gn:name":"Adaprasi",
    "gn:population":0,
    "gn:timezone":"Africa/Accra",
    "iso:country":"GH",
    "name:und_x_variant":[
        "Adaprase",
        "Adaprasi"
    ],
    "wof:name":"Adaprasi",
    "wof:placetype":"locality"
},
  "geometry": {"coordinates":[-1.27231,7.94951],"type":"Point"}
}