{
  "type": "Feature",
  "properties": {
    "gn:admin1_code":"09",
    "gn:asciiname":"Esuaso",
    "gn:country_code":"GH",
    "gn:dem":75,
    "gn:feature_class":"P",
    "gn:feature_code":"PPL",
    "gn:name":"Esuaso",
    "gn:population":0,
    "gn:timezone":"Africa/Accra",
    "iso:country":"GH",
    "name:und_x_variant":[
        "Asuaso",
        "Esuaso"
    ],
    "wof:name":"Esuaso",
    "wof:placetype":"locality"
},
  "geometry": {"coordinates":[-1.93293,5.1978],"type":"Point"}
}