{
  "type": "Feature",
  "properties": {
    "gn:admin1_code":"00",
    "gn:asciiname":"Nyimbunga",
    "gn:country_code":"GH",
    "gn:dem":155,
    "gn:feature_class":"P",
    "gn:feature_code":"PPL",
    "gn:name":"Nyimbunga",
    "gn:population":0,
    "gn:timezone":"Africa/Accra",
    "iso:country":"GH",
    "name:und_x_variant":[
        "Nimbunga",
        "Nyimbunga"
    ],
    "wof:name":"Nyimbunga",
    "wof:placetype":"locality"
},
  "geometry": {"coordinates":[-0.72193,10.04635],"type":"Point"}
}