{
  "type": "Feature",
  "properties": {
    "gn:admin1_code":"00",
    "gn:asciiname":"Denteso",
    "gn:country_code":"GH",
    "gn:dem":153,
    "gn:feature_class":"P",
    "gn:feature_code":"PPL",
    "gn:name":"Denteso",
    "gn:population":0,
    "gn:timezone":"Africa/Accra",
    "iso:country":"GH",
    "wof:name":"Denteso",
    "wof:placetype":"locality"
},
  "geometry": {"coordinates":[-1.17171,7.49727],"type":"Point"}
}