{
  "type": "Feature",
  "properties": {
    "gn:admin1_code":"00",
    "gn:asciiname":"Fuo",
    "gn:country_code":"GH",
    "gn:dem":107,
    "gn:feature_class":"P",
    "gn:feature_code":"PPL",
    "gn:name":"Fuo",
    "gn:population":0,
    "gn:timezone":"Africa/Accra",
    "iso:country":"GH",
    "name:und_x_variant":[
        "Fu",
        "Fuu",
        "Fuo"
    ],
    "wof:name":"Fuo",
    "wof:placetype":"locality"
},
  "geometry": {"coordinates":[-0.62645,9.26679],"type":"Point"}
}