{
  "type": "Feature",
  "properties": {
    "gn:admin1_code":"00",
    "gn:asciiname":"Asebuga",
    "gn:country_code":"GH",
    "gn:dem":249,
    "gn:feature_class":"P",
    "gn:feature_code":"PPL",
    "gn:name":"Asebuga",
    "gn:population":0,
    "gn:timezone":"Africa/Accra",
    "iso:country":"GH",
    "wof:name":"Asebuga",
    "wof:placetype":"locality"
},
  "geometry": {"coordinates":[-0.74148,10.91806],"type":"Point"}
}