{
  "type": "Feature",
  "properties": {
    "gn:admin1_code":"00",
    "gn:asciiname":"Anfeo",
    "gn:cc2":"GH",
    "gn:country_code":"GH",
    "gn:dem":70,
    "gn:feature_class":"P",
    "gn:feature_code":"PPL",
    "gn:name":"Anfeo",
    "gn:population":0,
    "gn:timezone":"Africa/Accra",
    "iso:country":"GH",
    "name:und_x_variant":[
        "Aufeo",
        "Anfeo"
    ],
    "wof:name":"Anfeo",
    "wof:placetype":"locality"
},
  "geometry": {"coordinates":[-1.06667,5.23333],"type":"Point"}
}