{
  "type": "Feature",
  "properties": {
    "gn:admin1_code":"01",
    "gn:asciiname":"Obakrowe",
    "gn:country_code":"GH",
    "gn:dem":40,
    "gn:feature_class":"P",
    "gn:feature_code":"PPL",
    "gn:name":"Obakrowe",
    "gn:population":0,
    "gn:timezone":"Africa/Accra",
    "iso:country":"GH",
    "name:eng_x_preferred":[
        "Obakrowe"
    ],
    "name:eng_x_variant":[
        "Obakrowa"
    ],
    "wof:name":"Obakrowe",
    "wof:placetype":"locality"
},
  "geometry": {"coordinates":[-0.40019,5.67519],"type":"Point"}
}