{
  "type": "Feature",
  "properties": {
    "gn:admin1_code":"00",
    "gn:asciiname":"Degedege",
    "gn:country_code":"GH",
    "gn:dem":256,
    "gn:feature_class":"P",
    "gn:feature_code":"PPL",
    "gn:name":"Degedege",
    "gn:population":0,
    "gn:timezone":"Africa/Accra",
    "iso:country":"GH",
    "wof:name":"Degedege",
    "wof:placetype":"locality"
},
  "geometry": {"coordinates":[-2.44171,7.79025],"type":"Point"}
}