{
  "type": "Feature",
  "properties": {
    "gn:admin1_code":"00",
    "gn:asciiname":"Kungkungbonge",
    "gn:country_code":"GH",
    "gn:dem":157,
    "gn:feature_class":"P",
    "gn:feature_code":"PPL",
    "gn:name":"Kungkungbonge",
    "gn:population":0,
    "gn:timezone":"Africa/Accra",
    "iso:country":"GH",
    "wof:name":"Kungkungbonge",
    "wof:placetype":"locality"
},
  "geometry": {"coordinates":[0.15128,10.47114],"type":"Point"}
}