{
  "type": "Feature",
  "properties": {
    "gn:admin1_code":"00",
    "gn:asciiname":"Atarakom",
    "gn:country_code":"GH",
    "gn:dem":225,
    "gn:feature_class":"P",
    "gn:feature_code":"PPL",
    "gn:name":"Atarakom",
    "gn:population":0,
    "gn:timezone":"Africa/Accra",
    "iso:country":"GH",
    "name:und_x_variant":[
        "Tarikomtili",
        "Atarakom"
    ],
    "wof:name":"Atarakom",
    "wof:placetype":"locality"
},
  "geometry": {"coordinates":[-0.52902,10.86541],"type":"Point"}
}