{
  "type": "Feature",
  "properties": {
    "gn:admin1_code":"04",
    "gn:asciiname":"Domenase",
    "gn:country_code":"GH",
    "gn:dem":132,
    "gn:feature_class":"P",
    "gn:feature_code":"PPL",
    "gn:name":"Domenase",
    "gn:population":0,
    "gn:timezone":"Africa/Accra",
    "iso:country":"GH",
    "name:eng_x_preferred":[
        "Domenase"
    ],
    "name:und_x_variant":[
        "Dominase",
        "Domenasi"
    ],
    "wof:name":"Domenase",
    "wof:placetype":"locality"
},
  "geometry": {"coordinates":[-1.96202,6.04754],"type":"Point"}
}