{
  "type": "Feature",
  "properties": {
    "gn:admin1_code":"00",
    "gn:asciiname":"Kpokofe",
    "gn:country_code":"GH",
    "gn:dem":56,
    "gn:feature_class":"P",
    "gn:feature_code":"PPL",
    "gn:name":"Kpokofe",
    "gn:population":0,
    "gn:timezone":"Africa/Accra",
    "iso:country":"GH",
    "name:und_x_variant":[
        "Kpokorpe",
        "Kpokofe"
    ],
    "wof:name":"Kpokofe",
    "wof:placetype":"locality"
},
  "geometry": {"coordinates":[0.52417,6.2462],"type":"Point"}
}