{
  "type": "Feature",
  "properties": {
    "gn:admin1_code":"00",
    "gn:asciiname":"Bepoasi",
    "gn:country_code":"GH",
    "gn:dem":324,
    "gn:feature_class":"P",
    "gn:feature_code":"PPL",
    "gn:name":"Bepoasi",
    "gn:population":0,
    "gn:timezone":"Africa/Accra",
    "iso:country":"GH",
    "name:und_x_variant":[
        "Bepoase",
        "Bepoasi"
    ],
    "wof:name":"Bepoasi",
    "wof:placetype":"locality"
},
  "geometry": {"coordinates":[-2.55749,7.77395],"type":"Point"}
}