{
  "type": "Feature",
  "properties": {
    "gn:admin1_code":"01",
    "gn:asciiname":"Esuochwi",
    "gn:country_code":"GH",
    "gn:dem":86,
    "gn:feature_class":"P",
    "gn:feature_code":"PPL",
    "gn:name":"Esuochwi",
    "gn:population":0,
    "gn:timezone":"Africa/Accra",
    "iso:country":"GH",
    "name:und_x_variant":[
        "Asuokyene",
        "Esuochwi"
    ],
    "wof:name":"Esuochwi",
    "wof:placetype":"locality"
},
  "geometry": {"coordinates":[-0.54145,5.7897],"type":"Point"}
}