{
  "type": "Feature",
  "properties": {
    "gn:admin1_code":"02",
    "gn:asciiname":"Odumasi",
    "gn:country_code":"GH",
    "gn:dem":200,
    "gn:feature_class":"P",
    "gn:feature_code":"PPL",
    "gn:name":"Odumasi",
    "gn:population":0,
    "gn:timezone":"Africa/Accra",
    "iso:country":"GH",
    "name:eng_x_preferred":[
        "Odumasi"
    ],
    "wof:name":"Odumasi",
    "wof:placetype":"locality"
},
  "geometry": {"coordinates":[-1.82225,6.4527],"type":"Point"}
}