{
  "type": "Feature",
  "properties": {
    "gn:admin1_code":"09",
    "gn:asciiname":"Tintinso",
    "gn:country_code":"GH",
    "gn:dem":117,
    "gn:feature_class":"P",
    "gn:feature_code":"PPL",
    "gn:name":"Tintinso",
    "gn:population":0,
    "gn:timezone":"Africa/Accra",
    "iso:country":"GH",
    "name:eng_x_preferred":[
        "Tintinso"
    ],
    "wof:name":"Tintinso",
    "wof:placetype":"locality"
},
  "geometry": {"coordinates":[-1.72274,5.24535],"type":"Point"}
}