{
  "type": "Feature",
  "properties": {
    "gn:admin1_code":"02",
    "gn:asciiname":"Hinimang",
    "gn:country_code":"GH",
    "gn:dem":202,
    "gn:feature_class":"P",
    "gn:feature_code":"PPL",
    "gn:name":"Hinimang",
    "gn:population":0,
    "gn:timezone":"Africa/Accra",
    "iso:country":"GH",
    "name:eng_x_preferred":[
        "Hinimang"
    ],
    "wof:name":"Hinimang",
    "wof:placetype":"locality"
},
  "geometry": {"coordinates":[-1.57228,6.36698],"type":"Point"}
}