{
  "type": "Feature",
  "properties": {
    "gn:admin1_code":"00",
    "gn:asciiname":"Achlulu",
    "gn:country_code":"GH",
    "gn:dem":65,
    "gn:feature_class":"P",
    "gn:feature_code":"PPL",
    "gn:name":"Achlulu",
    "gn:population":0,
    "gn:timezone":"Africa/Accra",
    "iso:country":"GH",
    "wof:name":"Achlulu",
    "wof:placetype":"locality"
},
  "geometry": {"coordinates":[0.72581,6.33907],"type":"Point"}
}