{
  "type": "Feature",
  "properties": {
    "gn:admin1_code":"00",
    "gn:asciiname":"Suani",
    "gn:country_code":"GH",
    "gn:dem":32,
    "gn:feature_class":"P",
    "gn:feature_code":"PPL",
    "gn:name":"Suani",
    "gn:population":0,
    "gn:timezone":"Africa/Accra",
    "iso:country":"GH",
    "wof:name":"Suani",
    "wof:placetype":"locality"
},
  "geometry": {"coordinates":[-0.85,5.28333],"type":"Point"}
}