{
  "type": "Feature",
  "properties": {
    "gn:admin1_code":"06",
    "gn:asciiname":"Nakpanduri",
    "gn:country_code":"GH",
    "gn:dem":413,
    "gn:feature_class":"P",
    "gn:feature_code":"PPL",
    "gn:name":"Nakpanduri",
    "gn:population":0,
    "gn:timezone":"Africa/Accra",
    "iso:country":"GH",
    "name:und_x_variant":[
        "Nakp\u00e1ndure",
        "Nakpandur",
        "Nakpanduri"
    ],
    "wof:name":"Nakpanduri",
    "wof:placetype":"locality"
},
  "geometry": {"coordinates":[-0.18191,10.63195],"type":"Point"}
}