{
  "type": "Feature",
  "properties": {
    "gn:admin1_code":"02",
    "gn:asciiname":"Kurase",
    "gn:country_code":"GH",
    "gn:dem":223,
    "gn:feature_class":"P",
    "gn:feature_code":"PPL",
    "gn:name":"Kurase",
    "gn:population":0,
    "gn:timezone":"Africa/Accra",
    "iso:country":"GH",
    "name:und_x_variant":[
        "Kurasi"
    ],
    "wof:name":"Kurase",
    "wof:placetype":"locality"
},
  "geometry": {"coordinates":[-1.52728,6.47949],"type":"Point"}
}