{
  "type": "Feature",
  "properties": {
    "gn:admin1_code":"02",
    "gn:asciiname":"Akwasiase",
    "gn:country_code":"GH",
    "gn:dem":246,
    "gn:feature_class":"P",
    "gn:feature_code":"PPL",
    "gn:name":"Akwasiase",
    "gn:population":0,
    "gn:timezone":"Africa/Accra",
    "iso:country":"GH",
    "name:eng_x_preferred":[
        "Akwasiase"
    ],
    "name:eng_x_variant":[
        "Akwesiasi One"
    ],
    "name:und_x_variant":[
        "Akwesiase",
        "Akwesiasi Number 2",
        "Akwasiase Number 1",
        "Akwesiasi I"
    ],
    "wof:name":"Akwasiase",
    "wof:placetype":"locality"
},
  "geometry": {"coordinates":[-2.20128,6.99203],"type":"Point"}
}