{
  "type": "Feature",
  "properties": {
    "gn:admin1_code":"00",
    "gn:asciiname":"Zoabuliga",
    "gn:country_code":"GH",
    "gn:dem":230,
    "gn:feature_class":"P",
    "gn:feature_code":"PPL",
    "gn:name":"Zoabuliga",
    "gn:population":0,
    "gn:timezone":"Africa/Accra",
    "iso:country":"GH",
    "wof:name":"Zoabuliga",
    "wof:placetype":"locality"
},
  "geometry": {"coordinates":[-0.14696,11.03716],"type":"Point"}
}