{
  "type": "Feature",
  "properties": {
    "gn:admin1_code":"02",
    "gn:asciiname":"Bokwankye",
    "gn:country_code":"GH",
    "gn:dem":253,
    "gn:feature_class":"P",
    "gn:feature_code":"PPL",
    "gn:name":"Bokwankye",
    "gn:population":0,
    "gn:timezone":"Africa/Accra",
    "iso:country":"GH",
    "name:und_x_variant":[
        "Bokanchi"
    ],
    "wof:name":"Bokwankye",
    "wof:placetype":"locality"
},
  "geometry": {"coordinates":[-1.69422,6.72258],"type":"Point"}
}