{
  "type": "Feature",
  "properties": {
    "gn:admin1_code":"02",
    "gn:asciiname":"Adamso Number Two",
    "gn:country_code":"GH",
    "gn:dem":142,
    "gn:feature_class":"P",
    "gn:feature_code":"PPL",
    "gn:name":"Adamso Number Two",
    "gn:population":0,
    "gn:timezone":"Africa/Accra",
    "iso:country":"GH",
    "name:eng_x_preferred":[
        "Adamso Number Two"
    ],
    "name:eng_x_variant":[
        "Adamso",
        "Adamso Number 2"
    ],
    "wof:name":"Adamso Number Two",
    "wof:placetype":"locality"
},
  "geometry": {"coordinates":[-1.78338,6.06456],"type":"Point"}
}