{
  "type": "Feature",
  "properties": {
    "gn:admin1_code":"00",
    "gn:asciiname":"Boanim",
    "gn:country_code":"GH",
    "gn:dem":452,
    "gn:feature_class":"P",
    "gn:feature_code":"PPL",
    "gn:name":"Boanim",
    "gn:population":0,
    "gn:timezone":"Africa/Accra",
    "iso:country":"GH",
    "name:und_x_variant":[
        "Bonim",
        "Boanim"
    ],
    "wof:name":"Boanim",
    "wof:placetype":"locality"
},
  "geometry": {"coordinates":[-1.48997,7.03233],"type":"Point"}
}