{
  "type": "Feature",
  "properties": {
    "gn:admin1_code":"00",
    "gn:asciiname":"Amangfrom",
    "gn:country_code":"GH",
    "gn:dem":239,
    "gn:feature_class":"P",
    "gn:feature_code":"PPL",
    "gn:name":"Amangfrom",
    "gn:population":0,
    "gn:timezone":"Africa/Accra",
    "iso:country":"GH",
    "name:und_x_variant":[
        "Wirenkyiren Amanforo",
        "Amangfrom"
    ],
    "wof:name":"Amangfrom",
    "wof:placetype":"locality"
},
  "geometry": {"coordinates":[-0.51151,6.10698],"type":"Point"}
}