{
  "type": "Feature",
  "properties": {
    "gn:admin1_code":"00",
    "gn:asciiname":"Tamalago",
    "gn:country_code":"GH",
    "gn:dem":135,
    "gn:feature_class":"P",
    "gn:feature_code":"PPL",
    "gn:name":"Tamalago",
    "gn:population":0,
    "gn:timezone":"Africa/Accra",
    "iso:country":"GH",
    "name:und_x_variant":[
        "Tamaligu",
        "Tamalago"
    ],
    "wof:name":"Tamalago",
    "wof:placetype":"locality"
},
  "geometry": {"coordinates":[-0.7292,9.85168],"type":"Point"}
}