{
  "type": "Feature",
  "properties": {
    "gn:admin1_code":"00",
    "gn:asciiname":"Adansemem",
    "gn:country_code":"GH",
    "gn:dem":37,
    "gn:feature_class":"P",
    "gn:feature_code":"PPL",
    "gn:name":"Adansemem",
    "gn:population":0,
    "gn:timezone":"Africa/Accra",
    "iso:country":"GH",
    "name:und_x_variant":[
        "Adansemanmu",
        "Adansimen",
        "Adansemem"
    ],
    "wof:name":"Adansemem",
    "wof:placetype":"locality"
},
  "geometry": {"coordinates":[-0.8812,5.26042],"type":"Point"}
}