{
  "type": "Feature",
  "properties": {
    "gn:admin1_code":"00",
    "gn:asciiname":"Kasa",
    "gn:country_code":"GH",
    "gn:dem":169,
    "gn:feature_class":"P",
    "gn:feature_code":"PPL",
    "gn:name":"Kasa",
    "gn:population":0,
    "gn:timezone":"Africa/Accra",
    "iso:country":"GH",
    "name:aze_x_preferred":[
        "Kasa"
    ],
    "name:ceb_x_preferred":[
        "Kasa"
    ],
    "name:deu_x_preferred":[
        "Kasa"
    ],
    "name:fra_x_preferred":[
        "Kasa"
    ],
    "name:ind_x_preferred":[
        "Kasa"
    ],
    "name:ita_x_preferred":[
        "Kasa"
    ],
    "name:pol_x_preferred":[
        "Kasa"
    ],
    "name:que_x_preferred":[
        "Kasa"
    ],
    "name:spa_x_preferred":[
        "Kasa"
    ],
    "name:swe_x_preferred":[
        "Kasa"
    ],
    "name:vie_x_preferred":[
        "Kasa"
    ],
    "wof:name":"Kasa",
    "wof:placetype":"locality"
},
  "geometry": {"coordinates":[-2.36956,8.37797],"type":"Point"}
}