{
  "type": "Feature",
  "properties": {
    "gn:admin1_code":"00",
    "gn:asciiname":"Hian",
    "gn:country_code":"GH",
    "gn:dem":282,
    "gn:feature_class":"P",
    "gn:feature_code":"PPL",
    "gn:name":"Hian",
    "gn:population":0,
    "gn:timezone":"Africa/Accra",
    "iso:country":"GH",
    "name:und_x_variant":[
        "Han"
    ],
    "wof:name":"Hian",
    "wof:placetype":"locality"
},
  "geometry": {"coordinates":[-2.44249,10.68772],"type":"Point"}
}