{
  "type": "Feature",
  "properties": {
    "gn:admin1_code":"00",
    "gn:asciiname":"Chachukope",
    "gn:country_code":"GH",
    "gn:dem":6,
    "gn:feature_class":"P",
    "gn:feature_code":"PPL",
    "gn:name":"Chachukope",
    "gn:population":0,
    "gn:timezone":"Africa/Accra",
    "iso:country":"GH",
    "wof:name":"Chachukope",
    "wof:placetype":"locality"
},
  "geometry": {"coordinates":[0.63131,5.85109],"type":"Point"}
}