{
  "type": "Feature",
  "properties": {
    "gn:admin1_code":"00",
    "gn:asciiname":"Atuna",
    "gn:country_code":"GH",
    "gn:dem":223,
    "gn:feature_class":"P",
    "gn:feature_code":"PPL",
    "gn:name":"Atuna",
    "gn:population":0,
    "gn:timezone":"Africa/Accra",
    "iso:country":"GH",
    "name:ceb_x_preferred":[
        "Atuna"
    ],
    "name:fra_x_preferred":[
        "Atuna"
    ],
    "name:por_x_preferred":[
        "Atuna"
    ],
    "name:spa_x_preferred":[
        "Atuna"
    ],
    "name:swe_x_preferred":[
        "Atuna"
    ],
    "name:vie_x_preferred":[
        "Atuna"
    ],
    "name:war_x_preferred":[
        "Atuna"
    ],
    "wof:name":"Atuna",
    "wof:placetype":"locality"
},
  "geometry": {"coordinates":[-2.91268,7.50338],"type":"Point"}
}