{
  "type": "Feature",
  "properties": {
    "gn:admin1_code":"09",
    "gn:asciiname":"Mpeasem",
    "gn:country_code":"GH",
    "gn:dem":217,
    "gn:feature_class":"P",
    "gn:feature_code":"PPL",
    "gn:name":"Mpeasem",
    "gn:population":0,
    "gn:timezone":"Africa/Accra",
    "iso:country":"GH",
    "name:eng_x_preferred":[
        "Mpeasem"
    ],
    "wof:name":"Mpeasem",
    "wof:placetype":"locality"
},
  "geometry": {"coordinates":[-1.9398,5.91717],"type":"Point"}
}