{
  "type": "Feature",
  "properties": {
    "gn:admin1_code":"00",
    "gn:asciiname":"Katenchi",
    "gn:country_code":"GH",
    "gn:dem":122,
    "gn:feature_class":"P",
    "gn:feature_code":"PPL",
    "gn:name":"Katenchi",
    "gn:population":0,
    "gn:timezone":"Africa/Accra",
    "iso:country":"GH",
    "wof:name":"Katenchi",
    "wof:placetype":"locality"
},
  "geometry": {"coordinates":[-1.40973,5.84692],"type":"Point"}
}