{
  "type": "Feature",
  "properties": {
    "gn:admin1_code":"09",
    "gn:asciiname":"Sumaso",
    "gn:country_code":"GH",
    "gn:dem":136,
    "gn:feature_class":"P",
    "gn:feature_code":"PPL",
    "gn:name":"Sumaso",
    "gn:population":0,
    "gn:timezone":"Africa/Accra",
    "iso:country":"GH",
    "name:eng_x_preferred":[
        "Sumaso"
    ],
    "name:und_x_variant":[
        "Sumuso"
    ],
    "wof:name":"Sumaso",
    "wof:placetype":"locality"
},
  "geometry": {"coordinates":[-1.99163,5.57925],"type":"Point"}
}