{
  "type": "Feature",
  "properties": {
    "gn:admin1_code":"00",
    "gn:asciiname":"Kpohagakofe",
    "gn:country_code":"GH",
    "gn:dem":12,
    "gn:feature_class":"P",
    "gn:feature_code":"PPL",
    "gn:name":"Kpohagakofe",
    "gn:population":0,
    "gn:timezone":"Africa/Accra",
    "iso:country":"GH",
    "wof:name":"Kpohagakofe",
    "wof:placetype":"locality"
},
  "geometry": {"coordinates":[1.04503,6.07523],"type":"Point"}
}