{
  "type": "Feature",
  "properties": {
    "gn:admin1_code":"00",
    "gn:asciiname":"Susanho",
    "gn:country_code":"GH",
    "gn:dem":289,
    "gn:feature_class":"P",
    "gn:feature_code":"PPL",
    "gn:name":"Susanho",
    "gn:population":0,
    "gn:timezone":"Africa/Accra",
    "iso:country":"GH",
    "wof:name":"Susanho",
    "wof:placetype":"locality"
},
  "geometry": {"coordinates":[-2.11224,7.2111],"type":"Point"}
}