{
  "type": "Feature",
  "properties": {
    "gn:admin1_code":"00",
    "gn:asciiname":"Jagogo",
    "gn:country_code":"GH",
    "gn:dem":180,
    "gn:feature_class":"P",
    "gn:feature_code":"PPL",
    "gn:name":"Jagogo",
    "gn:population":0,
    "gn:timezone":"Africa/Accra",
    "iso:country":"GH",
    "wof:name":"Jagogo",
    "wof:placetype":"locality"
},
  "geometry": {"coordinates":[-0.14441,10.32349],"type":"Point"}
}