{
  "type": "Feature",
  "properties": {
    "gn:admin1_code":"00",
    "gn:asciiname":"Ankasa",
    "gn:country_code":"GH",
    "gn:dem":59,
    "gn:feature_class":"P",
    "gn:feature_code":"PPL",
    "gn:name":"Ankasa",
    "gn:population":0,
    "gn:timezone":"Africa/Accra",
    "iso:country":"GH",
    "wof:name":"Ankasa",
    "wof:placetype":"locality"
},
  "geometry": {"coordinates":[-2.65206,5.21676],"type":"Point"}
}