{
  "type": "Feature",
  "properties": {
    "gn:admin1_code":"00",
    "gn:asciiname":"Ndumswaso",
    "gn:country_code":"GH",
    "gn:dem":42,
    "gn:feature_class":"P",
    "gn:feature_code":"PPL",
    "gn:name":"Ndumswaso",
    "gn:population":0,
    "gn:timezone":"Africa/Accra",
    "iso:country":"GH",
    "name:und_x_variant":[
        "Ndumsuazo",
        "Ndumswaso"
    ],
    "wof:name":"Ndumswaso",
    "wof:placetype":"locality"
},
  "geometry": {"coordinates":[-2.725,5.02944],"type":"Point"}
}