{
  "type": "Feature",
  "properties": {
    "gn:admin1_code":"00",
    "gn:asciiname":"Manie",
    "gn:country_code":"GH",
    "gn:dem":158,
    "gn:feature_class":"P",
    "gn:feature_code":"PPL",
    "gn:name":"Manie",
    "gn:population":0,
    "gn:timezone":"Africa/Accra",
    "iso:country":"GH",
    "name:azb_x_preferred":[
        "\u0645\u0627\u0646\u0642\u0647"
    ],
    "name:fas_x_preferred":[
        "\u0645\u0627\u0646\u06af\u0647"
    ],
    "name:fra_x_preferred":[
        "Manie"
    ],
    "name:lit_x_preferred":[
        "Maniai"
    ],
    "name:pol_x_preferred":[
        "Manie"
    ],
    "name:ukr_x_preferred":[
        "\u041c\u0430\u043d\u0435"
    ],
    "wof:name":"Manie",
    "wof:placetype":"locality"
},
  "geometry": {"coordinates":[-0.23242,10.14666],"type":"Point"}
}