{
  "type": "Feature",
  "properties": {
    "gn:admin1_code":"00",
    "gn:asciiname":"Boso",
    "gn:country_code":"GH",
    "gn:dem":216,
    "gn:feature_class":"P",
    "gn:feature_code":"PPL",
    "gn:name":"Boso",
    "gn:population":0,
    "gn:timezone":"Africa/Accra",
    "iso:country":"GH",
    "name:ceb_x_preferred":[
        "Boso"
    ],
    "name:deu_x_preferred":[
        "Boso"
    ],
    "name:fra_x_preferred":[
        "Boso"
    ],
    "name:hye_x_preferred":[
        "\u0532\u0578\u0566\u0578\u0576"
    ],
    "name:nld_x_preferred":[
        "Boso"
    ],
    "name:pol_x_preferred":[
        "Boso"
    ],
    "name:rus_x_preferred":[
        "\u0411\u043e\u0437\u043e\u043d"
    ],
    "name:swe_x_preferred":[
        "Boso"
    ],
    "name:ukr_x_preferred":[
        "\u0411\u043e\u0441\u043e"
    ],
    "wof:name":"Boso",
    "wof:placetype":"locality"
},
  "geometry": {"coordinates":[0.17325,6.5493],"type":"Point"}
}