{
  "type": "Feature",
  "properties": {
    "gn:admin1_code":"00",
    "gn:asciiname":"Panya",
    "gn:country_code":"GH",
    "gn:dem":7,
    "gn:feature_class":"P",
    "gn:feature_code":"PPL",
    "gn:name":"Panya",
    "gn:population":0,
    "gn:timezone":"Africa/Accra",
    "iso:country":"GH",
    "wof:name":"Panya",
    "wof:placetype":"locality"
},
  "geometry": {"coordinates":[0.46667,5.98333],"type":"Point"}
}