{
  "type": "Feature",
  "properties": {
    "gn:admin1_code":"00",
    "gn:asciiname":"Agbegakope",
    "gn:country_code":"GH",
    "gn:dem":26,
    "gn:feature_class":"P",
    "gn:feature_code":"PPL",
    "gn:name":"Agbegakope",
    "gn:population":0,
    "gn:timezone":"Africa/Accra",
    "iso:country":"GH",
    "name:und_x_variant":[
        "Agbenyaga",
        "Agbegakope"
    ],
    "wof:name":"Agbegakope",
    "wof:placetype":"locality"
},
  "geometry": {"coordinates":[0.46668,5.94295],"type":"Point"}
}