{
  "type": "Feature",
  "properties": {
    "gn:admin1_code":"00",
    "gn:asciiname":"Brofoyedru",
    "gn:country_code":"GH",
    "gn:dem":98,
    "gn:feature_class":"P",
    "gn:feature_code":"PPL",
    "gn:name":"Brofoyedru",
    "gn:population":0,
    "gn:timezone":"Africa/Accra",
    "iso:country":"GH",
    "name:und_x_variant":[
        "Brofoyedur",
        "Brofoyedru"
    ],
    "wof:name":"Brofoyedru",
    "wof:placetype":"locality"
},
  "geometry": {"coordinates":[-0.96881,5.44632],"type":"Point"}
}