{
  "type": "Feature",
  "properties": {
    "gn:admin1_code":"02",
    "gn:asciiname":"Pankrono",
    "gn:country_code":"GH",
    "gn:dem":314,
    "gn:feature_class":"P",
    "gn:feature_code":"PPL",
    "gn:name":"Pankrono",
    "gn:population":0,
    "gn:timezone":"Africa/Accra",
    "iso:country":"GH",
    "name:eng_x_preferred":[
        "Pankrono"
    ],
    "name:eng_x_variant":[
        "Pankronu"
    ],
    "wof:name":"Pankrono",
    "wof:placetype":"locality"
},
  "geometry": {"coordinates":[-1.60568,6.74994],"type":"Point"}
}