{
  "type": "Feature",
  "properties": {
    "gn:admin1_code":"00",
    "gn:asciiname":"Avedo",
    "gn:country_code":"GH",
    "gn:dem":33,
    "gn:feature_class":"P",
    "gn:feature_code":"PPL",
    "gn:name":"Avedo",
    "gn:population":0,
    "gn:timezone":"Africa/Accra",
    "iso:country":"GH",
    "wof:name":"Avedo",
    "wof:placetype":"locality"
},
  "geometry": {"coordinates":[0.63333,6.13333],"type":"Point"}
}