{
  "type": "Feature",
  "properties": {
    "gn:admin1_code":"00",
    "gn:asciiname":"Naja",
    "gn:country_code":"GH",
    "gn:dem":204,
    "gn:feature_class":"P",
    "gn:feature_code":"PPL",
    "gn:name":"Naja",
    "gn:population":0,
    "gn:timezone":"Africa/Accra",
    "iso:country":"GH",
    "wof:name":"Naja",
    "wof:placetype":"locality"
},
  "geometry": {"coordinates":[0.10036,10.26393],"type":"Point"}
}