{
  "type": "Feature",
  "properties": {
    "gn:admin1_code":"00",
    "gn:asciiname":"Moshiegu",
    "gn:cc2":"GH",
    "gn:country_code":"GH",
    "gn:dem":185,
    "gn:feature_class":"P",
    "gn:feature_code":"PPL",
    "gn:name":"Moshiegu",
    "gn:population":0,
    "gn:timezone":"Africa/Accra",
    "iso:country":"GH",
    "name:und_x_variant":[
        "Mossiegu",
        "Moshiego",
        "Moschiegu",
        "Moshiegu"
    ],
    "wof:name":"Moshiegu",
    "wof:placetype":"locality"
},
  "geometry": {"coordinates":[-0.03333,10.43333],"type":"Point"}
}