{
  "type": "Feature",
  "properties": {
    "gn:admin1_code":"00",
    "gn:asciiname":"Tsinyokofe",
    "gn:country_code":"GH",
    "gn:dem":-9999,
    "gn:feature_class":"P",
    "gn:feature_code":"PPL",
    "gn:name":"Tsinyokofe",
    "gn:population":0,
    "gn:timezone":"Africa/Accra",
    "iso:country":"GH",
    "wof:name":"Tsinyokofe",
    "wof:placetype":"locality"
},
  "geometry": {"coordinates":[0.98333,5.83333],"type":"Point"}
}