{
  "type": "Feature",
  "properties": {
    "gn:admin1_code":"00",
    "gn:asciiname":"Afiaso",
    "gn:country_code":"GH",
    "gn:dem":99,
    "gn:feature_class":"P",
    "gn:feature_code":"PPL",
    "gn:name":"Afiaso",
    "gn:population":0,
    "gn:timezone":"Africa/Accra",
    "iso:country":"GH",
    "wof:name":"Afiaso",
    "wof:placetype":"locality"
},
  "geometry": {"coordinates":[-1.44153,5.51314],"type":"Point"}
}