{
  "type": "Feature",
  "properties": {
    "gn:admin1_code":"00",
    "gn:asciiname":"Barelawn",
    "gn:country_code":"GH",
    "gn:dem":318,
    "gn:feature_class":"P",
    "gn:feature_code":"PPL",
    "gn:name":"Barelawn",
    "gn:population":0,
    "gn:timezone":"Africa/Accra",
    "iso:country":"GH",
    "wof:name":"Barelawn",
    "wof:placetype":"locality"
},
  "geometry": {"coordinates":[-0.21667,10.55],"type":"Point"}
}