{
  "type": "Feature",
  "properties": {
    "gn:admin1_code":"00",
    "gn:asciiname":"Avenui",
    "gn:country_code":"GH",
    "gn:dem":213,
    "gn:feature_class":"P",
    "gn:feature_code":"PPL",
    "gn:name":"Avenui",
    "gn:population":0,
    "gn:timezone":"Africa/Accra",
    "iso:country":"GH",
    "wof:name":"Avenui",
    "wof:placetype":"locality"
},
  "geometry": {"coordinates":[0.37065,6.71178],"type":"Point"}
}