{
  "type": "Feature",
  "properties": {
    "gn:admin1_code":"09",
    "gn:asciiname":"Satini",
    "gn:country_code":"GH",
    "gn:dem":134,
    "gn:feature_class":"P",
    "gn:feature_code":"PPL",
    "gn:name":"Satini",
    "gn:population":0,
    "gn:timezone":"Africa/Accra",
    "iso:country":"GH",
    "name:eng_x_preferred":[
        "Satini"
    ],
    "wof:name":"Satini",
    "wof:placetype":"locality"
},
  "geometry": {"coordinates":[-1.83973,5.53705],"type":"Point"}
}