{
  "type": "Feature",
  "properties": {
    "gn:admin1_code":"02",
    "gn:asciiname":"Boatenkrom",
    "gn:country_code":"GH",
    "gn:dem":135,
    "gn:feature_class":"P",
    "gn:feature_code":"PPL",
    "gn:name":"Boatenkrom",
    "gn:population":0,
    "gn:timezone":"Africa/Accra",
    "iso:country":"GH",
    "name:und_x_variant":[
        "Boatenkurom",
        "Boatenkrom"
    ],
    "wof:name":"Boatenkrom",
    "wof:placetype":"locality"
},
  "geometry": {"coordinates":[-1.90796,6.26518],"type":"Point"}
}