{
  "type": "Feature",
  "properties": {
    "gn:admin1_code":"00",
    "gn:asciiname":"Manyoro",
    "gn:country_code":"GH",
    "gn:dem":198,
    "gn:feature_class":"P",
    "gn:feature_code":"PPL",
    "gn:name":"Manyoro",
    "gn:population":0,
    "gn:timezone":"Africa/Accra",
    "iso:country":"GH",
    "name:und_x_variant":[
        "Song",
        "Mayoro",
        "Manyoro"
    ],
    "wof:name":"Manyoro",
    "wof:placetype":"locality"
},
  "geometry": {"coordinates":[-0.99803,10.97931],"type":"Point"}
}