{
  "type": "Feature",
  "properties": {
    "gn:admin1_code":"09",
    "gn:asciiname":"Edu",
    "gn:country_code":"GH",
    "gn:dem":77,
    "gn:feature_class":"P",
    "gn:feature_code":"PPL",
    "gn:name":"Edu",
    "gn:population":0,
    "gn:timezone":"Africa/Accra",
    "iso:country":"GH",
    "name:ceb_x_preferred":[
        "Edu"
    ],
    "name:deu_x_preferred":[
        "Edu"
    ],
    "name:est_x_preferred":[
        "Edu"
    ],
    "name:fas_x_preferred":[
        "\u0627\u062f\u0648"
    ],
    "name:fin_x_preferred":[
        "Edu"
    ],
    "name:fra_x_preferred":[
        "Edu"
    ],
    "name:nld_x_preferred":[
        "Edu"
    ],
    "name:pol_x_preferred":[
        "Edu"
    ],
    "name:por_x_preferred":[
        "Edu"
    ],
    "name:spa_x_preferred":[
        "Edu"
    ],
    "name:tur_x_preferred":[
        "Edu"
    ],
    "name:ukr_x_preferred":[
        "\u0415\u0434\u0443"
    ],
    "name:und_x_variant":[
        "Adusuazo",
        "Edu"
    ],
    "name:vie_x_preferred":[
        "Edu"
    ],
    "wof:name":"Edu",
    "wof:placetype":"locality"
},
  "geometry": {"coordinates":[-2.8463,5.08622],"type":"Point"}
}