{
  "type": "Feature",
  "properties": {
    "gn:admin1_code":"09",
    "gn:asciiname":"Edu",
    "gn:country_code":"GH",
    "gn:dem":77,
    "gn:feature_class":"P",
    "gn:feature_code":"PPL",
    "gn:name":"Edu",
    "gn:population":0,
    "gn:timezone":"Africa/Accra",
    "iso:country":"GH",
    "name:und_x_variant":[
        "Adusuazo",
        "Edu"
    ],
    "wof:name":"Edu",
    "wof:placetype":"locality"
},
  "geometry": {"coordinates":[-2.8463,5.08622],"type":"Point"}
}