{
  "type": "Feature",
  "properties": {
    "gn:admin1_code":"09",
    "gn:asciiname":"Antu",
    "gn:country_code":"GH",
    "gn:dem":61,
    "gn:feature_class":"P",
    "gn:feature_code":"PPL",
    "gn:name":"Antu",
    "gn:population":0,
    "gn:timezone":"Africa/Accra",
    "iso:country":"GH",
    "name:ceb_x_preferred":[
        "Antu"
    ],
    "name:deu_x_preferred":[
        "Antu"
    ],
    "name:eng_x_preferred":[
        "Antu"
    ],
    "name:fra_x_preferred":[
        "Antu"
    ],
    "name:ita_x_preferred":[
        "Antu"
    ],
    "name:new_x_preferred":[
        "\u0905\u0928\u094d\u0924\u0941"
    ],
    "name:nld_x_preferred":[
        "Antu"
    ],
    "name:pol_x_preferred":[
        "Antu"
    ],
    "name:spa_x_preferred":[
        "Antu"
    ],
    "name:swe_x_preferred":[
        "Antu"
    ],
    "name:tur_x_preferred":[
        "Antu"
    ],
    "wof:name":"Antu",
    "wof:placetype":"locality"
},
  "geometry": {"coordinates":[-1.56809,5.31872],"type":"Point"}
}