{
  "type": "Feature",
  "properties": {
    "gn:admin1_code":"00",
    "gn:asciiname":"Nkamandei",
    "gn:country_code":"GH",
    "gn:dem":130,
    "gn:feature_class":"P",
    "gn:feature_code":"PPL",
    "gn:name":"Nkamandei",
    "gn:population":0,
    "gn:timezone":"Africa/Accra",
    "iso:country":"GH",
    "wof:name":"Nkamandei",
    "wof:placetype":"locality"
},
  "geometry": {"coordinates":[-0.96667,8.61667],"type":"Point"}
}