{
  "type": "Feature",
  "properties": {
    "gn:admin1_code":"00",
    "gn:asciiname":"Akantin",
    "gn:country_code":"GH",
    "gn:dem":210,
    "gn:feature_class":"P",
    "gn:feature_code":"PPL",
    "gn:name":"Akantin",
    "gn:population":0,
    "gn:timezone":"Africa/Accra",
    "iso:country":"GH",
    "name:und_x_variant":[
        "Akanten",
        "Akantin"
    ],
    "wof:name":"Akantin",
    "wof:placetype":"locality"
},
  "geometry": {"coordinates":[-0.69034,6.01361],"type":"Point"}
}