{
  "type": "Feature",
  "properties": {
    "gn:admin1_code":"00",
    "gn:asciiname":"Babaso",
    "gn:country_code":"GH",
    "gn:dem":169,
    "gn:feature_class":"P",
    "gn:feature_code":"PPL",
    "gn:name":"Babaso",
    "gn:population":0,
    "gn:timezone":"Africa/Accra",
    "iso:country":"GH",
    "wof:name":"Babaso",
    "wof:placetype":"locality"
},
  "geometry": {"coordinates":[-1.28282,7.39593],"type":"Point"}
}