{
  "type": "Feature",
  "properties": {
    "gn:admin1_code":"11",
    "gn:asciiname":"Bazuu",
    "gn:country_code":"GH",
    "gn:dem":271,
    "gn:feature_class":"P",
    "gn:feature_code":"PPL",
    "gn:name":"Bazuu",
    "gn:population":0,
    "gn:timezone":"Africa/Accra",
    "iso:country":"GH",
    "name:eng_x_preferred":[
        "Bazuu"
    ],
    "name:und_x_variant":[
        "Baazu",
        "Boju"
    ],
    "wof:name":"Bazuu",
    "wof:placetype":"locality"
},
  "geometry": {"coordinates":[-2.67252,10.4709],"type":"Point"}
}