{
  "type": "Feature",
  "properties": {
    "gn:admin1_code":"00",
    "gn:asciiname":"Tale",
    "gn:country_code":"GH",
    "gn:dem":159,
    "gn:feature_class":"P",
    "gn:feature_code":"PPL",
    "gn:name":"Tale",
    "gn:population":0,
    "gn:timezone":"Africa/Accra",
    "iso:country":"GH",
    "name:ceb_x_preferred":[
        "Tale"
    ],
    "name:deu_x_preferred":[
        "Tale"
    ],
    "name:snd_x_preferred":[
        "\u062f\u0627\u0633\u062a\u0627\u0646"
    ],
    "name:swe_x_preferred":[
        "Tale"
    ],
    "name:tel_x_preferred":[
        "\u0c1f\u0c47\u0c32\u0c4d"
    ],
    "name:und_x_variant":[
        "Taali",
        "Tale"
    ],
    "wof:name":"Tale",
    "wof:placetype":"locality"
},
  "geometry": {"coordinates":[-0.05019,8.78537],"type":"Point"}
}