{
  "type": "Feature",
  "properties": {
    "gn:admin1_code":"00",
    "gn:asciiname":"Kukuadu",
    "gn:country_code":"GH",
    "gn:dem":29,
    "gn:feature_class":"P",
    "gn:feature_code":"PPL",
    "gn:name":"Kukuadu",
    "gn:population":0,
    "gn:timezone":"Africa/Accra",
    "iso:country":"GH",
    "name:und_x_variant":[
        "Kakuadu",
        "Kokwaado",
        "Kukuadu"
    ],
    "wof:name":"Kukuadu",
    "wof:placetype":"locality"
},
  "geometry": {"coordinates":[-1.47942,5.09988],"type":"Point"}
}