{
  "type": "Feature",
  "properties": {
    "gn:admin1_code":"01",
    "gn:asciiname":"Samsamso",
    "gn:country_code":"GH",
    "gn:dem":84,
    "gn:feature_class":"P",
    "gn:feature_code":"PPL",
    "gn:name":"Samsamso",
    "gn:population":0,
    "gn:timezone":"Africa/Accra",
    "iso:country":"GH",
    "wof:name":"Samsamso",
    "wof:placetype":"locality"
},
  "geometry": {"coordinates":[-0.56667,5.58333],"type":"Point"}
}