{
  "type": "Feature",
  "properties": {
    "gn:admin1_code":"00",
    "gn:asciiname":"Kpansera",
    "gn:cc2":"GH",
    "gn:country_code":"GH",
    "gn:dem":114,
    "gn:feature_class":"P",
    "gn:feature_code":"PPL",
    "gn:name":"Kpansera",
    "gn:population":0,
    "gn:timezone":"Africa/Accra",
    "iso:country":"GH",
    "name:und_x_variant":[
        "Pasara",
        "Kpasara",
        "Kpansera"
    ],
    "wof:name":"Kpansera",
    "wof:placetype":"locality"
},
  "geometry": {"coordinates":[-1.25,8.75],"type":"Point"}
}