{
  "type": "Feature",
  "properties": {
    "gn:admin1_code":"00",
    "gn:asciiname":"Belagu",
    "gn:country_code":"GH",
    "gn:dem":201,
    "gn:feature_class":"P",
    "gn:feature_code":"PPL",
    "gn:name":"Belagu",
    "gn:population":0,
    "gn:timezone":"Africa/Accra",
    "iso:country":"GH",
    "name:und_x_variant":[
        "Kpokparago",
        "Belagu"
    ],
    "wof:name":"Belagu",
    "wof:placetype":"locality"
},
  "geometry": {"coordinates":[-0.24427,10.90972],"type":"Point"}
}