{
  "type": "Feature",
  "properties": {
    "gn:admin1_code":"00",
    "gn:asciiname":"Kpatuse",
    "gn:country_code":"GH",
    "gn:dem":224,
    "gn:feature_class":"P",
    "gn:feature_code":"PPL",
    "gn:name":"Kpatuse",
    "gn:population":0,
    "gn:timezone":"Africa/Accra",
    "iso:country":"GH",
    "wof:name":"Kpatuse",
    "wof:placetype":"locality"
},
  "geometry": {"coordinates":[-0.75612,10.57373],"type":"Point"}
}