{
  "type": "Feature",
  "properties": {
    "gn:admin1_code":"00",
    "gn:asciiname":"Onuku",
    "gn:country_code":"GH",
    "gn:dem":426,
    "gn:feature_class":"P",
    "gn:feature_code":"PPL",
    "gn:name":"Onuku",
    "gn:population":0,
    "gn:timezone":"Africa/Accra",
    "iso:country":"GH",
    "wof:name":"Onuku",
    "wof:placetype":"locality"
},
  "geometry": {"coordinates":[-0.31642,6.4653],"type":"Point"}
}