{
  "type": "Feature",
  "properties": {
    "gn:admin1_code":"00",
    "gn:asciiname":"Edumata",
    "gn:country_code":"GH",
    "gn:dem":8,
    "gn:feature_class":"P",
    "gn:feature_code":"PPL",
    "gn:name":"Edumata",
    "gn:population":0,
    "gn:timezone":"Africa/Accra",
    "iso:country":"GH",
    "name:und_x_variant":[
        "Edumafa",
        "Edumata"
    ],
    "wof:name":"Edumata",
    "wof:placetype":"locality"
},
  "geometry": {"coordinates":[-0.9616,5.20412],"type":"Point"}
}