{
  "type": "Feature",
  "properties": {
    "gn:admin1_code":"09",
    "gn:asciiname":"Ohiankwanta",
    "gn:country_code":"GH",
    "gn:dem":207,
    "gn:feature_class":"P",
    "gn:feature_code":"PPL",
    "gn:name":"Ohiankwanta",
    "gn:population":0,
    "gn:timezone":"Africa/Accra",
    "iso:country":"GH",
    "name:eng_x_preferred":[
        "Ohiankwanta"
    ],
    "wof:name":"Ohiankwanta",
    "wof:placetype":"locality"
},
  "geometry": {"coordinates":[-1.95751,5.89614],"type":"Point"}
}