{
  "type": "Feature",
  "properties": {
    "gn:admin1_code":"00",
    "gn:asciiname":"Jamalega",
    "gn:country_code":"GH",
    "gn:dem":179,
    "gn:feature_class":"P",
    "gn:feature_code":"PPL",
    "gn:name":"Jamalega",
    "gn:population":0,
    "gn:timezone":"Africa/Accra",
    "iso:country":"GH",
    "name:und_x_variant":[
        "Njamaleg\u00e1",
        "Nyamaliga",
        "Jamalega"
    ],
    "wof:name":"Jamalega",
    "wof:placetype":"locality"
},
  "geometry": {"coordinates":[0.3551,9.01821],"type":"Point"}
}