{
  "type": "Feature",
  "properties": {
    "gn:admin1_code":"09",
    "gn:asciiname":"Kegyina",
    "gn:country_code":"GH",
    "gn:dem":23,
    "gn:feature_class":"P",
    "gn:feature_code":"PPL",
    "gn:name":"Kegyina",
    "gn:population":0,
    "gn:timezone":"Africa/Accra",
    "iso:country":"GH",
    "name:und_x_variant":[
        "Kojima"
    ],
    "wof:name":"Kegyina",
    "wof:placetype":"locality"
},
  "geometry": {"coordinates":[-2.13699,4.90312],"type":"Point"}
}