{
  "type": "Feature",
  "properties": {
    "gn:admin1_code":"09",
    "gn:asciiname":"Kwamintintin",
    "gn:country_code":"GH",
    "gn:dem":149,
    "gn:feature_class":"P",
    "gn:feature_code":"PPL",
    "gn:name":"Kwamintintin",
    "gn:population":0,
    "gn:timezone":"Africa/Accra",
    "iso:country":"GH",
    "name:eng_x_preferred":[
        "Kwamintintin"
    ],
    "wof:name":"Kwamintintin",
    "wof:placetype":"locality"
},
  "geometry": {"coordinates":[-1.96917,5.5129],"type":"Point"}
}