{
  "type": "Feature",
  "properties": {
    "gn:admin1_code":"09",
    "gn:asciiname":"Ajakukuso",
    "gn:country_code":"GH",
    "gn:dem":147,
    "gn:feature_class":"P",
    "gn:feature_code":"PPL",
    "gn:name":"Ajakukuso",
    "gn:population":0,
    "gn:timezone":"Africa/Accra",
    "iso:country":"GH",
    "name:und_x_variant":[
        "Ajakukuse",
        "Agyakoso",
        "Ajakukuso"
    ],
    "wof:name":"Ajakukuso",
    "wof:placetype":"locality"
},
  "geometry": {"coordinates":[-2.00626,5.95887],"type":"Point"}
}