{
  "type": "Feature",
  "properties": {
    "gn:admin1_code":"00",
    "gn:asciiname":"Chamimensakura",
    "gn:country_code":"GH",
    "gn:dem":139,
    "gn:feature_class":"P",
    "gn:feature_code":"PPL",
    "gn:name":"Chamimensakura",
    "gn:population":0,
    "gn:timezone":"Africa/Accra",
    "iso:country":"GH",
    "wof:name":"Chamimensakura",
    "wof:placetype":"locality"
},
  "geometry": {"coordinates":[-0.7893,5.65626],"type":"Point"}
}