{
  "type": "Feature",
  "properties": {
    "gn:admin1_code":"00",
    "gn:asciiname":"Kajasi",
    "gn:country_code":"GH",
    "gn:dem":126,
    "gn:feature_class":"P",
    "gn:feature_code":"PPL",
    "gn:name":"Kajasi",
    "gn:population":0,
    "gn:timezone":"Africa/Accra",
    "iso:country":"GH",
    "name:und_x_variant":[
        "Kajaso",
        "Kpabuso",
        "Kajasi"
    ],
    "wof:name":"Kajasi",
    "wof:placetype":"locality"
},
  "geometry": {"coordinates":[-1.16112,8.74005],"type":"Point"}
}