{
  "type": "Feature",
  "properties": {
    "gn:admin1_code":"01",
    "gn:asciiname":"Kwabenya",
    "gn:country_code":"GH",
    "gn:dem":118,
    "gn:feature_class":"P",
    "gn:feature_code":"PPL",
    "gn:name":"Kwabenya",
    "gn:population":0,
    "gn:timezone":"Africa/Accra",
    "iso:country":"GH",
    "wof:name":"Kwabenya",
    "wof:placetype":"locality"
},
  "geometry": {"coordinates":[-0.25139,5.69694],"type":"Point"}
}