{
  "type": "Feature",
  "properties": {
    "gn:admin1_code":"00",
    "gn:asciiname":"Jejeti",
    "gn:country_code":"GH",
    "gn:dem":202,
    "gn:feature_class":"P",
    "gn:feature_code":"PPL",
    "gn:name":"Jejeti",
    "gn:population":0,
    "gn:timezone":"Africa/Accra",
    "iso:country":"GH",
    "name:und_x_variant":[
        "Gyegyeti",
        "Jejeti"
    ],
    "wof:name":"Jejeti",
    "wof:placetype":"locality"
},
  "geometry": {"coordinates":[-0.65023,6.47466],"type":"Point"}
}