{
  "type": "Feature",
  "properties": {
    "gn:admin1_code":"00",
    "gn:asciiname":"Drabon",
    "gn:country_code":"GH",
    "gn:dem":252,
    "gn:feature_class":"P",
    "gn:feature_code":"PPL",
    "gn:name":"Drabon",
    "gn:population":0,
    "gn:timezone":"Africa/Accra",
    "iso:country":"GH",
    "wof:name":"Drabon",
    "wof:placetype":"locality"
},
  "geometry": {"coordinates":[-1.56084,7.36976],"type":"Point"}
}