{
  "type": "Feature",
  "properties": {
    "gn:admin1_code":"00",
    "gn:asciiname":"Saboro",
    "gn:country_code":"GH",
    "gn:dem":208,
    "gn:feature_class":"P",
    "gn:feature_code":"PPL",
    "gn:name":"Saboro",
    "gn:population":0,
    "gn:timezone":"Africa/Accra",
    "iso:country":"GH",
    "name:und_x_variant":[
        "Navrongo Saboro",
        "Saboro"
    ],
    "wof:name":"Saboro",
    "wof:placetype":"locality"
},
  "geometry": {"coordinates":[-1.09018,10.92043],"type":"Point"}
}