{
  "type": "Feature",
  "properties": {
    "gn:admin1_code":"02",
    "gn:asciiname":"Adowa",
    "gn:country_code":"GH",
    "gn:dem":177,
    "gn:feature_class":"P",
    "gn:feature_code":"PPL",
    "gn:name":"Adowa",
    "gn:population":0,
    "gn:timezone":"Africa/Accra",
    "iso:country":"GH",
    "name:und_x_variant":[
        "Adowa Number 2",
        "Adowa"
    ],
    "wof:name":"Adowa",
    "wof:placetype":"locality"
},
  "geometry": {"coordinates":[-1.74002,6.35886],"type":"Point"}
}