{
  "type": "Feature",
  "properties": {
    "gn:admin1_code":"00",
    "gn:asciiname":"Adiekpe",
    "gn:country_code":"GH",
    "gn:dem":60,
    "gn:feature_class":"P",
    "gn:feature_code":"PPL",
    "gn:name":"Adiekpe",
    "gn:population":0,
    "gn:timezone":"Africa/Accra",
    "iso:country":"GH",
    "wof:name":"Adiekpe",
    "wof:placetype":"locality"
},
  "geometry": {"coordinates":[0.50845,6.23473],"type":"Point"}
}