{
  "type": "Feature",
  "properties": {
    "gn:admin1_code":"02",
    "gn:asciiname":"Chireayowa",
    "gn:country_code":"GH",
    "gn:dem":161,
    "gn:feature_class":"P",
    "gn:feature_code":"PPL",
    "gn:name":"Chireayowa",
    "gn:population":0,
    "gn:timezone":"Africa/Accra",
    "iso:country":"GH",
    "name:eng_x_preferred":[
        "Chireayowa"
    ],
    "wof:name":"Chireayowa",
    "wof:placetype":"locality"
},
  "geometry": {"coordinates":[-1.86774,6.35965],"type":"Point"}
}