{
  "type": "Feature",
  "properties": {
    "gn:admin1_code":"09",
    "gn:asciiname":"Beyin",
    "gn:country_code":"GH",
    "gn:dem":9,
    "gn:feature_class":"P",
    "gn:feature_code":"PPL",
    "gn:name":"Beyin",
    "gn:population":0,
    "gn:timezone":"Africa/Accra",
    "iso:country":"GH",
    "name:fra_x_preferred":[
        "Beyin"
    ],
    "name:und_x_variant":[
        "Behin"
    ],
    "wof:name":"Beyin",
    "wof:placetype":"locality"
},
  "geometry": {"coordinates":[-2.58602,4.98662],"type":"Point"}
}