{
  "type": "Feature",
  "properties": {
    "gn:admin1_code":"00",
    "gn:asciiname":"Awurawa",
    "gn:country_code":"GH",
    "gn:dem":326,
    "gn:feature_class":"P",
    "gn:feature_code":"PPL",
    "gn:name":"Awurawa",
    "gn:population":0,
    "gn:timezone":"Africa/Accra",
    "iso:country":"GH",
    "name:und_x_variant":[
        "Aworowa",
        "Awurawa"
    ],
    "wof:name":"Awurawa",
    "wof:placetype":"locality"
},
  "geometry": {"coordinates":[-2.01549,7.62192],"type":"Point"}
}