{
  "type": "Feature",
  "properties": {
    "gn:admin1_code":"08",
    "gn:asciiname":"Demakope",
    "gn:country_code":"GH",
    "gn:dem":47,
    "gn:feature_class":"P",
    "gn:feature_code":"PPL",
    "gn:name":"Demakope",
    "gn:population":0,
    "gn:timezone":"Africa/Accra",
    "iso:country":"GH",
    "name:und_x_variant":[
        "Demekpo",
        "Demakope"
    ],
    "wof:name":"Demakope",
    "wof:placetype":"locality"
},
  "geometry": {"coordinates":[1.00007,6.22131],"type":"Point"}
}