{
  "type": "Feature",
  "properties": {
    "gn:admin1_code":"00",
    "gn:asciiname":"Kwasero Daboshi",
    "gn:country_code":"GH",
    "gn:dem":148,
    "gn:feature_class":"P",
    "gn:feature_code":"PPL",
    "gn:name":"Kwasero Daboshi",
    "gn:population":0,
    "gn:timezone":"Africa/Accra",
    "iso:country":"GH",
    "wof:name":"Kwasero Daboshi",
    "wof:placetype":"locality"
},
  "geometry": {"coordinates":[-1.08333,9.26667],"type":"Point"}
}