{
  "type": "Feature",
  "properties": {
    "gn:admin1_code":"00",
    "gn:asciiname":"Agblife",
    "gn:country_code":"GH",
    "gn:dem":109,
    "gn:feature_class":"P",
    "gn:feature_code":"PPL",
    "gn:name":"Agblife",
    "gn:population":0,
    "gn:timezone":"Africa/Accra",
    "iso:country":"GH",
    "wof:name":"Agblife",
    "wof:placetype":"locality"
},
  "geometry": {"coordinates":[0.48802,6.50014],"type":"Point"}
}