{
  "type": "Feature",
  "properties": {
    "gn:admin1_code":"00",
    "gn:asciiname":"Hirenve",
    "gn:country_code":"GH",
    "gn:dem":13,
    "gn:feature_class":"P",
    "gn:feature_code":"PPL",
    "gn:name":"Hirenve",
    "gn:population":0,
    "gn:timezone":"Africa/Accra",
    "iso:country":"GH",
    "wof:name":"Hirenve",
    "wof:placetype":"locality"
},
  "geometry": {"coordinates":[0.65,6.01667],"type":"Point"}
}