{
  "type": "Feature",
  "properties": {
    "gn:admin1_code":"01",
    "gn:asciiname":"Ofankor",
    "gn:country_code":"GH",
    "gn:dem":54,
    "gn:feature_class":"P",
    "gn:feature_code":"PPL",
    "gn:name":"Ofankor",
    "gn:population":0,
    "gn:timezone":"Africa/Accra",
    "iso:country":"GH",
    "name:und_x_variant":[
        "Ofako"
    ],
    "wof:name":"Ofankor",
    "wof:placetype":"locality"
},
  "geometry": {"coordinates":[-0.26921,5.65596],"type":"Point"}
}