{
  "type": "Feature",
  "properties": {
    "gn:admin1_code":"09",
    "gn:asciiname":"Boadi",
    "gn:country_code":"GH",
    "gn:dem":175,
    "gn:feature_class":"P",
    "gn:feature_code":"PPL",
    "gn:name":"Boadi",
    "gn:population":0,
    "gn:timezone":"Africa/Accra",
    "iso:country":"GH",
    "name:eng_x_preferred":[
        "Boadi"
    ],
    "name:eng_x_variant":[
        "Bodi"
    ],
    "wof:name":"Boadi",
    "wof:placetype":"locality"
},
  "geometry": {"coordinates":[-2.75728,6.2235],"type":"Point"}
}