{
  "type": "Feature",
  "properties": {
    "gn:admin1_code":"00",
    "gn:asciiname":"Gupanalgo",
    "gn:country_code":"GH",
    "gn:dem":174,
    "gn:feature_class":"P",
    "gn:feature_code":"PPL",
    "gn:name":"Gupanalgo",
    "gn:population":0,
    "gn:timezone":"Africa/Accra",
    "iso:country":"GH",
    "name:und_x_variant":[
        "Gupaneirigu",
        "Gupanalgo"
    ],
    "wof:name":"Gupanalgo",
    "wof:placetype":"locality"
},
  "geometry": {"coordinates":[-0.9512,9.50026],"type":"Point"}
}