{
  "type": "Feature",
  "properties": {
    "gn:admin1_code":"00",
    "gn:asciiname":"Aimaso",
    "gn:country_code":"GH",
    "gn:dem":159,
    "gn:feature_class":"P",
    "gn:feature_code":"PPL",
    "gn:name":"Aimaso",
    "gn:population":0,
    "gn:timezone":"Africa/Accra",
    "iso:country":"GH",
    "wof:name":"Aimaso",
    "wof:placetype":"locality"
},
  "geometry": {"coordinates":[0.01651,6.20342],"type":"Point"}
}