{
  "type": "Feature",
  "properties": {
    "gn:admin1_code":"02",
    "gn:asciiname":"Nyinanufu",
    "gn:country_code":"GH",
    "gn:dem":288,
    "gn:feature_class":"P",
    "gn:feature_code":"PPL",
    "gn:name":"Nyinanufu",
    "gn:population":0,
    "gn:timezone":"Africa/Accra",
    "iso:country":"GH",
    "name:eng_x_preferred":[
        "Nyinanufu"
    ],
    "name:eng_x_variant":[
        "Onyinanufuaro"
    ],
    "name:und_x_variant":[
        "Onyinanufoo",
        "Onyinanufuaw"
    ],
    "wof:name":"Nyinanufu",
    "wof:placetype":"locality"
},
  "geometry": {"coordinates":[-1.98132,6.88955],"type":"Point"}
}