{
  "type": "Feature",
  "properties": {
    "gn:admin1_code":"00",
    "gn:asciiname":"Kula",
    "gn:country_code":"GH",
    "gn:dem":136,
    "gn:feature_class":"P",
    "gn:feature_code":"PPL",
    "gn:name":"Kula",
    "gn:population":0,
    "gn:timezone":"Africa/Accra",
    "iso:country":"GH",
    "wof:name":"Kula",
    "wof:placetype":"locality"
},
  "geometry": {"coordinates":[-0.72884,9.44914],"type":"Point"}
}