{
  "type": "Feature",
  "properties": {
    "gn:admin1_code":"00",
    "gn:asciiname":"Huakpo",
    "gn:country_code":"GH",
    "gn:dem":21,
    "gn:feature_class":"P",
    "gn:feature_code":"PPL",
    "gn:name":"Huakpo",
    "gn:population":0,
    "gn:timezone":"Africa/Accra",
    "iso:country":"GH",
    "name:und_x_variant":[
        "Hwakpo",
        "Huakpo"
    ],
    "wof:name":"Huakpo",
    "wof:placetype":"locality"
},
  "geometry": {"coordinates":[0.47802,5.88996],"type":"Point"}
}