{
  "type": "Feature",
  "properties": {
    "gn:admin1_code":"02",
    "gn:asciiname":"Mawjiso",
    "gn:country_code":"GH",
    "gn:dem":141,
    "gn:feature_class":"P",
    "gn:feature_code":"PPL",
    "gn:name":"Mawjiso",
    "gn:population":0,
    "gn:timezone":"Africa/Accra",
    "iso:country":"GH",
    "name:eng_x_preferred":[
        "Mawjiso"
    ],
    "wof:name":"Mawjiso",
    "wof:placetype":"locality"
},
  "geometry": {"coordinates":[-1.5736,6.06362],"type":"Point"}
}