{
  "type": "Feature",
  "properties": {
    "gn:admin1_code":"02",
    "gn:asciiname":"Daku",
    "gn:country_code":"GH",
    "gn:dem":263,
    "gn:feature_class":"P",
    "gn:feature_code":"PPL",
    "gn:name":"Daku",
    "gn:population":0,
    "gn:timezone":"Africa/Accra",
    "iso:country":"GH",
    "name:und_x_variant":[
        "Dakum",
        "Daku"
    ],
    "wof:name":"Daku",
    "wof:placetype":"locality"
},
  "geometry": {"coordinates":[-1.6841,6.63091],"type":"Point"}
}