{
  "type": "Feature",
  "properties": {
    "gn:admin1_code":"00",
    "gn:asciiname":"Akligbekope",
    "gn:country_code":"GH",
    "gn:dem":7,
    "gn:feature_class":"P",
    "gn:feature_code":"PPL",
    "gn:name":"Akligbekope",
    "gn:population":0,
    "gn:timezone":"Africa/Accra",
    "iso:country":"GH",
    "name:und_x_variant":[
        "Aklibwekope",
        "Akligbe Korpe",
        "Akligbekope"
    ],
    "wof:name":"Akligbekope",
    "wof:placetype":"locality"
},
  "geometry": {"coordinates":[0.60511,5.87817],"type":"Point"}
}