{
  "type": "Feature",
  "properties": {
    "gn:admin1_code":"00",
    "gn:asciiname":"Kramokorasi",
    "gn:country_code":"GH",
    "gn:dem":103,
    "gn:feature_class":"P",
    "gn:feature_code":"PPL",
    "gn:name":"Kramokorasi",
    "gn:population":0,
    "gn:timezone":"Africa/Accra",
    "iso:country":"GH",
    "wof:name":"Kramokorasi",
    "wof:placetype":"locality"
},
  "geometry": {"coordinates":[-0.9484,5.61101],"type":"Point"}
}