{
  "type": "Feature",
  "properties": {
    "gn:admin1_code":"06",
    "gn:asciiname":"Tare",
    "gn:country_code":"GH",
    "gn:dem":280,
    "gn:feature_class":"P",
    "gn:feature_code":"PPL",
    "gn:name":"Tare",
    "gn:population":0,
    "gn:timezone":"Africa/Accra",
    "iso:country":"GH",
    "name:und_x_variant":[
        "Tari",
        "Tare"
    ],
    "wof:name":"Tare",
    "wof:placetype":"locality"
},
  "geometry": {"coordinates":[-2.51871,9.34088],"type":"Point"}
}