{
  "type": "Feature",
  "properties": {
    "gn:admin1_code":"09",
    "gn:asciiname":"Otodum",
    "gn:country_code":"GH",
    "gn:dem":44,
    "gn:feature_class":"P",
    "gn:feature_code":"PPL",
    "gn:name":"Otodum",
    "gn:population":0,
    "gn:timezone":"Africa/Accra",
    "iso:country":"GH",
    "name:eng_x_preferred":[
        "Otodum"
    ],
    "wof:name":"Otodum",
    "wof:placetype":"locality"
},
  "geometry": {"coordinates":[-1.62958,5.16253],"type":"Point"}
}