{
  "type": "Feature",
  "properties": {
    "gn:admin1_code":"02",
    "gn:asciiname":"Domi",
    "gn:country_code":"GH",
    "gn:dem":227,
    "gn:feature_class":"P",
    "gn:feature_code":"PPL",
    "gn:name":"Domi",
    "gn:population":0,
    "gn:timezone":"Africa/Accra",
    "iso:country":"GH",
    "name:ceb_x_preferred":[
        "Domi"
    ],
    "name:deu_x_preferred":[
        "Domi"
    ],
    "name:eng_x_preferred":[
        "Domi"
    ],
    "name:fin_x_preferred":[
        "Domi"
    ],
    "name:fra_x_preferred":[
        "Domi"
    ],
    "name:rus_x_preferred":[
        "\u0414\u043e\u043c\u0438"
    ],
    "name:ukr_x_preferred":[
        "\u0414\u043e\u043c\u0456"
    ],
    "wof:name":"Domi",
    "wof:placetype":"locality"
},
  "geometry": {"coordinates":[-1.86018,6.41214],"type":"Point"}
}