{
  "type": "Feature",
  "properties": {
    "gn:admin1_code":"00",
    "gn:asciiname":"Achibiasi",
    "gn:country_code":"GH",
    "gn:dem":27,
    "gn:feature_class":"P",
    "gn:feature_code":"PPL",
    "gn:name":"Achibiasi",
    "gn:population":0,
    "gn:timezone":"Africa/Accra",
    "iso:country":"GH",
    "wof:name":"Achibiasi",
    "wof:placetype":"locality"
},
  "geometry": {"coordinates":[-0.48333,5.43333],"type":"Point"}
}