{
  "type": "Feature",
  "properties": {
    "gn:admin1_code":"00",
    "gn:asciiname":"Prekumasi",
    "gn:country_code":"GH",
    "gn:dem":345,
    "gn:feature_class":"P",
    "gn:feature_code":"PPL",
    "gn:name":"Prekumasi",
    "gn:population":0,
    "gn:timezone":"Africa/Accra",
    "iso:country":"GH",
    "name:und_x_variant":[
        "Prekumase South",
        "Prekumasi"
    ],
    "wof:name":"Prekumasi",
    "wof:placetype":"locality"
},
  "geometry": {"coordinates":[-0.18918,6.34024],"type":"Point"}
}