{
  "type": "Feature",
  "properties": {
    "gn:admin1_code":"02",
    "gn:asciiname":"Ofinso",
    "gn:country_code":"GH",
    "gn:dem":105,
    "gn:feature_class":"P",
    "gn:feature_code":"PPL",
    "gn:name":"Ofinso",
    "gn:population":0,
    "gn:timezone":"Africa/Accra",
    "iso:country":"GH",
    "name:eng_x_preferred":[
        "Ofinso"
    ],
    "wof:name":"Ofinso",
    "wof:placetype":"locality"
},
  "geometry": {"coordinates":[-1.77086,5.99069],"type":"Point"}
}