{
  "type": "Feature",
  "properties": {
    "gn:admin1_code":"00",
    "gn:asciiname":"Bisaso",
    "gn:country_code":"GH",
    "gn:dem":99,
    "gn:feature_class":"P",
    "gn:feature_code":"PPL",
    "gn:name":"Bisaso",
    "gn:population":0,
    "gn:timezone":"Africa/Accra",
    "iso:country":"GH",
    "name:und_x_variant":[
        "N\u2019Kossas",
        "Biaso",
        "Bisaso"
    ],
    "wof:name":"Bisaso",
    "wof:placetype":"locality"
},
  "geometry": {"coordinates":[-2.5358,5.51622],"type":"Point"}
}