{
  "type": "Feature",
  "properties": {
    "gn:admin1_code":"09",
    "gn:asciiname":"Pomponadie",
    "gn:country_code":"GH",
    "gn:dem":69,
    "gn:feature_class":"P",
    "gn:feature_code":"PPL",
    "gn:name":"Pomponadie",
    "gn:population":0,
    "gn:timezone":"Africa/Accra",
    "iso:country":"GH",
    "name:eng_x_preferred":[
        "Pomponadie"
    ],
    "wof:name":"Pomponadie",
    "wof:placetype":"locality"
},
  "geometry": {"coordinates":[-2.10532,4.9915],"type":"Point"}
}