{
  "type": "Feature",
  "properties": {
    "gn:admin1_code":"04",
    "gn:asciiname":"Mradan",
    "gn:country_code":"GH",
    "gn:dem":135,
    "gn:feature_class":"P",
    "gn:feature_code":"PPL",
    "gn:name":"Mradan",
    "gn:population":0,
    "gn:timezone":"Africa/Accra",
    "iso:country":"GH",
    "name:und_x_variant":[
        "Mradam",
        "Mberadan",
        "Mradan"
    ],
    "wof:name":"Mradan",
    "wof:placetype":"locality"
},
  "geometry": {"coordinates":[-1.77233,5.9409],"type":"Point"}
}