{
  "type": "Feature",
  "properties": {
    "gn:admin1_code":"00",
    "gn:asciiname":"Nabisi",
    "gn:cc2":"GH",
    "gn:country_code":"GH",
    "gn:dem":222,
    "gn:feature_class":"P",
    "gn:feature_code":"PPL",
    "gn:name":"Nabisi",
    "gn:population":0,
    "gn:timezone":"Africa/Accra",
    "iso:country":"GH",
    "name:und_x_variant":[
        "Bongo Anarorabisi",
        "Nabisi"
    ],
    "wof:name":"Nabisi",
    "wof:placetype":"locality"
},
  "geometry": {"coordinates":[-0.78333,10.91667],"type":"Point"}
}