{
  "type": "Feature",
  "properties": {
    "gn:admin1_code":"02",
    "gn:asciiname":"Muohu",
    "gn:country_code":"GH",
    "gn:dem":183,
    "gn:feature_class":"P",
    "gn:feature_code":"PPL",
    "gn:name":"Muohu",
    "gn:population":0,
    "gn:timezone":"Africa/Accra",
    "iso:country":"GH",
    "name:eng_x_preferred":[
        "Muohu"
    ],
    "wof:name":"Muohu",
    "wof:placetype":"locality"
},
  "geometry": {"coordinates":[-1.99763,6.41307],"type":"Point"}
}