{
  "type": "Feature",
  "properties": {
    "gn:admin1_code":"08",
    "gn:asciiname":"Nkonya Wurapon",
    "gn:country_code":"GH",
    "gn:dem":144,
    "gn:feature_class":"P",
    "gn:feature_code":"PPL",
    "gn:name":"Nkonya Wurapon",
    "gn:population":0,
    "gn:timezone":"Africa/Accra",
    "iso:country":"GH",
    "wof:name":"Nkonya Wurapon",
    "wof:placetype":"locality"
},
  "geometry": {"coordinates":[0.33366,7.18025],"type":"Point"}
}