{
  "type": "Feature",
  "properties": {
    "gn:admin1_code":"00",
    "gn:asciiname":"Nyamibebu",
    "gn:country_code":"GH",
    "gn:dem":106,
    "gn:feature_class":"P",
    "gn:feature_code":"PPL",
    "gn:name":"Nyamibebu",
    "gn:population":0,
    "gn:timezone":"Africa/Accra",
    "iso:country":"GH",
    "name:und_x_variant":[
        "Nyamebebu",
        "Nyamibebu"
    ],
    "wof:name":"Nyamibebu",
    "wof:placetype":"locality"
},
  "geometry": {"coordinates":[-1.24319,5.36089],"type":"Point"}
}