{
  "type": "Feature",
  "properties": {
    "gn:admin1_code":"00",
    "gn:asciiname":"Abum",
    "gn:country_code":"GH",
    "gn:dem":232,
    "gn:feature_class":"P",
    "gn:feature_code":"PPL",
    "gn:name":"Abum",
    "gn:population":0,
    "gn:timezone":"Africa/Accra",
    "iso:country":"GH",
    "name:und_x_variant":[
        "Aboom",
        "Abum"
    ],
    "wof:name":"Abum",
    "wof:placetype":"locality"
},
  "geometry": {"coordinates":[-2.69799,6.61555],"type":"Point"}
}