{
  "type": "Feature",
  "properties": {
    "gn:admin1_code":"00",
    "gn:asciiname":"Kwaman",
    "gn:country_code":"GH",
    "gn:dem":126,
    "gn:feature_class":"P",
    "gn:feature_code":"PPL",
    "gn:name":"Kwaman",
    "gn:population":0,
    "gn:timezone":"Africa/Accra",
    "iso:country":"GH",
    "name:und_x_variant":[
        "Kwamang",
        "Kwaman"
    ],
    "wof:name":"Kwaman",
    "wof:placetype":"locality"
},
  "geometry": {"coordinates":[-0.83179,5.58144],"type":"Point"}
}