{
  "type": "Feature",
  "properties": {
    "gn:admin1_code":"00",
    "gn:asciiname":"Edumasin",
    "gn:country_code":"GH",
    "gn:dem":202,
    "gn:feature_class":"P",
    "gn:feature_code":"PPL",
    "gn:name":"Edumasin",
    "gn:population":0,
    "gn:timezone":"Africa/Accra",
    "iso:country":"GH",
    "name:und_x_variant":[
        "Adumasa",
        "Edumasin"
    ],
    "wof:name":"Edumasin",
    "wof:placetype":"locality"
},
  "geometry": {"coordinates":[0.06468,6.36788],"type":"Point"}
}