{
  "type": "Feature",
  "properties": {
    "gn:admin1_code":"00",
    "gn:asciiname":"Asunafo",
    "gn:country_code":"GH",
    "gn:dem":167,
    "gn:feature_class":"P",
    "gn:feature_code":"PPL",
    "gn:name":"Asunafo",
    "gn:population":0,
    "gn:timezone":"Africa/Accra",
    "iso:country":"GH",
    "wof:name":"Asunafo",
    "wof:placetype":"locality"
},
  "geometry": {"coordinates":[-1.08333,6.88333],"type":"Point"}
}