{
  "type": "Feature",
  "properties": {
    "gn:admin1_code":"00",
    "gn:asciiname":"Luomba",
    "gn:cc2":"GH",
    "gn:country_code":"GH",
    "gn:dem":184,
    "gn:feature_class":"P",
    "gn:feature_code":"PPL",
    "gn:name":"Luomba",
    "gn:population":0,
    "gn:timezone":"Africa/Accra",
    "iso:country":"GH",
    "name:und_x_variant":[
        "Lomba",
        "Luomba"
    ],
    "wof:name":"Luomba",
    "wof:placetype":"locality"
},
  "geometry": {"coordinates":[-0.06667,10.15],"type":"Point"}
}