{
  "type": "Feature",
  "properties": {
    "gn:admin1_code":"00",
    "gn:asciiname":"Jang",
    "gn:country_code":"GH",
    "gn:dem":345,
    "gn:feature_class":"P",
    "gn:feature_code":"PPL",
    "gn:name":"Jang",
    "gn:population":0,
    "gn:timezone":"Africa/Accra",
    "iso:country":"GH",
    "name:bul_x_preferred":[
        "\u0427\u0430\u043d"
    ],
    "name:ceb_x_preferred":[
        "Jang"
    ],
    "name:ces_x_preferred":[
        "Jang"
    ],
    "name:deu_x_preferred":[
        "Jang"
    ],
    "name:fin_x_preferred":[
        "Jang"
    ],
    "name:rus_x_preferred":[
        "\u0427\u0430\u043d"
    ],
    "name:swe_x_preferred":[
        "Jang"
    ],
    "name:ukr_x_preferred":[
        "\u0427\u0430\u043d"
    ],
    "wof:name":"Jang",
    "wof:placetype":"locality"
},
  "geometry": {"coordinates":[-2.46066,10.19973],"type":"Point"}
}