{
  "type": "Feature",
  "properties": {
    "gn:admin1_code":"00",
    "gn:asciiname":"Jang",
    "gn:country_code":"GH",
    "gn:dem":345,
    "gn:feature_class":"P",
    "gn:feature_code":"PPL",
    "gn:name":"Jang",
    "gn:population":0,
    "gn:timezone":"Africa/Accra",
    "iso:country":"GH",
    "wof:name":"Jang",
    "wof:placetype":"locality"
},
  "geometry": {"coordinates":[-2.46066,10.19973],"type":"Point"}
}