{
  "type": "Feature",
  "properties": {
    "gn:admin1_code":"00",
    "gn:asciiname":"Gwira Achinum",
    "gn:cc2":"GH",
    "gn:country_code":"GH",
    "gn:dem":5,
    "gn:feature_class":"P",
    "gn:feature_code":"PPL",
    "gn:name":"Gwira Achinum",
    "gn:population":0,
    "gn:timezone":"Africa/Accra",
    "iso:country":"GH",
    "name:und_x_variant":[
        "Gwira Akyinim",
        "Gwera Akyenmu",
        "Gwira",
        "Gwira Achinum"
    ],
    "wof:name":"Gwira Achinum",
    "wof:placetype":"locality"
},
  "geometry": {"coordinates":[-1.36667,5.08333],"type":"Point"}
}