{
  "type": "Feature",
  "properties": {
    "gn:admin1_code":"09",
    "gn:asciiname":"Animakrom",
    "gn:country_code":"GH",
    "gn:dem":13,
    "gn:feature_class":"P",
    "gn:feature_code":"PPL",
    "gn:name":"Animakrom",
    "gn:population":0,
    "gn:timezone":"Africa/Accra",
    "iso:country":"GH",
    "name:eng_x_preferred":[
        "Animakrom"
    ],
    "wof:name":"Animakrom",
    "wof:placetype":"locality"
},
  "geometry": {"coordinates":[-2.08361,4.83343],"type":"Point"}
}