{
  "type": "Feature",
  "properties": {
    "gn:admin1_code":"09",
    "gn:asciiname":"Mampong",
    "gn:country_code":"GH",
    "gn:dem":22,
    "gn:feature_class":"P",
    "gn:feature_code":"PPL",
    "gn:name":"Mampong",
    "gn:population":0,
    "gn:timezone":"Africa/Accra",
    "iso:country":"GH",
    "name:ceb_x_preferred":[
        "Mampong"
    ],
    "name:deu_x_preferred":[
        "Mampong"
    ],
    "name:fra_x_preferred":[
        "Mampong"
    ],
    "name:ita_x_preferred":[
        "Mampong"
    ],
    "name:nld_x_preferred":[
        "Mampong"
    ],
    "name:pol_x_preferred":[
        "Mampong"
    ],
    "name:spa_x_preferred":[
        "Mampong"
    ],
    "name:swe_x_preferred":[
        "Mampong"
    ],
    "name:und_x_variant":[
        "Mampon",
        "Mampong"
    ],
    "name:urd_x_preferred":[
        "\u0645\u0627\u0645\u067e\u0648\u0646\u06af"
    ],
    "wof:name":"Mampong",
    "wof:placetype":"locality"
},
  "geometry": {"coordinates":[-1.72861,5.11162],"type":"Point"}
}