{
  "type": "Feature",
  "properties": {
    "gn:admin1_code":"00",
    "gn:asciiname":"Gwosi",
    "gn:country_code":"GH",
    "gn:dem":209,
    "gn:feature_class":"P",
    "gn:feature_code":"PPL",
    "gn:name":"Gwosi",
    "gn:population":0,
    "gn:timezone":"Africa/Accra",
    "iso:country":"GH",
    "name:und_x_variant":[
        "Owosi",
        "Gwosi"
    ],
    "wof:name":"Gwosi",
    "wof:placetype":"locality"
},
  "geometry": {"coordinates":[-0.48369,10.70149],"type":"Point"}
}