{
  "type": "Feature",
  "properties": {
    "gn:admin1_code":"00",
    "gn:asciiname":"Bisitinga",
    "gn:country_code":"GH",
    "gn:dem":196,
    "gn:feature_class":"P",
    "gn:feature_code":"PPL",
    "gn:name":"Bisitinga",
    "gn:population":0,
    "gn:timezone":"Africa/Accra",
    "iso:country":"GH",
    "wof:name":"Bisitinga",
    "wof:placetype":"locality"
},
  "geometry": {"coordinates":[-0.01311,10.44422],"type":"Point"}
}