{
  "type": "Feature",
  "properties": {
    "gn:admin1_code":"00",
    "gn:asciiname":"Pemenasi",
    "gn:country_code":"GH",
    "gn:dem":193,
    "gn:feature_class":"P",
    "gn:feature_code":"PPL",
    "gn:name":"Pemenasi",
    "gn:population":0,
    "gn:timezone":"Africa/Accra",
    "iso:country":"GH",
    "name:und_x_variant":[
        "Pemenase",
        "Pemenasi"
    ],
    "wof:name":"Pemenasi",
    "wof:placetype":"locality"
},
  "geometry": {"coordinates":[-1.30993,6.52354],"type":"Point"}
}