{
  "type": "Feature",
  "properties": {
    "gn:admin1_code":"09",
    "gn:asciiname":"Dominibo",
    "gn:country_code":"GH",
    "gn:dem":173,
    "gn:feature_class":"P",
    "gn:feature_code":"PPL",
    "gn:name":"Dominibo",
    "gn:population":0,
    "gn:timezone":"Africa/Accra",
    "iso:country":"GH",
    "name:eng_x_preferred":[
        "Dominibo"
    ],
    "name:und_x_variant":[
        "Domenebo",
        "Domiabo"
    ],
    "wof:name":"Dominibo",
    "wof:placetype":"locality"
},
  "geometry": {"coordinates":[-2.91682,6.5154],"type":"Point"}
}