{
  "type": "Feature",
  "properties": {
    "gn:admin1_code":"11",
    "gn:asciiname":"Sangwia",
    "gn:country_code":"GH",
    "gn:dem":288,
    "gn:feature_class":"P",
    "gn:feature_code":"PPL",
    "gn:name":"Sangwia",
    "gn:population":0,
    "gn:timezone":"Africa/Accra",
    "iso:country":"GH",
    "name:und_x_variant":[
        "Sanwie",
        "Sangwia"
    ],
    "wof:name":"Sangwia",
    "wof:placetype":"locality"
},
  "geometry": {"coordinates":[-2.59395,10.48722],"type":"Point"}
}