{
  "type": "Feature",
  "properties": {
    "gn:admin1_code":"00",
    "gn:asciiname":"Adasan",
    "gn:country_code":"GH",
    "gn:dem":17,
    "gn:feature_class":"P",
    "gn:feature_code":"PPL",
    "gn:name":"Adasan",
    "gn:population":0,
    "gn:timezone":"Africa/Accra",
    "iso:country":"GH",
    "wof:name":"Adasan",
    "wof:placetype":"locality"
},
  "geometry": {"coordinates":[-2.21667,5.03333],"type":"Point"}
}