{
  "type": "Feature",
  "properties": {
    "gn:admin1_code":"00",
    "gn:asciiname":"Bong",
    "gn:country_code":"GH",
    "gn:dem":220,
    "gn:feature_class":"P",
    "gn:feature_code":"PPL",
    "gn:name":"Bong",
    "gn:population":0,
    "gn:timezone":"Africa/Accra",
    "iso:country":"GH",
    "wof:name":"Bong",
    "wof:placetype":"locality"
},
  "geometry": {"coordinates":[-0.21181,9.28843],"type":"Point"}
}