{
  "type": "Feature",
  "properties": {
    "gn:admin1_code":"02",
    "gn:asciiname":"Mamponteng",
    "gn:country_code":"GH",
    "gn:dem":274,
    "gn:feature_class":"P",
    "gn:feature_code":"PPLA2",
    "gn:name":"Mamponteng",
    "gn:population":0,
    "gn:timezone":"Africa/Accra",
    "iso:country":"GH",
    "name:swe_x_preferred":[
        "Mamponteng"
    ],
    "wof:name":"Mamponteng",
    "wof:placetype":"locality"
},
  "geometry": {"coordinates":[-1.55,6.73333],"type":"Point"}
}