{
  "type": "Feature",
  "properties": {
    "gn:admin1_code":"00",
    "gn:asciiname":"Dawa Trim",
    "gn:country_code":"GH",
    "gn:dem":368,
    "gn:feature_class":"P",
    "gn:feature_code":"PPL",
    "gn:name":"Dawa Trim",
    "gn:population":0,
    "gn:timezone":"Africa/Accra",
    "iso:country":"GH",
    "wof:name":"Dawa Trim",
    "wof:placetype":"locality"
},
  "geometry": {"coordinates":[-0.21932,6.38704],"type":"Point"}
}