{
  "type": "Feature",
  "properties": {
    "gn:admin1_code":"09",
    "gn:asciiname":"Anyuom",
    "gn:country_code":"GH",
    "gn:dem":68,
    "gn:feature_class":"P",
    "gn:feature_code":"PPL",
    "gn:name":"Anyuom",
    "gn:population":0,
    "gn:timezone":"Africa/Accra",
    "iso:country":"GH",
    "name:eng_x_preferred":[
        "Anyuom"
    ],
    "wof:name":"Anyuom",
    "wof:placetype":"locality"
},
  "geometry": {"coordinates":[-1.65643,5.20777],"type":"Point"}
}