{
  "type": "Feature",
  "properties": {
    "gn:admin1_code":"04",
    "gn:asciiname":"Anwiado",
    "gn:country_code":"GH",
    "gn:dem":-9999,
    "gn:feature_class":"P",
    "gn:feature_code":"PPL",
    "gn:name":"Anwiado",
    "gn:population":0,
    "gn:timezone":"Africa/Accra",
    "iso:country":"GH",
    "name:und_x_variant":[
        "Anwheado",
        "Anwiado"
    ],
    "wof:name":"Anwiado",
    "wof:placetype":"locality"
},
  "geometry": {"coordinates":[-1.59066,5.03451],"type":"Point"}
}