{
  "type": "Feature",
  "properties": {
    "gn:admin1_code":"00",
    "gn:asciiname":"Abodiem",
    "gn:cc2":"GH",
    "gn:country_code":"GH",
    "gn:dem":250,
    "gn:feature_class":"P",
    "gn:feature_code":"PPL",
    "gn:name":"Abodiem",
    "gn:population":0,
    "gn:timezone":"Africa/Accra",
    "iso:country":"GH",
    "name:und_x_variant":[
        "Abodeem",
        "Abodiem"
    ],
    "wof:name":"Abodiem",
    "wof:placetype":"locality"
},
  "geometry": {"coordinates":[-1.13333,6.95],"type":"Point"}
}