{
  "type": "Feature",
  "properties": {
    "gn:admin1_code":"00",
    "gn:asciiname":"Kwabenaponsakrom",
    "gn:cc2":"GH",
    "gn:country_code":"GH",
    "gn:dem":313,
    "gn:feature_class":"P",
    "gn:feature_code":"PPL",
    "gn:name":"Kwabenaponsakrom",
    "gn:population":0,
    "gn:timezone":"Africa/Accra",
    "iso:country":"GH",
    "name:und_x_variant":[
        "Kwabenaponsokrom",
        "Kwabenaponsakrom"
    ],
    "wof:name":"Kwabenaponsakrom",
    "wof:placetype":"locality"
},
  "geometry": {"coordinates":[-1.23333,6.98333],"type":"Point"}
}