{
  "type": "Feature",
  "properties": {
    "gn:admin1_code":"00",
    "gn:asciiname":"Asaman",
    "gn:country_code":"GH",
    "gn:dem":120,
    "gn:feature_class":"P",
    "gn:feature_code":"PPL",
    "gn:name":"Asaman",
    "gn:population":0,
    "gn:timezone":"Africa/Accra",
    "iso:country":"GH",
    "wof:name":"Asaman",
    "wof:placetype":"locality"
},
  "geometry": {"coordinates":[-1.0209,5.54095],"type":"Point"}
}