{
  "type": "Feature",
  "properties": {
    "gn:admin1_code":"00",
    "gn:asciiname":"Obodan",
    "gn:country_code":"GH",
    "gn:dem":118,
    "gn:feature_class":"P",
    "gn:feature_code":"PPL",
    "gn:name":"Obodan",
    "gn:population":0,
    "gn:timezone":"Africa/Accra",
    "iso:country":"GH",
    "wof:name":"Obodan",
    "wof:placetype":"locality"
},
  "geometry": {"coordinates":[-0.26166,5.81533],"type":"Point"}
}