{
  "type": "Feature",
  "properties": {
    "gn:admin1_code":"09",
    "gn:asciiname":"Kramokrom",
    "gn:country_code":"GH",
    "gn:dem":94,
    "gn:feature_class":"P",
    "gn:feature_code":"PPL",
    "gn:name":"Kramokrom",
    "gn:population":0,
    "gn:timezone":"Africa/Accra",
    "iso:country":"GH",
    "name:und_x_variant":[
        "Kamokrom"
    ],
    "wof:name":"Kramokrom",
    "wof:placetype":"locality"
},
  "geometry": {"coordinates":[-2.78662,5.76871],"type":"Point"}
}