{
  "type": "Feature",
  "properties": {
    "gn:admin1_code":"00",
    "gn:asciiname":"Lampol",
    "gn:cc2":"GH",
    "gn:country_code":"GH",
    "gn:dem":113,
    "gn:feature_class":"P",
    "gn:feature_code":"PPL",
    "gn:name":"Lampol",
    "gn:population":0,
    "gn:timezone":"Africa/Accra",
    "iso:country":"GH",
    "name:und_x_variant":[
        "Lampor",
        "Kunshi Sonupe",
        "Lampol"
    ],
    "wof:name":"Lampol",
    "wof:placetype":"locality"
},
  "geometry": {"coordinates":[-0.58333,8.65],"type":"Point"}
}