{
  "type": "Feature",
  "properties": {
    "gn:admin1_code":"00",
    "gn:asciiname":"Gumon",
    "gn:country_code":"GH",
    "gn:dem":177,
    "gn:feature_class":"P",
    "gn:feature_code":"PPL",
    "gn:name":"Gumon",
    "gn:population":0,
    "gn:timezone":"Africa/Accra",
    "iso:country":"GH",
    "name:und_x_variant":[
        "Gummo",
        "Gumo",
        "Gumon"
    ],
    "wof:name":"Gumon",
    "wof:placetype":"locality"
},
  "geometry": {"coordinates":[-0.89798,9.4979],"type":"Point"}
}