{
  "type": "Feature",
  "properties": {
    "gn:admin1_code":"00",
    "gn:asciiname":"Adidokpoe",
    "gn:country_code":"GH",
    "gn:dem":30,
    "gn:feature_class":"P",
    "gn:feature_code":"PPL",
    "gn:name":"Adidokpoe",
    "gn:population":0,
    "gn:timezone":"Africa/Accra",
    "iso:country":"GH",
    "wof:name":"Adidokpoe",
    "wof:placetype":"locality"
},
  "geometry": {"coordinates":[0.45982,6.27374],"type":"Point"}
}