{
  "type": "Feature",
  "properties": {
    "gn:admin1_code":"00",
    "gn:asciiname":"Nobeso",
    "gn:country_code":"GH",
    "gn:dem":312,
    "gn:feature_class":"P",
    "gn:feature_code":"PPL",
    "gn:name":"Nobeso",
    "gn:population":0,
    "gn:timezone":"Africa/Accra",
    "iso:country":"GH",
    "name:und_x_variant":[
        "Akyeansa Nnobesu",
        "Nobeso"
    ],
    "wof:name":"Nobeso",
    "wof:placetype":"locality"
},
  "geometry": {"coordinates":[-0.58251,6.03429],"type":"Point"}
}