{
  "type": "Feature",
  "properties": {
    "gn:admin1_code":"00",
    "gn:asciiname":"Apantem",
    "gn:cc2":"GH",
    "gn:country_code":"GH",
    "gn:dem":313,
    "gn:feature_class":"P",
    "gn:feature_code":"PPL",
    "gn:name":"Apantem",
    "gn:population":0,
    "gn:timezone":"Africa/Accra",
    "iso:country":"GH",
    "name:und_x_variant":[
        "Ampentem",
        "Apantem"
    ],
    "wof:name":"Apantem",
    "wof:placetype":"locality"
},
  "geometry": {"coordinates":[-0.23333,5.86667],"type":"Point"}
}