{
  "type": "Feature",
  "properties": {
    "gn:admin1_code":"00",
    "gn:asciiname":"Kugure",
    "gn:cc2":"GH",
    "gn:country_code":"GH",
    "gn:dem":223,
    "gn:feature_class":"P",
    "gn:feature_code":"PPL",
    "gn:name":"Kugure",
    "gn:population":0,
    "gn:timezone":"Africa/Accra",
    "iso:country":"GH",
    "name:und_x_variant":[
        "Sekoti Benzure Kugure",
        "Kugure"
    ],
    "wof:name":"Kugure",
    "wof:placetype":"locality"
},
  "geometry": {"coordinates":[-0.65,10.78333],"type":"Point"}
}