{
  "type": "Feature",
  "properties": {
    "gn:admin1_code":"00",
    "gn:asciiname":"Djave",
    "gn:country_code":"GH",
    "gn:dem":59,
    "gn:feature_class":"P",
    "gn:feature_code":"PPL",
    "gn:name":"Djave",
    "gn:population":0,
    "gn:timezone":"Africa/Accra",
    "iso:country":"GH",
    "wof:name":"Djave",
    "wof:placetype":"locality"
},
  "geometry": {"coordinates":[0.7336,6.32125],"type":"Point"}
}