{
  "type": "Feature",
  "properties": {
    "gn:admin1_code":"00",
    "gn:asciiname":"Fule",
    "gn:country_code":"GH",
    "gn:dem":233,
    "gn:feature_class":"P",
    "gn:feature_code":"PPL",
    "gn:name":"Fule",
    "gn:population":0,
    "gn:timezone":"Africa/Accra",
    "iso:country":"GH",
    "wof:name":"Fule",
    "wof:placetype":"locality"
},
  "geometry": {"coordinates":[-0.25375,9.34419],"type":"Point"}
}