{
  "type": "Feature",
  "properties": {
    "gn:admin1_code":"09",
    "gn:asciiname":"Arobaso",
    "gn:country_code":"GH",
    "gn:dem":17,
    "gn:feature_class":"P",
    "gn:feature_code":"PPL",
    "gn:name":"Arobaso",
    "gn:population":0,
    "gn:timezone":"Africa/Accra",
    "iso:country":"GH",
    "name:und_x_variant":[
        "Aro Bokaso",
        "Alabokazo",
        "Arobaso"
    ],
    "wof:name":"Arobaso",
    "wof:placetype":"locality"
},
  "geometry": {"coordinates":[-2.43404,4.99578],"type":"Point"}
}