{
  "type": "Feature",
  "properties": {
    "gn:admin1_code":"00",
    "gn:asciiname":"Dambrunsi",
    "gn:country_code":"GH",
    "gn:dem":166,
    "gn:feature_class":"P",
    "gn:feature_code":"PPL",
    "gn:name":"Dambrunsi",
    "gn:population":0,
    "gn:timezone":"Africa/Accra",
    "iso:country":"GH",
    "name:und_x_variant":[
        "Kanjarga Daburinsa",
        "Dambrunsi"
    ],
    "wof:name":"Dambrunsi",
    "wof:placetype":"locality"
},
  "geometry": {"coordinates":[-1.43097,10.5144],"type":"Point"}
}