{
  "type": "Feature",
  "properties": {
    "gn:admin1_code":"00",
    "gn:asciiname":"Metima",
    "gn:country_code":"GH",
    "gn:dem":320,
    "gn:feature_class":"P",
    "gn:feature_code":"PPL",
    "gn:name":"Metima",
    "gn:population":0,
    "gn:timezone":"Africa/Accra",
    "iso:country":"GH",
    "wof:name":"Metima",
    "wof:placetype":"locality"
},
  "geometry": {"coordinates":[-1.16667,6.98333],"type":"Point"}
}