{
  "type": "Feature",
  "properties": {
    "gn:admin1_code":"00",
    "gn:asciiname":"Siabuda",
    "gn:country_code":"GH",
    "gn:dem":73,
    "gn:feature_class":"P",
    "gn:feature_code":"PPL",
    "gn:name":"Siabuda",
    "gn:population":0,
    "gn:timezone":"Africa/Accra",
    "iso:country":"GH",
    "name:und_x_variant":[
        "Osiabura",
        "Siabuda"
    ],
    "wof:name":"Siabuda",
    "wof:placetype":"locality"
},
  "geometry": {"coordinates":[0.1961,6.37369],"type":"Point"}
}