{
  "type": "Feature",
  "properties": {
    "gn:admin1_code":"00",
    "gn:asciiname":"Nchirede",
    "gn:country_code":"GH",
    "gn:dem":222,
    "gn:feature_class":"P",
    "gn:feature_code":"PPL",
    "gn:name":"Nchirede",
    "gn:population":0,
    "gn:timezone":"Africa/Accra",
    "iso:country":"GH",
    "wof:name":"Nchirede",
    "wof:placetype":"locality"
},
  "geometry": {"coordinates":[-0.13333,5.88333],"type":"Point"}
}