{
  "type": "Feature",
  "properties": {
    "gn:admin1_code":"02",
    "gn:asciiname":"Adwumam",
    "gn:country_code":"GH",
    "gn:dem":202,
    "gn:feature_class":"P",
    "gn:feature_code":"PPL",
    "gn:name":"Adwumam",
    "gn:population":0,
    "gn:timezone":"Africa/Accra",
    "iso:country":"GH",
    "name:eng_x_preferred":[
        "Adwumam"
    ],
    "name:und_x_variant":[
        "Ajumum",
        "Ajumam"
    ],
    "wof:name":"Adwumam",
    "wof:placetype":"locality"
},
  "geometry": {"coordinates":[-1.56544,6.52767],"type":"Point"}
}