{
  "type": "Feature",
  "properties": {
    "gn:admin1_code":"00",
    "gn:asciiname":"Kwata",
    "gn:country_code":"GH",
    "gn:dem":128,
    "gn:feature_class":"P",
    "gn:feature_code":"PPL",
    "gn:name":"Kwata",
    "gn:population":0,
    "gn:timezone":"Africa/Accra",
    "iso:country":"GH",
    "name:und_x_variant":[
        "Kwataa",
        "Kwata"
    ],
    "wof:name":"Kwata",
    "wof:placetype":"locality"
},
  "geometry": {"coordinates":[-1.238,5.63936],"type":"Point"}
}