{
  "type": "Feature",
  "properties": {
    "gn:admin1_code":"00",
    "gn:asciiname":"Kanbowele",
    "gn:country_code":"GH",
    "gn:dem":161,
    "gn:feature_class":"P",
    "gn:feature_code":"PPL",
    "gn:name":"Kanbowele",
    "gn:population":0,
    "gn:timezone":"Africa/Accra",
    "iso:country":"GH",
    "name:und_x_variant":[
        "Kabonwole",
        "Kabauwele",
        "Kaponkp\u00e1n",
        "Kabonwule",
        "Kabonwele",
        "Kanbowele"
    ],
    "wof:name":"Kanbowele",
    "wof:placetype":"locality"
},
  "geometry": {"coordinates":[0.03306,8.35271],"type":"Point"}
}