{
  "type": "Feature",
  "properties": {
    "gn:admin1_code":"02",
    "gn:asciiname":"Maaban",
    "gn:country_code":"GH",
    "gn:dem":227,
    "gn:feature_class":"P",
    "gn:feature_code":"PPL",
    "gn:name":"Maaban",
    "gn:population":0,
    "gn:timezone":"Africa/Accra",
    "iso:country":"GH",
    "name:aka_x_preferred":[
        "Maaban"
    ],
    "name:und_x_variant":[
        "Mabang"
    ],
    "wof:name":"Maaban",
    "wof:placetype":"locality"
},
  "geometry": {"coordinates":[-2.22158,6.99595],"type":"Point"}
}