{
  "type": "Feature",
  "properties": {
    "gn:admin1_code":"00",
    "gn:asciiname":"Gambibigo",
    "gn:country_code":"GH",
    "gn:dem":179,
    "gn:feature_class":"P",
    "gn:feature_code":"PPL",
    "gn:name":"Gambibigo",
    "gn:population":0,
    "gn:timezone":"Africa/Accra",
    "iso:country":"GH",
    "name:und_x_variant":[
        "Bolga Gambibigo",
        "Gambugo",
        "Gambibigo"
    ],
    "wof:name":"Gambibigo",
    "wof:placetype":"locality"
},
  "geometry": {"coordinates":[-0.83831,10.76683],"type":"Point"}
}