{
  "type": "Feature",
  "properties": {
    "gn:admin1_code":"00",
    "gn:asciiname":"Abuchen",
    "gn:country_code":"GH",
    "gn:dem":182,
    "gn:feature_class":"P",
    "gn:feature_code":"PPL",
    "gn:name":"Abuchen",
    "gn:population":0,
    "gn:timezone":"Africa/Accra",
    "iso:country":"GH",
    "wof:name":"Abuchen",
    "wof:placetype":"locality"
},
  "geometry": {"coordinates":[-0.73333,5.85],"type":"Point"}
}