{
  "type": "Feature",
  "properties": {
    "gn:admin1_code":"00",
    "gn:asciiname":"Takwili",
    "gn:country_code":"GH",
    "gn:dem":124,
    "gn:feature_class":"P",
    "gn:feature_code":"PPL",
    "gn:name":"Takwili",
    "gn:population":0,
    "gn:timezone":"Africa/Accra",
    "iso:country":"GH",
    "name:und_x_variant":[
        "Takpili",
        "Takwil",
        "Takwili"
    ],
    "wof:name":"Takwili",
    "wof:placetype":"locality"
},
  "geometry": {"coordinates":[-0.57789,9.30147],"type":"Point"}
}