{
  "type": "Feature",
  "properties": {
    "gn:admin1_code":"00",
    "gn:asciiname":"Bonkrom",
    "gn:country_code":"GH",
    "gn:dem":168,
    "gn:feature_class":"P",
    "gn:feature_code":"PPL",
    "gn:name":"Bonkrom",
    "gn:population":0,
    "gn:timezone":"Africa/Accra",
    "iso:country":"GH",
    "wof:name":"Bonkrom",
    "wof:placetype":"locality"
},
  "geometry": {"coordinates":[-1.35,6.15],"type":"Point"}
}