{
  "type": "Feature",
  "properties": {
    "gn:admin1_code":"04",
    "gn:asciiname":"Owusukurom",
    "gn:country_code":"GH",
    "gn:dem":130,
    "gn:feature_class":"P",
    "gn:feature_code":"PPL",
    "gn:name":"Owusukurom",
    "gn:population":0,
    "gn:timezone":"Africa/Accra",
    "iso:country":"GH",
    "name:eng_x_preferred":[
        "Owusukurom"
    ],
    "name:und_x_variant":[
        "Yaowusukrom"
    ],
    "wof:name":"Owusukurom",
    "wof:placetype":"locality"
},
  "geometry": {"coordinates":[-1.66562,5.82724],"type":"Point"}
}