{
  "type": "Feature",
  "properties": {
    "gn:admin1_code":"00",
    "gn:asciiname":"Akuri",
    "gn:cc2":"GH",
    "gn:country_code":"GH",
    "gn:dem":223,
    "gn:feature_class":"P",
    "gn:feature_code":"PPL",
    "gn:name":"Akuri",
    "gn:population":0,
    "gn:timezone":"Africa/Accra",
    "iso:country":"GH",
    "name:und_x_variant":[
        "Gure",
        "Akure",
        "Akuri"
    ],
    "wof:name":"Akuri",
    "wof:placetype":"locality"
},
  "geometry": {"coordinates":[-0.48333,10.75],"type":"Point"}
}