{
  "type": "Feature",
  "properties": {
    "gn:admin1_code":"00",
    "gn:asciiname":"Anoe",
    "gn:country_code":"GH",
    "gn:dem":60,
    "gn:feature_class":"P",
    "gn:feature_code":"PPL",
    "gn:name":"Anoe",
    "gn:population":0,
    "gn:timezone":"Africa/Accra",
    "iso:country":"GH",
    "name:und_x_variant":[
        "Anbe",
        "Anoe"
    ],
    "wof:name":"Anoe",
    "wof:placetype":"locality"
},
  "geometry": {"coordinates":[-1.72991,4.98177],"type":"Point"}
}