{
  "type": "Feature",
  "properties": {
    "gn:admin1_code":"00",
    "gn:asciiname":"Longo",
    "gn:country_code":"GH",
    "gn:dem":198,
    "gn:feature_class":"P",
    "gn:feature_code":"PPL",
    "gn:name":"Longo",
    "gn:population":0,
    "gn:timezone":"Africa/Accra",
    "iso:country":"GH",
    "name:ita_x_preferred":[
        "Longo"
    ],
    "name:kat_x_preferred":[
        "\u10da\u10dd\u10dc\u10d2\u10dd"
    ],
    "name:und_x_variant":[
        "Kandiga Longo",
        "Longo"
    ],
    "wof:name":"Longo",
    "wof:placetype":"locality"
},
  "geometry": {"coordinates":[-0.97532,10.91143],"type":"Point"}
}