{
  "type": "Feature",
  "properties": {
    "gn:admin1_code":"00",
    "gn:asciiname":"Misikrom",
    "gn:cc2":"GH",
    "gn:country_code":"GH",
    "gn:dem":179,
    "gn:feature_class":"P",
    "gn:feature_code":"PPL",
    "gn:name":"Misikrom",
    "gn:population":0,
    "gn:timezone":"Africa/Accra",
    "iso:country":"GH",
    "name:und_x_variant":[
        "Besekurom",
        "Misikrum",
        "Misikrom"
    ],
    "wof:name":"Misikrom",
    "wof:placetype":"locality"
},
  "geometry": {"coordinates":[-0.08333,6.35],"type":"Point"}
}