{
  "type": "Feature",
  "properties": {
    "gn:admin1_code":"02",
    "gn:asciiname":"Abrobuesin",
    "gn:country_code":"GH",
    "gn:dem":152,
    "gn:feature_class":"P",
    "gn:feature_code":"PPL",
    "gn:name":"Abrobuesin",
    "gn:population":0,
    "gn:timezone":"Africa/Accra",
    "iso:country":"GH",
    "name:und_x_variant":[
        "Abrobuasen",
        "Abrobuesin"
    ],
    "wof:name":"Abrobuesin",
    "wof:placetype":"locality"
},
  "geometry": {"coordinates":[-1.88278,6.03438],"type":"Point"}
}