{
  "type": "Feature",
  "properties": {
    "gn:admin1_code":"01",
    "gn:asciiname":"Ashaliaman",
    "gn:country_code":"GH",
    "gn:dem":89,
    "gn:feature_class":"P",
    "gn:feature_code":"PPL",
    "gn:name":"Ashaliaman",
    "gn:population":0,
    "gn:timezone":"Africa/Accra",
    "iso:country":"GH",
    "name:eng_x_preferred":[
        "Ashaliaman"
    ],
    "name:eng_x_variant":[
        "Ashaleanan"
    ],
    "name:und_x_variant":[
        "Ashale Anan",
        "Ashalianan"
    ],
    "wof:name":"Ashaliaman",
    "wof:placetype":"locality"
},
  "geometry": {"coordinates":[-0.48525,5.7404],"type":"Point"}
}