{
  "type": "Feature",
  "properties": {
    "gn:admin1_code":"06",
    "gn:asciiname":"Larekago",
    "gn:country_code":"GH",
    "gn:dem":174,
    "gn:feature_class":"P",
    "gn:feature_code":"PPL",
    "gn:name":"Larekago",
    "gn:population":0,
    "gn:timezone":"Africa/Accra",
    "iso:country":"GH",
    "name:und_x_variant":[
        "Kago",
        "Lare",
        "Larekago"
    ],
    "wof:name":"Larekago",
    "wof:placetype":"locality"
},
  "geometry": {"coordinates":[0.10976,10.48236],"type":"Point"}
}