{
  "type": "Feature",
  "properties": {
    "gn:admin1_code":"03",
    "gn:asciiname":"Bodaa",
    "gn:country_code":"GH",
    "gn:dem":320,
    "gn:feature_class":"P",
    "gn:feature_code":"PPL",
    "gn:name":"Bodaa",
    "gn:population":0,
    "gn:timezone":"Africa/Accra",
    "iso:country":"GH",
    "name:und_x_variant":[
        "Bawda",
        "Bodaa",
        "Bawdah"
    ],
    "wof:name":"Bodaa",
    "wof:placetype":"locality"
},
  "geometry": {"coordinates":[-2.82177,7.78202],"type":"Point"}
}