{
  "type": "Feature",
  "properties": {
    "gn:admin1_code":"00",
    "gn:asciiname":"Aiyinabrim",
    "gn:country_code":"GH",
    "gn:dem":94,
    "gn:feature_class":"P",
    "gn:feature_code":"PPL",
    "gn:name":"Aiyinabrim",
    "gn:population":0,
    "gn:timezone":"Africa/Accra",
    "iso:country":"GH",
    "name:und_x_variant":[
        "Enyinaberemu",
        "Aiyinabrim"
    ],
    "wof:name":"Aiyinabrim",
    "wof:placetype":"locality"
},
  "geometry": {"coordinates":[-2.22033,5.7496],"type":"Point"}
}