{
  "type": "Feature",
  "properties": {
    "gn:admin1_code":"02",
    "gn:asciiname":"Asanso-Patase",
    "gn:country_code":"GH",
    "gn:dem":209,
    "gn:feature_class":"P",
    "gn:feature_code":"PPL",
    "gn:name":"Asanso-Patase",
    "gn:population":0,
    "gn:timezone":"Africa/Accra",
    "iso:country":"GH",
    "name:eng_x_preferred":[
        "Asanso-Patase"
    ],
    "name:und_x_variant":[
        "Patase",
        "Patasi"
    ],
    "wof:name":"Asanso-Patase",
    "wof:placetype":"locality"
},
  "geometry": {"coordinates":[-1.63967,6.42562],"type":"Point"}
}