{
  "type": "Feature",
  "properties": {
    "gn:admin1_code":"00",
    "gn:asciiname":"Agbechemekofe",
    "gn:country_code":"GH",
    "gn:dem":67,
    "gn:feature_class":"P",
    "gn:feature_code":"PPL",
    "gn:name":"Agbechemekofe",
    "gn:population":0,
    "gn:timezone":"Africa/Accra",
    "iso:country":"GH",
    "wof:name":"Agbechemekofe",
    "wof:placetype":"locality"
},
  "geometry": {"coordinates":[0.63543,6.3847],"type":"Point"}
}