{
  "type": "Feature",
  "properties": {
    "gn:admin1_code":"00",
    "gn:asciiname":"Yetuonia",
    "gn:country_code":"GH",
    "gn:dem":183,
    "gn:feature_class":"P",
    "gn:feature_code":"PPL",
    "gn:name":"Yetuonia",
    "gn:population":0,
    "gn:timezone":"Africa/Accra",
    "iso:country":"GH",
    "name:und_x_variant":[
        "Yetonia",
        "Yetuonia"
    ],
    "wof:name":"Yetuonia",
    "wof:placetype":"locality"
},
  "geometry": {"coordinates":[-1.06467,10.89214],"type":"Point"}
}