{
  "type": "Feature",
  "properties": {
    "gn:admin1_code":"00",
    "gn:asciiname":"Obum",
    "gn:country_code":"GH",
    "gn:dem":35,
    "gn:feature_class":"P",
    "gn:feature_code":"PPL",
    "gn:name":"Obum",
    "gn:population":0,
    "gn:timezone":"Africa/Accra",
    "iso:country":"GH",
    "name:und_x_variant":[
        "Oboum",
        "Obum"
    ],
    "wof:name":"Obum",
    "wof:placetype":"locality"
},
  "geometry": {"coordinates":[-1.02348,5.36304],"type":"Point"}
}