{
  "type": "Feature",
  "properties": {
    "gn:admin1_code":"00",
    "gn:asciiname":"Hiawa",
    "gn:country_code":"GH",
    "gn:dem":51,
    "gn:feature_class":"P",
    "gn:feature_code":"PPL",
    "gn:name":"Hiawa",
    "gn:population":0,
    "gn:timezone":"Africa/Accra",
    "iso:country":"GH",
    "name:und_x_variant":[
        "Nhia",
        "Hiawa"
    ],
    "wof:name":"Hiawa",
    "wof:placetype":"locality"
},
  "geometry": {"coordinates":[-2.16215,5.61662],"type":"Point"}
}