{
  "type": "Feature",
  "properties": {
    "gn:admin1_code":"00",
    "gn:asciiname":"Oworom",
    "gn:country_code":"GH",
    "gn:dem":152,
    "gn:feature_class":"P",
    "gn:feature_code":"PPL",
    "gn:name":"Oworom",
    "gn:population":0,
    "gn:timezone":"Africa/Accra",
    "iso:country":"GH",
    "name:und_x_variant":[
        "Oworam",
        "Oworom"
    ],
    "wof:name":"Oworom",
    "wof:placetype":"locality"
},
  "geometry": {"coordinates":[-0.60622,5.94121],"type":"Point"}
}