{
  "type": "Feature",
  "properties": {
    "gn:admin1_code":"00",
    "gn:asciiname":"Ninyawyiri",
    "gn:country_code":"GH",
    "gn:dem":127,
    "gn:feature_class":"P",
    "gn:feature_code":"PPL",
    "gn:name":"Ninyawyiri",
    "gn:population":0,
    "gn:timezone":"Africa/Accra",
    "iso:country":"GH",
    "wof:name":"Ninyawyiri",
    "wof:placetype":"locality"
},
  "geometry": {"coordinates":[-1.11197,9.33406],"type":"Point"}
}