{
  "type": "Feature",
  "properties": {
    "gn:admin1_code":"00",
    "gn:asciiname":"Buamadumasi",
    "gn:country_code":"GH",
    "gn:dem":201,
    "gn:feature_class":"P",
    "gn:feature_code":"PPL",
    "gn:name":"Buamadumasi",
    "gn:population":0,
    "gn:timezone":"Africa/Accra",
    "iso:country":"GH",
    "name:und_x_variant":[
        "Boamadumase",
        "Buamadumasi"
    ],
    "wof:name":"Buamadumasi",
    "wof:placetype":"locality"
},
  "geometry": {"coordinates":[-1.34217,6.61794],"type":"Point"}
}