{
  "type": "Feature",
  "properties": {
    "gn:admin1_code":"00",
    "gn:asciiname":"Awa",
    "gn:country_code":"GH",
    "gn:dem":250,
    "gn:feature_class":"P",
    "gn:feature_code":"PPL",
    "gn:name":"Awa",
    "gn:population":0,
    "gn:timezone":"Africa/Accra",
    "iso:country":"GH",
    "wof:name":"Awa",
    "wof:placetype":"locality"
},
  "geometry": {"coordinates":[-0.88333,10.91667],"type":"Point"}
}