{
  "type": "Feature",
  "properties": {
    "gn:admin1_code":"00",
    "gn:asciiname":"Berafe",
    "gn:country_code":"GH",
    "gn:dem":74,
    "gn:feature_class":"P",
    "gn:feature_code":"PPL",
    "gn:name":"Berafe",
    "gn:population":0,
    "gn:timezone":"Africa/Accra",
    "iso:country":"GH",
    "wof:name":"Berafe",
    "wof:placetype":"locality"
},
  "geometry": {"coordinates":[0.60016,6.42418],"type":"Point"}
}