{
  "type": "Feature",
  "properties": {
    "gn:admin1_code":"00",
    "gn:asciiname":"Kpoime",
    "gn:country_code":"GH",
    "gn:dem":55,
    "gn:feature_class":"P",
    "gn:feature_code":"PPL",
    "gn:name":"Kpoime",
    "gn:population":0,
    "gn:timezone":"Africa/Accra",
    "iso:country":"GH",
    "wof:name":"Kpoime",
    "wof:placetype":"locality"
},
  "geometry": {"coordinates":[0.71667,6.35],"type":"Point"}
}