{
  "type": "Feature",
  "properties": {
    "gn:admin1_code":"01",
    "gn:asciiname":"Nankanso",
    "gn:country_code":"GH",
    "gn:dem":70,
    "gn:feature_class":"P",
    "gn:feature_code":"PPL",
    "gn:name":"Nankanso",
    "gn:population":0,
    "gn:timezone":"Africa/Accra",
    "iso:country":"GH",
    "wof:name":"Nankanso",
    "wof:placetype":"locality"
},
  "geometry": {"coordinates":[-0.46667,5.75],"type":"Point"}
}