{
  "type": "Feature",
  "properties": {
    "gn:admin1_code":"00",
    "gn:asciiname":"Samanga",
    "gn:country_code":"GH",
    "gn:dem":183,
    "gn:feature_class":"P",
    "gn:feature_code":"PPL",
    "gn:name":"Samanga",
    "gn:population":0,
    "gn:timezone":"Africa/Accra",
    "iso:country":"GH",
    "name:und_x_variant":[
        "Samago",
        "Samanga"
    ],
    "wof:name":"Samanga",
    "wof:placetype":"locality"
},
  "geometry": {"coordinates":[-0.39203,9.80647],"type":"Point"}
}