{
  "type": "Feature",
  "properties": {
    "gn:admin1_code":"00",
    "gn:asciiname":"Veme",
    "gn:country_code":"GH",
    "gn:dem":16,
    "gn:feature_class":"P",
    "gn:feature_code":"PPL",
    "gn:name":"Veme",
    "gn:population":0,
    "gn:timezone":"Africa/Accra",
    "iso:country":"GH",
    "name:und_x_variant":[
        "Weme",
        "Veme"
    ],
    "wof:name":"Veme",
    "wof:placetype":"locality"
},
  "geometry": {"coordinates":[0.87227,6.05046],"type":"Point"}
}