{
  "type": "Feature",
  "properties": {
    "gn:admin1_code":"06",
    "gn:asciiname":"Voggo",
    "gn:country_code":"GH",
    "gn:dem":134,
    "gn:feature_class":"P",
    "gn:feature_code":"PPL",
    "gn:name":"Voggo",
    "gn:population":0,
    "gn:timezone":"Africa/Accra",
    "iso:country":"GH",
    "name:und_x_variant":[
        "Vogo",
        "Voggo"
    ],
    "wof:name":"Voggo",
    "wof:placetype":"locality"
},
  "geometry": {"coordinates":[-1.03516,9.53307],"type":"Point"}
}