{
  "type": "Feature",
  "properties": {
    "gn:admin1_code":"02",
    "gn:asciiname":"Esen",
    "gn:country_code":"GH",
    "gn:dem":301,
    "gn:feature_class":"P",
    "gn:feature_code":"PPL",
    "gn:name":"Esen",
    "gn:population":0,
    "gn:timezone":"Africa/Accra",
    "iso:country":"GH",
    "name:bul_x_preferred":[
        "\u0415\u0441\u0435\u043d"
    ],
    "name:ceb_x_preferred":[
        "Esen"
    ],
    "name:deu_x_preferred":[
        "Esen"
    ],
    "name:rus_x_preferred":[
        "\u042d\u0441\u0435\u043d"
    ],
    "name:swe_x_preferred":[
        "Esen"
    ],
    "name:und_x_variant":[
        "Essen",
        "Esen"
    ],
    "wof:name":"Esen",
    "wof:placetype":"locality"
},
  "geometry": {"coordinates":[-1.61691,6.77774],"type":"Point"}
}