{
  "type": "Feature",
  "properties": {
    "gn:admin1_code":"00",
    "gn:asciiname":"Tintari",
    "gn:country_code":"GH",
    "gn:dem":143,
    "gn:feature_class":"P",
    "gn:feature_code":"PPL",
    "gn:name":"Tintari",
    "gn:population":0,
    "gn:timezone":"Africa/Accra",
    "iso:country":"GH",
    "name:und_x_variant":[
        "Tentare",
        "Tintari"
    ],
    "wof:name":"Tintari",
    "wof:placetype":"locality"
},
  "geometry": {"coordinates":[-0.88582,7.73332],"type":"Point"}
}