{
  "type": "Feature",
  "properties": {
    "gn:admin1_code":"09",
    "gn:asciiname":"Anochi",
    "gn:country_code":"GH",
    "gn:dem":6,
    "gn:feature_class":"P",
    "gn:feature_code":"PPL",
    "gn:name":"Anochi",
    "gn:population":0,
    "gn:timezone":"Africa/Accra",
    "iso:country":"GH",
    "name:und_x_variant":[
        "Nalochi",
        "Anochi"
    ],
    "wof:name":"Anochi",
    "wof:placetype":"locality"
},
  "geometry": {"coordinates":[-2.52047,4.97295],"type":"Point"}
}