{
  "type": "Feature",
  "properties": {
    "gn:admin1_code":"09",
    "gn:asciiname":"Ahyenlezo",
    "gn:country_code":"GH",
    "gn:dem":10,
    "gn:feature_class":"P",
    "gn:feature_code":"PPL",
    "gn:name":"Ahyenlezo",
    "gn:population":0,
    "gn:timezone":"Africa/Accra",
    "iso:country":"GH",
    "name:eng_x_preferred":[
        "Ahyenlezo"
    ],
    "name:eng_x_variant":[
        "Achim",
        "Akyinim"
    ],
    "wof:name":"Ahyenlezo",
    "wof:placetype":"locality"
},
  "geometry": {"coordinates":[-2.24646,4.87985],"type":"Point"}
}