{
  "type": "Feature",
  "properties": {
    "gn:admin1_code":"00",
    "gn:asciiname":"Dodo",
    "gn:country_code":"GH",
    "gn:dem":198,
    "gn:feature_class":"P",
    "gn:feature_code":"PPL",
    "gn:name":"Dodo",
    "gn:population":0,
    "gn:timezone":"Africa/Accra",
    "iso:country":"GH",
    "wof:name":"Dodo",
    "wof:placetype":"locality"
},
  "geometry": {"coordinates":[0.50682,7.82127],"type":"Point"}
}