{
  "type": "Feature",
  "properties": {
    "gn:admin1_code":"02",
    "gn:asciiname":"Kemyemua",
    "gn:country_code":"GH",
    "gn:dem":215,
    "gn:feature_class":"P",
    "gn:feature_code":"PPL",
    "gn:name":"Kemyemua",
    "gn:population":0,
    "gn:timezone":"Africa/Accra",
    "iso:country":"GH",
    "name:eng_x_preferred":[
        "Kemyemua"
    ],
    "name:eng_x_variant":[
        "Kumyemua"
    ],
    "wof:name":"Kemyemua",
    "wof:placetype":"locality"
},
  "geometry": {"coordinates":[-1.72555,6.03928],"type":"Point"}
}