{
  "type": "Feature",
  "properties": {
    "gn:admin1_code":"00",
    "gn:asciiname":"Bomodin",
    "gn:country_code":"GH",
    "gn:dem":68,
    "gn:feature_class":"P",
    "gn:feature_code":"PPL",
    "gn:name":"Bomodin",
    "gn:population":0,
    "gn:timezone":"Africa/Accra",
    "iso:country":"GH",
    "wof:name":"Bomodin",
    "wof:placetype":"locality"
},
  "geometry": {"coordinates":[-1.4921,5.25859],"type":"Point"}
}