{
  "type": "Feature",
  "properties": {
    "gn:admin1_code":"00",
    "gn:asciiname":"Jakwa",
    "gn:country_code":"GH",
    "gn:dem":187,
    "gn:feature_class":"P",
    "gn:feature_code":"PPL",
    "gn:name":"Jakwa",
    "gn:population":0,
    "gn:timezone":"Africa/Accra",
    "iso:country":"GH",
    "name:und_x_variant":[
        "Jakpa",
        "Jakwa"
    ],
    "wof:name":"Jakwa",
    "wof:placetype":"locality"
},
  "geometry": {"coordinates":[0.23656,10.12484],"type":"Point"}
}