{
  "type": "Feature",
  "properties": {
    "iso:country":"GH",
    "qs:gn_pop":0,
    "qs:name":"Teshi",
    "qs:name_adm0":"Ghana",
    "qs:name_adm1":"Greater Accra",
    "qs:photos":181,
    "qs:photos_1k":37,
    "qs:photos_9k":1,
    "qs:photos_9r":4,
    "qs:photos_all":181,
    "qs:photos_sr":4,
    "qs:placetype":"Town",
    "qs:pop_sr":"0",
    "qs:woe_adm0":23424824,
    "wd:wordcount":18,
    "wof:name":"Teshi",
    "wof:placetype":"locality"
},
  "geometry": {"coordinates":[-0.10025,5.593434],"type":"Point"}
}