{
  "type": "Feature",
  "properties": {
    "gn:admin1_code":"00",
    "gn:asciiname":"Achichere",
    "gn:country_code":"GH",
    "gn:dem":132,
    "gn:feature_class":"P",
    "gn:feature_code":"PPL",
    "gn:name":"Achichere",
    "gn:population":0,
    "gn:timezone":"Africa/Accra",
    "iso:country":"GH",
    "name:und_x_variant":[
        "Akyekyere",
        "Achichere"
    ],
    "wof:name":"Achichere",
    "wof:placetype":"locality"
},
  "geometry": {"coordinates":[-2.32811,5.71295],"type":"Point"}
}