{
  "type": "Feature",
  "properties": {
    "gn:admin1_code":"00",
    "gn:asciiname":"Nadumbali",
    "gn:country_code":"GH",
    "gn:dem":191,
    "gn:feature_class":"P",
    "gn:feature_code":"PPL",
    "gn:name":"Nadumbali",
    "gn:population":0,
    "gn:timezone":"Africa/Accra",
    "iso:country":"GH",
    "name:und_x_variant":[
        "Nadumgbari",
        "Nadumbali"
    ],
    "wof:name":"Nadumbali",
    "wof:placetype":"locality"
},
  "geometry": {"coordinates":[0.10426,10.25434],"type":"Point"}
}