{
  "type": "Feature",
  "properties": {
    "gn:admin1_code":"04",
    "gn:asciiname":"Chirebraso",
    "gn:country_code":"GH",
    "gn:dem":216,
    "gn:feature_class":"P",
    "gn:feature_code":"PPL",
    "gn:name":"Chirebraso",
    "gn:population":0,
    "gn:timezone":"Africa/Accra",
    "iso:country":"GH",
    "name:eng_x_preferred":[
        "Chirebraso"
    ],
    "wof:name":"Chirebraso",
    "wof:placetype":"locality"
},
  "geometry": {"coordinates":[-1.82288,5.91271],"type":"Point"}
}