{
  "type": "Feature",
  "properties": {
    "gn:admin1_code":"01",
    "gn:asciiname":"Tetegbu",
    "gn:country_code":"GH",
    "gn:dem":4,
    "gn:feature_class":"P",
    "gn:feature_code":"PPL",
    "gn:name":"Tetegbu",
    "gn:population":0,
    "gn:timezone":"Africa/Accra",
    "iso:country":"GH",
    "name:eng_x_preferred":[
        "Teteogbu"
    ],
    "name:und_x_variant":[
        "Tete Ogbu",
        "Tetegbu"
    ],
    "wof:name":"Tetegbu",
    "wof:placetype":"locality"
},
  "geometry": {"coordinates":[-0.31211,5.54157],"type":"Point"}
}