{
  "type": "Feature",
  "properties": {
    "gn:admin1_code":"00",
    "gn:asciiname":"Hlum",
    "gn:country_code":"GH",
    "gn:dem":153,
    "gn:feature_class":"P",
    "gn:feature_code":"PPL",
    "gn:name":"Hlum",
    "gn:population":0,
    "gn:timezone":"Africa/Accra",
    "iso:country":"GH",
    "wof:name":"Hlum",
    "wof:placetype":"locality"
},
  "geometry": {"coordinates":[0.00634,6.28336],"type":"Point"}
}