{
  "type": "Feature",
  "properties": {
    "gn:admin1_code":"00",
    "gn:asciiname":"Kungbo",
    "gn:country_code":"GH",
    "gn:dem":25,
    "gn:feature_class":"P",
    "gn:feature_code":"PPL",
    "gn:name":"Kungbo",
    "gn:population":0,
    "gn:timezone":"Africa/Accra",
    "iso:country":"GH",
    "name:und_x_variant":[
        "Kunmo",
        "Kungbo"
    ],
    "wof:name":"Kungbo",
    "wof:placetype":"locality"
},
  "geometry": {"coordinates":[0.50914,5.91109],"type":"Point"}
}