{
  "type": "Feature",
  "properties": {
    "gn:admin1_code":"00",
    "gn:asciiname":"Tsibu",
    "gn:country_code":"GH",
    "gn:dem":163,
    "gn:feature_class":"P",
    "gn:feature_code":"PPL",
    "gn:name":"Tsibu",
    "gn:population":0,
    "gn:timezone":"Africa/Accra",
    "iso:country":"GH",
    "wof:name":"Tsibu",
    "wof:placetype":"locality"
},
  "geometry": {"coordinates":[0.28232,6.58425],"type":"Point"}
}