{
  "type": "Feature",
  "properties": {
    "gn:admin1_code":"00",
    "gn:asciiname":"Bugade",
    "gn:country_code":"GH",
    "gn:dem":243,
    "gn:feature_class":"P",
    "gn:feature_code":"PPL",
    "gn:name":"Bugade",
    "gn:population":0,
    "gn:timezone":"Africa/Accra",
    "iso:country":"GH",
    "name:und_x_variant":[
        "Bugaad",
        "Bugade"
    ],
    "wof:name":"Bugade",
    "wof:placetype":"locality"
},
  "geometry": {"coordinates":[-0.45839,10.70763],"type":"Point"}
}