{
  "type": "Feature",
  "properties": {
    "gn:admin1_code":"04",
    "gn:asciiname":"Oseikurom",
    "gn:country_code":"GH",
    "gn:dem":135,
    "gn:feature_class":"P",
    "gn:feature_code":"PPL",
    "gn:name":"Oseikurom",
    "gn:population":0,
    "gn:timezone":"Africa/Accra",
    "iso:country":"GH",
    "name:eng_x_preferred":[
        "Oseikurom"
    ],
    "name:und_x_variant":[
        "Yanka",
        "Isakakrom"
    ],
    "wof:name":"Oseikurom",
    "wof:placetype":"locality"
},
  "geometry": {"coordinates":[-1.66565,5.83003],"type":"Point"}
}