{
  "type": "Feature",
  "properties": {
    "gn:admin1_code":"04",
    "gn:asciiname":"Nkrang",
    "gn:country_code":"GH",
    "gn:dem":130,
    "gn:feature_class":"P",
    "gn:feature_code":"PPL",
    "gn:name":"Nkrang",
    "gn:population":0,
    "gn:timezone":"Africa/Accra",
    "iso:country":"GH",
    "name:eng_x_preferred":[
        "Nkrang"
    ],
    "wof:name":"Nkrang",
    "wof:placetype":"locality"
},
  "geometry": {"coordinates":[-1.70592,5.89134],"type":"Point"}
}