{
  "type": "Feature",
  "properties": {
    "gn:admin1_code":"00",
    "gn:asciiname":"Akoraso",
    "gn:country_code":"GH",
    "gn:dem":152,
    "gn:feature_class":"P",
    "gn:feature_code":"PPL",
    "gn:name":"Akoraso",
    "gn:population":0,
    "gn:timezone":"Africa/Accra",
    "iso:country":"GH",
    "wof:name":"Akoraso",
    "wof:placetype":"locality"
},
  "geometry": {"coordinates":[-0.73333,5.78333],"type":"Point"}
}