{
  "type": "Feature",
  "properties": {
    "gn:admin1_code":"00",
    "gn:asciiname":"Brewaniase",
    "gn:country_code":"GH",
    "gn:dem":273,
    "gn:feature_class":"P",
    "gn:feature_code":"PPL",
    "gn:name":"Brewaniase",
    "gn:population":0,
    "gn:timezone":"Africa/Accra",
    "iso:country":"GH",
    "name:und_x_variant":[
        "Berowaniasse",
        "Breniasse",
        "Brewaniase",
        "Breniase",
        "Berowaniase",
        "Breniasi"
    ],
    "wof:name":"Brewaniase",
    "wof:placetype":"locality"
},
  "geometry": {"coordinates":[0.56029,8.00226],"type":"Point"}
}