{
  "type": "Feature",
  "properties": {
    "gn:admin1_code":"00",
    "gn:asciiname":"Unya",
    "gn:country_code":"GH",
    "gn:dem":191,
    "gn:feature_class":"P",
    "gn:feature_code":"PPL",
    "gn:name":"Unya",
    "gn:population":0,
    "gn:timezone":"Africa/Accra",
    "iso:country":"GH",
    "name:und_x_variant":[
        "Unyu",
        "Unya"
    ],
    "wof:name":"Unya",
    "wof:placetype":"locality"
},
  "geometry": {"coordinates":[-1.27006,7.42731],"type":"Point"}
}