{
  "type": "Feature",
  "properties": {
    "gn:admin1_code":"00",
    "gn:asciiname":"Dawa Amanfro",
    "gn:country_code":"GH",
    "gn:dem":227,
    "gn:feature_class":"P",
    "gn:feature_code":"PPL",
    "gn:name":"Dawa Amanfro",
    "gn:population":0,
    "gn:timezone":"Africa/Accra",
    "iso:country":"GH",
    "name:und_x_variant":[
        "Dawa Amanfrom",
        "Dawa Amanfro"
    ],
    "wof:name":"Dawa Amanfro",
    "wof:placetype":"locality"
},
  "geometry": {"coordinates":[-0.14866,6.32418],"type":"Point"}
}