{
  "type": "Feature",
  "properties": {
    "gn:admin1_code":"00",
    "gn:asciiname":"Nangmong",
    "gn:country_code":"GH",
    "gn:dem":221,
    "gn:feature_class":"P",
    "gn:feature_code":"PPL",
    "gn:name":"Nangmong",
    "gn:population":0,
    "gn:timezone":"Africa/Accra",
    "iso:country":"GH",
    "name:und_x_variant":[
        "Nanmon",
        "Namong",
        "Namwangu",
        "Nangmong"
    ],
    "wof:name":"Nangmong",
    "wof:placetype":"locality"
},
  "geometry": {"coordinates":[-0.09987,10.44344],"type":"Point"}
}