{
  "type": "Feature",
  "properties": {
    "gn:admin1_code":"08",
    "gn:asciiname":"Gbedjikofe",
    "gn:country_code":"GH",
    "gn:dem":10,
    "gn:feature_class":"P",
    "gn:feature_code":"PPL",
    "gn:name":"Gbedjikofe",
    "gn:population":0,
    "gn:timezone":"Africa/Accra",
    "iso:country":"GH",
    "name:und_x_variant":[
        "Gbedzikorpe",
        "Gbedjikofe"
    ],
    "wof:name":"Gbedjikofe",
    "wof:placetype":"locality"
},
  "geometry": {"coordinates":[1.0833,6.09712],"type":"Point"}
}