{
  "type": "Feature",
  "properties": {
    "gn:admin1_code":"00",
    "gn:asciiname":"Kangberigu",
    "gn:cc2":"GH",
    "gn:country_code":"GH",
    "gn:dem":240,
    "gn:feature_class":"P",
    "gn:feature_code":"PPL",
    "gn:name":"Kangberigu",
    "gn:population":0,
    "gn:timezone":"Africa/Accra",
    "iso:country":"GH",
    "name:und_x_variant":[
        "Kanjerigu",
        "Kangberigu"
    ],
    "wof:name":"Kangberigu",
    "wof:placetype":"locality"
},
  "geometry": {"coordinates":[-0.15,11.13333],"type":"Point"}
}