{
  "type": "Feature",
  "properties": {
    "gn:admin1_code":"02",
    "gn:asciiname":"Winisosechikrom",
    "gn:country_code":"GH",
    "gn:dem":225,
    "gn:feature_class":"P",
    "gn:feature_code":"PPL",
    "gn:name":"Winisosechikrom",
    "gn:population":0,
    "gn:timezone":"Africa/Accra",
    "iso:country":"GH",
    "name:und_x_variant":[
        "Winiso Sekyekurom",
        "Winisosechikrom"
    ],
    "wof:name":"Winisosechikrom",
    "wof:placetype":"locality"
},
  "geometry": {"coordinates":[-1.79675,6.53383],"type":"Point"}
}