{
  "type": "Feature",
  "properties": {
    "gn:admin1_code":"02",
    "gn:asciiname":"Akawkawso",
    "gn:country_code":"GH",
    "gn:dem":163,
    "gn:feature_class":"P",
    "gn:feature_code":"PPL",
    "gn:name":"Akawkawso",
    "gn:population":0,
    "gn:timezone":"Africa/Accra",
    "iso:country":"GH",
    "name:eng_x_preferred":[
        "Akawkawso"
    ],
    "wof:name":"Akawkawso",
    "wof:placetype":"locality"
},
  "geometry": {"coordinates":[-1.77709,6.35435],"type":"Point"}
}