{
  "type": "Feature",
  "properties": {
    "gn:admin1_code":"00",
    "gn:asciiname":"Obosomasi",
    "gn:country_code":"GH",
    "gn:dem":424,
    "gn:feature_class":"P",
    "gn:feature_code":"PPL",
    "gn:name":"Obosomasi",
    "gn:population":0,
    "gn:timezone":"Africa/Accra",
    "iso:country":"GH",
    "name:und_x_variant":[
        "Obosomase",
        "Obosomasi"
    ],
    "wof:name":"Obosomasi",
    "wof:placetype":"locality"
},
  "geometry": {"coordinates":[-0.15539,5.87566],"type":"Point"}
}