{
  "type": "Feature",
  "properties": {
    "gn:admin1_code":"00",
    "gn:asciiname":"Nyamedema",
    "gn:cc2":"GH",
    "gn:country_code":"GH",
    "gn:dem":85,
    "gn:feature_class":"P",
    "gn:feature_code":"PPL",
    "gn:name":"Nyamedema",
    "gn:population":0,
    "gn:timezone":"Africa/Accra",
    "iso:country":"GH",
    "name:und_x_variant":[
        "Nyamedzema Number 1",
        "Nyamedema"
    ],
    "wof:name":"Nyamedema",
    "wof:placetype":"locality"
},
  "geometry": {"coordinates":[-1.55,5.63333],"type":"Point"}
}