{
  "type": "Feature",
  "properties": {
    "gn:admin1_code":"00",
    "gn:asciiname":"Sibinsu",
    "gn:country_code":"GH",
    "gn:dem":103,
    "gn:feature_class":"P",
    "gn:feature_code":"PPL",
    "gn:name":"Sibinsu",
    "gn:population":0,
    "gn:timezone":"Africa/Accra",
    "iso:country":"GH",
    "name:und_x_variant":[
        "Sabrinsu",
        "Sibinsu"
    ],
    "wof:name":"Sibinsu",
    "wof:placetype":"locality"
},
  "geometry": {"coordinates":[-1.15189,5.41139],"type":"Point"}
}