{
  "type": "Feature",
  "properties": {
    "gn:admin1_code":"00",
    "gn:asciiname":"Huananaoba",
    "gn:country_code":"GH",
    "gn:dem":72,
    "gn:feature_class":"P",
    "gn:feature_code":"PPL",
    "gn:name":"Huananaoba",
    "gn:population":0,
    "gn:timezone":"Africa/Accra",
    "iso:country":"GH",
    "name:und_x_variant":[
        "Huananuoba",
        "Huananaoba"
    ],
    "wof:name":"Huananaoba",
    "wof:placetype":"locality"
},
  "geometry": {"coordinates":[-1.47604,5.24801],"type":"Point"}
}