{
  "type": "Feature",
  "properties": {
    "gn:admin1_code":"00",
    "gn:asciiname":"Piasi",
    "gn:country_code":"GH",
    "gn:dem":272,
    "gn:feature_class":"P",
    "gn:feature_code":"PPL",
    "gn:name":"Piasi",
    "gn:population":0,
    "gn:timezone":"Africa/Accra",
    "iso:country":"GH",
    "wof:name":"Piasi",
    "wof:placetype":"locality"
},
  "geometry": {"coordinates":[-1.45151,6.58779],"type":"Point"}
}