{
  "type": "Feature",
  "properties": {
    "gn:admin1_code":"02",
    "gn:asciiname":"Pasoro",
    "gn:country_code":"GH",
    "gn:dem":246,
    "gn:feature_class":"P",
    "gn:feature_code":"PPL",
    "gn:name":"Pasoro",
    "gn:population":0,
    "gn:timezone":"Africa/Accra",
    "iso:country":"GH",
    "name:und_x_variant":[
        "Pasaro"
    ],
    "wof:name":"Pasoro",
    "wof:placetype":"locality"
},
  "geometry": {"coordinates":[-1.75018,6.78875],"type":"Point"}
}