{
  "type": "Feature",
  "properties": {
    "gn:admin1_code":"00",
    "gn:asciiname":"Dobinyetaw",
    "gn:country_code":"GH",
    "gn:dem":206,
    "gn:feature_class":"P",
    "gn:feature_code":"PPL",
    "gn:name":"Dobinyetaw",
    "gn:population":0,
    "gn:timezone":"Africa/Accra",
    "iso:country":"GH",
    "wof:name":"Dobinyetaw",
    "wof:placetype":"locality"
},
  "geometry": {"coordinates":[-0.09364,10.39913],"type":"Point"}
}