{
  "type": "Feature",
  "properties": {
    "gn:admin1_code":"00",
    "gn:asciiname":"Nakpa",
    "gn:cc2":"GH",
    "gn:country_code":"GH",
    "gn:dem":194,
    "gn:feature_class":"P",
    "gn:feature_code":"PPL",
    "gn:name":"Nakpa",
    "gn:population":0,
    "gn:timezone":"Africa/Accra",
    "iso:country":"GH",
    "name:und_x_variant":[
        "Nakpa Daboli",
        "Nakpa"
    ],
    "wof:name":"Nakpa",
    "wof:placetype":"locality"
},
  "geometry": {"coordinates":[-0.13333,9.05],"type":"Point"}
}