{
  "type": "Feature",
  "properties": {
    "gn:admin1_code":"00",
    "gn:asciiname":"Kokosua Number Two",
    "gn:country_code":"GH",
    "gn:dem":289,
    "gn:feature_class":"P",
    "gn:feature_code":"PPL",
    "gn:name":"Kokosua Number Two",
    "gn:population":0,
    "gn:timezone":"Africa/Accra",
    "iso:country":"GH",
    "name:eng_x_preferred":[
        "Kokosua Number Two"
    ],
    "name:und_x_variant":[
        "Kokosua Number 2",
        "Kokosua"
    ],
    "wof:name":"Kokosua Number Two",
    "wof:placetype":"locality"
},
  "geometry": {"coordinates":[-2.78485,7.87897],"type":"Point"}
}