{
  "type": "Feature",
  "properties": {
    "gn:admin1_code":"00",
    "gn:asciiname":"Akitikofe",
    "gn:country_code":"GH",
    "gn:dem":106,
    "gn:feature_class":"P",
    "gn:feature_code":"PPL",
    "gn:name":"Akitikofe",
    "gn:population":0,
    "gn:timezone":"Africa/Accra",
    "iso:country":"GH",
    "wof:name":"Akitikofe",
    "wof:placetype":"locality"
},
  "geometry": {"coordinates":[0.25891,6.41608],"type":"Point"}
}