{
  "type": "Feature",
  "properties": {
    "gn:admin1_code":"00",
    "gn:asciiname":"Chungasi",
    "gn:country_code":"GH",
    "gn:dem":196,
    "gn:feature_class":"P",
    "gn:feature_code":"PPL",
    "gn:name":"Chungasi",
    "gn:population":0,
    "gn:timezone":"Africa/Accra",
    "iso:country":"GH",
    "wof:name":"Chungasi",
    "wof:placetype":"locality"
},
  "geometry": {"coordinates":[-0.41144,9.07481],"type":"Point"}
}