{
  "type": "Feature",
  "properties": {
    "gn:admin1_code":"00",
    "gn:asciiname":"Bora",
    "gn:cc2":"GH",
    "gn:country_code":"GH",
    "gn:dem":146,
    "gn:feature_class":"P",
    "gn:feature_code":"PPL",
    "gn:name":"Bora",
    "gn:population":0,
    "gn:timezone":"Africa/Accra",
    "iso:country":"GH",
    "name:cat_x_preferred":[
        "Bora"
    ],
    "name:ceb_x_preferred":[
        "Bora"
    ],
    "name:ces_x_preferred":[
        "Bora"
    ],
    "name:dan_x_preferred":[
        "Bora"
    ],
    "name:deu_x_preferred":[
        "Bora"
    ],
    "name:fin_x_preferred":[
        "Bora"
    ],
    "name:fra_x_preferred":[
        "Bora"
    ],
    "name:ita_x_preferred":[
        "Bora"
    ],
    "name:jpn_x_preferred":[
        "\u30dc\u30e9"
    ],
    "name:kor_x_preferred":[
        "\ubcf4\ub77c"
    ],
    "name:lav_x_preferred":[
        "Bora"
    ],
    "name:nld_x_preferred":[
        "Bora"
    ],
    "name:nor_x_preferred":[
        "Bora"
    ],
    "name:por_x_preferred":[
        "Bora"
    ],
    "name:ron_x_preferred":[
        "Bora"
    ],
    "name:rus_x_preferred":[
        "\u0411\u043e\u0440\u0430"
    ],
    "name:slk_x_preferred":[
        "Bora"
    ],
    "name:spa_x_preferred":[
        "Bora"
    ],
    "name:swe_x_preferred":[
        "Bora"
    ],
    "name:ukr_x_preferred":[
        "\u0411\u043e\u0440\u0430"
    ],
    "name:und_x_variant":[
        "Borai",
        "Borae Number 1"
    ],
    "wof:name":"Bora",
    "wof:placetype":"locality"
},
  "geometry": {"coordinates":[-0.13333,8.31667],"type":"Point"}
}