{
  "type": "Feature",
  "properties": {
    "gn:admin1_code":"00",
    "gn:asciiname":"Bora",
    "gn:cc2":"GH",
    "gn:country_code":"GH",
    "gn:dem":146,
    "gn:feature_class":"P",
    "gn:feature_code":"PPL",
    "gn:name":"Bora",
    "gn:population":0,
    "gn:timezone":"Africa/Accra",
    "iso:country":"GH",
    "name:und_x_variant":[
        "Borai",
        "Borae Number 1",
        "Bora"
    ],
    "wof:name":"Bora",
    "wof:placetype":"locality"
},
  "geometry": {"coordinates":[-0.13333,8.31667],"type":"Point"}
}