{
  "type": "Feature",
  "properties": {
    "gn:admin1_code":"02",
    "gn:asciiname":"Aboaso",
    "gn:country_code":"GH",
    "gn:dem":305,
    "gn:feature_class":"P",
    "gn:feature_code":"PPL",
    "gn:name":"Aboaso",
    "gn:population":0,
    "gn:timezone":"Africa/Accra",
    "iso:country":"GH",
    "name:und_x_variant":[
        "Aboaso Nkwanta",
        "Aboabo Nkwanta"
    ],
    "wof:name":"Aboaso",
    "wof:placetype":"locality"
},
  "geometry": {"coordinates":[-1.53668,6.81009],"type":"Point"}
}