{
  "type": "Feature",
  "properties": {
    "gn:admin1_code":"00",
    "gn:asciiname":"Kukurantumi",
    "gn:country_code":"GH",
    "gn:dem":206,
    "gn:feature_class":"P",
    "gn:feature_code":"PPL",
    "gn:name":"Kukurantumi",
    "gn:population":0,
    "gn:timezone":"Africa/Accra",
    "iso:country":"GH",
    "name:und_x_variant":[
        "Kokorantumi",
        "Kukurantumi"
    ],
    "wof:name":"Kukurantumi",
    "wof:placetype":"locality"
},
  "geometry": {"coordinates":[-0.36553,6.18827],"type":"Point"}
}