{
  "type": "Feature",
  "properties": {
    "gn:admin1_code":"00",
    "gn:asciiname":"Bamiankaw",
    "gn:cc2":"GH",
    "gn:country_code":"GH",
    "gn:dem":26,
    "gn:feature_class":"P",
    "gn:feature_code":"PPL",
    "gn:name":"Bamiankaw",
    "gn:population":0,
    "gn:timezone":"Africa/Accra",
    "iso:country":"GH",
    "name:und_x_variant":[
        "Bamiankor",
        "Bamiankaw"
    ],
    "wof:name":"Bamiankaw",
    "wof:placetype":"locality"
},
  "geometry": {"coordinates":[-2.41667,5.01667],"type":"Point"}
}