{
  "type": "Feature",
  "properties": {
    "gn:admin1_code":"00",
    "gn:asciiname":"Kukuom",
    "gn:country_code":"GH",
    "gn:dem":201,
    "gn:feature_class":"P",
    "gn:feature_code":"PPL",
    "gn:name":"Kukuom",
    "gn:population":0,
    "gn:timezone":"Africa/Accra",
    "iso:country":"GH",
    "wof:name":"Kukuom",
    "wof:placetype":"locality"
},
  "geometry": {"coordinates":[-2.44275,6.69447],"type":"Point"}
}