{
  "type": "Feature",
  "properties": {
    "gn:admin1_code":"00",
    "gn:asciiname":"Abuife",
    "gn:country_code":"GH",
    "gn:dem":102,
    "gn:feature_class":"P",
    "gn:feature_code":"PPL",
    "gn:name":"Abuife",
    "gn:population":0,
    "gn:timezone":"Africa/Accra",
    "iso:country":"GH",
    "name:und_x_variant":[
        "Abuipe",
        "Abuife"
    ],
    "wof:name":"Abuife",
    "wof:placetype":"locality"
},
  "geometry": {"coordinates":[0.34966,6.85923],"type":"Point"}
}