{
  "type": "Feature",
  "properties": {
    "gn:admin1_code":"00",
    "gn:asciiname":"Aninenya",
    "gn:country_code":"GH",
    "gn:dem":407,
    "gn:feature_class":"P",
    "gn:feature_code":"PPL",
    "gn:name":"Aninenya",
    "gn:population":0,
    "gn:timezone":"Africa/Accra",
    "iso:country":"GH",
    "wof:name":"Aninenya",
    "wof:placetype":"locality"
},
  "geometry": {"coordinates":[-1.27215,6.88021],"type":"Point"}
}