{
  "type": "Feature",
  "properties": {
    "gn:admin1_code":"00",
    "gn:asciiname":"Dublinbo",
    "gn:country_code":"GH",
    "gn:dem":0,
    "gn:feature_class":"P",
    "gn:feature_code":"PPL",
    "gn:name":"Dublinbo",
    "gn:population":0,
    "gn:timezone":"Africa/Accra",
    "iso:country":"GH",
    "wof:name":"Dublinbo",
    "wof:placetype":"locality"
},
  "geometry": {"coordinates":[-3.01667,5.11667],"type":"Point"}
}