{
  "type": "Feature",
  "properties": {
    "gn:admin1_code":"10",
    "gn:asciiname":"Feo Nabisi",
    "gn:country_code":"GH",
    "gn:dem":241,
    "gn:feature_class":"P",
    "gn:feature_code":"PPL",
    "gn:name":"Feo Nabisi",
    "gn:population":0,
    "gn:timezone":"Africa/Accra",
    "iso:country":"GH",
    "name:und_x_variant":[
        "Fiogu",
        "Fiagu",
        "Feo Nabisi"
    ],
    "wof:name":"Feo Nabisi",
    "wof:placetype":"locality"
},
  "geometry": {"coordinates":[-0.80301,10.99321],"type":"Point"}
}