{
  "type": "Feature",
  "properties": {
    "gn:admin1_code":"00",
    "gn:asciiname":"Bame",
    "gn:country_code":"GH",
    "gn:dem":39,
    "gn:feature_class":"P",
    "gn:feature_code":"PPL",
    "gn:name":"Bame",
    "gn:population":0,
    "gn:timezone":"Africa/Accra",
    "iso:country":"GH",
    "name:ceb_x_preferred":[
        "Bame"
    ],
    "name:spa_x_preferred":[
        "Bame"
    ],
    "name:swe_x_preferred":[
        "Bame"
    ],
    "wof:name":"Bame",
    "wof:placetype":"locality"
},
  "geometry": {"coordinates":[0.96723,6.2382],"type":"Point"}
}