{
  "type": "Feature",
  "properties": {
    "gn:admin1_code":"00",
    "gn:asciiname":"Tolesem",
    "gn:country_code":"GH",
    "gn:dem":0,
    "gn:feature_class":"P",
    "gn:feature_code":"PPL",
    "gn:name":"Tolesem",
    "gn:population":0,
    "gn:timezone":"Africa/Accra",
    "iso:country":"GH",
    "name:und_x_variant":[
        "Towlesam",
        "Tolesem"
    ],
    "wof:name":"Tolesem",
    "wof:placetype":"locality"
},
  "geometry": {"coordinates":[0.66634,5.88458],"type":"Point"}
}