{
  "type": "Feature",
  "properties": {
    "gn:admin1_code":"00",
    "gn:asciiname":"Sakuba",
    "gn:country_code":"GH",
    "gn:dem":139,
    "gn:feature_class":"P",
    "gn:feature_code":"PPL",
    "gn:name":"Sakuba",
    "gn:population":0,
    "gn:timezone":"Africa/Accra",
    "iso:country":"GH",
    "name:und_x_variant":[
        "Saakuba",
        "Sakuba"
    ],
    "wof:name":"Sakuba",
    "wof:placetype":"locality"
},
  "geometry": {"coordinates":[-0.99677,9.59598],"type":"Point"}
}