{
  "type": "Feature",
  "properties": {
    "gn:admin1_code":"02",
    "gn:asciiname":"Amankwakrom",
    "gn:country_code":"GH",
    "gn:dem":248,
    "gn:feature_class":"P",
    "gn:feature_code":"PPL",
    "gn:name":"Amankwakrom",
    "gn:population":0,
    "gn:timezone":"Africa/Accra",
    "iso:country":"GH",
    "name:und_x_variant":[
        "Tete Armakurom",
        "Amankwakrom"
    ],
    "wof:name":"Amankwakrom",
    "wof:placetype":"locality"
},
  "geometry": {"coordinates":[-2.13816,6.95549],"type":"Point"}
}