{
  "type": "Feature",
  "properties": {
    "gn:admin1_code":"08",
    "gn:asciiname":"Darege",
    "gn:country_code":"GH",
    "gn:dem":24,
    "gn:feature_class":"P",
    "gn:feature_code":"PPL",
    "gn:name":"Darege",
    "gn:population":0,
    "gn:timezone":"Africa/Accra",
    "iso:country":"GH",
    "wof:name":"Darege",
    "wof:placetype":"locality"
},
  "geometry": {"coordinates":[1.13444,6.16167],"type":"Point"}
}