{
  "type": "Feature",
  "properties": {
    "gn:admin1_code":"00",
    "gn:asciiname":"Some",
    "gn:country_code":"GH",
    "gn:dem":33,
    "gn:feature_class":"P",
    "gn:feature_code":"PPL",
    "gn:name":"Some",
    "gn:population":0,
    "gn:timezone":"Africa/Accra",
    "iso:country":"GH",
    "name:ceb_x_preferred":[
        "Some"
    ],
    "name:por_x_preferred":[
        "Some"
    ],
    "name:swe_x_preferred":[
        "Some"
    ],
    "wof:name":"Some",
    "wof:placetype":"locality"
},
  "geometry": {"coordinates":[0.22223,5.87369],"type":"Point"}
}