{
  "type": "Feature",
  "properties": {
    "gn:admin1_code":"00",
    "gn:asciiname":"Kasi",
    "gn:country_code":"GH",
    "gn:dem":191,
    "gn:feature_class":"P",
    "gn:feature_code":"PPL",
    "gn:name":"Kasi",
    "gn:population":0,
    "gn:timezone":"Africa/Accra",
    "iso:country":"GH",
    "name:ceb_x_preferred":[
        "Kasi"
    ],
    "name:swe_x_preferred":[
        "Kasi"
    ],
    "name:und_x_variant":[
        "Kandiga Kasi",
        "Kasi"
    ],
    "wof:name":"Kasi",
    "wof:placetype":"locality"
},
  "geometry": {"coordinates":[-0.95462,10.87223],"type":"Point"}
}