{
  "type": "Feature",
  "properties": {
    "gn:admin1_code":"02",
    "gn:asciiname":"Wamase",
    "gn:country_code":"GH",
    "gn:dem":258,
    "gn:feature_class":"P",
    "gn:feature_code":"PPL",
    "gn:name":"Wamase",
    "gn:population":0,
    "gn:timezone":"Africa/Accra",
    "iso:country":"GH",
    "name:eng_x_preferred":[
        "Wamase"
    ],
    "name:eng_x_variant":[
        "Womasi"
    ],
    "wof:name":"Wamase",
    "wof:placetype":"locality"
},
  "geometry": {"coordinates":[-1.66265,6.66299],"type":"Point"}
}