{
  "type": "Feature",
  "properties": {
    "gn:admin1_code":"00",
    "gn:asciiname":"Danome",
    "gn:country_code":"GH",
    "gn:dem":2,
    "gn:feature_class":"P",
    "gn:feature_code":"PPL",
    "gn:name":"Danome",
    "gn:population":0,
    "gn:timezone":"Africa/Accra",
    "iso:country":"GH",
    "wof:name":"Danome",
    "wof:placetype":"locality"
},
  "geometry": {"coordinates":[1.13532,6.11071],"type":"Point"}
}