{
  "type": "Feature",
  "properties": {
    "gn:admin1_code":"02",
    "gn:asciiname":"Domiabra",
    "gn:country_code":"GH",
    "gn:dem":198,
    "gn:feature_class":"P",
    "gn:feature_code":"PPL",
    "gn:name":"Domiabra",
    "gn:population":0,
    "gn:timezone":"Africa/Accra",
    "iso:country":"GH",
    "name:eng_x_preferred":[
        "Domiabra"
    ],
    "wof:name":"Domiabra",
    "wof:placetype":"locality"
},
  "geometry": {"coordinates":[-1.74564,6.2916],"type":"Point"}
}