{
  "type": "Feature",
  "properties": {
    "gn:admin1_code":"09",
    "gn:asciiname":"Alomatuope",
    "gn:country_code":"GH",
    "gn:dem":4,
    "gn:feature_class":"P",
    "gn:feature_code":"PPL",
    "gn:name":"Alomatuope",
    "gn:population":0,
    "gn:timezone":"Africa/Accra",
    "iso:country":"GH",
    "name:und_x_variant":[
        "Alomatoupe",
        "Anomatuepin"
    ],
    "wof:name":"Alomatuope",
    "wof:placetype":"locality"
},
  "geometry": {"coordinates":[-2.94315,5.0595],"type":"Point"}
}