{
  "type": "Feature",
  "properties": {
    "gn:admin1_code":"00",
    "gn:asciiname":"Lume",
    "gn:country_code":"GH",
    "gn:dem":160,
    "gn:feature_class":"P",
    "gn:feature_code":"PPL",
    "gn:name":"Lume",
    "gn:population":0,
    "gn:timezone":"Africa/Accra",
    "iso:country":"GH",
    "wof:name":"Lume",
    "wof:placetype":"locality"
},
  "geometry": {"coordinates":[0.44215,6.65028],"type":"Point"}
}