{
  "type": "Feature",
  "properties": {
    "gn:admin1_code":"00",
    "gn:asciiname":"Kasaim",
    "gn:country_code":"GH",
    "gn:dem":328,
    "gn:feature_class":"P",
    "gn:feature_code":"PPL",
    "gn:name":"Kasaim",
    "gn:population":0,
    "gn:timezone":"Africa/Accra",
    "iso:country":"GH",
    "name:und_x_variant":[
        "Kasem",
        "Kasaem",
        "Kasaim"
    ],
    "wof:name":"Kasaim",
    "wof:placetype":"locality"
},
  "geometry": {"coordinates":[-1.46718,6.84624],"type":"Point"}
}