{
  "type": "Feature",
  "properties": {
    "gn:admin1_code":"00",
    "gn:asciiname":"Obuasi",
    "gn:country_code":"GH",
    "gn:dem":257,
    "gn:feature_class":"P",
    "gn:feature_code":"PPL",
    "gn:name":"Obuasi",
    "gn:population":0,
    "gn:timezone":"Africa/Accra",
    "iso:country":"GH",
    "name:und_x_variant":[
        "Oboase",
        "Obuasi"
    ],
    "wof:name":"Obuasi",
    "wof:placetype":"locality"
},
  "geometry": {"coordinates":[-2.2988,8.02571],"type":"Point"}
}