{
  "type": "Feature",
  "properties": {
    "gn:admin1_code":"00",
    "gn:asciiname":"Morawtuo",
    "gn:country_code":"GH",
    "gn:dem":164,
    "gn:feature_class":"P",
    "gn:feature_code":"PPL",
    "gn:name":"Morawtuo",
    "gn:population":0,
    "gn:timezone":"Africa/Accra",
    "iso:country":"GH",
    "wof:name":"Morawtuo",
    "wof:placetype":"locality"
},
  "geometry": {"coordinates":[-1.43333,6.46667],"type":"Point"}
}