{
  "type": "Feature",
  "properties": {
    "gn:admin1_code":"00",
    "gn:asciiname":"Efiena",
    "gn:country_code":"GH",
    "gn:dem":178,
    "gn:feature_class":"P",
    "gn:feature_code":"PPL",
    "gn:name":"Efiena",
    "gn:population":0,
    "gn:timezone":"Africa/Accra",
    "iso:country":"GH",
    "wof:name":"Efiena",
    "wof:placetype":"locality"
},
  "geometry": {"coordinates":[-2.48435,5.89399],"type":"Point"}
}