{
  "type": "Feature",
  "properties": {
    "gn:admin1_code":"01",
    "gn:asciiname":"Amamole",
    "gn:country_code":"GH",
    "gn:dem":46,
    "gn:feature_class":"P",
    "gn:feature_code":"PPL",
    "gn:name":"Amamole",
    "gn:population":0,
    "gn:timezone":"Africa/Accra",
    "iso:country":"GH",
    "name:und_x_variant":[
        "Amamoli",
        "Amamorley"
    ],
    "wof:name":"Amamole",
    "wof:placetype":"locality"
},
  "geometry": {"coordinates":[-0.29852,5.66202],"type":"Point"}
}