{
  "type": "Feature",
  "properties": {
    "gn:admin1_code":"02",
    "gn:asciiname":"Nyankumasi Kese",
    "gn:country_code":"GH",
    "gn:dem":228,
    "gn:feature_class":"P",
    "gn:feature_code":"PPL",
    "gn:name":"Nyankumasi Kese",
    "gn:population":0,
    "gn:timezone":"Africa/Accra",
    "iso:country":"GH",
    "name:eng_x_preferred":[
        "Nyankumasi Kese"
    ],
    "wof:name":"Nyankumasi Kese",
    "wof:placetype":"locality"
},
  "geometry": {"coordinates":[-1.9319,6.38717],"type":"Point"}
}