{
  "type": "Feature",
  "properties": {
    "gn:admin1_code":"06",
    "gn:asciiname":"Tachegu",
    "gn:country_code":"GH",
    "gn:dem":155,
    "gn:feature_class":"P",
    "gn:feature_code":"PPL",
    "gn:name":"Tachegu",
    "gn:population":0,
    "gn:timezone":"Africa/Accra",
    "iso:country":"GH",
    "name:und_x_variant":[
        "Tati\u0113gu",
        "Tacheku",
        "Techagou",
        "Tachegu"
    ],
    "wof:name":"Tachegu",
    "wof:placetype":"locality"
},
  "geometry": {"coordinates":[0.30351,10.07606],"type":"Point"}
}