{
  "type": "Feature",
  "properties": {
    "gn:admin1_code":"00",
    "gn:asciiname":"Ajaw",
    "gn:country_code":"GH",
    "gn:dem":70,
    "gn:feature_class":"P",
    "gn:feature_code":"PPL",
    "gn:name":"Ajaw",
    "gn:population":0,
    "gn:timezone":"Africa/Accra",
    "iso:country":"GH",
    "wof:name":"Ajaw",
    "wof:placetype":"locality"
},
  "geometry": {"coordinates":[-2.16794,5.40711],"type":"Point"}
}