{
  "type": "Feature",
  "properties": {
    "gn:admin1_code":"01",
    "gn:asciiname":"Obeyie",
    "gn:country_code":"GH",
    "gn:dem":40,
    "gn:feature_class":"P",
    "gn:feature_code":"PPL",
    "gn:name":"Obeyie",
    "gn:population":0,
    "gn:timezone":"Africa/Accra",
    "iso:country":"GH",
    "name:eng_x_preferred":[
        "Obeyie"
    ],
    "wof:name":"Obeyie",
    "wof:placetype":"locality"
},
  "geometry": {"coordinates":[-0.33618,5.68183],"type":"Point"}
}