{
  "type": "Feature",
  "properties": {
    "gn:admin1_code":"00",
    "gn:asciiname":"Ansakwa",
    "gn:country_code":"GH",
    "gn:dem":111,
    "gn:feature_class":"P",
    "gn:feature_code":"PPL",
    "gn:name":"Ansakwa",
    "gn:population":0,
    "gn:timezone":"Africa/Accra",
    "iso:country":"GH",
    "wof:name":"Ansakwa",
    "wof:placetype":"locality"
},
  "geometry": {"coordinates":[-0.66667,5.68333],"type":"Point"}
}