{
  "type": "Feature",
  "properties": {
    "gn:admin1_code":"00",
    "gn:asciiname":"Apeosika",
    "gn:country_code":"GH",
    "gn:dem":7,
    "gn:feature_class":"P",
    "gn:feature_code":"PPL",
    "gn:name":"Apeosika",
    "gn:population":0,
    "gn:timezone":"Africa/Accra",
    "iso:country":"GH",
    "wof:name":"Apeosika",
    "wof:placetype":"locality"
},
  "geometry": {"coordinates":[-1.29612,5.10865],"type":"Point"}
}