{
  "type": "Feature",
  "properties": {
    "gn:admin1_code":"02",
    "gn:asciiname":"Amponya",
    "gn:country_code":"GH",
    "gn:dem":222,
    "gn:feature_class":"P",
    "gn:feature_code":"PPL",
    "gn:name":"Amponya",
    "gn:population":0,
    "gn:timezone":"Africa/Accra",
    "iso:country":"GH",
    "name:eng_x_preferred":[
        "Amponya"
    ],
    "wof:name":"Amponya",
    "wof:placetype":"locality"
},
  "geometry": {"coordinates":[-1.61641,6.39877],"type":"Point"}
}