{
  "type": "Feature",
  "properties": {
    "gn:admin1_code":"00",
    "gn:asciiname":"Gnani",
    "gn:country_code":"GH",
    "gn:dem":145,
    "gn:feature_class":"P",
    "gn:feature_code":"PPL",
    "gn:name":"Gnani",
    "gn:population":0,
    "gn:timezone":"Africa/Accra",
    "iso:country":"GH",
    "name:und_x_variant":[
        "Ghani",
        "Gnani"
    ],
    "wof:name":"Gnani",
    "wof:placetype":"locality"
},
  "geometry": {"coordinates":[0.2017,9.35408],"type":"Point"}
}