{
  "type": "Feature",
  "properties": {
    "gn:admin1_code":"00",
    "gn:asciiname":"Achati",
    "gn:country_code":"GH",
    "gn:dem":71,
    "gn:feature_class":"P",
    "gn:feature_code":"PPL",
    "gn:name":"Achati",
    "gn:population":0,
    "gn:timezone":"Africa/Accra",
    "iso:country":"GH",
    "wof:name":"Achati",
    "wof:placetype":"locality"
},
  "geometry": {"coordinates":[0.58188,6.25585],"type":"Point"}
}