{
  "type": "Feature",
  "properties": {
    "gn:admin1_code":"02",
    "gn:asciiname":"Supong",
    "gn:country_code":"GH",
    "gn:dem":127,
    "gn:feature_class":"P",
    "gn:feature_code":"PPL",
    "gn:name":"Supong",
    "gn:population":0,
    "gn:timezone":"Africa/Accra",
    "iso:country":"GH",
    "name:eng_x_preferred":[
        "Supong"
    ],
    "wof:name":"Supong",
    "wof:placetype":"locality"
},
  "geometry": {"coordinates":[-1.50072,5.92654],"type":"Point"}
}