{
  "type": "Feature",
  "properties": {
    "gn:admin1_code":"00",
    "gn:asciiname":"Chansia",
    "gn:country_code":"GH",
    "gn:dem":145,
    "gn:feature_class":"P",
    "gn:feature_code":"PPL",
    "gn:name":"Chansia",
    "gn:population":0,
    "gn:timezone":"Africa/Accra",
    "iso:country":"GH",
    "name:und_x_variant":[
        "Kadema Changsa",
        "Chansia"
    ],
    "wof:name":"Chansia",
    "wof:placetype":"locality"
},
  "geometry": {"coordinates":[-1.10585,10.49493],"type":"Point"}
}