{
  "type": "Feature",
  "properties": {
    "gn:admin1_code":"00",
    "gn:asciiname":"Kpodiwuro",
    "gn:country_code":"GH",
    "gn:dem":83,
    "gn:feature_class":"P",
    "gn:feature_code":"PPL",
    "gn:name":"Kpodiwuro",
    "gn:population":0,
    "gn:timezone":"Africa/Accra",
    "iso:country":"GH",
    "name:und_x_variant":[
        "Kpordiwlor",
        "Kpodiwuro"
    ],
    "wof:name":"Kpodiwuro",
    "wof:placetype":"locality"
},
  "geometry": {"coordinates":[0.58057,6.27353],"type":"Point"}
}