{
  "type": "Feature",
  "properties": {
    "gn:admin1_code":"02",
    "gn:asciiname":"Asokwa",
    "gn:country_code":"GH",
    "gn:dem":268,
    "gn:feature_class":"P",
    "gn:feature_code":"PPL",
    "gn:name":"Asokwa",
    "gn:population":0,
    "gn:timezone":"Africa/Accra",
    "iso:country":"GH",
    "wof:name":"Asokwa",
    "wof:placetype":"locality"
},
  "geometry": {"coordinates":[-1.58414,6.67754],"type":"Point"}
}