{
  "type": "Feature",
  "properties": {
    "gn:admin1_code":"09",
    "gn:asciiname":"Krobo",
    "gn:country_code":"GH",
    "gn:dem":4,
    "gn:feature_class":"P",
    "gn:feature_code":"PPL",
    "gn:name":"Krobo",
    "gn:population":0,
    "gn:timezone":"Africa/Accra",
    "iso:country":"GH",
    "name:eng_x_preferred":[
        "Krobo"
    ],
    "wof:name":"Krobo",
    "wof:placetype":"locality"
},
  "geometry": {"coordinates":[-1.61201,5.05261],"type":"Point"}
}