{
  "type": "Feature",
  "properties": {
    "gn:admin1_code":"09",
    "gn:asciiname":"Aserim",
    "gn:country_code":"GH",
    "gn:dem":29,
    "gn:feature_class":"P",
    "gn:feature_code":"PPL",
    "gn:name":"Aserim",
    "gn:population":0,
    "gn:timezone":"Africa/Accra",
    "iso:country":"GH",
    "name:eng_x_preferred":[
        "Aserim"
    ],
    "wof:name":"Aserim",
    "wof:placetype":"locality"
},
  "geometry": {"coordinates":[-2.13569,4.90116],"type":"Point"}
}