{
  "type": "Feature",
  "properties": {
    "gn:admin1_code":"00",
    "gn:asciiname":"Akokobenumsu",
    "gn:country_code":"GH",
    "gn:dem":173,
    "gn:feature_class":"P",
    "gn:feature_code":"PPL",
    "gn:name":"Akokobenumsu",
    "gn:population":0,
    "gn:timezone":"Africa/Accra",
    "iso:country":"GH",
    "wof:name":"Akokobenumsu",
    "wof:placetype":"locality"
},
  "geometry": {"coordinates":[-1.37014,5.41835],"type":"Point"}
}