{
  "type": "Feature",
  "properties": {
    "gn:admin1_code":"00",
    "gn:asciiname":"Dasubansi",
    "gn:country_code":"GH",
    "gn:dem":223,
    "gn:feature_class":"P",
    "gn:feature_code":"PPL",
    "gn:name":"Dasubansi",
    "gn:population":0,
    "gn:timezone":"Africa/Accra",
    "iso:country":"GH",
    "name:und_x_variant":[
        "Dazubansi",
        "Dasubansi"
    ],
    "wof:name":"Dasubansi",
    "wof:placetype":"locality"
},
  "geometry": {"coordinates":[-0.20187,10.79918],"type":"Point"}
}