{
  "type": "Feature",
  "properties": {
    "gn:admin1_code":"09",
    "gn:asciiname":"Gyawue Wharf",
    "gn:country_code":"GH",
    "gn:dem":3,
    "gn:feature_class":"P",
    "gn:feature_code":"PPL",
    "gn:name":"Gyawue Wharf",
    "gn:population":0,
    "gn:timezone":"Africa/Accra",
    "iso:country":"GH",
    "name:und_x_variant":[
        "Jewi Wharf",
        "Jewi Ahonozo"
    ],
    "wof:name":"Gyawue Wharf",
    "wof:placetype":"locality"
},
  "geometry": {"coordinates":[-2.94124,5.08609],"type":"Point"}
}