{
  "type": "Feature",
  "properties": {
    "gn:admin1_code":"00",
    "gn:asciiname":"Asempaneye",
    "gn:country_code":"GH",
    "gn:dem":85,
    "gn:feature_class":"P",
    "gn:feature_code":"PPL",
    "gn:name":"Asempaneye",
    "gn:population":0,
    "gn:timezone":"Africa/Accra",
    "iso:country":"GH",
    "name:und_x_variant":[
        "Akaukrom",
        "Asempaneye"
    ],
    "wof:name":"Asempaneye",
    "wof:placetype":"locality"
},
  "geometry": {"coordinates":[-2.52703,5.95073],"type":"Point"}
}