{
  "type": "Feature",
  "properties": {
    "gn:admin1_code":"02",
    "gn:asciiname":"Kwamidurokrom",
    "gn:country_code":"GH",
    "gn:dem":283,
    "gn:feature_class":"P",
    "gn:feature_code":"PPL",
    "gn:name":"Kwamidurokrom",
    "gn:population":0,
    "gn:timezone":"Africa/Accra",
    "iso:country":"GH",
    "name:eng_x_preferred":[
        "Kwamidurokrom"
    ],
    "wof:name":"Kwamidurokrom",
    "wof:placetype":"locality"
},
  "geometry": {"coordinates":[-1.65009,6.97118],"type":"Point"}
}