{
  "type": "Feature",
  "properties": {
    "gn:admin1_code":"09",
    "gn:asciiname":"Ewuku",
    "gn:country_code":"GH",
    "gn:dem":26,
    "gn:feature_class":"P",
    "gn:feature_code":"PPL",
    "gn:name":"Ewuku",
    "gn:population":0,
    "gn:timezone":"Africa/Accra",
    "iso:country":"GH",
    "name:eng_x_preferred":[
        "Ewuku"
    ],
    "wof:name":"Ewuku",
    "wof:placetype":"locality"
},
  "geometry": {"coordinates":[-2.1968,4.86317],"type":"Point"}
}