{
  "type": "Feature",
  "properties": {
    "gn:admin1_code":"00",
    "gn:asciiname":"Tindayili",
    "gn:country_code":"GH",
    "gn:dem":215,
    "gn:feature_class":"P",
    "gn:feature_code":"PPL",
    "gn:name":"Tindayili",
    "gn:population":0,
    "gn:timezone":"Africa/Accra",
    "iso:country":"GH",
    "wof:name":"Tindayili",
    "wof:placetype":"locality"
},
  "geometry": {"coordinates":[-0.26667,9.38333],"type":"Point"}
}