{
  "type": "Feature",
  "properties": {
    "gn:admin1_code":"02",
    "gn:asciiname":"Amamon",
    "gn:country_code":"GH",
    "gn:dem":195,
    "gn:feature_class":"P",
    "gn:feature_code":"PPL",
    "gn:name":"Amamon",
    "gn:population":0,
    "gn:timezone":"Africa/Accra",
    "iso:country":"GH",
    "name:eng_x_preferred":[
        "Amamon"
    ],
    "name:eng_x_variant":[
        "Amamum"
    ],
    "wof:name":"Amamon",
    "wof:placetype":"locality"
},
  "geometry": {"coordinates":[-1.7014,6.27111],"type":"Point"}
}