{
  "type": "Feature",
  "properties": {
    "gn:admin1_code":"00",
    "gn:asciiname":"Petonu",
    "gn:country_code":"GH",
    "gn:dem":117,
    "gn:feature_class":"P",
    "gn:feature_code":"PPL",
    "gn:name":"Petonu",
    "gn:population":0,
    "gn:timezone":"Africa/Accra",
    "iso:country":"GH",
    "name:und_x_variant":[
        "Kpetornu",
        "Petonu"
    ],
    "wof:name":"Petonu",
    "wof:placetype":"locality"
},
  "geometry": {"coordinates":[0.23873,6.49804],"type":"Point"}
}