{
  "type": "Feature",
  "properties": {
    "gn:admin1_code":"00",
    "gn:asciiname":"Agove",
    "gn:country_code":"GH",
    "gn:dem":2,
    "gn:feature_class":"P",
    "gn:feature_code":"PPL",
    "gn:name":"Agove",
    "gn:population":0,
    "gn:timezone":"Africa/Accra",
    "iso:country":"GH",
    "name:und_x_variant":[
        "Agorve",
        "Agove"
    ],
    "wof:name":"Agove",
    "wof:placetype":"locality"
},
  "geometry": {"coordinates":[0.71612,5.93426],"type":"Point"}
}