{
  "type": "Feature",
  "properties": {
    "gn:admin1_code":"02",
    "gn:asciiname":"Abasuapayin",
    "gn:country_code":"GH",
    "gn:dem":196,
    "gn:feature_class":"P",
    "gn:feature_code":"PPL",
    "gn:name":"Abasuapayin",
    "gn:population":0,
    "gn:timezone":"Africa/Accra",
    "iso:country":"GH",
    "name:und_x_variant":[
        "Abansua Panyin",
        "Abasuapayin"
    ],
    "wof:name":"Abasuapayin",
    "wof:placetype":"locality"
},
  "geometry": {"coordinates":[-1.93977,6.72293],"type":"Point"}
}