{
  "type": "Feature",
  "properties": {
    "gn:admin1_code":"00",
    "gn:asciiname":"Ohianimegywasi",
    "gn:country_code":"GH",
    "gn:dem":206,
    "gn:feature_class":"P",
    "gn:feature_code":"PPL",
    "gn:name":"Ohianimegywasi",
    "gn:population":0,
    "gn:timezone":"Africa/Accra",
    "iso:country":"GH",
    "wof:name":"Ohianimegywasi",
    "wof:placetype":"locality"
},
  "geometry": {"coordinates":[-1.31667,6.65],"type":"Point"}
}