{
  "type": "Feature",
  "properties": {
    "gn:admin1_code":"00",
    "gn:asciiname":"Shama",
    "gn:cc2":"GH",
    "gn:country_code":"GH",
    "gn:dem":4,
    "gn:feature_class":"P",
    "gn:feature_code":"PPL",
    "gn:name":"Shama",
    "gn:population":0,
    "gn:timezone":"Africa/Accra",
    "iso:country":"GH",
    "name:ceb_x_preferred":[
        "Shama"
    ],
    "name:deu_x_preferred":[
        "Shama"
    ],
    "name:fra_x_preferred":[
        "Shama"
    ],
    "name:swe_x_preferred":[
        "Shama"
    ],
    "name:und_x_variant":[
        "Chama",
        "Sima",
        "Chamah"
    ],
    "wof:name":"Shama",
    "wof:placetype":"locality"
},
  "geometry": {"coordinates":[-1.62709,5.01973],"type":"Point"}
}