{
  "type": "Feature",
  "properties": {
    "gn:admin1_code":"11",
    "gn:asciiname":"Sira",
    "gn:country_code":"GH",
    "gn:dem":251,
    "gn:feature_class":"P",
    "gn:feature_code":"PPL",
    "gn:name":"Sira",
    "gn:population":0,
    "gn:timezone":"Africa/Accra",
    "iso:country":"GH",
    "name:und_x_variant":[
        "Sirra",
        "Sira"
    ],
    "wof:name":"Sira",
    "wof:placetype":"locality"
},
  "geometry": {"coordinates":[-2.76814,10.12883],"type":"Point"}
}