{
  "type": "Feature",
  "properties": {
    "gn:admin1_code":"11",
    "gn:asciiname":"Sira",
    "gn:country_code":"GH",
    "gn:dem":251,
    "gn:feature_class":"P",
    "gn:feature_code":"PPL",
    "gn:name":"Sira",
    "gn:population":0,
    "gn:timezone":"Africa/Accra",
    "iso:country":"GH",
    "name:ceb_x_preferred":[
        "Sira"
    ],
    "name:ces_x_preferred":[
        "Sira"
    ],
    "name:dan_x_preferred":[
        "Sira"
    ],
    "name:deu_x_preferred":[
        "Sira"
    ],
    "name:fra_x_preferred":[
        "Sira"
    ],
    "name:ita_x_preferred":[
        "Sira"
    ],
    "name:msa_x_preferred":[
        "Sira"
    ],
    "name:nld_x_preferred":[
        "Sira"
    ],
    "name:nor_x_preferred":[
        "Sira"
    ],
    "name:rus_x_preferred":[
        "\u0421\u0438\u0440\u0430"
    ],
    "name:spa_x_preferred":[
        "Sira"
    ],
    "name:srp_x_preferred":[
        "Sira"
    ],
    "name:swe_x_preferred":[
        "Sira"
    ],
    "name:ukr_x_preferred":[
        "\u0421\u0456\u0440\u0430"
    ],
    "name:und_x_variant":[
        "Sirra"
    ],
    "wof:name":"Sira",
    "wof:placetype":"locality"
},
  "geometry": {"coordinates":[-2.76814,10.12883],"type":"Point"}
}