{
  "type": "Feature",
  "properties": {
    "gn:admin1_code":"10",
    "gn:asciiname":"Pusiga",
    "gn:country_code":"GH",
    "gn:dem":241,
    "gn:feature_class":"P",
    "gn:feature_code":"PPL",
    "gn:name":"Pusiga",
    "gn:population":0,
    "gn:timezone":"Africa/Accra",
    "iso:country":"GH",
    "name:und_x_variant":[
        "Pussiga",
        "Pusiga"
    ],
    "wof:name":"Pusiga",
    "wof:placetype":"locality"
},
  "geometry": {"coordinates":[-0.12789,11.08461],"type":"Point"}
}