{
  "type": "Feature",
  "properties": {
    "gn:admin1_code":"00",
    "gn:asciiname":"Brodekwano",
    "gn:country_code":"GH",
    "gn:dem":104,
    "gn:feature_class":"P",
    "gn:feature_code":"PPL",
    "gn:name":"Brodekwano",
    "gn:population":0,
    "gn:timezone":"Africa/Accra",
    "iso:country":"GH",
    "name:und_x_variant":[
        "Bodekwano",
        "Brodekwano"
    ],
    "wof:name":"Brodekwano",
    "wof:placetype":"locality"
},
  "geometry": {"coordinates":[-1.37377,6.51773],"type":"Point"}
}