{
  "type": "Feature",
  "properties": {
    "gn:admin1_code":"09",
    "gn:asciiname":"Nkoti",
    "gn:country_code":"GH",
    "gn:dem":109,
    "gn:feature_class":"P",
    "gn:feature_code":"PPL",
    "gn:name":"Nkoti",
    "gn:population":0,
    "gn:timezone":"Africa/Accra",
    "iso:country":"GH",
    "name:eng_x_preferred":[
        "Nkoti"
    ],
    "wof:name":"Nkoti",
    "wof:placetype":"locality"
},
  "geometry": {"coordinates":[-1.945,5.80213],"type":"Point"}
}