{
  "type": "Feature",
  "properties": {
    "gn:admin1_code":"02",
    "gn:asciiname":"Owusu Ansakura",
    "gn:country_code":"GH",
    "gn:dem":228,
    "gn:feature_class":"P",
    "gn:feature_code":"PPL",
    "gn:name":"Owusu Ansakura",
    "gn:population":0,
    "gn:timezone":"Africa/Accra",
    "iso:country":"GH",
    "name:und_x_variant":[
        "Mmadwaye",
        "Owusu Ansakura"
    ],
    "wof:name":"Owusu Ansakura",
    "wof:placetype":"locality"
},
  "geometry": {"coordinates":[-1.75476,6.43814],"type":"Point"}
}