{
  "type": "Feature",
  "properties": {
    "gn:admin1_code":"00",
    "gn:asciiname":"Nsoatre",
    "gn:country_code":"GH",
    "gn:dem":331,
    "gn:feature_class":"P",
    "gn:feature_code":"PPL",
    "gn:name":"Nsoatre",
    "gn:population":0,
    "gn:timezone":"Africa/Accra",
    "iso:country":"GH",
    "name:spa_x_preferred":[
        "Nsuatre"
    ],
    "name:und_x_variant":[
        "Suatre",
        "Nsuatre",
        "Nsoatre"
    ],
    "wof:name":"Nsoatre",
    "wof:placetype":"locality"
},
  "geometry": {"coordinates":[-2.4695,7.4047],"type":"Point"}
}