{
  "type": "Feature",
  "properties": {
    "gn:admin1_code":"00",
    "gn:asciiname":"Chichiwere",
    "gn:country_code":"GH",
    "gn:dem":220,
    "gn:feature_class":"P",
    "gn:feature_code":"PPL",
    "gn:name":"Chichiwere",
    "gn:population":0,
    "gn:timezone":"Africa/Accra",
    "iso:country":"GH",
    "wof:name":"Chichiwere",
    "wof:placetype":"locality"
},
  "geometry": {"coordinates":[-1.23333,6.65],"type":"Point"}
}