{
  "type": "Feature",
  "properties": {
    "gn:admin1_code":"00",
    "gn:asciiname":"Akokwasa",
    "gn:country_code":"GH",
    "gn:dem":134,
    "gn:feature_class":"P",
    "gn:feature_code":"PPL",
    "gn:name":"Akokwasa",
    "gn:population":0,
    "gn:timezone":"Africa/Accra",
    "iso:country":"GH",
    "wof:name":"Akokwasa",
    "wof:placetype":"locality"
},
  "geometry": {"coordinates":[-0.68767,5.65194],"type":"Point"}
}