{
  "type": "Feature",
  "properties": {
    "gn:admin1_code":"02",
    "gn:asciiname":"Akotiantra",
    "gn:country_code":"GH",
    "gn:dem":158,
    "gn:feature_class":"P",
    "gn:feature_code":"PPL",
    "gn:name":"Akotiantra",
    "gn:population":0,
    "gn:timezone":"Africa/Accra",
    "iso:country":"GH",
    "name:eng_x_preferred":[
        "Akotiantra"
    ],
    "wof:name":"Akotiantra",
    "wof:placetype":"locality"
},
  "geometry": {"coordinates":[-1.88141,6.09751],"type":"Point"}
}