{
  "type": "Feature",
  "properties": {
    "gn:admin1_code":"00",
    "gn:asciiname":"Nkwanta",
    "gn:country_code":"GH",
    "gn:dem":79,
    "gn:feature_class":"P",
    "gn:feature_code":"PPL",
    "gn:name":"Nkwanta",
    "gn:population":0,
    "gn:timezone":"Africa/Accra",
    "iso:country":"GH",
    "name:swe_x_preferred":[
        "Nkwanta"
    ],
    "name:und_x_variant":[
        "Nkwanda"
    ],
    "wof:name":"Nkwanta",
    "wof:placetype":"locality"
},
  "geometry": {"coordinates":[-2.6416,5.2833],"type":"Point"}
}