{
  "type": "Feature",
  "properties": {
    "gn:admin1_code":"00",
    "gn:asciiname":"Teshi",
    "gn:country_code":"GH",
    "gn:dem":246,
    "gn:feature_class":"P",
    "gn:feature_code":"PPL",
    "gn:name":"Teshi",
    "gn:population":0,
    "gn:timezone":"Africa/Accra",
    "iso:country":"GH",
    "name:und_x_variant":[
        "Teshi Natinga",
        "Tesi",
        "Teshi"
    ],
    "wof:name":"Teshi",
    "wof:placetype":"locality"
},
  "geometry": {"coordinates":[-0.47921,10.97449],"type":"Point"}
}