{
  "type": "Feature",
  "properties": {
    "gn:admin1_code":"08",
    "gn:asciiname":"Adedido",
    "gn:country_code":"GH",
    "gn:dem":30,
    "gn:feature_class":"P",
    "gn:feature_code":"PPL",
    "gn:name":"Adedido",
    "gn:population":0,
    "gn:timezone":"Africa/Accra",
    "iso:country":"GH",
    "wof:name":"Adedido",
    "wof:placetype":"locality"
},
  "geometry": {"coordinates":[1.14,6.16278],"type":"Point"}
}