{
  "type": "Feature",
  "properties": {
    "gn:admin1_code":"02",
    "gn:asciiname":"Sefwi",
    "gn:country_code":"GH",
    "gn:dem":220,
    "gn:feature_class":"P",
    "gn:feature_code":"PPL",
    "gn:name":"Sefwi",
    "gn:population":0,
    "gn:timezone":"Africa/Accra",
    "iso:country":"GH",
    "name:eng_x_preferred":[
        "Sefwi"
    ],
    "name:eng_x_variant":[
        "Sehwi"
    ],
    "wof:name":"Sefwi",
    "wof:placetype":"locality"
},
  "geometry": {"coordinates":[-1.63596,6.52306],"type":"Point"}
}