{
  "type": "Feature",
  "properties": {
    "gn:admin1_code":"09",
    "gn:asciiname":"Essipon",
    "gn:country_code":"GH",
    "gn:dem":25,
    "gn:feature_class":"P",
    "gn:feature_code":"PPL",
    "gn:name":"Essipon",
    "gn:population":0,
    "gn:timezone":"Africa/Accra",
    "iso:country":"GH",
    "wof:name":"Essipon",
    "wof:placetype":"locality"
},
  "geometry": {"coordinates":[-1.69602,4.97201],"type":"Point"}
}