{
  "type": "Feature",
  "properties": {
    "gn:admin1_code":"00",
    "gn:asciiname":"Yilong",
    "gn:country_code":"GH",
    "gn:dem":137,
    "gn:feature_class":"P",
    "gn:feature_code":"PPL",
    "gn:name":"Yilong",
    "gn:population":0,
    "gn:timezone":"Africa/Accra",
    "iso:country":"GH",
    "name:und_x_variant":[
        "Yelong",
        "Yilong"
    ],
    "wof:name":"Yilong",
    "wof:placetype":"locality"
},
  "geometry": {"coordinates":[-0.38646,10.19382],"type":"Point"}
}