{
  "type": "Feature",
  "properties": {
    "gn:admin1_code":"00",
    "gn:asciiname":"Abakanunkun",
    "gn:country_code":"GH",
    "gn:dem":21,
    "gn:feature_class":"P",
    "gn:feature_code":"PPL",
    "gn:name":"Abakanunkun",
    "gn:population":0,
    "gn:timezone":"Africa/Accra",
    "iso:country":"GH",
    "name:und_x_variant":[
        "Abakunkam",
        "Abakanunkun"
    ],
    "wof:name":"Abakanunkun",
    "wof:placetype":"locality"
},
  "geometry": {"coordinates":[-1.45602,5.10115],"type":"Point"}
}