{
  "type": "Feature",
  "properties": {
    "gn:admin1_code":"11",
    "gn:asciiname":"Falu",
    "gn:country_code":"GH",
    "gn:dem":266,
    "gn:feature_class":"P",
    "gn:feature_code":"PPL",
    "gn:name":"Falu",
    "gn:population":0,
    "gn:timezone":"Africa/Accra",
    "iso:country":"GH",
    "name:por_x_preferred":[
        "Falu"
    ],
    "name:und_x_variant":[
        "Pavuu",
        "Falu"
    ],
    "name:urd_x_preferred":[
        "\u0641\u0627\u0644\u0648"
    ],
    "wof:name":"Falu",
    "wof:placetype":"locality"
},
  "geometry": {"coordinates":[-2.81902,10.60426],"type":"Point"}
}