{
  "type": "Feature",
  "properties": {
    "gn:admin1_code":"00",
    "gn:asciiname":"Tanla",
    "gn:country_code":"GH",
    "gn:dem":291,
    "gn:feature_class":"P",
    "gn:feature_code":"PPL",
    "gn:name":"Tanla",
    "gn:population":0,
    "gn:timezone":"Africa/Accra",
    "iso:country":"GH",
    "wof:name":"Tanla",
    "wof:placetype":"locality"
},
  "geometry": {"coordinates":[-1.69686,10.92278],"type":"Point"}
}