{
  "type": "Feature",
  "properties": {
    "gn:admin1_code":"09",
    "gn:asciiname":"Abase",
    "gn:country_code":"GH",
    "gn:dem":35,
    "gn:feature_class":"P",
    "gn:feature_code":"PPL",
    "gn:name":"Abase",
    "gn:population":0,
    "gn:timezone":"Africa/Accra",
    "iso:country":"GH",
    "name:und_x_variant":[
        "Abasi"
    ],
    "wof:name":"Abase",
    "wof:placetype":"locality"
},
  "geometry": {"coordinates":[-2.06067,4.88192],"type":"Point"}
}