{
  "type": "Feature",
  "properties": {
    "gn:admin1_code":"00",
    "gn:asciiname":"Akwadum",
    "gn:country_code":"GH",
    "gn:dem":74,
    "gn:feature_class":"P",
    "gn:feature_code":"PPL",
    "gn:name":"Akwadum",
    "gn:population":0,
    "gn:timezone":"Africa/Accra",
    "iso:country":"GH",
    "wof:name":"Akwadum",
    "wof:placetype":"locality"
},
  "geometry": {"coordinates":[-2.17922,5.38906],"type":"Point"}
}