{
  "type": "Feature",
  "properties": {
    "gn:admin1_code":"00",
    "gn:asciiname":"Wegbe",
    "gn:country_code":"GH",
    "gn:dem":167,
    "gn:feature_class":"P",
    "gn:feature_code":"PPL",
    "gn:name":"Wegbe",
    "gn:population":0,
    "gn:timezone":"Africa/Accra",
    "iso:country":"GH",
    "name:ewe_x_preferred":[
        "\u01b2egbe Kpalime"
    ],
    "name:twi_x_preferred":[
        "Wegbe Kpalime"
    ],
    "name:und_x_variant":[
        "Wegbe Kpalime",
        "Wegbe"
    ],
    "wof:name":"Wegbe",
    "wof:placetype":"locality"
},
  "geometry": {"coordinates":[0.34068,6.64998],"type":"Point"}
}