{
  "type": "Feature",
  "properties": {
    "gn:admin1_code":"00",
    "gn:asciiname":"Tintimshe",
    "gn:country_code":"GH",
    "gn:dem":149,
    "gn:feature_class":"P",
    "gn:feature_code":"PPL",
    "gn:name":"Tintimshe",
    "gn:population":0,
    "gn:timezone":"Africa/Accra",
    "iso:country":"GH",
    "wof:name":"Tintimshe",
    "wof:placetype":"locality"
},
  "geometry": {"coordinates":[-1.73333,5.55],"type":"Point"}
}