{
  "type": "Feature",
  "properties": {
    "gn:admin1_code":"04",
    "gn:asciiname":"Fourteen",
    "gn:country_code":"GH",
    "gn:dem":173,
    "gn:feature_class":"P",
    "gn:feature_code":"PPL",
    "gn:name":"Fourteen",
    "gn:population":0,
    "gn:timezone":"Africa/Accra",
    "iso:country":"GH",
    "name:eng_x_preferred":[
        "Fourteen"
    ],
    "wof:name":"Fourteen",
    "wof:placetype":"locality"
},
  "geometry": {"coordinates":[-1.92332,6.00278],"type":"Point"}
}