{
  "type": "Feature",
  "properties": {
    "gn:admin1_code":"00",
    "gn:asciiname":"Efwhia",
    "gn:country_code":"GH",
    "gn:dem":266,
    "gn:feature_class":"P",
    "gn:feature_code":"PPL",
    "gn:name":"Efwhia",
    "gn:population":0,
    "gn:timezone":"Africa/Accra",
    "iso:country":"GH",
    "name:und_x_variant":[
        "Awhiaah",
        "Efhwia",
        "Anhwea",
        "Efwhia"
    ],
    "wof:name":"Efwhia",
    "wof:placetype":"locality"
},
  "geometry": {"coordinates":[-2.42805,6.1962],"type":"Point"}
}