{
  "type": "Feature",
  "properties": {
    "gn:admin1_code":"00",
    "gn:asciiname":"Kasanpari",
    "gn:country_code":"GH",
    "gn:dem":302,
    "gn:feature_class":"P",
    "gn:feature_code":"PPL",
    "gn:name":"Kasanpari",
    "gn:population":0,
    "gn:timezone":"Africa/Accra",
    "iso:country":"GH",
    "name:und_x_variant":[
        "Kassenpuori",
        "Kasanpari"
    ],
    "wof:name":"Kasanpari",
    "wof:placetype":"locality"
},
  "geometry": {"coordinates":[-1.85948,10.97417],"type":"Point"}
}