{
  "type": "Feature",
  "properties": {
    "gn:admin1_code":"00",
    "gn:asciiname":"Adewuke",
    "gn:country_code":"GH",
    "gn:dem":0,
    "gn:feature_class":"P",
    "gn:feature_code":"PPL",
    "gn:name":"Adewuke",
    "gn:population":0,
    "gn:timezone":"Africa/Accra",
    "iso:country":"GH",
    "name:und_x_variant":[
        "Adouke",
        "Adewuke"
    ],
    "wof:name":"Adewuke",
    "wof:placetype":"locality"
},
  "geometry": {"coordinates":[0.65928,5.77817],"type":"Point"}
}