{
  "type": "Feature",
  "properties": {
    "gn:admin1_code":"00",
    "gn:asciiname":"Ahunjo",
    "gn:country_code":"GH",
    "gn:dem":104,
    "gn:feature_class":"P",
    "gn:feature_code":"PPL",
    "gn:name":"Ahunjo",
    "gn:population":0,
    "gn:timezone":"Africa/Accra",
    "iso:country":"GH",
    "wof:name":"Ahunjo",
    "wof:placetype":"locality"
},
  "geometry": {"coordinates":[-1.405,5.91347],"type":"Point"}
}