{
  "type": "Feature",
  "properties": {
    "gn:admin1_code":"09",
    "gn:asciiname":"Dukoto",
    "gn:country_code":"GH",
    "gn:dem":59,
    "gn:feature_class":"P",
    "gn:feature_code":"PPL",
    "gn:name":"Dukoto",
    "gn:population":0,
    "gn:timezone":"Africa/Accra",
    "iso:country":"GH",
    "name:eng_x_preferred":[
        "Dukoto"
    ],
    "wof:name":"Dukoto",
    "wof:placetype":"locality"
},
  "geometry": {"coordinates":[-2.17037,5.79477],"type":"Point"}
}