{
  "type": "Feature",
  "properties": {
    "gn:admin1_code":"02",
    "gn:asciiname":"Enianti",
    "gn:country_code":"GH",
    "gn:dem":278,
    "gn:feature_class":"P",
    "gn:feature_code":"PPL",
    "gn:name":"Enianti",
    "gn:population":0,
    "gn:timezone":"Africa/Accra",
    "iso:country":"GH",
    "name:und_x_variant":[
        "Aniante",
        "Enianti"
    ],
    "wof:name":"Enianti",
    "wof:placetype":"locality"
},
  "geometry": {"coordinates":[-1.73069,6.9708],"type":"Point"}
}