{
  "type": "Feature",
  "properties": {
    "gn:admin1_code":"00",
    "gn:asciiname":"Kpani",
    "gn:country_code":"GH",
    "gn:dem":127,
    "gn:feature_class":"P",
    "gn:feature_code":"PPL",
    "gn:name":"Kpani",
    "gn:population":0,
    "gn:timezone":"Africa/Accra",
    "iso:country":"GH",
    "name:und_x_variant":[
        "B\u0101ni",
        "Kpani"
    ],
    "wof:name":"Kpani",
    "wof:placetype":"locality"
},
  "geometry": {"coordinates":[0.3546,10.25824],"type":"Point"}
}