{
  "type": "Feature",
  "properties": {
    "gn:admin1_code":"00",
    "gn:asciiname":"Gbeogo",
    "gn:country_code":"GH",
    "gn:dem":152,
    "gn:feature_class":"P",
    "gn:feature_code":"PPL",
    "gn:name":"Gbeogo",
    "gn:population":0,
    "gn:timezone":"Africa/Accra",
    "iso:country":"GH",
    "name:aka_x_preferred":[
        "Gbeogo"
    ],
    "name:und_x_variant":[
        "Biagu",
        "Gbeo",
        "Gbeogo"
    ],
    "wof:name":"Gbeogo",
    "wof:placetype":"locality"
},
  "geometry": {"coordinates":[-0.80285,10.59965],"type":"Point"}
}