{
  "type": "Feature",
  "properties": {
    "gn:admin1_code":"00",
    "gn:asciiname":"Kasuridaborshi",
    "gn:country_code":"GH",
    "gn:dem":137,
    "gn:feature_class":"P",
    "gn:feature_code":"PPL",
    "gn:name":"Kasuridaborshi",
    "gn:population":0,
    "gn:timezone":"Africa/Accra",
    "iso:country":"GH",
    "wof:name":"Kasuridaborshi",
    "wof:placetype":"locality"
},
  "geometry": {"coordinates":[-1.11773,9.55262],"type":"Point"}
}