{
  "type": "Feature",
  "properties": {
    "gn:admin1_code":"00",
    "gn:asciiname":"Seneso",
    "gn:country_code":"GH",
    "gn:dem":109,
    "gn:feature_class":"P",
    "gn:feature_code":"PPL",
    "gn:name":"Seneso",
    "gn:population":0,
    "gn:timezone":"Africa/Accra",
    "iso:country":"GH",
    "wof:name":"Seneso",
    "wof:placetype":"locality"
},
  "geometry": {"coordinates":[-0.89645,7.49395],"type":"Point"}
}