{
  "type": "Feature",
  "properties": {
    "gn:admin1_code":"00",
    "gn:asciiname":"Mpem",
    "gn:country_code":"GH",
    "gn:dem":18,
    "gn:feature_class":"P",
    "gn:feature_code":"PPL",
    "gn:name":"Mpem",
    "gn:population":0,
    "gn:timezone":"Africa/Accra",
    "iso:country":"GH",
    "name:und_x_variant":[
        "Mgbem",
        "Mpem"
    ],
    "wof:name":"Mpem",
    "wof:placetype":"locality"
},
  "geometry": {"coordinates":[-2.5352,5.05726],"type":"Point"}
}