{
  "type": "Feature",
  "properties": {
    "gn:admin1_code":"00",
    "gn:asciiname":"Mpeasem",
    "gn:country_code":"GH",
    "gn:dem":56,
    "gn:feature_class":"P",
    "gn:feature_code":"PPL",
    "gn:name":"Mpeasem",
    "gn:population":0,
    "gn:timezone":"Africa/Accra",
    "iso:country":"GH",
    "name:und_x_variant":[
        "Mpasem",
        "Mpeasem"
    ],
    "wof:name":"Mpeasem",
    "wof:placetype":"locality"
},
  "geometry": {"coordinates":[-2.20199,5.38963],"type":"Point"}
}