{
  "type": "Feature",
  "properties": {
    "gn:admin1_code":"00",
    "gn:asciiname":"Tapiramang",
    "gn:country_code":"GH",
    "gn:dem":148,
    "gn:feature_class":"P",
    "gn:feature_code":"PPL",
    "gn:name":"Tapiramang",
    "gn:population":0,
    "gn:timezone":"Africa/Accra",
    "iso:country":"GH",
    "name:und_x_variant":[
        "Topreman",
        "Topireming",
        "Tapiramang"
    ],
    "wof:name":"Tapiramang",
    "wof:placetype":"locality"
},
  "geometry": {"coordinates":[-0.77624,6.05613],"type":"Point"}
}