{
  "type": "Feature",
  "properties": {
    "gn:admin1_code":"02",
    "gn:asciiname":"Ntinanko",
    "gn:country_code":"GH",
    "gn:dem":208,
    "gn:feature_class":"P",
    "gn:feature_code":"PPL",
    "gn:name":"Ntinanko",
    "gn:population":0,
    "gn:timezone":"Africa/Accra",
    "iso:country":"GH",
    "name:und_x_variant":[
        "Ntinankaw"
    ],
    "wof:name":"Ntinanko",
    "wof:placetype":"locality"
},
  "geometry": {"coordinates":[-1.69027,6.42595],"type":"Point"}
}