{
  "type": "Feature",
  "properties": {
    "gn:admin1_code":"00",
    "gn:asciiname":"Avega",
    "gn:country_code":"GH",
    "gn:dem":60,
    "gn:feature_class":"P",
    "gn:feature_code":"PPL",
    "gn:name":"Avega",
    "gn:population":0,
    "gn:timezone":"Africa/Accra",
    "iso:country":"GH",
    "wof:name":"Avega",
    "wof:placetype":"locality"
},
  "geometry": {"coordinates":[0.81667,6.31667],"type":"Point"}
}