{
  "type": "Feature",
  "properties": {
    "gn:admin1_code":"00",
    "gn:asciiname":"Pisi",
    "gn:country_code":"GH",
    "gn:dem":303,
    "gn:feature_class":"P",
    "gn:feature_code":"PPL",
    "gn:name":"Pisi",
    "gn:population":0,
    "gn:timezone":"Africa/Accra",
    "iso:country":"GH",
    "wof:name":"Pisi",
    "wof:placetype":"locality"
},
  "geometry": {"coordinates":[-2.46011,9.95937],"type":"Point"}
}