{
  "type": "Feature",
  "properties": {
    "gn:admin1_code":"10",
    "gn:asciiname":"Uwasi",
    "gn:country_code":"GH",
    "gn:dem":192,
    "gn:feature_class":"P",
    "gn:feature_code":"PPL",
    "gn:name":"Uwasi",
    "gn:population":0,
    "gn:timezone":"Africa/Accra",
    "iso:country":"GH",
    "name:und_x_variant":[
        "Uwasi Central",
        "Uwasi Kazengsa",
        "Uwasi"
    ],
    "wof:name":"Uwasi",
    "wof:placetype":"locality"
},
  "geometry": {"coordinates":[-1.22839,10.47889],"type":"Point"}
}