{
  "type": "Feature",
  "properties": {
    "gn:admin1_code":"00",
    "gn:asciiname":"Mampong",
    "gn:country_code":"GH",
    "gn:dem":110,
    "gn:feature_class":"P",
    "gn:feature_code":"PPL",
    "gn:name":"Mampong",
    "gn:population":0,
    "gn:timezone":"Africa/Accra",
    "iso:country":"GH",
    "name:und_x_variant":[
        "Mampon",
        "Mampong"
    ],
    "wof:name":"Mampong",
    "wof:placetype":"locality"
},
  "geometry": {"coordinates":[-2.15252,6.03008],"type":"Point"}
}