{
  "type": "Feature",
  "properties": {
    "gn:admin1_code":"00",
    "gn:asciiname":"Ohua",
    "gn:country_code":"GH",
    "gn:dem":66,
    "gn:feature_class":"P",
    "gn:feature_code":"PPL",
    "gn:name":"Ohua",
    "gn:population":0,
    "gn:timezone":"Africa/Accra",
    "iso:country":"GH",
    "name:und_x_variant":[
        "Ahua",
        "Ohua"
    ],
    "wof:name":"Ohua",
    "wof:placetype":"locality"
},
  "geometry": {"coordinates":[-0.82328,5.3735],"type":"Point"}
}