{
  "type": "Feature",
  "properties": {
    "gn:admin1_code":"02",
    "gn:asciiname":"Bonsaiso",
    "gn:country_code":"GH",
    "gn:dem":153,
    "gn:feature_class":"P",
    "gn:feature_code":"PPL",
    "gn:name":"Bonsaiso",
    "gn:population":0,
    "gn:timezone":"Africa/Accra",
    "iso:country":"GH",
    "name:eng_x_preferred":[
        "Bonsaiso"
    ],
    "wof:name":"Bonsaiso",
    "wof:placetype":"locality"
},
  "geometry": {"coordinates":[-1.9985,6.23591],"type":"Point"}
}