{
  "type": "Feature",
  "properties": {
    "gn:admin1_code":"00",
    "gn:asciiname":"Djopo",
    "gn:country_code":"GH",
    "gn:dem":43,
    "gn:feature_class":"P",
    "gn:feature_code":"PPL",
    "gn:name":"Djopo",
    "gn:population":0,
    "gn:timezone":"Africa/Accra",
    "iso:country":"GH",
    "name:und_x_variant":[
        "Djobo",
        "Djopo"
    ],
    "wof:name":"Djopo",
    "wof:placetype":"locality"
},
  "geometry": {"coordinates":[0.6632,6.29508],"type":"Point"}
}