{
  "type": "Feature",
  "properties": {
    "gn:admin1_code":"00",
    "gn:asciiname":"Aiwata",
    "gn:country_code":"GH",
    "gn:dem":38,
    "gn:feature_class":"P",
    "gn:feature_code":"PPL",
    "gn:name":"Aiwata",
    "gn:population":0,
    "gn:timezone":"Africa/Accra",
    "iso:country":"GH",
    "wof:name":"Aiwata",
    "wof:placetype":"locality"
},
  "geometry": {"coordinates":[0.35937,6.28302],"type":"Point"}
}