{
  "type": "Feature",
  "properties": {
    "gn:admin1_code":"00",
    "gn:asciiname":"Seripe",
    "gn:country_code":"GH",
    "gn:dem":287,
    "gn:feature_class":"P",
    "gn:feature_code":"PPL",
    "gn:name":"Seripe",
    "gn:population":0,
    "gn:timezone":"Africa/Accra",
    "iso:country":"GH",
    "name:und_x_variant":[
        "Siripe",
        "Seripe"
    ],
    "wof:name":"Seripe",
    "wof:placetype":"locality"
},
  "geometry": {"coordinates":[-2.39665,8.92925],"type":"Point"}
}