{
  "type": "Feature",
  "properties": {
    "gn:admin1_code":"02",
    "gn:asciiname":"Paa",
    "gn:country_code":"GH",
    "gn:dem":249,
    "gn:feature_class":"P",
    "gn:feature_code":"PPL",
    "gn:name":"Paa",
    "gn:population":0,
    "gn:timezone":"Africa/Accra",
    "iso:country":"GH",
    "name:ceb_x_preferred":[
        "Paa"
    ],
    "name:swe_x_preferred":[
        "Paa"
    ],
    "name:und_x_variant":[
        "Pa"
    ],
    "wof:name":"Paa",
    "wof:placetype":"locality"
},
  "geometry": {"coordinates":[-1.66079,6.56713],"type":"Point"}
}