{
  "type": "Feature",
  "properties": {
    "gn:admin1_code":"00",
    "gn:asciiname":"Gari",
    "gn:country_code":"GH",
    "gn:dem":244,
    "gn:feature_class":"P",
    "gn:feature_code":"PPL",
    "gn:name":"Gari",
    "gn:population":0,
    "gn:timezone":"Africa/Accra",
    "iso:country":"GH",
    "name:und_x_variant":[
        "Dusi Gari",
        "Gari"
    ],
    "wof:name":"Gari",
    "wof:placetype":"locality"
},
  "geometry": {"coordinates":[-0.69872,10.75303],"type":"Point"}
}