{
  "type": "Feature",
  "properties": {
    "gn:admin1_code":"00",
    "gn:asciiname":"Gari",
    "gn:country_code":"GH",
    "gn:dem":244,
    "gn:feature_class":"P",
    "gn:feature_code":"PPL",
    "gn:name":"Gari",
    "gn:population":0,
    "gn:timezone":"Africa/Accra",
    "iso:country":"GH",
    "name:bul_x_preferred":[
        "\u0413\u0430\u0440\u0438"
    ],
    "name:ceb_x_preferred":[
        "Gari"
    ],
    "name:deu_x_preferred":[
        "Gari"
    ],
    "name:eus_x_preferred":[
        "Gari"
    ],
    "name:fra_x_preferred":[
        "Gari"
    ],
    "name:ita_x_preferred":[
        "Gari"
    ],
    "name:jpn_x_preferred":[
        "\u30ac\u30ea"
    ],
    "name:nld_x_preferred":[
        "Gari"
    ],
    "name:por_x_preferred":[
        "Gari"
    ],
    "name:rus_x_preferred":[
        "\u0413\u0430\u0440\u0438"
    ],
    "name:spa_x_preferred":[
        "Gari"
    ],
    "name:srp_x_preferred":[
        "\u0413\u0430\u0440\u0438"
    ],
    "name:swe_x_preferred":[
        "Gari"
    ],
    "name:ukr_x_preferred":[
        "\u0413\u0430\u0440\u0456"
    ],
    "name:und_x_variant":[
        "Dusi Gari"
    ],
    "name:vie_x_preferred":[
        "Gari"
    ],
    "wof:name":"Gari",
    "wof:placetype":"locality"
},
  "geometry": {"coordinates":[-0.69872,10.75303],"type":"Point"}
}