{
  "type": "Feature",
  "properties": {
    "gn:admin1_code":"02",
    "gn:asciiname":"Nsutem",
    "gn:country_code":"GH",
    "gn:dem":111,
    "gn:feature_class":"P",
    "gn:feature_code":"PPL",
    "gn:name":"Nsutem",
    "gn:population":0,
    "gn:timezone":"Africa/Accra",
    "iso:country":"GH",
    "name:eng_x_preferred":[
        "Nsutem"
    ],
    "wof:name":"Nsutem",
    "wof:placetype":"locality"
},
  "geometry": {"coordinates":[-1.53929,5.98191],"type":"Point"}
}