{
  "type": "Feature",
  "properties": {
    "gn:admin1_code":"02",
    "gn:asciiname":"Anensuja",
    "gn:country_code":"GH",
    "gn:dem":228,
    "gn:feature_class":"P",
    "gn:feature_code":"PPL",
    "gn:name":"Anensuja",
    "gn:population":0,
    "gn:timezone":"Africa/Accra",
    "iso:country":"GH",
    "name:und_x_variant":[
        "Anansugya",
        "Anensogya",
        "Anensuja"
    ],
    "wof:name":"Anensuja",
    "wof:placetype":"locality"
},
  "geometry": {"coordinates":[-1.7748,6.53536],"type":"Point"}
}