{
  "type": "Feature",
  "properties": {
    "gn:admin1_code":"00",
    "gn:asciiname":"Pameng",
    "gn:country_code":"GH",
    "gn:dem":214,
    "gn:feature_class":"P",
    "gn:feature_code":"PPL",
    "gn:name":"Pameng",
    "gn:population":0,
    "gn:timezone":"Africa/Accra",
    "iso:country":"GH",
    "name:und_x_variant":[
        "Pamen",
        "Pameng"
    ],
    "wof:name":"Pameng",
    "wof:placetype":"locality"
},
  "geometry": {"coordinates":[-0.62392,6.20924],"type":"Point"}
}