{
  "type": "Feature",
  "properties": {
    "gn:admin1_code":"09",
    "gn:asciiname":"Bonsu Nkwata",
    "gn:country_code":"GH",
    "gn:dem":9,
    "gn:feature_class":"P",
    "gn:feature_code":"PPL",
    "gn:name":"Bonsu Nkwata",
    "gn:population":0,
    "gn:timezone":"Africa/Accra",
    "iso:country":"GH",
    "wof:name":"Bonsu Nkwata",
    "wof:placetype":"locality"
},
  "geometry": {"coordinates":[-1.76668,4.90006],"type":"Point"}
}