{
  "type": "Feature",
  "properties": {
    "gn:admin1_code":"00",
    "gn:asciiname":"Akokoma",
    "gn:country_code":"GH",
    "gn:dem":152,
    "gn:feature_class":"P",
    "gn:feature_code":"PPL",
    "gn:name":"Akokoma",
    "gn:population":0,
    "gn:timezone":"Africa/Accra",
    "iso:country":"GH",
    "name:und_x_variant":[
        "Akokoma Teima",
        "Akokoma"
    ],
    "wof:name":"Akokoma",
    "wof:placetype":"locality"
},
  "geometry": {"coordinates":[-0.07539,6.38995],"type":"Point"}
}