{
  "type": "Feature",
  "properties": {
    "gn:admin1_code":"00",
    "gn:asciiname":"Bantambari",
    "gn:cc2":"GH",
    "gn:country_code":"GH",
    "gn:dem":319,
    "gn:feature_class":"P",
    "gn:feature_code":"PPL",
    "gn:name":"Bantambari",
    "gn:population":0,
    "gn:timezone":"Africa/Accra",
    "iso:country":"GH",
    "name:und_x_variant":[
        "Batamb",
        "Bantambari"
    ],
    "wof:name":"Bantambari",
    "wof:placetype":"locality"
},
  "geometry": {"coordinates":[-0.56667,10.48333],"type":"Point"}
}