{
  "type": "Feature",
  "properties": {
    "gn:admin1_code":"00",
    "gn:asciiname":"Ojashewano",
    "gn:cc2":"GH",
    "gn:country_code":"GH",
    "gn:dem":97,
    "gn:feature_class":"P",
    "gn:feature_code":"PPL",
    "gn:name":"Ojashewano",
    "gn:population":0,
    "gn:timezone":"Africa/Accra",
    "iso:country":"GH",
    "name:und_x_variant":[
        "Ogyanhyewano",
        "Ojashewano"
    ],
    "wof:name":"Ojashewano",
    "wof:placetype":"locality"
},
  "geometry": {"coordinates":[-0.65,5.65],"type":"Point"}
}