{
  "type": "Feature",
  "properties": {
    "gn:country":"GH",
    "gn:fcode":"PPL",
    "gn:population":32950,
    "iso:country":"GH",
    "name:ceb_x_preferred":[
        "Nsawam"
    ],
    "name:deu_x_preferred":[
        "Nsawam"
    ],
    "name:eng_x_preferred":[
        "Nsawam"
    ],
    "name:glg_x_preferred":[
        "Nsawam"
    ],
    "name:gpe_x_preferred":[
        "Nsawam"
    ],
    "name:hau_x_preferred":[
        "Nsawam"
    ],
    "name:jpn_x_preferred":[
        "\u30f3\u30b5\u30ef\u30e0"
    ],
    "name:nld_x_preferred":[
        "Nsawam"
    ],
    "name:pol_x_preferred":[
        "Nsawam"
    ],
    "name:spa_x_preferred":[
        "Nsawam"
    ],
    "name:swa_x_preferred":[
        "Nsawam"
    ],
    "name:swe_x_preferred":[
        "Nsawam"
    ],
    "name:twi_x_preferred":[
        "Nsawam"
    ],
    "name:urd_x_preferred":[
        "\u0646\u0633\u0627\u0648\u0627\u0645"
    ],
    "name:yor_x_preferred":[
        "Nsawam"
    ],
    "name:zho_x_preferred":[
        "\u6069\u85a9\u74e6\u59c6"
    ],
    "qs_pg:aaroncc":"GH",
    "qs_pg:gn_country":"GH",
    "qs_pg:gn_fcode":"PPL",
    "qs_pg:gn_pop":32950,
    "qs_pg:name":"Nsawam",
    "qs_pg:photos_9r":0,
    "qs_pg:photos_sr":0,
    "qs_pg:pop_sr":7,
    "qs_pg:qs_pg_placetype":"locality",
    "wof:name":"Nsawam",
    "wof:placetype":"locality",
    "wof:population":44522
},
  "geometry": {"coordinates":[-0.35026,5.80893],"type":"Point"}
}