{
  "type": "Feature",
  "properties": {
    "gn:admin1_code":"00",
    "gn:asciiname":"Anokwa",
    "gn:country_code":"GH",
    "gn:dem":71,
    "gn:feature_class":"P",
    "gn:feature_code":"PPL",
    "gn:name":"Anokwa",
    "gn:population":0,
    "gn:timezone":"Africa/Accra",
    "iso:country":"GH",
    "name:und_x_variant":[
        "Anokwaa",
        "Andokwaa",
        "Anokwa"
    ],
    "wof:name":"Anokwa",
    "wof:placetype":"locality"
},
  "geometry": {"coordinates":[-0.60604,5.51019],"type":"Point"}
}