{
  "type": "Feature",
  "properties": {
    "gn:admin1_code":"00",
    "gn:asciiname":"Mim Mohu",
    "gn:country_code":"GH",
    "gn:dem":227,
    "gn:feature_class":"P",
    "gn:feature_code":"PPL",
    "gn:name":"Mim Mohu",
    "gn:population":0,
    "gn:timezone":"Africa/Accra",
    "iso:country":"GH",
    "name:und_x_variant":[
        "Mim Muohu",
        "Mim Mohu"
    ],
    "wof:name":"Mim Mohu",
    "wof:placetype":"locality"
},
  "geometry": {"coordinates":[-2.61106,6.93166],"type":"Point"}
}