{
  "type": "Feature",
  "properties": {
    "gn:admin1_code":"02",
    "gn:asciiname":"Heman",
    "gn:country_code":"GH",
    "gn:dem":258,
    "gn:feature_class":"P",
    "gn:feature_code":"PPL",
    "gn:name":"Heman",
    "gn:population":0,
    "gn:timezone":"Africa/Accra",
    "iso:country":"GH",
    "name:eng_x_preferred":[
        "Heman"
    ],
    "name:und_x_variant":[
        "Himan",
        "Himang"
    ],
    "wof:name":"Heman",
    "wof:placetype":"locality"
},
  "geometry": {"coordinates":[-1.67162,6.64468],"type":"Point"}
}