{
  "type": "Feature",
  "properties": {
    "gn:admin1_code":"01",
    "gn:asciiname":"Owuraman",
    "gn:country_code":"GH",
    "gn:dem":28,
    "gn:feature_class":"P",
    "gn:feature_code":"PPL",
    "gn:name":"Owuraman",
    "gn:population":0,
    "gn:timezone":"Africa/Accra",
    "iso:country":"GH",
    "name:eng_x_preferred":[
        "Owuraman"
    ],
    "wof:name":"Owuraman",
    "wof:placetype":"locality"
},
  "geometry": {"coordinates":[-0.28961,5.59271],"type":"Point"}
}