{
  "type": "Feature",
  "properties": {
    "gn:admin1_code":"01",
    "gn:asciiname":"Ofada",
    "gn:country_code":"GH",
    "gn:dem":139,
    "gn:feature_class":"P",
    "gn:feature_code":"PPL",
    "gn:name":"Ofada",
    "gn:population":0,
    "gn:timezone":"Africa/Accra",
    "iso:country":"GH",
    "wof:name":"Ofada",
    "wof:placetype":"locality"
},
  "geometry": {"coordinates":[-0.54221,5.72956],"type":"Point"}
}