{
  "type": "Feature",
  "properties": {
    "gn:admin1_code":"02",
    "gn:asciiname":"Dichemso",
    "gn:country_code":"GH",
    "gn:dem":283,
    "gn:feature_class":"P",
    "gn:feature_code":"PPL",
    "gn:name":"Dichemso",
    "gn:population":0,
    "gn:timezone":"Africa/Accra",
    "iso:country":"GH",
    "wof:name":"Dichemso",
    "wof:placetype":"locality"
},
  "geometry": {"coordinates":[-1.61059,6.71075],"type":"Point"}
}