{
  "type": "Feature",
  "properties": {
    "gn:admin1_code":"00",
    "gn:asciiname":"Kakpanjag",
    "gn:country_code":"GH",
    "gn:dem":113,
    "gn:feature_class":"P",
    "gn:feature_code":"PPL",
    "gn:name":"Kakpanjag",
    "gn:population":0,
    "gn:timezone":"Africa/Accra",
    "iso:country":"GH",
    "wof:name":"Kakpanjag",
    "wof:placetype":"locality"
},
  "geometry": {"coordinates":[0.23272,9.38315],"type":"Point"}
}