{
  "type": "Feature",
  "properties": {
    "gn:admin1_code":"00",
    "gn:asciiname":"Esuadai",
    "gn:cc2":"GH",
    "gn:country_code":"GH",
    "gn:dem":130,
    "gn:feature_class":"P",
    "gn:feature_code":"PPL",
    "gn:name":"Esuadai",
    "gn:population":0,
    "gn:timezone":"Africa/Accra",
    "iso:country":"GH",
    "name:und_x_variant":[
        "Esuadei",
        "Esuadai"
    ],
    "wof:name":"Esuadai",
    "wof:placetype":"locality"
},
  "geometry": {"coordinates":[-2.11667,6.16667],"type":"Point"}
}