{
  "type": "Feature",
  "properties": {
    "gn:admin1_code":"09",
    "gn:asciiname":"Nyamelisa",
    "gn:country_code":"GH",
    "gn:dem":103,
    "gn:feature_class":"P",
    "gn:feature_code":"PPL",
    "gn:name":"Nyamelisa",
    "gn:population":0,
    "gn:timezone":"Africa/Accra",
    "iso:country":"GH",
    "name:eng_x_preferred":[
        "Nyamelisa"
    ],
    "wof:name":"Nyamelisa",
    "wof:placetype":"locality"
},
  "geometry": {"coordinates":[-2.78524,5.76625],"type":"Point"}
}