{
  "type": "Feature",
  "properties": {
    "gn:admin1_code":"00",
    "gn:asciiname":"Nyebiribi",
    "gn:country_code":"GH",
    "gn:dem":57,
    "gn:feature_class":"P",
    "gn:feature_code":"PPL",
    "gn:name":"Nyebiribi",
    "gn:population":0,
    "gn:timezone":"Africa/Accra",
    "iso:country":"GH",
    "name:und_x_variant":[
        "Nyebribi",
        "Nyebiribi"
    ],
    "wof:name":"Nyebiribi",
    "wof:placetype":"locality"
},
  "geometry": {"coordinates":[-2.16157,5.43189],"type":"Point"}
}