{
  "type": "Feature",
  "properties": {
    "gn:admin1_code":"00",
    "gn:asciiname":"Achiasi",
    "gn:country_code":"GH",
    "gn:dem":128,
    "gn:feature_class":"P",
    "gn:feature_code":"PPL",
    "gn:name":"Achiasi",
    "gn:population":0,
    "gn:timezone":"Africa/Accra",
    "iso:country":"GH",
    "name:fas_x_preferred":[
        "\u0627\u0686\u06cc\u0627\u0633\u06cc"
    ],
    "wof:name":"Achiasi",
    "wof:placetype":"locality"
},
  "geometry": {"coordinates":[-0.46667,5.85],"type":"Point"}
}