{
  "type": "Feature",
  "properties": {
    "gn:admin1_code":"09",
    "gn:asciiname":"Nyubasa",
    "gn:country_code":"GH",
    "gn:dem":33,
    "gn:feature_class":"P",
    "gn:feature_code":"PPL",
    "gn:name":"Nyubasa",
    "gn:population":0,
    "gn:timezone":"Africa/Accra",
    "iso:country":"GH",
    "name:eng_x_preferred":[
        "Nyubasa"
    ],
    "wof:name":"Nyubasa",
    "wof:placetype":"locality"
},
  "geometry": {"coordinates":[-2.10442,4.9164],"type":"Point"}
}