{
  "type": "Feature",
  "properties": {
    "gn:admin1_code":"00",
    "gn:asciiname":"Adintiasi",
    "gn:cc2":"GH",
    "gn:country_code":"GH",
    "gn:dem":101,
    "gn:feature_class":"P",
    "gn:feature_code":"PPL",
    "gn:name":"Adintiasi",
    "gn:population":0,
    "gn:timezone":"Africa/Accra",
    "iso:country":"GH",
    "name:und_x_variant":[
        "Adintasi",
        "Adintiasi"
    ],
    "wof:name":"Adintiasi",
    "wof:placetype":"locality"
},
  "geometry": {"coordinates":[-1.23333,5.98333],"type":"Point"}
}