{
  "type": "Feature",
  "properties": {
    "gn:admin1_code":"00",
    "gn:asciiname":"Tili",
    "gn:country_code":"GH",
    "gn:dem":235,
    "gn:feature_class":"P",
    "gn:feature_code":"PPL",
    "gn:name":"Tili",
    "gn:population":0,
    "gn:timezone":"Africa/Accra",
    "iso:country":"GH",
    "name:und_x_variant":[
        "Tili Natinga",
        "Tili"
    ],
    "wof:name":"Tili",
    "wof:placetype":"locality"
},
  "geometry": {"coordinates":[-0.55896,10.88295],"type":"Point"}
}