{
  "type": "Feature",
  "properties": {
    "gn:admin1_code":"00",
    "gn:asciiname":"Janyuni",
    "gn:country_code":"GH",
    "gn:dem":173,
    "gn:feature_class":"P",
    "gn:feature_code":"PPL",
    "gn:name":"Janyuni",
    "gn:population":0,
    "gn:timezone":"Africa/Accra",
    "iso:country":"GH",
    "wof:name":"Janyuni",
    "wof:placetype":"locality"
},
  "geometry": {"coordinates":[0.15,9.98333],"type":"Point"}
}