{
  "type": "Feature",
  "properties": {
    "gn:admin1_code":"00",
    "gn:asciiname":"Wasakuse Wayo",
    "gn:country_code":"GH",
    "gn:dem":5,
    "gn:feature_class":"P",
    "gn:feature_code":"PPL",
    "gn:name":"Wasakuse Wayo",
    "gn:population":0,
    "gn:timezone":"Africa/Accra",
    "iso:country":"GH",
    "name:und_x_variant":[
        "Wasakuse",
        "Wasakusi",
        "Wasakuse Wayo"
    ],
    "wof:name":"Wasakuse Wayo",
    "wof:placetype":"locality"
},
  "geometry": {"coordinates":[0.55411,5.84319],"type":"Point"}
}