{
  "type": "Feature",
  "properties": {
    "gn:admin1_code":"00",
    "gn:asciiname":"Agogbe",
    "gn:country_code":"GH",
    "gn:dem":1,
    "gn:feature_class":"P",
    "gn:feature_code":"PPL",
    "gn:name":"Agogbe",
    "gn:population":0,
    "gn:timezone":"Africa/Accra",
    "iso:country":"GH",
    "wof:name":"Agogbe",
    "wof:placetype":"locality"
},
  "geometry": {"coordinates":[0.54902,5.98132],"type":"Point"}
}