{
  "type": "Feature",
  "properties": {
    "gn:admin1_code":"00",
    "gn:asciiname":"Kobreso",
    "gn:country_code":"GH",
    "gn:dem":254,
    "gn:feature_class":"P",
    "gn:feature_code":"PPL",
    "gn:name":"Kobreso",
    "gn:population":0,
    "gn:timezone":"Africa/Accra",
    "iso:country":"GH",
    "wof:name":"Kobreso",
    "wof:placetype":"locality"
},
  "geometry": {"coordinates":[-1.83871,7.2825],"type":"Point"}
}