{
  "type": "Feature",
  "properties": {
    "gn:admin1_code":"00",
    "gn:asciiname":"Nkwanta",
    "gn:country_code":"GH",
    "gn:dem":48,
    "gn:feature_class":"P",
    "gn:feature_code":"PPL",
    "gn:name":"Nkwanta",
    "gn:population":0,
    "gn:timezone":"Africa/Accra",
    "iso:country":"GH",
    "wof:name":"Nkwanta",
    "wof:placetype":"locality"
},
  "geometry": {"coordinates":[-2.07515,5.25213],"type":"Point"}
}