{
  "type": "Feature",
  "properties": {
    "gn:admin1_code":"00",
    "gn:asciiname":"Soko",
    "gn:country_code":"GH",
    "gn:dem":159,
    "gn:feature_class":"P",
    "gn:feature_code":"PPL",
    "gn:name":"Soko",
    "gn:population":0,
    "gn:timezone":"Africa/Accra",
    "iso:country":"GH",
    "name:bos_x_preferred":[
        "Soko"
    ],
    "name:ceb_x_preferred":[
        "Soko"
    ],
    "name:fra_x_preferred":[
        "Soko"
    ],
    "name:heb_x_preferred":[
        "\u05e1\u05d5\u05e7\u05d5"
    ],
    "name:mlg_x_preferred":[
        "Soko"
    ],
    "name:nld_x_preferred":[
        "Soko"
    ],
    "name:pol_x_preferred":[
        "Soko"
    ],
    "name:spa_x_preferred":[
        "Soko"
    ],
    "name:swe_x_preferred":[
        "Soko"
    ],
    "wof:name":"Soko",
    "wof:placetype":"locality"
},
  "geometry": {"coordinates":[-1.88333,6.31667],"type":"Point"}
}