{
  "type": "Feature",
  "properties": {
    "gn:admin1_code":"00",
    "gn:asciiname":"Bresua",
    "gn:country_code":"GH",
    "gn:dem":376,
    "gn:feature_class":"P",
    "gn:feature_code":"PPL",
    "gn:name":"Bresua",
    "gn:population":0,
    "gn:timezone":"Africa/Accra",
    "iso:country":"GH",
    "wof:name":"Bresua",
    "wof:placetype":"locality"
},
  "geometry": {"coordinates":[-1.43156,7.06808],"type":"Point"}
}