{
  "type": "Feature",
  "properties": {
    "gn:admin1_code":"00",
    "gn:asciiname":"Biakpa",
    "gn:country_code":"GH",
    "gn:dem":508,
    "gn:feature_class":"P",
    "gn:feature_code":"PPL",
    "gn:name":"Biakpa",
    "gn:population":0,
    "gn:timezone":"Africa/Accra",
    "iso:country":"GH",
    "wof:name":"Biakpa",
    "wof:placetype":"locality"
},
  "geometry": {"coordinates":[0.42589,6.82491],"type":"Point"}
}