{
  "type": "Feature",
  "properties": {
    "gn:admin1_code":"00",
    "gn:asciiname":"Obenyemi",
    "gn:country_code":"GH",
    "gn:dem":156,
    "gn:feature_class":"P",
    "gn:feature_code":"PPL",
    "gn:name":"Obenyemi",
    "gn:population":0,
    "gn:timezone":"Africa/Accra",
    "iso:country":"GH",
    "wof:name":"Obenyemi",
    "wof:placetype":"locality"
},
  "geometry": {"coordinates":[-0.07052,6.1501],"type":"Point"}
}