{
  "type": "Feature",
  "properties": {
    "gn:admin1_code":"00",
    "gn:asciiname":"Agwetiabuom",
    "gn:country_code":"GH",
    "gn:dem":69,
    "gn:feature_class":"P",
    "gn:feature_code":"PPL",
    "gn:name":"Agwetiabuom",
    "gn:population":0,
    "gn:timezone":"Africa/Accra",
    "iso:country":"GH",
    "wof:name":"Agwetiabuom",
    "wof:placetype":"locality"
},
  "geometry": {"coordinates":[-1.11667,5.26667],"type":"Point"}
}