{
  "type": "Feature",
  "properties": {
    "gn:admin1_code":"00",
    "gn:asciiname":"Big Ada",
    "gn:country_code":"GH",
    "gn:dem":3,
    "gn:feature_class":"P",
    "gn:feature_code":"PPL",
    "gn:name":"Big Ada",
    "gn:population":0,
    "gn:timezone":"Africa/Accra",
    "iso:country":"GH",
    "name:und_x_variant":[
        "Big Adda",
        "Big Ada"
    ],
    "wof:name":"Big Ada",
    "wof:placetype":"locality"
},
  "geometry": {"coordinates":[0.61428,5.82324],"type":"Point"}
}