{
  "type": "Feature",
  "properties": {
    "gn:admin1_code":"00",
    "gn:asciiname":"Forinsa",
    "gn:country_code":"GH",
    "gn:dem":169,
    "gn:feature_class":"P",
    "gn:feature_code":"PPL",
    "gn:name":"Forinsa",
    "gn:population":0,
    "gn:timezone":"Africa/Accra",
    "iso:country":"GH",
    "name:und_x_variant":[
        "Doninga Farinsa",
        "Forinsa"
    ],
    "wof:name":"Forinsa",
    "wof:placetype":"locality"
},
  "geometry": {"coordinates":[-1.40297,10.61162],"type":"Point"}
}