{
  "type": "Feature",
  "properties": {
    "gn:admin1_code":"00",
    "gn:asciiname":"Kanga",
    "gn:country_code":"GH",
    "gn:dem":189,
    "gn:feature_class":"P",
    "gn:feature_code":"PPL",
    "gn:name":"Kanga",
    "gn:population":0,
    "gn:timezone":"Africa/Accra",
    "iso:country":"GH",
    "wof:name":"Kanga",
    "wof:placetype":"locality"
},
  "geometry": {"coordinates":[-0.93333,10.91667],"type":"Point"}
}