{
  "type": "Feature",
  "properties": {
    "gn:admin1_code":"00",
    "gn:asciiname":"Kanga",
    "gn:country_code":"GH",
    "gn:dem":189,
    "gn:feature_class":"P",
    "gn:feature_code":"PPL",
    "gn:name":"Kanga",
    "gn:population":0,
    "gn:timezone":"Africa/Accra",
    "iso:country":"GH",
    "name:ceb_x_preferred":[
        "Kanga"
    ],
    "name:deu_x_preferred":[
        "Kanga"
    ],
    "name:fra_x_preferred":[
        "Kanga"
    ],
    "name:ita_x_preferred":[
        "Kanga"
    ],
    "name:nld_x_preferred":[
        "Kanga"
    ],
    "name:rus_x_preferred":[
        "\u041a\u0430\u043d\u0433\u0430"
    ],
    "name:swa_x_preferred":[
        "Kanga"
    ],
    "name:swe_x_preferred":[
        "Kanga"
    ],
    "wof:name":"Kanga",
    "wof:placetype":"locality"
},
  "geometry": {"coordinates":[-0.93333,10.91667],"type":"Point"}
}