{
  "type": "Feature",
  "properties": {
    "gn:admin1_code":"00",
    "gn:asciiname":"Bankuda",
    "gn:country_code":"GH",
    "gn:dem":171,
    "gn:feature_class":"P",
    "gn:feature_code":"PPL",
    "gn:name":"Bankuda",
    "gn:population":0,
    "gn:timezone":"Africa/Accra",
    "iso:country":"GH",
    "wof:name":"Bankuda",
    "wof:placetype":"locality"
},
  "geometry": {"coordinates":[-0.69317,10.35434],"type":"Point"}
}