{
  "type": "Feature",
  "properties": {
    "gn:admin1_code":"00",
    "gn:asciiname":"Avergi",
    "gn:country_code":"GH",
    "gn:dem":51,
    "gn:feature_class":"P",
    "gn:feature_code":"PPL",
    "gn:name":"Avergi",
    "gn:population":0,
    "gn:timezone":"Africa/Accra",
    "iso:country":"GH",
    "name:und_x_variant":[
        "Avedje",
        "Avergi"
    ],
    "wof:name":"Avergi",
    "wof:placetype":"locality"
},
  "geometry": {"coordinates":[1.01297,5.97074],"type":"Point"}
}