{
  "type": "Feature",
  "properties": {
    "gn:admin1_code":"06",
    "gn:asciiname":"Singa",
    "gn:country_code":"GH",
    "gn:dem":115,
    "gn:feature_class":"P",
    "gn:feature_code":"PPL",
    "gn:name":"Singa",
    "gn:population":0,
    "gn:timezone":"Africa/Accra",
    "iso:country":"GH",
    "name:ceb_x_preferred":[
        "Singa"
    ],
    "name:deu_x_preferred":[
        "Singa"
    ],
    "name:fra_x_preferred":[
        "Singa"
    ],
    "name:ita_x_preferred":[
        "Singa"
    ],
    "name:new_x_preferred":[
        "\u0938\u093f\u0902\u0917\u093e"
    ],
    "name:nld_x_preferred":[
        "Singa"
    ],
    "name:por_x_preferred":[
        "Singa"
    ],
    "name:swe_x_preferred":[
        "Singa"
    ],
    "wof:name":"Singa",
    "wof:placetype":"locality"
},
  "geometry": {"coordinates":[-1.06244,9.73341],"type":"Point"}
}