{
  "type": "Feature",
  "properties": {
    "gn:admin1_code":"00",
    "gn:asciiname":"Bankame",
    "gn:country_code":"GH",
    "gn:dem":199,
    "gn:feature_class":"P",
    "gn:feature_code":"PPL",
    "gn:name":"Bankame",
    "gn:population":0,
    "gn:timezone":"Africa/Accra",
    "iso:country":"GH",
    "wof:name":"Bankame",
    "wof:placetype":"locality"
},
  "geometry": {"coordinates":[-1.22483,6.45409],"type":"Point"}
}