{
  "type": "Feature",
  "properties": {
    "gn:admin1_code":"00",
    "gn:asciiname":"Kpale",
    "gn:country_code":"GH",
    "gn:dem":209,
    "gn:feature_class":"P",
    "gn:feature_code":"PPL",
    "gn:name":"Kpale",
    "gn:population":0,
    "gn:timezone":"Africa/Accra",
    "iso:country":"GH",
    "wof:name":"Kpale",
    "wof:placetype":"locality"
},
  "geometry": {"coordinates":[0.36147,6.70041],"type":"Point"}
}