{
  "type": "Feature",
  "properties": {
    "gn:admin1_code":"00",
    "gn:asciiname":"Koklokome",
    "gn:country_code":"GH",
    "gn:dem":45,
    "gn:feature_class":"P",
    "gn:feature_code":"PPL",
    "gn:name":"Koklokome",
    "gn:population":0,
    "gn:timezone":"Africa/Accra",
    "iso:country":"GH",
    "wof:name":"Koklokome",
    "wof:placetype":"locality"
},
  "geometry": {"coordinates":[0.26667,6.25],"type":"Point"}
}