{
  "type": "Feature",
  "properties": {
    "gn:admin1_code":"00",
    "gn:asciiname":"Agu",
    "gn:country_code":"GH",
    "gn:dem":154,
    "gn:feature_class":"P",
    "gn:feature_code":"PPL",
    "gn:name":"Agu",
    "gn:population":0,
    "gn:timezone":"Africa/Accra",
    "iso:country":"GH",
    "wof:name":"Agu",
    "wof:placetype":"locality"
},
  "geometry": {"coordinates":[0.16703,6.45239],"type":"Point"}
}