{
  "type": "Feature",
  "properties": {
    "gn:admin1_code":"00",
    "gn:asciiname":"Banda Nkwanta",
    "gn:country_code":"GH",
    "gn:dem":214,
    "gn:feature_class":"P",
    "gn:feature_code":"PPL",
    "gn:name":"Banda Nkwanta",
    "gn:population":0,
    "gn:timezone":"Africa/Accra",
    "iso:country":"GH",
    "wof:name":"Banda Nkwanta",
    "wof:placetype":"locality"
},
  "geometry": {"coordinates":[-2.13673,8.35092],"type":"Point"}
}