{
  "type": "Feature",
  "properties": {
    "gn:admin1_code":"00",
    "gn:asciiname":"Etibedu",
    "gn:country_code":"GH",
    "gn:dem":34,
    "gn:feature_class":"P",
    "gn:feature_code":"PPL",
    "gn:name":"Etibedu",
    "gn:population":0,
    "gn:timezone":"Africa/Accra",
    "iso:country":"GH",
    "name:und_x_variant":[
        "Etsibado",
        "Etibedu"
    ],
    "wof:name":"Etibedu",
    "wof:placetype":"locality"
},
  "geometry": {"coordinates":[-0.83002,5.23593],"type":"Point"}
}