{
  "type": "Feature",
  "properties": {
    "gn:admin1_code":"00",
    "gn:asciiname":"Nakago",
    "gn:country_code":"GH",
    "gn:dem":129,
    "gn:feature_class":"P",
    "gn:feature_code":"PPL",
    "gn:name":"Nakago",
    "gn:population":0,
    "gn:timezone":"Africa/Accra",
    "iso:country":"GH",
    "name:und_x_variant":[
        "Nakaku",
        "Nakago"
    ],
    "wof:name":"Nakago",
    "wof:placetype":"locality"
},
  "geometry": {"coordinates":[0.34549,10.02826],"type":"Point"}
}