{
  "type": "Feature",
  "properties": {
    "gn:admin1_code":"02",
    "gn:asciiname":"Amoaful",
    "gn:country_code":"GH",
    "gn:dem":233,
    "gn:feature_class":"P",
    "gn:feature_code":"PPL",
    "gn:name":"Amoaful",
    "gn:population":0,
    "gn:timezone":"Africa/Accra",
    "iso:country":"GH",
    "name:und_x_variant":[
        "Amoafo"
    ],
    "wof:name":"Amoaful",
    "wof:placetype":"locality"
},
  "geometry": {"coordinates":[-1.56406,6.44943],"type":"Point"}
}