{
  "type": "Feature",
  "properties": {
    "gn:admin1_code":"00",
    "gn:asciiname":"Okwenya",
    "gn:country_code":"GH",
    "gn:dem":21,
    "gn:feature_class":"P",
    "gn:feature_code":"PPL",
    "gn:name":"Okwenya",
    "gn:population":0,
    "gn:timezone":"Africa/Accra",
    "iso:country":"GH",
    "wof:name":"Okwenya",
    "wof:placetype":"locality"
},
  "geometry": {"coordinates":[0.05434,6.12913],"type":"Point"}
}