{
  "type": "Feature",
  "properties": {
    "gn:admin1_code":"00",
    "gn:asciiname":"Adusukofe",
    "gn:country_code":"GH",
    "gn:dem":23,
    "gn:feature_class":"P",
    "gn:feature_code":"PPL",
    "gn:name":"Adusukofe",
    "gn:population":0,
    "gn:timezone":"Africa/Accra",
    "iso:country":"GH",
    "name:und_x_variant":[
        "Adusukorpe",
        "Adusukofe"
    ],
    "wof:name":"Adusukofe",
    "wof:placetype":"locality"
},
  "geometry": {"coordinates":[0.68872,6.037],"type":"Point"}
}