{
  "type": "Feature",
  "properties": {
    "gn:admin1_code":"00",
    "gn:asciiname":"Kandem",
    "gn:country_code":"GH",
    "gn:dem":204,
    "gn:feature_class":"P",
    "gn:feature_code":"PPL",
    "gn:name":"Kandem",
    "gn:population":0,
    "gn:timezone":"Africa/Accra",
    "iso:country":"GH",
    "name:und_x_variant":[
        "Sandema Kandem",
        "Kandem"
    ],
    "wof:name":"Kandem",
    "wof:placetype":"locality"
},
  "geometry": {"coordinates":[-1.33785,10.74323],"type":"Point"}
}