{
  "type": "Feature",
  "properties": {
    "gn:admin1_code":"00",
    "gn:asciiname":"Ajum",
    "gn:cc2":"GH",
    "gn:country_code":"GH",
    "gn:dem":104,
    "gn:feature_class":"P",
    "gn:feature_code":"PPL",
    "gn:name":"Ajum",
    "gn:population":0,
    "gn:timezone":"Africa/Accra",
    "iso:country":"GH",
    "name:und_x_variant":[
        "Ajum Menu",
        "Adwum",
        "Ajum"
    ],
    "wof:name":"Ajum",
    "wof:placetype":"locality"
},
  "geometry": {"coordinates":[-2.65,5.68333],"type":"Point"}
}