{
  "type": "Feature",
  "properties": {
    "gn:admin1_code":"02",
    "gn:asciiname":"Baso",
    "gn:country_code":"GH",
    "gn:dem":252,
    "gn:feature_class":"P",
    "gn:feature_code":"PPL",
    "gn:name":"Baso",
    "gn:population":0,
    "gn:timezone":"Africa/Accra",
    "iso:country":"GH",
    "name:eng_x_preferred":[
        "Baso"
    ],
    "wof:name":"Baso",
    "wof:placetype":"locality"
},
  "geometry": {"coordinates":[-1.81998,6.93765],"type":"Point"}
}