{
  "type": "Feature",
  "properties": {
    "gn:admin1_code":"00",
    "gn:asciiname":"Asuboni Station",
    "gn:country_code":"GH",
    "gn:dem":204,
    "gn:feature_class":"P",
    "gn:feature_code":"PPL",
    "gn:name":"Asuboni Station",
    "gn:population":0,
    "gn:timezone":"Africa/Accra",
    "iso:country":"GH",
    "name:und_x_variant":[
        "Asubone Station",
        "Asuboni",
        "Asuboni Station"
    ],
    "wof:name":"Asuboni Station",
    "wof:placetype":"locality"
},
  "geometry": {"coordinates":[-0.72936,6.4719],"type":"Point"}
}