{
  "type": "Feature",
  "properties": {
    "gn:admin1_code":"00",
    "gn:asciiname":"Banso",
    "gn:country_code":"GH",
    "gn:dem":251,
    "gn:feature_class":"P",
    "gn:feature_code":"PPL",
    "gn:name":"Banso",
    "gn:population":0,
    "gn:timezone":"Africa/Accra",
    "iso:country":"GH",
    "wof:name":"Banso",
    "wof:placetype":"locality"
},
  "geometry": {"coordinates":[-1.19841,6.47378],"type":"Point"}
}