{
  "type": "Feature",
  "properties": {
    "gn:admin1_code":"06",
    "gn:asciiname":"Bunkpurugu",
    "gn:cc2":"GH",
    "gn:country_code":"GH",
    "gn:dem":229,
    "gn:feature_class":"P",
    "gn:feature_code":"PPL",
    "gn:name":"Bunkpurugu",
    "gn:population":0,
    "gn:timezone":"Africa/Accra",
    "iso:country":"GH",
    "name:swe_x_preferred":[
        "Bunkpurugu"
    ],
    "name:und_x_variant":[
        "Gbankurugu",
        "Bunkpurk"
    ],
    "wof:name":"Bunkpurugu",
    "wof:placetype":"locality"
},
  "geometry": {"coordinates":[0.09639,10.51917],"type":"Point"}
}