{
  "type": "Feature",
  "properties": {
    "gn:admin1_code":"03",
    "gn:asciiname":"Domaa-Ahenkro",
    "gn:country_code":"GH",
    "gn:dem":276,
    "gn:feature_class":"P",
    "gn:feature_code":"PPL",
    "gn:name":"Domaa-Ahenkro",
    "gn:population":0,
    "gn:timezone":"Africa/Accra",
    "iso:country":"GH",
    "name:aka_x_preferred":[
        "Domaa Ahenkro"
    ],
    "name:ceb_x_preferred":[
        "Dormaa"
    ],
    "name:deu_x_preferred":[
        "Dormaa Ahenkro"
    ],
    "name:eng_x_preferred":[
        "Dormaa-Ahenkro"
    ],
    "name:eng_x_variant":[
        "Domaa-Ahenkro"
    ],
    "name:por_x_preferred":[
        "Dormaa"
    ],
    "name:spa_x_preferred":[
        "Dormaa Ahenkro"
    ],
    "name:swe_x_preferred":[
        "Dormaa Ahenkro"
    ],
    "name:und_x_variant":[
        "Ahinkrom",
        "Pamu"
    ],
    "name:zho_x_preferred":[
        "\u591a\u99ac\u963f\u4ea8\u514b\u7f85"
    ],
    "wof:name":"Domaa-Ahenkro",
    "wof:placetype":"locality"
},
  "geometry": {"coordinates":[-2.87348,7.27386],"type":"Point"}
}