{
  "type": "Feature",
  "properties": {
    "gn:admin1_code":"02",
    "gn:asciiname":"Hiamenkwa",
    "gn:country_code":"GH",
    "gn:dem":244,
    "gn:feature_class":"P",
    "gn:feature_code":"PPL",
    "gn:name":"Hiamenkwa",
    "gn:population":0,
    "gn:timezone":"Africa/Accra",
    "iso:country":"GH",
    "name:eng_x_preferred":[
        "Hiamenkwa"
    ],
    "wof:name":"Hiamenkwa",
    "wof:placetype":"locality"
},
  "geometry": {"coordinates":[-1.80227,6.89465],"type":"Point"}
}