{
  "type": "Feature",
  "properties": {
    "gn:admin1_code":"00",
    "gn:asciiname":"Opesika",
    "gn:country_code":"GH",
    "gn:dem":326,
    "gn:feature_class":"P",
    "gn:feature_code":"PPL",
    "gn:name":"Opesika",
    "gn:population":0,
    "gn:timezone":"Africa/Accra",
    "iso:country":"GH",
    "wof:name":"Opesika",
    "wof:placetype":"locality"
},
  "geometry": {"coordinates":[-0.24451,6.21974],"type":"Point"}
}