{
  "type": "Feature",
  "properties": {
    "gn:admin1_code":"00",
    "gn:asciiname":"Iyecheri",
    "gn:country_code":"GH",
    "gn:dem":150,
    "gn:feature_class":"P",
    "gn:feature_code":"PPL",
    "gn:name":"Iyecheri",
    "gn:population":0,
    "gn:timezone":"Africa/Accra",
    "iso:country":"GH",
    "name:und_x_variant":[
        "Achiachiga",
        "Ekyinkyie",
        "Iyecheri"
    ],
    "wof:name":"Iyecheri",
    "wof:placetype":"locality"
},
  "geometry": {"coordinates":[-2.67003,6.35177],"type":"Point"}
}