{
  "type": "Feature",
  "properties": {
    "gn:admin1_code":"00",
    "gn:asciiname":"Ochereso",
    "gn:country_code":"GH",
    "gn:dem":122,
    "gn:feature_class":"P",
    "gn:feature_code":"PPL",
    "gn:name":"Ochereso",
    "gn:population":0,
    "gn:timezone":"Africa/Accra",
    "iso:country":"GH",
    "name:und_x_variant":[
        "Otwereso",
        "Ochereso"
    ],
    "wof:name":"Ochereso",
    "wof:placetype":"locality"
},
  "geometry": {"coordinates":[-1.14247,6.0143],"type":"Point"}
}