{
  "type": "Feature",
  "properties": {
    "gn:admin1_code":"00",
    "gn:asciiname":"Tenkpanga",
    "gn:country_code":"GH",
    "gn:dem":167,
    "gn:feature_class":"P",
    "gn:feature_code":"PPL",
    "gn:name":"Tenkpanga",
    "gn:population":0,
    "gn:timezone":"Africa/Accra",
    "iso:country":"GH",
    "name:und_x_variant":[
        "Tengpongo",
        "Tenkpanga"
    ],
    "wof:name":"Tenkpanga",
    "wof:placetype":"locality"
},
  "geometry": {"coordinates":[-0.75067,10.42427],"type":"Point"}
}