{
  "type": "Feature",
  "properties": {
    "gn:admin1_code":"00",
    "gn:asciiname":"Chere",
    "gn:country_code":"GH",
    "gn:dem":162,
    "gn:feature_class":"P",
    "gn:feature_code":"PPL",
    "gn:name":"Chere",
    "gn:population":0,
    "gn:timezone":"Africa/Accra",
    "iso:country":"GH",
    "name:und_x_variant":[
        "Tiere",
        "Chere"
    ],
    "wof:name":"Chere",
    "wof:placetype":"locality"
},
  "geometry": {"coordinates":[0.28705,10.27732],"type":"Point"}
}