{
  "type": "Feature",
  "properties": {
    "gn:admin1_code":"00",
    "gn:asciiname":"Amoana",
    "gn:country_code":"GH",
    "gn:dem":18,
    "gn:feature_class":"P",
    "gn:feature_code":"PPL",
    "gn:name":"Amoana",
    "gn:population":0,
    "gn:timezone":"Africa/Accra",
    "iso:country":"GH",
    "wof:name":"Amoana",
    "wof:placetype":"locality"
},
  "geometry": {"coordinates":[-1.35819,5.1345],"type":"Point"}
}