{
  "type": "Feature",
  "properties": {
    "gn:admin1_code":"00",
    "gn:asciiname":"Vitin",
    "gn:country_code":"GH",
    "gn:dem":158,
    "gn:feature_class":"P",
    "gn:feature_code":"PPL",
    "gn:name":"Vitin",
    "gn:population":0,
    "gn:timezone":"Africa/Accra",
    "iso:country":"GH",
    "name:und_x_variant":[
        "Viteng",
        "Vitin"
    ],
    "wof:name":"Vitin",
    "wof:placetype":"locality"
},
  "geometry": {"coordinates":[-0.80184,9.38108],"type":"Point"}
}