{
  "type": "Feature",
  "properties": {
    "gn:admin1_code":"00",
    "gn:asciiname":"Nenkogo",
    "gn:country_code":"GH",
    "gn:dem":226,
    "gn:feature_class":"P",
    "gn:feature_code":"PPL",
    "gn:name":"Nenkogo",
    "gn:population":0,
    "gn:timezone":"Africa/Accra",
    "iso:country":"GH",
    "name:und_x_variant":[
        "Nkawgo",
        "Nenkogo"
    ],
    "wof:name":"Nenkogo",
    "wof:placetype":"locality"
},
  "geometry": {"coordinates":[-0.17542,11.0816],"type":"Point"}
}