{
  "type": "Feature",
  "properties": {
    "gn:admin1_code":"00",
    "gn:asciiname":"Yede",
    "gn:country_code":"GH",
    "gn:dem":361,
    "gn:feature_class":"P",
    "gn:feature_code":"PPL",
    "gn:name":"Yede",
    "gn:population":0,
    "gn:timezone":"Africa/Accra",
    "iso:country":"GH",
    "wof:name":"Yede",
    "wof:placetype":"locality"
},
  "geometry": {"coordinates":[0.03333,6.23333],"type":"Point"}
}