{
  "type": "Feature",
  "properties": {
    "gn:admin1_code":"02",
    "gn:asciiname":"Yabi",
    "gn:country_code":"GH",
    "gn:dem":256,
    "gn:feature_class":"P",
    "gn:feature_code":"PPL",
    "gn:name":"Yabi",
    "gn:population":0,
    "gn:timezone":"Africa/Accra",
    "iso:country":"GH",
    "name:und_x_variant":[
        "Yabe",
        "Yabi"
    ],
    "wof:name":"Yabi",
    "wof:placetype":"locality"
},
  "geometry": {"coordinates":[-1.70875,6.65055],"type":"Point"}
}