{
  "type": "Feature",
  "properties": {
    "gn:admin1_code":"00",
    "gn:asciiname":"Nkuben",
    "gn:country_code":"GH",
    "gn:dem":109,
    "gn:feature_class":"P",
    "gn:feature_code":"PPL",
    "gn:name":"Nkuben",
    "gn:population":0,
    "gn:timezone":"Africa/Accra",
    "iso:country":"GH",
    "wof:name":"Nkuben",
    "wof:placetype":"locality"
},
  "geometry": {"coordinates":[-1.15261,5.59304],"type":"Point"}
}