{
  "type": "Feature",
  "properties": {
    "gn:admin1_code":"00",
    "gn:asciiname":"Yapala",
    "gn:country_code":"GH",
    "gn:dem":166,
    "gn:feature_class":"P",
    "gn:feature_code":"PPL",
    "gn:name":"Yapala",
    "gn:population":0,
    "gn:timezone":"Africa/Accra",
    "iso:country":"GH",
    "name:und_x_variant":[
        "Japala",
        "Yakpalla",
        "Yapala"
    ],
    "wof:name":"Yapala",
    "wof:placetype":"locality"
},
  "geometry": {"coordinates":[-0.18074,9.05569],"type":"Point"}
}