{
  "type": "Feature",
  "properties": {
    "gn:admin1_code":"00",
    "gn:asciiname":"Awiaso",
    "gn:country_code":"GH",
    "gn:dem":263,
    "gn:feature_class":"P",
    "gn:feature_code":"PPL",
    "gn:name":"Awiaso",
    "gn:population":0,
    "gn:timezone":"Africa/Accra",
    "iso:country":"GH",
    "wof:name":"Awiaso",
    "wof:placetype":"locality"
},
  "geometry": {"coordinates":[0.51577,6.76851],"type":"Point"}
}