{
  "type": "Feature",
  "properties": {
    "gn:country":"GH",
    "gn:fcode":"PPL",
    "gn:pop":44227,
    "iso:country":"GH",
    "name:aka_x_preferred":[
        "Oduponkpehe"
    ],
    "name:deu_x_preferred":[
        "Oduponkpehe"
    ],
    "name:eng_x_preferred":[
        "Kasoa"
    ],
    "name:jpn_x_preferred":[
        "\u30aa\u30c9\u30a5\u30dd\u30f3\u30af\u30da\u30d8"
    ],
    "name:nld_x_preferred":[
        "Oduponkpehe"
    ],
    "name:pol_x_preferred":[
        "Oduponkpehe"
    ],
    "name:swe_x_preferred":[
        "Kasoa"
    ],
    "name:unk_x_variant":[
        "Oduponkpehe"
    ],
    "name:urd_x_preferred":[
        "\u06a9\u0627\u0633\u0648\u0627"
    ],
    "qs:name":"Kasoa",
    "qs:photos_9r":0,
    "qs:photos_sr":0,
    "qs:pop_sr":"7",
    "wd:wordcount":2673,
    "wof:name":"Kasoa",
    "wof:placetype":"locality",
    "wof:population":44227
},
  "geometry": {"coordinates":[-0.41679,5.53449],"type":"Point"}
}