{
  "type": "Feature",
  "properties": {
    "gn:admin1_code":"00",
    "gn:asciiname":"Tanoso",
    "gn:country_code":"GH",
    "gn:dem":149,
    "gn:feature_class":"P",
    "gn:feature_code":"PPL",
    "gn:name":"Tanoso",
    "gn:population":0,
    "gn:timezone":"Africa/Accra",
    "iso:country":"GH",
    "wof:name":"Tanoso",
    "wof:placetype":"locality"
},
  "geometry": {"coordinates":[-2.25943,6.33441],"type":"Point"}
}