{
  "type": "Feature",
  "properties": {
    "gn:admin1_code":"09",
    "gn:asciiname":"Ntamakrom",
    "gn:country_code":"GH",
    "gn:dem":52,
    "gn:feature_class":"P",
    "gn:feature_code":"PPL",
    "gn:name":"Ntamakrom",
    "gn:population":0,
    "gn:timezone":"Africa/Accra",
    "iso:country":"GH",
    "name:eng_x_preferred":[
        "Ntamakrom"
    ],
    "wof:name":"Ntamakrom",
    "wof:placetype":"locality"
},
  "geometry": {"coordinates":[-1.73632,5.02876],"type":"Point"}
}