{
  "type": "Feature",
  "properties": {
    "gn:admin1_code":"00",
    "gn:asciiname":"Janania",
    "gn:country_code":"GH",
    "gn:dem":200,
    "gn:feature_class":"P",
    "gn:feature_code":"PPL",
    "gn:name":"Janania",
    "gn:population":0,
    "gn:timezone":"Africa/Accra",
    "iso:country":"GH",
    "wof:name":"Janania",
    "wof:placetype":"locality"
},
  "geometry": {"coordinates":[-1.06217,10.84821],"type":"Point"}
}