{
  "type": "Feature",
  "properties": {
    "gn:admin1_code":"00",
    "gn:asciiname":"Kpakalga",
    "gn:country_code":"GH",
    "gn:dem":190,
    "gn:feature_class":"P",
    "gn:feature_code":"PPL",
    "gn:name":"Kpakalga",
    "gn:population":0,
    "gn:timezone":"Africa/Accra",
    "iso:country":"GH",
    "wof:name":"Kpakalga",
    "wof:placetype":"locality"
},
  "geometry": {"coordinates":[-0.10297,10.15729],"type":"Point"}
}