{
  "type": "Feature",
  "properties": {
    "gn:admin1_code":"00",
    "gn:asciiname":"Jasikan",
    "gn:country_code":"GH",
    "gn:dem":174,
    "gn:feature_class":"P",
    "gn:feature_code":"PPL",
    "gn:name":"Jasikan",
    "gn:population":0,
    "gn:timezone":"Africa/Accra",
    "iso:country":"GH",
    "name:swe_x_preferred":[
        "Jasikan"
    ],
    "name:und_x_variant":[
        "Gyasekan",
        "Gj\u00e1sekan",
        "Gjasekang",
        "Gyasikan"
    ],
    "name:urd_x_preferred":[
        "\u062c\u0633\u06a9\u0627\u0646"
    ],
    "wof:name":"Jasikan",
    "wof:placetype":"locality"
},
  "geometry": {"coordinates":[0.46771,7.40941],"type":"Point"}
}