{
  "type": "Feature",
  "properties": {
    "gn:admin1_code":"00",
    "gn:asciiname":"Sagaduguwira",
    "gn:country_code":"GH",
    "gn:dem":189,
    "gn:feature_class":"P",
    "gn:feature_code":"PPL",
    "gn:name":"Sagaduguwira",
    "gn:population":0,
    "gn:timezone":"Africa/Accra",
    "iso:country":"GH",
    "name:und_x_variant":[
        "Takorayiri",
        "Sagaduguwira"
    ],
    "wof:name":"Sagaduguwira",
    "wof:placetype":"locality"
},
  "geometry": {"coordinates":[-0.65102,10.35787],"type":"Point"}
}