{
  "type": "Feature",
  "properties": {
    "gn:admin1_code":"00",
    "gn:asciiname":"Yeliwoko",
    "gn:country_code":"GH",
    "gn:dem":209,
    "gn:feature_class":"P",
    "gn:feature_code":"PPL",
    "gn:name":"Yeliwoko",
    "gn:population":0,
    "gn:timezone":"Africa/Accra",
    "iso:country":"GH",
    "wof:name":"Yeliwoko",
    "wof:placetype":"locality"
},
  "geometry": {"coordinates":[-0.49277,10.85791],"type":"Point"}
}