{
  "type": "Feature",
  "properties": {
    "gn:admin1_code":"00",
    "gn:asciiname":"Bellu",
    "gn:country_code":"GH",
    "gn:dem":273,
    "gn:feature_class":"P",
    "gn:feature_code":"PPL",
    "gn:name":"Bellu",
    "gn:population":0,
    "gn:timezone":"Africa/Accra",
    "iso:country":"GH",
    "name:deu_x_preferred":[
        "Bellu"
    ],
    "name:fra_x_preferred":[
        "Bellu"
    ],
    "name:ron_x_preferred":[
        "Bellu"
    ],
    "name:rus_x_preferred":[
        "\u0411\u0435\u043b\u043b\u0443"
    ],
    "name:ukr_x_preferred":[
        "\u0411\u0435\u043b\u043b\u0443"
    ],
    "name:und_x_variant":[
        "Bullu",
        "Bellu"
    ],
    "wof:name":"Bellu",
    "wof:placetype":"locality"
},
  "geometry": {"coordinates":[-2.28082,10.86876],"type":"Point"}
}