{
  "type": "Feature",
  "properties": {
    "gn:admin1_code":"02",
    "gn:asciiname":"Boni",
    "gn:country_code":"GH",
    "gn:dem":217,
    "gn:feature_class":"P",
    "gn:feature_code":"PPL",
    "gn:name":"Boni",
    "gn:population":0,
    "gn:timezone":"Africa/Accra",
    "iso:country":"GH",
    "name:ceb_x_preferred":[
        "Boni"
    ],
    "name:deu_x_preferred":[
        "Boni"
    ],
    "name:eng_x_preferred":[
        "Boni"
    ],
    "name:eng_x_variant":[
        "Bonne"
    ],
    "name:fas_x_preferred":[
        "\u0628\u0648\u0646\u06cc"
    ],
    "name:fra_x_preferred":[
        "Boni"
    ],
    "name:ita_x_preferred":[
        "Boni"
    ],
    "name:nld_x_preferred":[
        "Boni"
    ],
    "name:pol_x_preferred":[
        "Boni"
    ],
    "name:por_x_preferred":[
        "Boni"
    ],
    "name:rus_x_preferred":[
        "\u0411\u043e\u043d\u0438"
    ],
    "name:srp_x_preferred":[
        "\u0411\u043e\u043d\u0438"
    ],
    "name:swe_x_preferred":[
        "Boni"
    ],
    "wof:name":"Boni",
    "wof:placetype":"locality"
},
  "geometry": {"coordinates":[-1.65646,6.45517],"type":"Point"}
}