{
  "type": "Feature",
  "properties": {
    "gn:admin1_code":"00",
    "gn:asciiname":"Apilga",
    "gn:country_code":"GH",
    "gn:dem":190,
    "gn:feature_class":"P",
    "gn:feature_code":"PPL",
    "gn:name":"Apilga",
    "gn:population":0,
    "gn:timezone":"Africa/Accra",
    "iso:country":"GH",
    "name:und_x_variant":[
        "Sherigu Apilgo",
        "Apilga"
    ],
    "wof:name":"Apilga",
    "wof:placetype":"locality"
},
  "geometry": {"coordinates":[-0.89142,10.75361],"type":"Point"}
}