{
  "type": "Feature",
  "properties": {
    "gn:admin1_code":"00",
    "gn:asciiname":"Dzita",
    "gn:country_code":"GH",
    "gn:dem":5,
    "gn:feature_class":"P",
    "gn:feature_code":"PPL",
    "gn:name":"Dzita",
    "gn:population":0,
    "gn:timezone":"Africa/Accra",
    "iso:country":"GH",
    "name:und_x_variant":[
        "Jita",
        "Dzita"
    ],
    "wof:name":"Dzita",
    "wof:placetype":"locality"
},
  "geometry": {"coordinates":[0.7532,5.77954],"type":"Point"}
}