{
  "type": "Feature",
  "properties": {
    "gn:admin1_code":"03",
    "gn:asciiname":"Krakrom",
    "gn:country_code":"GH",
    "gn:dem":226,
    "gn:feature_class":"P",
    "gn:feature_code":"PPL",
    "gn:name":"Krakrom",
    "gn:population":0,
    "gn:timezone":"Africa/Accra",
    "iso:country":"GH",
    "name:eng_x_preferred":[
        "Krakrom"
    ],
    "name:eng_x_variant":[
        "Okirakrom"
    ],
    "wof:name":"Krakrom",
    "wof:placetype":"locality"
},
  "geometry": {"coordinates":[-3.03752,6.95743],"type":"Point"}
}