{
  "type": "Feature",
  "properties": {
    "gn:admin1_code":"09",
    "gn:asciiname":"Amankrom",
    "gn:country_code":"GH",
    "gn:dem":75,
    "gn:feature_class":"P",
    "gn:feature_code":"PPL",
    "gn:name":"Amankrom",
    "gn:population":0,
    "gn:timezone":"Africa/Accra",
    "iso:country":"GH",
    "name:eng_x_preferred":[
        "Amankrom"
    ],
    "wof:name":"Amankrom",
    "wof:placetype":"locality"
},
  "geometry": {"coordinates":[-1.94338,5.39807],"type":"Point"}
}