{
  "type": "Feature",
  "properties": {
    "gn:admin1_code":"09",
    "gn:asciiname":"Kahinibuoso",
    "gn:country_code":"GH",
    "gn:dem":77,
    "gn:feature_class":"P",
    "gn:feature_code":"PPL",
    "gn:name":"Kahinibuoso",
    "gn:population":0,
    "gn:timezone":"Africa/Accra",
    "iso:country":"GH",
    "name:eng_x_preferred":[
        "Kahinibuoso"
    ],
    "wof:name":"Kahinibuoso",
    "wof:placetype":"locality"
},
  "geometry": {"coordinates":[-1.71792,5.17913],"type":"Point"}
}