{
  "type": "Feature",
  "properties": {
    "gn:admin1_code":"00",
    "gn:asciiname":"Todome",
    "gn:country_code":"GH",
    "gn:dem":348,
    "gn:feature_class":"P",
    "gn:feature_code":"PPL",
    "gn:name":"Todome",
    "gn:population":0,
    "gn:timezone":"Africa/Accra",
    "iso:country":"GH",
    "wof:name":"Todome",
    "wof:placetype":"locality"
},
  "geometry": {"coordinates":[0.25,6.78333],"type":"Point"}
}