{
  "type": "Feature",
  "properties": {
    "gn:country":"GH",
    "gn:fcode":"PPL",
    "gn:population":44645,
    "iso:country":"GH",
    "name:aka_x_preferred":[
        "Gbawe"
    ],
    "name:ceb_x_preferred":[
        "Gbawe"
    ],
    "name:deu_x_preferred":[
        "Gbawe"
    ],
    "name:eng_x_preferred":[
        "Gbawe"
    ],
    "name:fra_x_preferred":[
        "Gbawe"
    ],
    "name:gpe_x_preferred":[
        "Gbawe"
    ],
    "name:hau_x_preferred":[
        "Gbawe"
    ],
    "name:ita_x_preferred":[
        "Gbawe"
    ],
    "name:jpn_x_preferred":[
        "\u30b0\u30d0\u30a6\u30a7"
    ],
    "name:nld_x_preferred":[
        "Gbawe"
    ],
    "name:pol_x_preferred":[
        "Gbawe"
    ],
    "name:spa_x_preferred":[
        "Gbawe"
    ],
    "name:swa_x_preferred":[
        "Gbawe"
    ],
    "name:swe_x_preferred":[
        "Gbawe"
    ],
    "name:urd_x_preferred":[
        "\u06af\u0628\u0627\u0648\u06d2"
    ],
    "name:yor_x_preferred":[
        "Gbawe"
    ],
    "qs_pg:aaroncc":"GH",
    "qs_pg:gn_country":"GH",
    "qs_pg:gn_fcode":"PPL",
    "qs_pg:gn_pop":44645,
    "qs_pg:name":"Gbawe",
    "qs_pg:photos_9r":0,
    "qs_pg:photos_sr":0,
    "qs_pg:pop_sr":7,
    "qs_pg:qs_pg_placetype":"locality",
    "wof:name":"Gbawe",
    "wof:placetype":"locality",
    "wof:population":44645
},
  "geometry": {"coordinates":[-0.31035,5.57714],"type":"Point"}
}