{
  "type": "Feature",
  "properties": {
    "gn:admin1_code":"00",
    "gn:asciiname":"Nakoli",
    "gn:country_code":"GH",
    "gn:dem":243,
    "gn:feature_class":"P",
    "gn:feature_code":"PPL",
    "gn:name":"Nakoli",
    "gn:population":0,
    "gn:timezone":"Africa/Accra",
    "iso:country":"GH",
    "wof:name":"Nakoli",
    "wof:placetype":"locality"
},
  "geometry": {"coordinates":[-0.09782,10.03068],"type":"Point"}
}