{
  "type": "Feature",
  "properties": {
    "gn:admin1_code":"00",
    "gn:asciiname":"Botugu",
    "gn:country_code":"GH",
    "gn:dem":115,
    "gn:feature_class":"P",
    "gn:feature_code":"PPL",
    "gn:name":"Botugu",
    "gn:population":0,
    "gn:timezone":"Africa/Accra",
    "iso:country":"GH",
    "name:und_x_variant":[
        "Botugo",
        "Butugu",
        "Botugu"
    ],
    "wof:name":"Botugu",
    "wof:placetype":"locality"
},
  "geometry": {"coordinates":[-0.42514,8.60729],"type":"Point"}
}