{
  "type": "Feature",
  "properties": {
    "gn:admin1_code":"00",
    "gn:asciiname":"Sabiyi",
    "gn:country_code":"GH",
    "gn:dem":204,
    "gn:feature_class":"P",
    "gn:feature_code":"PPL",
    "gn:name":"Sabiyi",
    "gn:population":0,
    "gn:timezone":"Africa/Accra",
    "iso:country":"GH",
    "name:und_x_variant":[
        "Sabiya",
        "Sabiyi"
    ],
    "wof:name":"Sabiyi",
    "wof:placetype":"locality"
},
  "geometry": {"coordinates":[-2.3523,8.07426],"type":"Point"}
}