{
  "type": "Feature",
  "properties": {
    "gn:admin1_code":"00",
    "gn:asciiname":"Kantankufri",
    "gn:country_code":"GH",
    "gn:dem":118,
    "gn:feature_class":"P",
    "gn:feature_code":"PPL",
    "gn:name":"Kantankufri",
    "gn:population":0,
    "gn:timezone":"Africa/Accra",
    "iso:country":"GH",
    "wof:name":"Kantankufri",
    "wof:placetype":"locality"
},
  "geometry": {"coordinates":[-0.03725,7.80775],"type":"Point"}
}