{
  "type": "Feature",
  "properties": {
    "gn:admin1_code":"00",
    "gn:asciiname":"Jelekologo",
    "gn:country_code":"GH",
    "gn:dem":213,
    "gn:feature_class":"P",
    "gn:feature_code":"PPL",
    "gn:name":"Jelekologo",
    "gn:population":0,
    "gn:timezone":"Africa/Accra",
    "iso:country":"GH",
    "name:und_x_variant":[
        "Gyelakologo",
        "Jelekologo"
    ],
    "wof:name":"Jelekologo",
    "wof:placetype":"locality"
},
  "geometry": {"coordinates":[-0.1416,10.87777],"type":"Point"}
}