{
  "type": "Feature",
  "properties": {
    "gn:admin1_code":"00",
    "gn:asciiname":"Numa",
    "gn:country_code":"GH",
    "gn:dem":81,
    "gn:feature_class":"P",
    "gn:feature_code":"PPL",
    "gn:name":"Numa",
    "gn:population":0,
    "gn:timezone":"Africa/Accra",
    "iso:country":"GH",
    "name:ceb_x_preferred":[
        "Numa"
    ],
    "name:deu_x_preferred":[
        "Numa"
    ],
    "name:fra_x_preferred":[
        "Numa"
    ],
    "name:ita_x_preferred":[
        "Numa"
    ],
    "name:por_x_preferred":[
        "Numa"
    ],
    "name:swe_x_preferred":[
        "Numa"
    ],
    "wof:name":"Numa",
    "wof:placetype":"locality"
},
  "geometry": {"coordinates":[-1.01667,5.48333],"type":"Point"}
}