{
  "type": "Feature",
  "properties": {
    "gn:admin1_code":"00",
    "gn:asciiname":"Baglo",
    "gn:country_code":"GH",
    "gn:dem":396,
    "gn:feature_class":"P",
    "gn:feature_code":"PPL",
    "gn:name":"Baglo",
    "gn:population":0,
    "gn:timezone":"Africa/Accra",
    "iso:country":"GH",
    "wof:name":"Baglo",
    "wof:placetype":"locality"
},
  "geometry": {"coordinates":[0.63315,7.3032],"type":"Point"}
}