{
  "type": "Feature",
  "properties": {
    "gn:admin1_code":"00",
    "gn:asciiname":"Kulupene",
    "gn:country_code":"GH",
    "gn:dem":170,
    "gn:feature_class":"P",
    "gn:feature_code":"PPL",
    "gn:name":"Kulupene",
    "gn:population":0,
    "gn:timezone":"Africa/Accra",
    "iso:country":"GH",
    "wof:name":"Kulupene",
    "wof:placetype":"locality"
},
  "geometry": {"coordinates":[-0.06667,9.41667],"type":"Point"}
}