{
  "type": "Feature",
  "properties": {
    "gn:admin1_code":"02",
    "gn:asciiname":"Manfo",
    "gn:country_code":"GH",
    "gn:dem":152,
    "gn:feature_class":"P",
    "gn:feature_code":"PPL",
    "gn:name":"Manfo",
    "gn:population":0,
    "gn:timezone":"Africa/Accra",
    "iso:country":"GH",
    "wof:name":"Manfo",
    "wof:placetype":"locality"
},
  "geometry": {"coordinates":[-1.82674,6.25177],"type":"Point"}
}