{
  "type": "Feature",
  "properties": {
    "gn:admin1_code":"00",
    "gn:asciiname":"Katachiasi",
    "gn:country_code":"GH",
    "gn:dem":109,
    "gn:feature_class":"P",
    "gn:feature_code":"PPL",
    "gn:name":"Katachiasi",
    "gn:population":0,
    "gn:timezone":"Africa/Accra",
    "iso:country":"GH",
    "name:und_x_variant":[
        "Katakyiase",
        "Katachiasi"
    ],
    "wof:name":"Katachiasi",
    "wof:placetype":"locality"
},
  "geometry": {"coordinates":[-1.1505,5.38773],"type":"Point"}
}