{
  "type": "Feature",
  "properties": {
    "gn:admin1_code":"00",
    "gn:asciiname":"Yemo-karaga",
    "gn:country_code":"GH",
    "gn:dem":162,
    "gn:feature_class":"P",
    "gn:feature_code":"PPL",
    "gn:name":"Yemo-karaga",
    "gn:population":0,
    "gn:timezone":"Africa/Accra",
    "iso:country":"GH",
    "name:und_x_variant":[
        "Yamong Karaga",
        "Yamalkaraga",
        "Yemo-karaga"
    ],
    "wof:name":"Yemo-karaga",
    "wof:placetype":"locality"
},
  "geometry": {"coordinates":[-0.50991,9.66881],"type":"Point"}
}