{
  "type": "Feature",
  "properties": {
    "gn:admin1_code":"00",
    "gn:asciiname":"Odumasi",
    "gn:cc2":"GH",
    "gn:country_code":"GH",
    "gn:dem":172,
    "gn:feature_class":"P",
    "gn:feature_code":"PPL",
    "gn:name":"Odumasi",
    "gn:population":0,
    "gn:timezone":"Africa/Accra",
    "iso:country":"GH",
    "name:und_x_variant":[
        "Odumase",
        "Odumasi"
    ],
    "wof:name":"Odumasi",
    "wof:placetype":"locality"
},
  "geometry": {"coordinates":[-0.01667,6.13333],"type":"Point"}
}