{
  "type": "Feature",
  "properties": {
    "gn:admin1_code":"02",
    "gn:asciiname":"Fumisua",
    "gn:country_code":"GH",
    "gn:dem":291,
    "gn:feature_class":"P",
    "gn:feature_code":"PPL",
    "gn:name":"Fumisua",
    "gn:population":0,
    "gn:timezone":"Africa/Accra",
    "iso:country":"GH",
    "name:und_x_variant":[
        "Fomasua",
        "Fumisua"
    ],
    "wof:name":"Fumisua",
    "wof:placetype":"locality"
},
  "geometry": {"coordinates":[-1.52141,6.71145],"type":"Point"}
}