{
  "type": "Feature",
  "properties": {
    "gn:admin1_code":"00",
    "gn:asciiname":"Garin Dogo",
    "gn:country_code":"GH",
    "gn:dem":130,
    "gn:feature_class":"P",
    "gn:feature_code":"PPL",
    "gn:name":"Garin Dogo",
    "gn:population":0,
    "gn:timezone":"Africa/Accra",
    "iso:country":"GH",
    "name:und_x_variant":[
        "Dogope",
        "Garin Dogo"
    ],
    "wof:name":"Garin Dogo",
    "wof:placetype":"locality"
},
  "geometry": {"coordinates":[-0.34749,8.34823],"type":"Point"}
}