{
  "type": "Feature",
  "properties": {
    "gn:admin1_code":"00",
    "gn:asciiname":"Dungu",
    "gn:country_code":"GH",
    "gn:dem":176,
    "gn:feature_class":"P",
    "gn:feature_code":"PPL",
    "gn:name":"Dungu",
    "gn:population":0,
    "gn:timezone":"Africa/Accra",
    "iso:country":"GH",
    "name:ceb_x_preferred":[
        "Dungu"
    ],
    "name:deu_x_preferred":[
        "Dungu"
    ],
    "name:swe_x_preferred":[
        "Dungu"
    ],
    "name:und_x_variant":[
        "Dungo",
        "Dungu"
    ],
    "wof:name":"Dungu",
    "wof:placetype":"locality"
},
  "geometry": {"coordinates":[-0.84485,9.48922],"type":"Point"}
}