{
  "type": "Feature",
  "properties": {
    "gn:admin1_code":"00",
    "gn:asciiname":"Wania",
    "gn:country_code":"GH",
    "gn:dem":228,
    "gn:feature_class":"P",
    "gn:feature_code":"PPL",
    "gn:name":"Wania",
    "gn:population":0,
    "gn:timezone":"Africa/Accra",
    "iso:country":"GH",
    "wof:name":"Wania",
    "wof:placetype":"locality"
},
  "geometry": {"coordinates":[-1.41667,10.78333],"type":"Point"}
}