{
  "type": "Feature",
  "properties": {
    "gn:admin1_code":"09",
    "gn:asciiname":"Alabanketa",
    "gn:country_code":"GH",
    "gn:dem":22,
    "gn:feature_class":"P",
    "gn:feature_code":"PPL",
    "gn:name":"Alabanketa",
    "gn:population":0,
    "gn:timezone":"Africa/Accra",
    "iso:country":"GH",
    "name:eng_x_preferred":[
        "Alabanketa"
    ],
    "name:eng_x_variant":[
        "Elabankata"
    ],
    "name:und_x_variant":[
        "Elobankata"
    ],
    "wof:name":"Alabanketa",
    "wof:placetype":"locality"
},
  "geometry": {"coordinates":[-1.98559,4.83402],"type":"Point"}
}