{
  "type": "Feature",
  "properties": {
    "gn:admin1_code":"00",
    "gn:asciiname":"Oboyani",
    "gn:country_code":"GH",
    "gn:dem":322,
    "gn:feature_class":"P",
    "gn:feature_code":"PPL",
    "gn:name":"Oboyani",
    "gn:population":0,
    "gn:timezone":"Africa/Accra",
    "iso:country":"GH",
    "name:und_x_variant":[
        "Oboyan Number 2",
        "Oboyani"
    ],
    "wof:name":"Oboyani",
    "wof:placetype":"locality"
},
  "geometry": {"coordinates":[-0.87006,6.73104],"type":"Point"}
}