{
  "type": "Feature",
  "properties": {
    "gn:admin1_code":"00",
    "gn:asciiname":"Ayensuhu",
    "gn:country_code":"GH",
    "gn:dem":146,
    "gn:feature_class":"P",
    "gn:feature_code":"PPL",
    "gn:name":"Ayensuhu",
    "gn:population":0,
    "gn:timezone":"Africa/Accra",
    "iso:country":"GH",
    "wof:name":"Ayensuhu",
    "wof:placetype":"locality"
},
  "geometry": {"coordinates":[-0.5596,5.94681],"type":"Point"}
}