{
  "type": "Feature",
  "properties": {
    "gn:admin1_code":"00",
    "gn:asciiname":"Amipakwebi",
    "gn:country_code":"GH",
    "gn:dem":162,
    "gn:feature_class":"P",
    "gn:feature_code":"PPL",
    "gn:name":"Amipakwebi",
    "gn:population":0,
    "gn:timezone":"Africa/Accra",
    "iso:country":"GH",
    "wof:name":"Amipakwebi",
    "wof:placetype":"locality"
},
  "geometry": {"coordinates":[-1.0797,5.72574],"type":"Point"}
}