{
  "type": "Feature",
  "properties": {
    "gn:admin1_code":"00",
    "gn:asciiname":"Jwenjweasi",
    "gn:country_code":"GH",
    "gn:dem":227,
    "gn:feature_class":"P",
    "gn:feature_code":"PPL",
    "gn:name":"Jwenjweasi",
    "gn:population":0,
    "gn:timezone":"Africa/Accra",
    "iso:country":"GH",
    "name:und_x_variant":[
        "Dwindwinase",
        "Jwenjweasi"
    ],
    "wof:name":"Jwenjweasi",
    "wof:placetype":"locality"
},
  "geometry": {"coordinates":[-1.20158,6.40869],"type":"Point"}
}