{
  "type": "Feature",
  "properties": {
    "gn:admin1_code":"09",
    "gn:asciiname":"Saman",
    "gn:country_code":"GH",
    "gn:dem":99,
    "gn:feature_class":"P",
    "gn:feature_code":"PPL",
    "gn:name":"Saman",
    "gn:population":0,
    "gn:timezone":"Africa/Accra",
    "iso:country":"GH",
    "name:eng_x_preferred":[
        "Saman"
    ],
    "name:und_x_variant":[
        "Sarman",
        "Samang"
    ],
    "wof:name":"Saman",
    "wof:placetype":"locality"
},
  "geometry": {"coordinates":[-2.12946,5.81638],"type":"Point"}
}