{
  "type": "Feature",
  "properties": {
    "gn:admin1_code":"00",
    "gn:asciiname":"Ofebri",
    "gn:country_code":"GH",
    "gn:dem":37,
    "gn:feature_class":"P",
    "gn:feature_code":"PPL",
    "gn:name":"Ofebri",
    "gn:population":0,
    "gn:timezone":"Africa/Accra",
    "iso:country":"GH",
    "wof:name":"Ofebri",
    "wof:placetype":"locality"
},
  "geometry": {"coordinates":[-0.63333,5.56667],"type":"Point"}
}