{
  "type": "Feature",
  "properties": {
    "gn:admin1_code":"00",
    "gn:asciiname":"Kusawgu",
    "gn:country_code":"GH",
    "gn:dem":149,
    "gn:feature_class":"P",
    "gn:feature_code":"PPL",
    "gn:name":"Kusawgu",
    "gn:population":0,
    "gn:timezone":"Africa/Accra",
    "iso:country":"GH",
    "name:und_x_variant":[
        "Kashaw",
        "Kusawgu"
    ],
    "wof:name":"Kusawgu",
    "wof:placetype":"locality"
},
  "geometry": {"coordinates":[-1.04348,9.19661],"type":"Point"}
}