{
  "type": "Feature",
  "properties": {
    "gn:admin1_code":"00",
    "gn:asciiname":"Mprenchi",
    "gn:country_code":"GH",
    "gn:dem":38,
    "gn:feature_class":"P",
    "gn:feature_code":"PPL",
    "gn:name":"Mprenchi",
    "gn:population":0,
    "gn:timezone":"Africa/Accra",
    "iso:country":"GH",
    "name:und_x_variant":[
        "Mprenkye",
        "Mprenchi"
    ],
    "wof:name":"Mprenchi",
    "wof:placetype":"locality"
},
  "geometry": {"coordinates":[-1.06294,5.36017],"type":"Point"}
}