{
  "type": "Feature",
  "properties": {
    "gn:admin1_code":"01",
    "gn:asciiname":"Akomato",
    "gn:country_code":"GH",
    "gn:dem":106,
    "gn:feature_class":"P",
    "gn:feature_code":"PPL",
    "gn:name":"Akomato",
    "gn:population":0,
    "gn:timezone":"Africa/Accra",
    "iso:country":"GH",
    "wof:name":"Akomato",
    "wof:placetype":"locality"
},
  "geometry": {"coordinates":[-0.58333,5.71667],"type":"Point"}
}