{
  "type": "Feature",
  "properties": {
    "gn:admin1_code":"00",
    "gn:asciiname":"Kraboa Coaltar",
    "gn:country_code":"GH",
    "gn:dem":169,
    "gn:feature_class":"P",
    "gn:feature_code":"PPL",
    "gn:name":"Kraboa Coaltar",
    "gn:population":0,
    "gn:timezone":"Africa/Accra",
    "iso:country":"GH",
    "name:und_x_variant":[
        "Kraboa",
        "Kraboa Coaltar"
    ],
    "wof:name":"Kraboa Coaltar",
    "wof:placetype":"locality"
},
  "geometry": {"coordinates":[-0.46248,5.90864],"type":"Point"}
}