{
  "type": "Feature",
  "properties": {
    "gn:admin1_code":"00",
    "gn:asciiname":"Ntobriso",
    "gn:country_code":"GH",
    "gn:dem":149,
    "gn:feature_class":"P",
    "gn:feature_code":"PPL",
    "gn:name":"Ntobriso",
    "gn:population":0,
    "gn:timezone":"Africa/Accra",
    "iso:country":"GH",
    "name:und_x_variant":[
        "Ntrubuso",
        "Ntobriso"
    ],
    "wof:name":"Ntobriso",
    "wof:placetype":"locality"
},
  "geometry": {"coordinates":[-0.61367,7.76474],"type":"Point"}
}