{
  "type": "Feature",
  "properties": {
    "gn:admin1_code":"00",
    "gn:asciiname":"Teti",
    "gn:country_code":"GH",
    "gn:dem":93,
    "gn:feature_class":"P",
    "gn:feature_code":"PPL",
    "gn:name":"Teti",
    "gn:population":0,
    "gn:timezone":"Africa/Accra",
    "iso:country":"GH",
    "name:und_x_variant":[
        "Tetsi",
        "Teti"
    ],
    "wof:name":"Teti",
    "wof:placetype":"locality"
},
  "geometry": {"coordinates":[-1.15916,5.34993],"type":"Point"}
}