{
  "type": "Feature",
  "properties": {
    "gn:admin1_code":"00",
    "gn:asciiname":"Amantem Nkwanta",
    "gn:country_code":"GH",
    "gn:dem":141,
    "gn:feature_class":"P",
    "gn:feature_code":"PPL",
    "gn:name":"Amantem Nkwanta",
    "gn:population":0,
    "gn:timezone":"Africa/Accra",
    "iso:country":"GH",
    "wof:name":"Amantem Nkwanta",
    "wof:placetype":"locality"
},
  "geometry": {"coordinates":[-0.83318,5.93949],"type":"Point"}
}