{
  "type": "Feature",
  "properties": {
    "gn:admin1_code":"09",
    "gn:asciiname":"Nkokraba",
    "gn:country_code":"GH",
    "gn:dem":10,
    "gn:feature_class":"P",
    "gn:feature_code":"PPL",
    "gn:name":"Nkokraba",
    "gn:population":0,
    "gn:timezone":"Africa/Accra",
    "iso:country":"GH",
    "wof:name":"Nkokraba",
    "wof:placetype":"locality"
},
  "geometry": {"coordinates":[-2.39417,4.96806],"type":"Point"}
}