{
  "type": "Feature",
  "properties": {
    "gn:admin1_code":"00",
    "gn:asciiname":"Molume",
    "gn:country_code":"GH",
    "gn:dem":45,
    "gn:feature_class":"P",
    "gn:feature_code":"PPL",
    "gn:name":"Molume",
    "gn:population":0,
    "gn:timezone":"Africa/Accra",
    "iso:country":"GH",
    "wof:name":"Molume",
    "wof:placetype":"locality"
},
  "geometry": {"coordinates":[0.83333,6.11667],"type":"Point"}
}