{
  "type": "Feature",
  "properties": {
    "gn:admin1_code":"08",
    "gn:asciiname":"Agbosokope",
    "gn:country_code":"GH",
    "gn:dem":29,
    "gn:feature_class":"P",
    "gn:feature_code":"PPL",
    "gn:name":"Agbosokope",
    "gn:population":0,
    "gn:timezone":"Africa/Accra",
    "iso:country":"GH",
    "wof:name":"Agbosokope",
    "wof:placetype":"locality"
},
  "geometry": {"coordinates":[1.03861,6.13278],"type":"Point"}
}