{
  "type": "Feature",
  "properties": {
    "gn:admin1_code":"00",
    "gn:asciiname":"Angwo",
    "gn:country_code":"GH",
    "gn:dem":185,
    "gn:feature_class":"P",
    "gn:feature_code":"PPL",
    "gn:name":"Angwo",
    "gn:population":0,
    "gn:timezone":"Africa/Accra",
    "iso:country":"GH",
    "wof:name":"Angwo",
    "wof:placetype":"locality"
},
  "geometry": {"coordinates":[0.23333,10.16667],"type":"Point"}
}