{
  "type": "Feature",
  "properties": {
    "gn:admin1_code":"10",
    "gn:asciiname":"Kayoro",
    "gn:country_code":"GH",
    "gn:dem":275,
    "gn:feature_class":"P",
    "gn:feature_code":"PPL",
    "gn:name":"Kayoro",
    "gn:population":0,
    "gn:timezone":"Africa/Accra",
    "iso:country":"GH",
    "name:und_x_variant":[
        "Kaiyoro",
        "Kayoro Achasongo",
        "Kayoro"
    ],
    "wof:name":"Kayoro",
    "wof:placetype":"locality"
},
  "geometry": {"coordinates":[-1.33608,10.96491],"type":"Point"}
}