{
  "type": "Feature",
  "properties": {
    "gn:admin1_code":"00",
    "gn:asciiname":"Nabansong",
    "gn:country_code":"GH",
    "gn:dem":183,
    "gn:feature_class":"P",
    "gn:feature_code":"PPL",
    "gn:name":"Nabansong",
    "gn:population":0,
    "gn:timezone":"Africa/Accra",
    "iso:country":"GH",
    "name:und_x_variant":[
        "Mgbansong",
        "Nabansong"
    ],
    "wof:name":"Nabansong",
    "wof:placetype":"locality"
},
  "geometry": {"coordinates":[-0.1327,10.36044],"type":"Point"}
}