{
  "type": "Feature",
  "properties": {
    "gn:admin1_code":"00",
    "gn:asciiname":"Nyamieni",
    "gn:country_code":"GH",
    "gn:dem":92,
    "gn:feature_class":"P",
    "gn:feature_code":"PPL",
    "gn:name":"Nyamieni",
    "gn:population":0,
    "gn:timezone":"Africa/Accra",
    "iso:country":"GH",
    "name:und_x_variant":[
        "Nyameeni",
        "Nyamieni"
    ],
    "wof:name":"Nyamieni",
    "wof:placetype":"locality"
},
  "geometry": {"coordinates":[-1.34603,5.28395],"type":"Point"}
}