{
  "type": "Feature",
  "properties": {
    "gn:admin1_code":"02",
    "gn:asciiname":"Jeniso",
    "gn:country_code":"GH",
    "gn:dem":220,
    "gn:feature_class":"P",
    "gn:feature_code":"PPL",
    "gn:name":"Jeniso",
    "gn:population":0,
    "gn:timezone":"Africa/Accra",
    "iso:country":"GH",
    "name:und_x_variant":[
        "Gyensiso",
        "Jeniso"
    ],
    "wof:name":"Jeniso",
    "wof:placetype":"locality"
},
  "geometry": {"coordinates":[-1.95941,6.51011],"type":"Point"}
}