{
  "type": "Feature",
  "properties": {
    "gn:admin1_code":"00",
    "gn:asciiname":"Akunduo",
    "gn:country_code":"GH",
    "gn:dem":224,
    "gn:feature_class":"P",
    "gn:feature_code":"PPL",
    "gn:name":"Akunduo",
    "gn:population":0,
    "gn:timezone":"Africa/Accra",
    "iso:country":"GH",
    "wof:name":"Akunduo",
    "wof:placetype":"locality"
},
  "geometry": {"coordinates":[-0.79935,10.93652],"type":"Point"}
}