{
  "type": "Feature",
  "properties": {
    "gn:admin1_code":"09",
    "gn:asciiname":"Katakul",
    "gn:country_code":"GH",
    "gn:dem":15,
    "gn:feature_class":"P",
    "gn:feature_code":"PPL",
    "gn:name":"Katakul",
    "gn:population":0,
    "gn:timezone":"Africa/Accra",
    "iso:country":"GH",
    "name:eng_x_preferred":[
        "Katakul"
    ],
    "name:und_x_variant":[
        "Katakro",
        "Katakor",
        "Katakwo"
    ],
    "wof:name":"Katakul",
    "wof:placetype":"locality"
},
  "geometry": {"coordinates":[-2.04362,4.75524],"type":"Point"}
}