{
  "type": "Feature",
  "properties": {
    "gn:admin1_code":"00",
    "gn:asciiname":"Deme",
    "gn:country_code":"GH",
    "gn:dem":225,
    "gn:feature_class":"P",
    "gn:feature_code":"PPL",
    "gn:name":"Deme",
    "gn:population":0,
    "gn:timezone":"Africa/Accra",
    "iso:country":"GH",
    "name:afr_x_preferred":[
        "D\u00eamos"
    ],
    "name:cat_x_preferred":[
        "Demos"
    ],
    "name:dan_x_preferred":[
        "Deme"
    ],
    "name:deu_x_preferred":[
        "Demos"
    ],
    "name:ell_x_preferred":[
        "\u0394\u03ae\u03bc\u03bf\u03b9"
    ],
    "name:fin_x_preferred":[
        "Demos"
    ],
    "name:fra_x_preferred":[
        "D\u00e8me"
    ],
    "name:hun_x_preferred":[
        "D\u00e9mosz"
    ],
    "name:ita_x_preferred":[
        "Demo"
    ],
    "name:lat_x_preferred":[
        "Demus"
    ],
    "name:lit_x_preferred":[
        "Demas"
    ],
    "name:nld_x_preferred":[
        "Deme"
    ],
    "name:nor_x_preferred":[
        "Deme"
    ],
    "name:pol_x_preferred":[
        "Dem"
    ],
    "name:por_x_preferred":[
        "Demo"
    ],
    "name:ron_x_preferred":[
        "Deme"
    ],
    "name:rus_x_preferred":[
        "\u0414\u0435\u043c"
    ],
    "name:slv_x_preferred":[
        "Dema"
    ],
    "name:spa_x_preferred":[
        "Demo \u00e1tico"
    ],
    "name:swe_x_preferred":[
        "Demos"
    ],
    "name:tgl_x_preferred":[
        "Dimos"
    ],
    "name:ukr_x_preferred":[
        "\u0414\u0435\u043c\u0438"
    ],
    "wof:name":"Deme",
    "wof:placetype":"locality"
},
  "geometry": {"coordinates":[0.48283,6.6367],"type":"Point"}
}