{
  "type": "Feature",
  "properties": {
    "gn:admin1_code":"00",
    "gn:asciiname":"Deme",
    "gn:country_code":"GH",
    "gn:dem":225,
    "gn:feature_class":"P",
    "gn:feature_code":"PPL",
    "gn:name":"Deme",
    "gn:population":0,
    "gn:timezone":"Africa/Accra",
    "iso:country":"GH",
    "wof:name":"Deme",
    "wof:placetype":"locality"
},
  "geometry": {"coordinates":[0.48283,6.6367],"type":"Point"}
}