{
  "type": "Feature",
  "properties": {
    "gn:admin1_code":"00",
    "gn:asciiname":"Atiteti",
    "gn:country_code":"GH",
    "gn:dem":15,
    "gn:feature_class":"P",
    "gn:feature_code":"PPL",
    "gn:name":"Atiteti",
    "gn:population":0,
    "gn:timezone":"Africa/Accra",
    "iso:country":"GH",
    "wof:name":"Atiteti",
    "wof:placetype":"locality"
},
  "geometry": {"coordinates":[0.45887,6.13406],"type":"Point"}
}