{
  "type": "Feature",
  "properties": {
    "gn:admin1_code":"02",
    "gn:asciiname":"Duakoben",
    "gn:country_code":"GH",
    "gn:dem":252,
    "gn:feature_class":"P",
    "gn:feature_code":"PPL",
    "gn:name":"Duakoben",
    "gn:population":0,
    "gn:timezone":"Africa/Accra",
    "iso:country":"GH",
    "name:und_x_variant":[
        "Duakobin"
    ],
    "wof:name":"Duakoben",
    "wof:placetype":"locality"
},
  "geometry": {"coordinates":[-1.71958,6.56729],"type":"Point"}
}