{
  "type": "Feature",
  "properties": {
    "gn:admin1_code":"09",
    "gn:asciiname":"Ekalesuazo",
    "gn:country_code":"GH",
    "gn:dem":6,
    "gn:feature_class":"P",
    "gn:feature_code":"PPL",
    "gn:name":"Ekalesuazo",
    "gn:population":0,
    "gn:timezone":"Africa/Accra",
    "iso:country":"GH",
    "name:eng_x_preferred":[
        "Ekalesuazo"
    ],
    "name:und_x_variant":[
        "Ekrakrom",
        "Akrakrom"
    ],
    "wof:name":"Ekalesuazo",
    "wof:placetype":"locality"
},
  "geometry": {"coordinates":[-2.07764,4.74985],"type":"Point"}
}