{
  "type": "Feature",
  "properties": {
    "gn:admin1_code":"00",
    "gn:asciiname":"Odahu",
    "gn:country_code":"GH",
    "gn:dem":271,
    "gn:feature_class":"P",
    "gn:feature_code":"PPL",
    "gn:name":"Odahu",
    "gn:population":0,
    "gn:timezone":"Africa/Accra",
    "iso:country":"GH",
    "wof:name":"Odahu",
    "wof:placetype":"locality"
},
  "geometry": {"coordinates":[-1.45216,6.68755],"type":"Point"}
}