{
  "type": "Feature",
  "properties": {
    "gn:admin1_code":"08",
    "gn:asciiname":"Milegbakope",
    "gn:country_code":"GH",
    "gn:dem":8,
    "gn:feature_class":"P",
    "gn:feature_code":"PPL",
    "gn:name":"Milegbakope",
    "gn:population":0,
    "gn:timezone":"Africa/Accra",
    "iso:country":"GH",
    "name:und_x_variant":[
        "Milegbakofe",
        "Milegbakope"
    ],
    "wof:name":"Milegbakope",
    "wof:placetype":"locality"
},
  "geometry": {"coordinates":[1.02779,6.04681],"type":"Point"}
}