{
  "type": "Feature",
  "properties": {
    "gn:admin1_code":"00",
    "gn:asciiname":"Mankuma",
    "gn:country_code":"GH",
    "gn:dem":313,
    "gn:feature_class":"P",
    "gn:feature_code":"PPL",
    "gn:name":"Mankuma",
    "gn:population":0,
    "gn:timezone":"Africa/Accra",
    "iso:country":"GH",
    "name:und_x_variant":[
        "Mamkuma",
        "Mankuma"
    ],
    "wof:name":"Mankuma",
    "wof:placetype":"locality"
},
  "geometry": {"coordinates":[-2.48812,9.15361],"type":"Point"}
}