{
  "type": "Feature",
  "properties": {
    "gn:admin1_code":"00",
    "gn:asciiname":"Ofuve",
    "gn:country_code":"GH",
    "gn:dem":54,
    "gn:feature_class":"P",
    "gn:feature_code":"PPL",
    "gn:name":"Ofuve",
    "gn:population":0,
    "gn:timezone":"Africa/Accra",
    "iso:country":"GH",
    "wof:name":"Ofuve",
    "wof:placetype":"locality"
},
  "geometry": {"coordinates":[0.72189,6.35893],"type":"Point"}
}