{
  "type": "Feature",
  "properties": {
    "gn:admin1_code":"00",
    "gn:asciiname":"Apemtu",
    "gn:country_code":"GH",
    "gn:dem":316,
    "gn:feature_class":"P",
    "gn:feature_code":"PPL",
    "gn:name":"Apemtu",
    "gn:population":0,
    "gn:timezone":"Africa/Accra",
    "iso:country":"GH",
    "wof:name":"Apemtu",
    "wof:placetype":"locality"
},
  "geometry": {"coordinates":[-1.45,6.46667],"type":"Point"}
}