{
  "type": "Feature",
  "properties": {
    "gn:admin1_code":"02",
    "gn:asciiname":"Konkoja",
    "gn:country_code":"GH",
    "gn:dem":137,
    "gn:feature_class":"P",
    "gn:feature_code":"PPL",
    "gn:name":"Konkoja",
    "gn:population":0,
    "gn:timezone":"Africa/Accra",
    "iso:country":"GH",
    "name:eng_x_preferred":[
        "Konkoja"
    ],
    "wof:name":"Konkoja",
    "wof:placetype":"locality"
},
  "geometry": {"coordinates":[-1.78302,6.01111],"type":"Point"}
}