{
  "type": "Feature",
  "properties": {
    "gn:admin1_code":"01",
    "gn:asciiname":"Atoman",
    "gn:country_code":"GH",
    "gn:dem":63,
    "gn:feature_class":"P",
    "gn:feature_code":"PPL",
    "gn:name":"Atoman",
    "gn:population":0,
    "gn:timezone":"Africa/Accra",
    "iso:country":"GH",
    "wof:name":"Atoman",
    "wof:placetype":"locality"
},
  "geometry": {"coordinates":[-0.49466,5.79073],"type":"Point"}
}