{
  "type": "Feature",
  "properties": {
    "gn:admin1_code":"00",
    "gn:asciiname":"Agotoe",
    "gn:country_code":"GH",
    "gn:dem":2,
    "gn:feature_class":"P",
    "gn:feature_code":"PPL",
    "gn:name":"Agotoe",
    "gn:population":0,
    "gn:timezone":"Africa/Accra",
    "iso:country":"GH",
    "name:und_x_variant":[
        "Agove",
        "Agawtaw",
        "Agortoe",
        "Agotoe"
    ],
    "wof:name":"Agotoe",
    "wof:placetype":"locality"
},
  "geometry": {"coordinates":[0.76048,5.85679],"type":"Point"}
}