{
  "type": "Feature",
  "properties": {
    "gn:admin1_code":"09",
    "gn:asciiname":"Atababo",
    "gn:country_code":"GH",
    "gn:dem":16,
    "gn:feature_class":"P",
    "gn:feature_code":"PPL",
    "gn:name":"Atababo",
    "gn:population":0,
    "gn:timezone":"Africa/Accra",
    "iso:country":"GH",
    "wof:name":"Atababo",
    "wof:placetype":"locality"
},
  "geometry": {"coordinates":[-2.29222,4.95611],"type":"Point"}
}