{
  "type": "Feature",
  "properties": {
    "gn:admin1_code":"00",
    "gn:asciiname":"Narongo",
    "gn:country_code":"GH",
    "gn:dem":217,
    "gn:feature_class":"P",
    "gn:feature_code":"PPL",
    "gn:name":"Narongo",
    "gn:population":0,
    "gn:timezone":"Africa/Accra",
    "iso:country":"GH",
    "name:und_x_variant":[
        "Narango",
        "Narongo"
    ],
    "wof:name":"Narongo",
    "wof:placetype":"locality"
},
  "geometry": {"coordinates":[-0.26422,10.97409],"type":"Point"}
}