{
  "type": "Feature",
  "properties": {
    "gn:admin1_code":"00",
    "gn:asciiname":"Anumenchen",
    "gn:country_code":"GH",
    "gn:dem":33,
    "gn:feature_class":"P",
    "gn:feature_code":"PPL",
    "gn:name":"Anumenchen",
    "gn:population":0,
    "gn:timezone":"Africa/Accra",
    "iso:country":"GH",
    "wof:name":"Anumenchen",
    "wof:placetype":"locality"
},
  "geometry": {"coordinates":[-0.98333,5.28333],"type":"Point"}
}