{
  "type": "Feature",
  "properties": {
    "gn:admin1_code":"08",
    "gn:asciiname":"Dzablikope",
    "gn:country_code":"GH",
    "gn:dem":4,
    "gn:feature_class":"P",
    "gn:feature_code":"PPL",
    "gn:name":"Dzablikope",
    "gn:population":0,
    "gn:timezone":"Africa/Accra",
    "iso:country":"GH",
    "wof:name":"Dzablikope",
    "wof:placetype":"locality"
},
  "geometry": {"coordinates":[1.11361,6.10722],"type":"Point"}
}