{
  "type": "Feature",
  "properties": {
    "gn:admin1_code":"06",
    "gn:asciiname":"Samene",
    "gn:country_code":"GH",
    "gn:dem":310,
    "gn:feature_class":"P",
    "gn:feature_code":"PPL",
    "gn:name":"Samene",
    "gn:population":0,
    "gn:timezone":"Africa/Accra",
    "iso:country":"GH",
    "name:und_x_variant":[
        "Sameni",
        "Samene"
    ],
    "wof:name":"Samene",
    "wof:placetype":"locality"
},
  "geometry": {"coordinates":[-0.62246,10.47088],"type":"Point"}
}