{
  "type": "Feature",
  "properties": {
    "gn:admin1_code":"00",
    "gn:asciiname":"Tambinga",
    "gn:country_code":"GH",
    "gn:dem":137,
    "gn:feature_class":"P",
    "gn:feature_code":"PPL",
    "gn:name":"Tambinga",
    "gn:population":0,
    "gn:timezone":"Africa/Accra",
    "iso:country":"GH",
    "name:und_x_variant":[
        "Tambeeng",
        "Tambinga"
    ],
    "wof:name":"Tambinga",
    "wof:placetype":"locality"
},
  "geometry": {"coordinates":[0.1736,10.40691],"type":"Point"}
}