{
  "type": "Feature",
  "properties": {
    "gn:admin1_code":"00",
    "gn:asciiname":"Odumase",
    "gn:country_code":"GH",
    "gn:dem":301,
    "gn:feature_class":"P",
    "gn:feature_code":"PPL",
    "gn:name":"Odumase",
    "gn:population":0,
    "gn:timezone":"Africa/Accra",
    "iso:country":"GH",
    "name:und_x_variant":[
        "Odumasi",
        "Odumase"
    ],
    "wof:name":"Odumase",
    "wof:placetype":"locality"
},
  "geometry": {"coordinates":[-2.31819,7.37134],"type":"Point"}
}