{
  "type": "Feature",
  "properties": {
    "gn:admin1_code":"00",
    "gn:asciiname":"Mania",
    "gn:country_code":"GH",
    "gn:dem":7,
    "gn:feature_class":"P",
    "gn:feature_code":"PPL",
    "gn:name":"Mania",
    "gn:population":0,
    "gn:timezone":"Africa/Accra",
    "iso:country":"GH",
    "name:und_x_variant":[
        "Manya",
        "Mania"
    ],
    "wof:name":"Mania",
    "wof:placetype":"locality"
},
  "geometry": {"coordinates":[0.3984,6.05747],"type":"Point"}
}