{
  "type": "Feature",
  "properties": {
    "gn:admin1_code":"00",
    "gn:asciiname":"Akpakpavikope",
    "gn:country_code":"GH",
    "gn:dem":9,
    "gn:feature_class":"P",
    "gn:feature_code":"PPL",
    "gn:name":"Akpakpavikope",
    "gn:population":0,
    "gn:timezone":"Africa/Accra",
    "iso:country":"GH",
    "name:und_x_variant":[
        "Akpakpavi Korpe",
        "Akpakpavikope"
    ],
    "wof:name":"Akpakpavikope",
    "wof:placetype":"locality"
},
  "geometry": {"coordinates":[0.48596,5.97188],"type":"Point"}
}