{
  "type": "Feature",
  "properties": {
    "gn:admin1_code":"00",
    "gn:asciiname":"Pirisi",
    "gn:country_code":"GH",
    "gn:dem":330,
    "gn:feature_class":"P",
    "gn:feature_code":"PPL",
    "gn:name":"Pirisi",
    "gn:population":0,
    "gn:timezone":"Africa/Accra",
    "iso:country":"GH",
    "name:und_x_variant":[
        "Perisi",
        "Pirisi"
    ],
    "wof:name":"Pirisi",
    "wof:placetype":"locality"
},
  "geometry": {"coordinates":[-2.45644,10.1144],"type":"Point"}
}