{
  "type": "Feature",
  "properties": {
    "gn:admin1_code":"11",
    "gn:asciiname":"Nabugangn",
    "gn:country_code":"GH",
    "gn:dem":289,
    "gn:feature_class":"P",
    "gn:feature_code":"PPL",
    "gn:name":"Nabugangn",
    "gn:population":0,
    "gn:timezone":"Africa/Accra",
    "iso:country":"GH",
    "name:eng_x_preferred":[
        "Nabugangn"
    ],
    "name:und_x_variant":[
        "Naburnye",
        "Nabrunjan"
    ],
    "wof:name":"Nabugangn",
    "wof:placetype":"locality"
},
  "geometry": {"coordinates":[-2.78874,10.63752],"type":"Point"}
}