{
  "type": "Feature",
  "properties": {
    "gn:admin1_code":"00",
    "gn:asciiname":"Bopa",
    "gn:country_code":"GH",
    "gn:dem":155,
    "gn:feature_class":"P",
    "gn:feature_code":"PPL",
    "gn:name":"Bopa",
    "gn:population":0,
    "gn:timezone":"Africa/Accra",
    "iso:country":"GH",
    "wof:name":"Bopa",
    "wof:placetype":"locality"
},
  "geometry": {"coordinates":[-2.57643,6.08712],"type":"Point"}
}