{
  "type": "Feature",
  "properties": {
    "gn:admin1_code":"00",
    "gn:asciiname":"Fiapri",
    "gn:country_code":"GH",
    "gn:dem":291,
    "gn:feature_class":"P",
    "gn:feature_code":"PPL",
    "gn:name":"Fiapri",
    "gn:population":0,
    "gn:timezone":"Africa/Accra",
    "iso:country":"GH",
    "name:und_x_variant":[
        "Fiapire",
        "Fiapri"
    ],
    "wof:name":"Fiapri",
    "wof:placetype":"locality"
},
  "geometry": {"coordinates":[-2.3464,7.36242],"type":"Point"}
}