{
  "type": "Feature",
  "properties": {
    "iso:country":"GH",
    "name:bul_x_preferred":[
        "\u0410\u0431\u0443\u0440\u0438"
    ],
    "name:cat_x_preferred":[
        "Aburi"
    ],
    "name:ceb_x_preferred":[
        "Aburi"
    ],
    "name:deu_x_preferred":[
        "Aburi"
    ],
    "name:eng_x_preferred":[
        "Aburi"
    ],
    "name:epo_x_preferred":[
        "Aburi"
    ],
    "name:fas_x_preferred":[
        "\u0627\u0628\u0648\u0631\u06cc"
    ],
    "name:glg_x_preferred":[
        "Aburi"
    ],
    "name:jpn_x_preferred":[
        "\u30a2\u30d6\u30ea"
    ],
    "name:nld_x_preferred":[
        "Aburi"
    ],
    "name:rus_x_preferred":[
        "\u0410\u0431\u0443\u0440\u0438"
    ],
    "name:spa_x_preferred":[
        "Aburi"
    ],
    "name:swe_x_preferred":[
        "Aburi"
    ],
    "qs:gn_country":"GH",
    "qs:gn_fcode":"PPL",
    "qs:gn_pop":18399,
    "qs:name":"Aburi",
    "qs:name_adm0":"Ghana",
    "qs:name_adm1":"Eastern",
    "qs:photos":292,
    "qs:photos_1k":59,
    "qs:photos_9k":1,
    "qs:photos_9r":4,
    "qs:photos_all":292,
    "qs:photos_sr":5,
    "qs:placetype":"Town",
    "qs:pop_sr":"6",
    "qs:woe_adm0":23424824,
    "wd:wordcount":874,
    "wof:name":"Aburi",
    "wof:placetype":"locality",
    "wof:population":18399
},
  "geometry": {"coordinates":[-0.17449,5.84802],"type":"Point"}
}