{
  "type": "Feature",
  "properties": {
    "gn:admin1_code":"00",
    "gn:asciiname":"Dedeso",
    "gn:country_code":"GH",
    "gn:dem":215,
    "gn:feature_class":"P",
    "gn:feature_code":"PPL",
    "gn:name":"Dedeso",
    "gn:population":0,
    "gn:timezone":"Africa/Accra",
    "iso:country":"GH",
    "wof:name":"Dedeso",
    "wof:placetype":"locality"
},
  "geometry": {"coordinates":[-0.22196,6.9577],"type":"Point"}
}