{
  "type": "Feature",
  "properties": {
    "gn:admin1_code":"00",
    "gn:asciiname":"Dubia",
    "gn:country_code":"GH",
    "gn:dem":291,
    "gn:feature_class":"P",
    "gn:feature_code":"PPL",
    "gn:name":"Dubia",
    "gn:population":0,
    "gn:timezone":"Africa/Accra",
    "iso:country":"GH",
    "name:und_x_variant":[
        "Duwie",
        "Dubia"
    ],
    "wof:name":"Dubia",
    "wof:placetype":"locality"
},
  "geometry": {"coordinates":[-2.22787,10.68574],"type":"Point"}
}