{
  "type": "Feature",
  "properties": {
    "gn:admin1_code":"00",
    "gn:asciiname":"Zabzugu",
    "gn:country_code":"GH",
    "gn:dem":168,
    "gn:feature_class":"P",
    "gn:feature_code":"PPL",
    "gn:name":"Zabzugu",
    "gn:population":0,
    "gn:timezone":"Africa/Accra",
    "iso:country":"GH",
    "name:swe_x_preferred":[
        "Zabzugu"
    ],
    "name:und_x_variant":[
        "Sansugu"
    ],
    "name:urd_x_preferred":[
        "\u0632\u0628\u0632\u06af\u0648"
    ],
    "wof:name":"Zabzugu",
    "wof:placetype":"locality"
},
  "geometry": {"coordinates":[0.36784,9.29322],"type":"Point"}
}