{
  "type": "Feature",
  "properties": {
    "gn:admin1_code":"00",
    "gn:asciiname":"Asebem",
    "gn:country_code":"GH",
    "gn:dem":151,
    "gn:feature_class":"P",
    "gn:feature_code":"PPL",
    "gn:name":"Asebem",
    "gn:population":0,
    "gn:timezone":"Africa/Accra",
    "iso:country":"GH",
    "wof:name":"Asebem",
    "wof:placetype":"locality"
},
  "geometry": {"coordinates":[-1.10543,5.61183],"type":"Point"}
}