{
  "type": "Feature",
  "properties": {
    "gn:admin1_code":"02",
    "gn:asciiname":"Nyamibechire",
    "gn:country_code":"GH",
    "gn:dem":114,
    "gn:feature_class":"P",
    "gn:feature_code":"PPL",
    "gn:name":"Nyamibechire",
    "gn:population":0,
    "gn:timezone":"Africa/Accra",
    "iso:country":"GH",
    "name:eng_x_preferred":[
        "Nyamibechire"
    ],
    "wof:name":"Nyamibechire",
    "wof:placetype":"locality"
},
  "geometry": {"coordinates":[-1.75898,6.00327],"type":"Point"}
}